Workbook

Sheet 解禁情報
A1: メーカー | B1: SKU | C1: 情報解禁 | D1: サプライヤー出荷 | E1: 出荷解禁
X73: 200
X74: 10
W75: 20
W78: 200 | X78: 2000
X79: 100
W80: 20 | X80: 120
X85: 300
W86: 100 | X86: 150
W93: 8720 | X93: 5300
W94: 1660 | X94: 1200
W102: 2225
W131: 360 | X131: 500
W134: 150 | X134: 1250
W135: 90 | X135: 950
W136: 250 | X136: 500 | Y136: =IF(Y$6="",X136*Y$4,X136*Y$6) -> 0
W142: 5300
W145: 3300
W146: 3100

Sheet 全体
G1: 月次日数→ | AR1: 手入力→ | AS1: 30
G2: 進捗日数→ | AS2: =結果貼付!$A$3 -> 14
A3: EOL | J3: 結果 | K3: 結果 | L3: 結果 | M3: 結果 | N3: 結果 | O3: 結果 | P3: 結果 | Q3: 結果 | R3: 結果 | S3: 結果 | T3: 結果 | U3: 結果 | V3: 結果 | W3: 結果 | AR3: 結果 | AS3: 着地見込 | AT3: 手動補正 | AU3: 手動補正 | AV3: 手動補正 | AW3: 手動補正 | AX3: 手動補正 | AY3: 手動補正
A4: 調整した部材 | G4: 前月比(補正値) | AT4: =HLOOKUP(AT20,係数計算!$B$21:$M$25,4,0) -> 1.1299426 | AU4: =HLOOKUP(AU20,係数計算!$B$21:$M$25,4,0) -> 1.1478954 | AV4: =HLOOKUP(AV20,係数計算!$B$21:$M$25,4,0) -> 0.84745459 | AW4: =HLOOKUP(AW20,係数計算!$B$21:$M$25,4,0) -> 0.98024011 | AX4: =HLOOKUP(AX20,係数計算!$B$21:$M$25,4,0) -> 0.86629134 | AY4: =HLOOKUP(AY20,係数計算!$B$21:$M$25,4,0) -> 0.99099277
A5: ブースト期間 | G5: 季節指数(参考値) | AT5: =HLOOKUP(AT20,係数計算!$B$21:$M$25,5,0) -> 0.95505496 | AU5: =HLOOKUP(AU20,係数計算!$B$21:$M$25,5,0) -> 1.0963032 | AV5: =HLOOKUP(AV20,係数計算!$B$21:$M$25,5,0) -> 0.92906718 | AW5: =HLOOKUP(AW20,係数計算!$B$21:$M$25,5,0) -> 0.91070892 | AX5: =HLOOKUP(AX20,係数計算!$B$21:$M$25,5,0) -> 0.78893925 | AY5: =HLOOKUP(AY20,係数計算!$B$21:$M$25,5,0) -> 0.78183309
A6: 新規追加もしくは通常調整外で更新 | G6: 全体手動補正(%)
AT7: =+AT8/AT9 -> 0.78223399 | AU7: =+AU8/AU9 -> 0.86979401 | AV7: =+AV8/AV9 -> 0.85131694 | AW7: =+AW8/AW9 -> 0.84173863 | AX7: =+AX8/AX9 -> 0.79082408 | AY7: =+AY8/AY9 -> 0.79082654
G8: VGA | J8: =J76 -> 7361 | K8: =K76 -> 6711 | L8: =L76 -> 5300 | M8: =M76 -> 6715 | N8: =N76 -> 9492 | O8: =O76 -> 9638 | P8: =P76 -> 6711 | Q8: =Q76 -> 7612 | ... AG8: =AG76 -> 18695 | AI8: 11927 | AK8: 11832 | AL8: 20509.355 | AM8: 14613.031 | AN8: 7987 | AO8: 9079 | AP8: 9624 | AQ8: 11021 | AR8: =AR76 -> 8227.5 | AS8: =AS76 -> 7658.5 | AT8: =AT76 -> 10062.855 | AU8: =AU76 -> 12033.276 | AV8: =AV76 -> 9689.2245 | AW8: =AW76 -> 9465.0664 | AX8: =AX76 -> 8349.6201 | AY8: =AY76 -> 8279.9528
G9: CPU | J9: =SUM(J109,J137) -> 3540 | K9: =SUM(K109,K137) -> 2969 | L9: =SUM(L109,L137) -> 2890 | M9: =SUM(M109,M137) -> 3616 | N9: =SUM(N109,N137) -> 5188 | O9: =SUM(O109,O137) -> 8450 | P9: =SUM(P109,P137) -> 14874 | Q9: =SUM(Q109,Q137) -> 16368 | ... AG9: =SUM(AG109,AG137) -> 29684 | AI9: 17469 | AK9: 14537 | AL9: 23007.097 | AM9: 17104.974 | AN9: 8804 | AO9: 10773 | AP9: 12038 | AQ9: 13322 | AR9: =SUM(AR109,AR137) -> 10808.036 | AS9: =SUM(AS109,AS137) -> 10944.536 | AT9: =SUM(AT109,AT137) -> 12864.252 | AU9: =SUM(AU109,AU137) -> 13834.627 | AV9: =SUM(AV109,AV137) -> 11381.454 | AW9: =SUM(AW109,AW137) -> 11244.662 | AX9: =SUM(AX109,AX137) -> 10558.126 | AY9: =SUM(AY109,AY137) -> 10469.999
G10: INTEL | J10: =J109/J9 -> 0.31638418 | K10: =K109/K9 -> 0.40114517 | L10: =L109/L9 -> 0.39896194 | M10: =M109/M9 -> 0.54120575 | N10: =N109/N9 -> 0.47841172 | O10: =O109/O9 -> 0.66426036 | P10: =P109/P9 -> 0.82546726 | Q10: =Q109/Q9 -> 0.81433284 | ... AG10: =AG109/AG9 -> 0.70307236 | AI10: 0.61938291 | AK10: 0.49205476 | AL10: 0.45638092 | AM10: 0.49942914 | AN10: 0.44388914 | AO10: 0.41928896 | AP10: 0.42739658 | AQ10: 0.45053295 | AR10: =AR109/AR9 -> 0.5151425 | AS10: =AS109/AS9 -> 0.5125095 | AT10: =AT109/AT9 -> 0.47907983 | AU10: =AU109/AU9 -> 0.42253464 | AV10: =AV109/AV9 -> 0.44172594 | AW10: =AW109/AW9 -> 0.43150941 | AX10: =AX109/AX9 -> 0.4145289 | AY10: =AY109/AY9 -> 0.41477591
G11: AMD | J11: =J137/J9 -> 0.68361582 | K11: =K137/K9 -> 0.59885483 | L11: =L137/L9 -> 0.60103806 | M11: =M137/M9 -> 0.45879425 | N11: =N137/N9 -> 0.52158828 | O11: =O137/O9 -> 0.33573964 | P11: =P137/P9 -> 0.17453274 | Q11: =Q137/Q9 -> 0.18566716 | ... AG11: =AG137/AG9 -> 0.29692764 | AI11: 0.38061709 | AK11: 0.50794524 | AL11: 0.54361908 | AM11: 0.50057086 | AN11: 0.55611086 | AO11: 0.58071104 | AP11: 0.57260342 | AQ11: 0.54946705 | AR11: =AR137/AR9 -> 0.4848575 | AS11: =AS137/AS9 -> 0.4874905 | AT11: =AT137/AT9 -> 0.52092017 | AU11: =AU137/AU9 -> 0.57746536 | AV11: =AV137/AV9 -> 0.55827406 | AW11: =AW137/AW9 -> 0.56849059 | AX11: =AX137/AX9 -> 0.5854711 | AY11: =AY137/AY9 -> 0.58522409
G12: MB | J12: =SUM(J156,J173) -> 1088 | K12: =SUM(K156,K173) -> 850 | L12: =SUM(L156,L173) -> 876 | M12: =SUM(M156,M173) -> 848 | N12: =SUM(N156,N173) -> 1409 | O12: =SUM(O156,O173) -> 1111 | P12: =SUM(P156,P173) -> 1021 | Q12: =SUM(Q156,Q173) -> 1045 | ... AG12: =SUM(AG156,AG173) -> 20166 | AI12: 18689 | AK12: 11665 | AL12: 17879.032 | AM12: 17151.097 | AN12: 7550 | AO12: 9538 | AP12: 10983 | AQ12: 12577 | AR12: =SUM(AR156,AR173) -> 7079.4643 | AS12: =SUM(AS156,AS173) -> 9270.5 | AT12: =SUM(AT156,AT173) -> 12870.718 | AU12: =SUM(AU156,AU173) -> 13944.316 | AV12: =SUM(AV156,AV173) -> 11591.125 | AW12: =SUM(AW156,AW173) -> 11607.486 | AX12: =SUM(AX156,AX173) -> 10961.328 | AY12: =SUM(AY156,AY173) -> 10861.231
G13: INTEL | J13: =J156/J12 -> 0 | K13: =K156/K12 -> 0 | L13: =L156/L12 -> 0 | M13: =M156/M12 -> 0 | N13: =N156/N12 -> 0 | O13: =O156/O12 -> 0 | P13: =P156/P12 -> 0 | Q13: =Q156/Q12 -> 0 | ... AG13: =AG156/AG12 -> 0.74233859 | AI13: 0.56642945 | AK13: 0.60385769 | AL13: 0.5797023 | AM13: 0.48893181 | AN13: 0.51443709 | AO13: 0.46246593 | AP13: 0.37558044 | AQ13: 0.39095174 | AR13: =AR156/AR12 -> 0.27120696 | AS13: =AS156/AS12 -> 0.44380408 | AT13: =AT156/AT12 -> 0.47482525 | AU13: =AU156/AU12 -> 0.42690261 | AV13: =AV156/AV12 -> 0.44570703 | AW13: =AW156/AW12 -> 0.44738282 | AX13: =AX156/AX12 -> 0.43057666 | AY13: =AY156/AY12 -> 0.43034087
G14: AMD | J14: =J173/J12 -> 1 | K14: =K173/K12 -> 1 | L14: =L173/L12 -> 1 | M14: =M173/M12 -> 1 | N14: =N173/N12 -> 1 | O14: =O173/O12 -> 1 | P14: =P173/P12 -> 1 | Q14: =Q173/Q12 -> 1 | ... AG14: =AG173/AG12 -> 0.25766141 | AI14: 0.43357055 | AK14: 0.39614231 | AL14: 0.4202977 | AM14: 0.51106819 | AN14: 0.48556291 | AO14: 0.53753407 | AP14: 0.62441956 | AQ14: 0.60904826 | AR14: =AR173/AR12 -> 0.72879304 | AS14: =AS173/AS12 -> 0.55619592 | AT14: =AT173/AT12 -> 0.52517475 | AU14: =AU173/AU12 -> 0.57309739 | AV14: =AV173/AV12 -> 0.55429297 | AW14: =AW173/AW12 -> 0.55261718 | AX14: =AX173/AX12 -> 0.56942334 | AY14: =AY173/AY12 -> 0.56965913
G15: CASE | J15: =J225 -> 3676 | K15: =K225 -> 3935 | L15: =L225 -> 4942 | M15: =M225 -> 8478 | N15: =N225 -> 9476 | O15: =O225 -> 13798 | P15: =P225 -> 14956 | Q15: =Q225 -> 17309 | ... AG15: =AG225 -> 24135 | AI15: 15756 | AK15: 9971 | AL15: 14078.71 | AM15: 17773.5 | AN15: 4564 | AO15: 6683 | AP15: 11409 | AQ15: 13627 | AR15: =AR225 -> 10922.679 | AS15: =AS225 -> 10895.929 | AT15: =AT225 -> 12940.99 | AU15: =AU225 -> 14032.023 | AV15: =AV225 -> 11999.204 | AW15: =AW225 -> 12425.948 | AX15: =AX225 -> 11164.076 | AY15: =AY225 -> 11353.433
G16: 予算 | AT16: =+予算!M3 -> 27062.866 | AU16: =+予算!N3 -> 21647.58 | AV16: =+予算!O3 -> 27533.343 | AW16: =+予算!P3 -> 21879.851 | AX16: =+予算!Q3 -> 20223.643 | AY16: =+予算!R3 -> 21233.239
G17: 予算に対してのCPU差 | AT17: =SUM(AT9-AT16) -> -14198.614 | AU17: =SUM(AU9-AU16) -> -7812.9524 | AV17: =SUM(AV9-AV16) -> -16151.889 | AW17: =SUM(AW9-AW16) -> -10635.19 | AX17: =SUM(AX9-AX16) -> -9665.5174 | AY17: =SUM(AY9-AY16) -> -10763.24
G18: 予算に対してのMB差 | AT18: =+AT12-AT16 -> -14192.148 | AU18: =+AU12-AU16 -> -7703.2635 | AV18: =+AV12-AV16 -> -15942.218 | AW18: =+AW12-AW16 -> -10272.365 | AX18: =+AX12-AX16 -> -9262.315 | AY18: =+AY12-AY16 -> -10372.007
G19: 予算に対してのケース差 | J19: 41期→ | AT19: =+AT15-AT16 -> -14121.876 | AU19: =+AU15-AU16 -> -7615.5571 | AV19: =+AV15-AV16 -> -15534.139 | AW19: =+AW15-AW16 -> -9453.9036 | AX19: =+AX15-AX16 -> -9059.5673 | AY19: =+AY15-AY16 -> -9879.8054
A20: 現在庫 | B20: 発注済 | C20: FCST | D20: 合計 | E20: 差分 | G20: 識別子1 | H20: コン | I20: コマ | J20: 8月 | K20: 9月 | L20: 10月 | M20: 11月 | N20: 12月 | O20: 1月 | P20: 2月 | Q20: 3月 | R20: 4月 | S20: 5月 | T20: 6月 | U20: 7月 | V20: 8月 | W20: 9月 | X20: 10月 | Y20: 11月 | Z20: 12月 | AA20: 1月 | AB20: 2月 | AC20: 3月 | AD20: 4月 | AE20: 5月 | AF20: 6月 | AG20: 7月 | AH20: 8月 | AI20: ９月 | AJ20: 10月 | AK20: 11月 | AL20: 12月 | AM20: 1月 | AN20: 2月 | AO20: 3月 | AP20: 4月 | AQ20: 5月 | AR20: 当月結果 | AS20: 当月見込 | AT20: 6月 | AU20: 7月 | AV20: 8月 | AW20: 9月 | AX20: 10月 | AY20: 11月
A21: =SUMIFS(SAP貼付!K:K,SAP貼付!C:C,全体!G21) -> 451 | B21: =SUMIFS(VGAMBFCST貼付!D:D,VGAMBFCST貼付!B:B,G21,VGAMBFCST貼付!C:C,全体!$B$20) -> 445 | C21: =SUMIFS(VGAMBFCST貼付!D:D,VGAMBFCST貼付!B:B,G21,VGAMBFCST貼付!C:C,全体!$C$20) -> 0 | D21: =SUM(A21:C21) -> 896 | E21: =IFERROR(D21-SUM(AT21:AV21)," ") -> 706.33909 | G21: RTX5090 | H21: =IFERROR(IF(MATCH($G21,コンシューマー!B:B,0),"Y"),"-") -> Y | I21: =IFERROR(IF(MATCH($G21,コマーシャル!B:B,0),"Y"),"-") -> Y | J21: =SUMIF(コンシューマー!$B:$B,全体!$G21,コンシューマー!D:D) -> 0 | K21: =SUMIF(コンシューマー!$B:$B,全体!$G21,コンシューマー!E:E) -> 0 | L21: =SUMIF(コンシューマー!$B:$B,全体!$G21,コンシューマー!F:F) -> 0 | M21: =SUMIF(コンシューマー!$B:$B,全体!$G21,コンシューマー!G:G) -> 0 | N21: =SUMIF(コンシューマー!$B:$B,全体!$G21,コンシューマー!H:H) -> 0 | O21: =SUMIF(コンシューマー!$B:$B,全体!$G21,コンシューマー!I:I) -> 0 | P21: =SUMIF(コンシューマー!$B:$B,全体!$G21,コンシューマー!J:J) -> 0 | Q21: =SUMIF(コンシューマー!$B:$B,全体!$G21,コンシューマー!K:K) -> 0 | R21: =SUMIF(コンシューマー!$B:$B,全体!$G21,コンシューマー!L:L) -> 0 | S21: =SUMIF(コンシューマー!$B:$B,全体!$G21,コンシューマー!M:M) -> 0 | T21: =SUMIF(コンシューマー!$B:$B,全体!$G21,コンシューマー!N:N) -> 0 | U21: =SUMIF(コンシューマー!$B:$B,全体!$G21,コンシューマー!O:O) -> 0 | V21: =SUMIF(コンシューマー!$B:$B,全体!$G21,コンシューマー!P:P) -> 0 | W21: =SUMIF(コンシューマー!$B:$B,全体!$G21,コンシューマー!Q:Q) -> 0 | X21: =SUMIF(コンシューマー!$B:$B,全体!$G21,コンシューマー!R:R) -> 0 | Y21: =SUMIF(コンシューマー!$B:$B,全体!$G21,コンシューマー!S:S) -> 0 | Z21: =SUMIF(コンシューマー!$B:$B,全体!$G21,コンシューマー!T:T) -> 0 | AA21: =SUMIF(コンシューマー!$B:$B,全体!$G21,コンシューマー!U:U) -> 0 | AB21: =SUMIF(コンシューマー!$B:$B,全体!$G21,コンシューマー!V:V) -> 40 | AC21: =SUMIF(コンシューマー!$B:$B,全体!$G21,コンシューマー!W:W) -> 144 | AD21: =SUMIF(コンシューマー!$B:$B,全体!$G21,コンシューマー!X:X) -> 92 | AE21: =SUMIF(コンシューマー!$B:$B,全体!$G21,コンシューマー!Y:Y) -> 113 | AF21: =SUMIF(コンシューマー!$B:$B,全体!$G21,コンシューマー!Z:Z) -> 109 | AG21: =SUMIF(コンシューマー!$B:$B,全体!$G21,コンシューマー!AA:AA) -> 175 | AI21: 97 | AK21: 144 | AL21: 224.51613 | AM21: 229.99333 | AN21: 61 | AO21: 89 | AP21: 78 | AQ21: 68 | AR21: =SUMIF(結果貼付!$A:$A,G21,結果貼付!$D:$D) -> 29 | AS21: =(AR21/AS$2)*AS$1 -> 62.142857 | AT21: =SUM(SUMIF(コンシューマー!$B:$B,全体!$G21,コンシューマー!AO:AO),SUMIF(コマーシャル!$B:$B,全体!$G21,コマーシャル!AK:AK)) -> 75 | AU21: =SUM(SUMIF(コンシューマー!$B:$B,全体!$G21,コンシューマー!AP:AP),SUMIF(コマーシャル!$B:$B,全体!$G21,コマーシャル!AL:AL)) -> 60 | AV21: =SUM(SUMIF(コンシューマー!$B:$B,全体!$G21,コンシューマー!AQ:AQ),SUMIF(コマーシャル!$B:$B,全体!$G21,コマーシャル!AM:AM)) -> 54.660911 | AW21: =SUM(SUMIF(コンシューマー!$B:$B,全体!$G21,コンシューマー!AR:AR),SUMIF(コマーシャル!$B:$B,全体!$G21,コマーシャル!AN:AN)) -> 54.074814 | AX21: =SUM(SUMIF(コンシューマー!$B:$B,全体!$G21,コンシューマー!AS:AS),SUMIF(コマーシャル!$B:$B,全体!$G21,コマーシャル!AO:AO)) -> 55.18726 | AY21: =SUM(SUMIF(コンシューマー!$B:$B,全体!$G21,コンシューマー!AT:AT),SUMIF(コマーシャル!$B:$B,全体!$G21,コマーシャル!AP:AP)) -> 54.960392
A22: =SUMIFS(SAP貼付!K:K,SAP貼付!C:C,全体!G22) -> 246 | B22: =SUMIFS(VGAMBFCST貼付!D:D,VGAMBFCST貼付!B:B,G22,VGAMBFCST貼付!C:C,全体!$B$20) -> 4739 | C22: =SUMIFS(VGAMBFCST貼付!D:D,VGAMBFCST貼付!B:B,G22,VGAMBFCST貼付!C:C,全体!$C$20) -> 3500 | D22: =SUM(A22:C22) -> 8485 | E22: =IFERROR(D22-SUM(AT22:AV22)," ") -> 5582.416 | G22: RTX5080 | H22: =IFERROR(IF(MATCH($G22,コンシューマー!B:B,0),"Y"),"-") -> Y | I22: =IFERROR(IF(MATCH($G22,コマーシャル!B:B,0),"Y"),"-") -> Y | J22: =SUMIF(コンシューマー!$B:$B,全体!$G22,コンシューマー!D:D) -> 0 | K22: =SUMIF(コンシューマー!$B:$B,全体!$G22,コンシューマー!E:E) -> 0 | L22: =SUMIF(コンシューマー!$B:$B,全体!$G22,コンシューマー!F:F) -> 0 | M22: =SUMIF(コンシューマー!$B:$B,全体!$G22,コンシューマー!G:G) -> 0 | N22: =SUMIF(コンシューマー!$B:$B,全体!$G22,コンシューマー!H:H) -> 0 | O22: =SUMIF(コンシューマー!$B:$B,全体!$G22,コンシューマー!I:I) -> 0 | P22: =SUMIF(コンシューマー!$B:$B,全体!$G22,コンシューマー!J:J) -> 0 | Q22: =SUMIF(コンシューマー!$B:$B,全体!$G22,コンシューマー!K:K) -> 0 | R22: =SUMIF(コンシューマー!$B:$B,全体!$G22,コンシューマー!L:L) -> 0 | S22: =SUMIF(コンシューマー!$B:$B,全体!$G22,コンシューマー!M:M) -> 0 | T22: =SUMIF(コンシューマー!$B:$B,全体!$G22,コンシューマー!N:N) -> 0 | U22: =SUMIF(コンシューマー!$B:$B,全体!$G22,コンシューマー!O:O) -> 0 | V22: =SUMIF(コンシューマー!$B:$B,全体!$G22,コンシューマー!P:P) -> 0 | W22: =SUMIF(コンシューマー!$B:$B,全体!$G22,コンシューマー!Q:Q) -> 0 | X22: =SUMIF(コンシューマー!$B:$B,全体!$G22,コンシューマー!R:R) -> 0 | Y22: =SUMIF(コンシューマー!$B:$B,全体!$G22,コンシューマー!S:S) -> 0 | Z22: =SUMIF(コンシューマー!$B:$B,全体!$G22,コンシューマー!T:T) -> 0 | AA22: =SUMIF(コンシューマー!$B:$B,全体!$G22,コンシューマー!U:U) -> 0 | AB22: =SUMIF(コンシューマー!$B:$B,全体!$G22,コンシューマー!V:V) -> 1175 | AC22: =SUMIF(コンシューマー!$B:$B,全体!$G22,コンシューマー!W:W) -> 725 | AD22: =SUMIF(コンシューマー!$B:$B,全体!$G22,コンシューマー!X:X) -> 628 | AE22: =SUMIF(コンシューマー!$B:$B,全体!$G22,コンシューマー!Y:Y) -> 511 | AF22: =SUMIF(コンシューマー!$B:$B,全体!$G22,コンシューマー!Z:Z) -> 495 | AG22: =SUMIF(コンシューマー!$B:$B,全体!$G22,コンシューマー!AA:AA) -> 986 | AI22: 395 | AK22: 514 | AL22: 970.64516 | AM22: 701.47833 | AN22: 326 | AO22: 216 | AP22: 539 | AQ22: 761 | AR22: =SUMIF(結果貼付!$A:$A,G22,結果貼付!$D:$D) -> 283 | AS22: =(AR22/AS$2)*AS$1 -> 606.42857 | AT22: =SUM(SUMIF(コンシューマー!$B:$B,全体!$G22,コンシューマー!AO:AO),SUMIF(コマーシャル!$B:$B,全体!$G22,コマーシャル!AK:AK)) -> 935.72 | AU22: =SUM(SUMIF(コンシューマー!$B:$B,全体!$G22,コンシューマー!AP:AP),SUMIF(コマーシャル!$B:$B,全体!$G22,コマーシャル!AL:AL)) -> 1115.864 | AV22: =SUM(SUMIF(コンシューマー!$B:$B,全体!$G22,コンシューマー!AQ:AQ),SUMIF(コマーシャル!$B:$B,全体!$G22,コマーシャル!AM:AM)) -> 851 | AW22: =SUM(SUMIF(コンシューマー!$B:$B,全体!$G22,コンシューマー!AR:AR),SUMIF(コマーシャル!$B:$B,全体!$G22,コマーシャル!AN:AN)) -> 834.87593 | AX22: =SUM(SUMIF(コンシューマー!$B:$B,全体!$G22,コンシューマー!AS:AS),SUMIF(コマーシャル!$B:$B,全体!$G22,コマーシャル!AO:AO)) -> 732.92559 | AY22: =SUM(SUMIF(コンシューマー!$B:$B,全体!$G22,コンシューマー!AT:AT),SUMIF(コマーシャル!$B:$B,全体!$G22,コマーシャル!AP:AP)) -> 726.68425
A23: =SUMIFS(SAP貼付!K:K,SAP貼付!C:C,全体!G23) -> 864 | B23: =SUMIFS(VGAMBFCST貼付!D:D,VGAMBFCST貼付!B:B,G23,VGAMBFCST貼付!C:C,全体!$B$20) -> 5057 | C23: =SUMIFS(VGAMBFCST貼付!D:D,VGAMBFCST貼付!B:B,G23,VGAMBFCST貼付!C:C,全体!$C$20) -> 5543 | D23: =SUM(A23:C23) -> 11464 | E23: =IFERROR(D23-SUM(AT23:AV23)," ") -> 10534.718 | G23: RTX5070Ti | H23: =IFERROR(IF(MATCH($G23,コンシューマー!B:B,0),"Y"),"-") -> Y | I23: =IFERROR(IF(MATCH($G23,コマーシャル!B:B,0),"Y"),"-") -> Y | J23: =SUMIF(コンシューマー!$B:$B,全体!$G23,コンシューマー!D:D) -> 0 | K23: =SUMIF(コンシューマー!$B:$B,全体!$G23,コンシューマー!E:E) -> 0 | L23: =SUMIF(コンシューマー!$B:$B,全体!$G23,コンシューマー!F:F) -> 0 | M23: =SUMIF(コンシューマー!$B:$B,全体!$G23,コンシューマー!G:G) -> 0 | N23: =SUMIF(コンシューマー!$B:$B,全体!$G23,コンシューマー!H:H) -> 0 | O23: =SUMIF(コンシューマー!$B:$B,全体!$G23,コンシューマー!I:I) -> 0 | P23: =SUMIF(コンシューマー!$B:$B,全体!$G23,コンシューマー!J:J) -> 0 | Q23: =SUMIF(コンシューマー!$B:$B,全体!$G23,コンシューマー!K:K) -> 0 | R23: =SUMIF(コンシューマー!$B:$B,全体!$G23,コンシューマー!L:L) -> 0 | S23: =SUMIF(コンシューマー!$B:$B,全体!$G23,コンシューマー!M:M) -> 0 | T23: =SUMIF(コンシューマー!$B:$B,全体!$G23,コンシューマー!N:N) -> 0 | U23: =SUMIF(コンシューマー!$B:$B,全体!$G23,コンシューマー!O:O) -> 0 | V23: =SUMIF(コンシューマー!$B:$B,全体!$G23,コンシューマー!P:P) -> 0 | W23: =SUMIF(コンシューマー!$B:$B,全体!$G23,コンシューマー!Q:Q) -> 0 | X23: =SUMIF(コンシューマー!$B:$B,全体!$G23,コンシューマー!R:R) -> 0 | Y23: =SUMIF(コンシューマー!$B:$B,全体!$G23,コンシューマー!S:S) -> 0 | Z23: =SUMIF(コンシューマー!$B:$B,全体!$G23,コンシューマー!T:T) -> 0 | AA23: =SUMIF(コンシューマー!$B:$B,全体!$G23,コンシューマー!U:U) -> 0 | AB23: =SUMIF(コンシューマー!$B:$B,全体!$G23,コンシューマー!V:V) -> 0 | AC23: =SUMIF(コンシューマー!$B:$B,全体!$G23,コンシューマー!W:W) -> 1480 | AD23: =SUMIF(コンシューマー!$B:$B,全体!$G23,コンシューマー!X:X) -> 1588 | AE23: =SUMIF(コンシューマー!$B:$B,全体!$G23,コンシューマー!Y:Y) -> 1062 | AF23: =SUMIF(コンシューマー!$B:$B,全体!$G23,コンシューマー!Z:Z) -> 1178 | AG23: =SUMIF(コンシューマー!$B:$B,全体!$G23,コンシューマー!AA:AA) -> 2495 | AI23: 769 | AK23: 837 | AL23: 1863.871 | AM23: 1393.3883 | AN23: 585 | AO23: 426 | AP23: 275 | AQ23: 218 | AR23: =SUMIF(結果貼付!$A:$A,G23,結果貼付!$D:$D) -> 80 | AS23: =(AR23/AS$2)*AS$1 -> 171.42857 | AT23: =SUM(SUMIF(コンシューマー!$B:$B,全体!$G23,コンシューマー!AO:AO),SUMIF(コマーシャル!$B:$B,全体!$G23,コマーシャル!AK:AK)) -> 289.54528 | AU23: =SUM(SUMIF(コンシューマー!$B:$B,全体!$G23,コンシューマー!AP:AP),SUMIF(コマーシャル!$B:$B,全体!$G23,コマーシャル!AL:AL)) -> 345.45433 | AV23: =SUM(SUMIF(コンシューマー!$B:$B,全体!$G23,コンシューマー!AQ:AQ),SUMIF(コマーシャル!$B:$B,全体!$G23,コマーシャル!AM:AM)) -> 294.28231 | AW23: =SUM(SUMIF(コンシューマー!$B:$B,全体!$G23,コンシューマー!AR:AR),SUMIF(コマーシャル!$B:$B,全体!$G23,コマーシャル!AN:AN)) -> 288.66493 | AX23: =SUM(SUMIF(コンシューマー!$B:$B,全体!$G23,コンシューマー!AS:AS),SUMIF(コマーシャル!$B:$B,全体!$G23,コマーシャル!AO:AO)) -> 211 | AY23: =SUM(SUMIF(コンシューマー!$B:$B,全体!$G23,コンシューマー!AT:AT),SUMIF(コマーシャル!$B:$B,全体!$G23,コマーシャル!AP:AP)) -> 209.18955
A24: =SUMIFS(SAP貼付!K:K,SAP貼付!C:C,全体!G24) -> 70 | B24: =SUMIFS(VGAMBFCST貼付!D:D,VGAMBFCST貼付!B:B,G24,VGAMBFCST貼付!C:C,全体!$B$20) -> 10313 | C24: =SUMIFS(VGAMBFCST貼付!D:D,VGAMBFCST貼付!B:B,G24,VGAMBFCST貼付!C:C,全体!$C$20) -> 6200 | D24: =SUM(A24:C24) -> 16583 | E24: =IFERROR(D24-SUM(AT24:AV24)," ") -> 4241.4 | G24: RTX5070 | H24: =IFERROR(IF(MATCH($G24,コンシューマー!B:B,0),"Y"),"-") -> Y | I24: =IFERROR(IF(MATCH($G24,コマーシャル!B:B,0),"Y"),"-") -> Y | J24: =SUMIF(コンシューマー!$B:$B,全体!$G24,コンシューマー!D:D) -> 0 | K24: =SUMIF(コンシューマー!$B:$B,全体!$G24,コンシューマー!E:E) -> 0 | L24: =SUMIF(コンシューマー!$B:$B,全体!$G24,コンシューマー!F:F) -> 0 | M24: =SUMIF(コンシューマー!$B:$B,全体!$G24,コンシューマー!G:G) -> 0 | N24: =SUMIF(コンシューマー!$B:$B,全体!$G24,コンシューマー!H:H) -> 0 | O24: =SUMIF(コンシューマー!$B:$B,全体!$G24,コンシューマー!I:I) -> 0 | P24: =SUMIF(コンシューマー!$B:$B,全体!$G24,コンシューマー!J:J) -> 0 | Q24: =SUMIF(コンシューマー!$B:$B,全体!$G24,コンシューマー!K:K) -> 0 | R24: =SUMIF(コンシューマー!$B:$B,全体!$G24,コンシューマー!L:L) -> 0 | S24: =SUMIF(コンシューマー!$B:$B,全体!$G24,コンシューマー!M:M) -> 0 | T24: =SUMIF(コンシューマー!$B:$B,全体!$G24,コンシューマー!N:N) -> 0 | U24: =SUMIF(コンシューマー!$B:$B,全体!$G24,コンシューマー!O:O) -> 0 | V24: =SUMIF(コンシューマー!$B:$B,全体!$G24,コンシューマー!P:P) -> 0 | W24: =SUMIF(コンシューマー!$B:$B,全体!$G24,コンシューマー!Q:Q) -> 0 | X24: =SUMIF(コンシューマー!$B:$B,全体!$G24,コンシューマー!R:R) -> 0 | Y24: =SUMIF(コンシューマー!$B:$B,全体!$G24,コンシューマー!S:S) -> 0 | Z24: =SUMIF(コンシューマー!$B:$B,全体!$G24,コンシューマー!T:T) -> 0 | AA24: =SUMIF(コンシューマー!$B:$B,全体!$G24,コンシューマー!U:U) -> 0 | AB24: =SUMIF(コンシューマー!$B:$B,全体!$G24,コンシューマー!V:V) -> 0 | AC24: =SUMIF(コンシューマー!$B:$B,全体!$G24,コンシューマー!W:W) -> 3854 | AD24: =SUMIF(コンシューマー!$B:$B,全体!$G24,コンシューマー!X:X) -> 4592 | AE24: =SUMIF(コンシューマー!$B:$B,全体!$G24,コンシューマー!Y:Y) -> 3139 | AF24: =SUMIF(コンシューマー!$B:$B,全体!$G24,コンシューマー!Z:Z) -> 3271 | AG24: =SUMIF(コンシューマー!$B:$B,全体!$G24,コンシューマー!AA:AA) -> 4684 | AI24: 3815 | AK24: 3730 | AL24: 6454.8387 | AM24: 3964.1558 | AN24: 1755 | AO24: 2128 | AP24: 3054 | AQ24: 4665 | AR24: =SUMIF(結果貼付!$A:$A,G24,結果貼付!$D:$D) -> 1529 | AS24: =(AR24/AS$2)*AS$1 -> 3276.4286 | AT24: =SUM(SUMIF(コンシューマー!$B:$B,全体!$G24,コンシューマー!AO:AO),SUMIF(コマーシャル!$B:$B,全体!$G24,コマーシャル!AK:AK)) -> 3888 | AU24: =SUM(SUMIF(コンシューマー!$B:$B,全体!$G24,コンシューマー!AP:AP),SUMIF(コマーシャル!$B:$B,全体!$G24,コマーシャル!AL:AL)) -> 4621.6 | AV24: =SUM(SUMIF(コンシューマー!$B:$B,全体!$G24,コンシューマー!AQ:AQ),SUMIF(コマーシャル!$B:$B,全体!$G24,コマーシャル!AM:AM)) -> 3832 | AW24: =SUM(SUMIF(コンシューマー!$B:$B,全体!$G24,コンシューマー!AR:AR),SUMIF(コマーシャル!$B:$B,全体!$G24,コマーシャル!AN:AN)) -> 3591 | AX24: =SUM(SUMIF(コンシューマー!$B:$B,全体!$G24,コンシューマー!AS:AS),SUMIF(コマーシャル!$B:$B,全体!$G24,コマーシャル!AO:AO)) -> 3300 | AY24: =SUM(SUMIF(コンシューマー!$B:$B,全体!$G24,コンシューマー!AT:AT),SUMIF(コマーシャル!$B:$B,全体!$G24,コマーシャル!AP:AP)) -> 3271.2669
E25: =IFERROR(D25-SUM(AT25:AV25)," ") -> -222.63776 | G25: RTX5070 WH | H25: =IFERROR(IF(MATCH($G25,コンシューマー!B:B,0),"Y"),"-") -> Y | I25: =IFERROR(IF(MATCH($G25,コマーシャル!B:B,0),"Y"),"-") -> - | J25: =SUMIF(コンシューマー!$B:$B,全体!$G25,コンシューマー!D:D) -> 0 | K25: =SUMIF(コンシューマー!$B:$B,全体!$G25,コンシューマー!E:E) -> 0 | L25: =SUMIF(コンシューマー!$B:$B,全体!$G25,コンシューマー!F:F) -> 0 | M25: =SUMIF(コンシューマー!$B:$B,全体!$G25,コンシューマー!G:G) -> 0 | N25: =SUMIF(コンシューマー!$B:$B,全体!$G25,コンシューマー!H:H) -> 0 | O25: =SUMIF(コンシューマー!$B:$B,全体!$G25,コンシューマー!I:I) -> 0 | P25: =SUMIF(コンシューマー!$B:$B,全体!$G25,コンシューマー!J:J) -> 0 | Q25: =SUMIF(コンシューマー!$B:$B,全体!$G25,コンシューマー!K:K) -> 0 | R25: =SUMIF(コンシューマー!$B:$B,全体!$G25,コンシューマー!L:L) -> 0 | S25: =SUMIF(コンシューマー!$B:$B,全体!$G25,コンシューマー!M:M) -> 0 | T25: =SUMIF(コンシューマー!$B:$B,全体!$G25,コンシューマー!N:N) -> 0 | U25: =SUMIF(コンシューマー!$B:$B,全体!$G25,コンシューマー!O:O) -> 0 | V25: =SUMIF(コンシューマー!$B:$B,全体!$G25,コンシューマー!P:P) -> 0 | W25: =SUMIF(コンシューマー!$B:$B,全体!$G25,コンシューマー!Q:Q) -> 0 | X25: =SUMIF(コンシューマー!$B:$B,全体!$G25,コンシューマー!R:R) -> 0 | Y25: =SUMIF(コンシューマー!$B:$B,全体!$G25,コンシューマー!S:S) -> 0 | Z25: =SUMIF(コンシューマー!$B:$B,全体!$G25,コンシューマー!T:T) -> 0 | AA25: =SUMIF(コンシューマー!$B:$B,全体!$G25,コンシューマー!U:U) -> 0 | AB25: =SUMIF(コンシューマー!$B:$B,全体!$G25,コンシューマー!V:V) -> 0 | AC25: =SUMIF(コンシューマー!$B:$B,全体!$G25,コンシューマー!W:W) -> 0 | AD25: =SUMIF(コンシューマー!$B:$B,全体!$G25,コンシューマー!X:X) -> 0 | AE25: =SUMIF(コンシューマー!$B:$B,全体!$G25,コンシューマー!Y:Y) -> 0 | AF25: =SUMIF(コンシューマー!$B:$B,全体!$G25,コンシューマー!Z:Z) -> 0 | AG25: =SUMIF(コンシューマー!$B:$B,全体!$G25,コンシューマー!AA:AA) -> 0 | AI25: 0 | AK25: 135 | AL25: 94.83871 | AM25: 13.743333 | AN25: 18 | AO25: 81 | AP25: 80 | AQ25: 51 | AR25: =SUMIF(結果貼付!$A:$A,G25,結果貼付!$D:$D) -> 17 | AS25: =(AR25/AS$2)*AS$1 -> 36.428571 | AT25: =SUM(SUMIF(コンシューマー!$B:$B,全体!$G25,コンシューマー!AO:AO),SUMIF(コマーシャル!$B:$B,全体!$G25,コマーシャル!AK:AK)) -> 69.207811 | AU25: =SUM(SUMIF(コンシューマー!$B:$B,全体!$G25,コンシューマー!AP:AP),SUMIF(コマーシャル!$B:$B,全体!$G25,コマーシャル!AL:AL)) -> 83.049373 | AV25: =SUM(SUMIF(コンシューマー!$B:$B,全体!$G25,コンシューマー!AQ:AQ),SUMIF(コマーシャル!$B:$B,全体!$G25,コマーシャル!AM:AM)) -> 70.380573 | AW25: =SUM(SUMIF(コンシューマー!$B:$B,全体!$G25,コンシューマー!AR:AR),SUMIF(コマーシャル!$B:$B,全体!$G25,コマーシャル!AN:AN)) -> 68.98986 | AX25: =SUM(SUMIF(コンシューマー!$B:$B,全体!$G25,コンシューマー!AS:AS),SUMIF(コマーシャル!$B:$B,全体!$G25,コマーシャル!AO:AO)) -> 59.765318 | AY25: =SUM(SUMIF(コンシューマー!$B:$B,全体!$G25,コンシューマー!AT:AT),SUMIF(コマーシャル!$B:$B,全体!$G25,コマーシャル!AP:AP)) -> 59.226998
A26: =SUMIFS(SAP貼付!K:K,SAP貼付!C:C,全体!G26) -> 0 | B26: =SUMIFS(VGAMBFCST貼付!D:D,VGAMBFCST貼付!B:B,G26,VGAMBFCST貼付!C:C,全体!$B$20) -> 0 | C26: =SUMIFS(VGAMBFCST貼付!D:D,VGAMBFCST貼付!B:B,G26,VGAMBFCST貼付!C:C,全体!$C$20) -> 0 | D26: =SUM(A26:C26) -> 0 | E26: =IFERROR(D26-SUM(AT26:AV26)," ") -> -1429.7205 | G26: RTX5060Ti 16GB | H26: =IFERROR(IF(MATCH($G26,コンシューマー!B:B,0),"Y"),"-") -> Y | I26: =IFERROR(IF(MATCH($G26,コマーシャル!B:B,0),"Y"),"-") -> Y | J26: =SUMIF(コンシューマー!$B:$B,全体!$G26,コンシューマー!D:D) -> 0 | K26: =SUMIF(コンシューマー!$B:$B,全体!$G26,コンシューマー!E:E) -> 0 | L26: =SUMIF(コンシューマー!$B:$B,全体!$G26,コンシューマー!F:F) -> 0 | M26: =SUMIF(コンシューマー!$B:$B,全体!$G26,コンシューマー!G:G) -> 0 | N26: =SUMIF(コンシューマー!$B:$B,全体!$G26,コンシューマー!H:H) -> 0 | O26: =SUMIF(コンシューマー!$B:$B,全体!$G26,コンシューマー!I:I) -> 0 | P26: =SUMIF(コンシューマー!$B:$B,全体!$G26,コンシューマー!J:J) -> 0 | Q26: =SUMIF(コンシューマー!$B:$B,全体!$G26,コンシューマー!K:K) -> 0 | R26: =SUMIF(コンシューマー!$B:$B,全体!$G26,コンシューマー!L:L) -> 0 | S26: =SUMIF(コンシューマー!$B:$B,全体!$G26,コンシューマー!M:M) -> 0 | T26: =SUMIF(コンシューマー!$B:$B,全体!$G26,コンシューマー!N:N) -> 0 | U26: =SUMIF(コンシューマー!$B:$B,全体!$G26,コンシューマー!O:O) -> 0 | V26: =SUMIF(コンシューマー!$B:$B,全体!$G26,コンシューマー!P:P) -> 0 | W26: =SUMIF(コンシューマー!$B:$B,全体!$G26,コンシューマー!Q:Q) -> 0 | X26: =SUMIF(コンシューマー!$B:$B,全体!$G26,コンシューマー!R:R) -> 0 | Y26: =SUMIF(コンシューマー!$B:$B,全体!$G26,コンシューマー!S:S) -> 0 | Z26: =SUMIF(コンシューマー!$B:$B,全体!$G26,コンシューマー!T:T) -> 0 | AA26: =SUMIF(コンシューマー!$B:$B,全体!$G26,コンシューマー!U:U) -> 0 | AB26: =SUMIF(コンシューマー!$B:$B,全体!$G26,コンシューマー!V:V) -> -1 | AC26: =SUMIF(コンシューマー!$B:$B,全体!$G26,コンシューマー!W:W) -> 0 | AD26: =SUMIF(コンシューマー!$B:$B,全体!$G26,コンシューマー!X:X) -> 250 | AE26: =SUMIF(コンシューマー!$B:$B,全体!$G26,コンシューマー!Y:Y) -> 639 | AF26: =SUMIF(コンシューマー!$B:$B,全体!$G26,コンシューマー!Z:Z) -> 1248 | AG26: =SUMIF(コンシューマー!$B:$B,全体!$G26,コンシューマー!AA:AA) -> 1907 | AI26: 1352 | AK26: 1624 | AL26: 3109.3548 | AM26: 1673.41 | AN26: 765 | AO26: 589 | AP26: 462 | AQ26: 302 | AR26: =SUMIF(結果貼付!$A:$A,G26,結果貼付!$D:$D) -> 156 | AS26: =(AR26/AS$2)*AS$1 -> 334.28571 | AT26: =SUM(SUMIF(コンシューマー!$B:$B,全体!$G26,コンシューマー!AO:AO),SUMIF(コマーシャル!$B:$B,全体!$G26,コマーシャル!AK:AK)) -> 452 | AU26: =SUM(SUMIF(コンシューマー!$B:$B,全体!$G26,コンシューマー!AP:AP),SUMIF(コマーシャル!$B:$B,全体!$G26,コマーシャル!AL:AL)) -> 528.4 | AV26: =SUM(SUMIF(コンシューマー!$B:$B,全体!$G26,コンシューマー!AQ:AQ),SUMIF(コマーシャル!$B:$B,全体!$G26,コマーシャル!AM:AM)) -> 449.32046 | AW26: =SUM(SUMIF(コンシューマー!$B:$B,全体!$G26,コンシューマー!AR:AR),SUMIF(コマーシャル!$B:$B,全体!$G26,コマーシャル!AN:AN)) -> 540.63954 | AX26: =SUM(SUMIF(コンシューマー!$B:$B,全体!$G26,コンシューマー!AS:AS),SUMIF(コマーシャル!$B:$B,全体!$G26,コマーシャル!AO:AO)) -> 383.0593 | AY26: =SUM(SUMIF(コンシューマー!$B:$B,全体!$G26,コンシューマー!AT:AT),SUMIF(コマーシャル!$B:$B,全体!$G26,コマーシャル!AP:AP)) -> 379.69907
E27: =IFERROR(D27-SUM(AT27:AV27)," ") -> -8.7308924 | G27: RTX5060Ti 16GB WH | H27: =IFERROR(IF(MATCH($G27,コンシューマー!B:B,0),"Y"),"-") -> Y | I27: =IFERROR(IF(MATCH($G27,コマーシャル!B:B,0),"Y"),"-") -> - | J27: =SUMIF(コンシューマー!$B:$B,全体!$G27,コンシューマー!D:D) -> 0 | K27: =SUMIF(コンシューマー!$B:$B,全体!$G27,コンシューマー!E:E) -> 0 | L27: =SUMIF(コンシューマー!$B:$B,全体!$G27,コンシューマー!F:F) -> 0 | M27: =SUMIF(コンシューマー!$B:$B,全体!$G27,コンシューマー!G:G) -> 0 | N27: =SUMIF(コンシューマー!$B:$B,全体!$G27,コンシューマー!H:H) -> 0 | O27: =SUMIF(コンシューマー!$B:$B,全体!$G27,コンシューマー!I:I) -> 0 | P27: =SUMIF(コンシューマー!$B:$B,全体!$G27,コンシューマー!J:J) -> 0 | Q27: =SUMIF(コンシューマー!$B:$B,全体!$G27,コンシューマー!K:K) -> 0 | R27: =SUMIF(コンシューマー!$B:$B,全体!$G27,コンシューマー!L:L) -> 0 | S27: =SUMIF(コンシューマー!$B:$B,全体!$G27,コンシューマー!M:M) -> 0 | T27: =SUMIF(コンシューマー!$B:$B,全体!$G27,コンシューマー!N:N) -> 0 | U27: =SUMIF(コンシューマー!$B:$B,全体!$G27,コンシューマー!O:O) -> 0 | V27: =SUMIF(コンシューマー!$B:$B,全体!$G27,コンシューマー!P:P) -> 0 | W27: =SUMIF(コンシューマー!$B:$B,全体!$G27,コンシューマー!Q:Q) -> 0 | X27: =SUMIF(コンシューマー!$B:$B,全体!$G27,コンシューマー!R:R) -> 0 | Y27: =SUMIF(コンシューマー!$B:$B,全体!$G27,コンシューマー!S:S) -> 0 | Z27: =SUMIF(コンシューマー!$B:$B,全体!$G27,コンシューマー!T:T) -> 0 | AA27: =SUMIF(コンシューマー!$B:$B,全体!$G27,コンシューマー!U:U) -> 0 | AB27: =SUMIF(コンシューマー!$B:$B,全体!$G27,コンシューマー!V:V) -> 0 | AC27: =SUMIF(コンシューマー!$B:$B,全体!$G27,コンシューマー!W:W) -> 0 | AD27: =SUMIF(コンシューマー!$B:$B,全体!$G27,コンシューマー!X:X) -> 0 | AE27: =SUMIF(コンシューマー!$B:$B,全体!$G27,コンシューマー!Y:Y) -> 0 | AF27: =SUMIF(コンシューマー!$B:$B,全体!$G27,コンシューマー!Z:Z) -> 0 | AG27: =SUMIF(コンシューマー!$B:$B,全体!$G27,コンシューマー!AA:AA) -> 0 | AI27: 1 | AK27: 33 | AL27: 116.12903 | AM27: 49.083333 | AN27: 38 | AO27: 13 | AP27: 15 | AQ27: 2 | AR27: =SUMIF(結果貼付!$A:$A,G27,結果貼付!$D:$D) -> 1 | AS27: =(AR27/AS$2)*AS$1 -> 2.1428571 | AT27: =SUM(SUMIF(コンシューマー!$B:$B,全体!$G27,コンシューマー!AO:AO),SUMIF(コマーシャル!$B:$B,全体!$G27,コマーシャル!AK:AK)) -> 2.7140318 | AU27: =SUM(SUMIF(コンシューマー!$B:$B,全体!$G27,コンシューマー!AP:AP),SUMIF(コマーシャル!$B:$B,全体!$G27,コマーシャル!AL:AL)) -> 3.2568382 | AV27: =SUM(SUMIF(コンシューマー!$B:$B,全体!$G27,コンシューマー!AQ:AQ),SUMIF(コマーシャル!$B:$B,全体!$G27,コマーシャル!AM:AM)) -> 2.7600225 | AW27: =SUM(SUMIF(コンシューマー!$B:$B,全体!$G27,コンシューマー!AR:AR),SUMIF(コマーシャル!$B:$B,全体!$G27,コマーシャル!AN:AN)) -> 2.7054847 | AX27: =SUM(SUMIF(コンシューマー!$B:$B,全体!$G27,コンシューマー!AS:AS),SUMIF(コマーシャル!$B:$B,全体!$G27,コマーシャル!AO:AO)) -> 2.343738 | AY27: =SUM(SUMIF(コンシューマー!$B:$B,全体!$G27,コンシューマー!AT:AT),SUMIF(コマーシャル!$B:$B,全体!$G27,コマーシャル!AP:AP)) -> 2.3226274
A28: =SUMIFS(SAP貼付!K:K,SAP貼付!C:C,全体!G28) -> 0 | B28: =SUMIFS(VGAMBFCST貼付!D:D,VGAMBFCST貼付!B:B,G28,VGAMBFCST貼付!C:C,全体!$B$20) -> 0 | C28: =SUMIFS(VGAMBFCST貼付!D:D,VGAMBFCST貼付!B:B,G28,VGAMBFCST貼付!C:C,全体!$C$20) -> 0 | D28: =SUM(A28:C28) -> 0 | E28: =IFERROR(D28-SUM(AT28:AV28)," ") -> -6455 | G28: RTX5060Ti 8GB | H28: =IFERROR(IF(MATCH($G28,コンシューマー!B:B,0),"Y"),"-") -> Y | I28: =IFERROR(IF(MATCH($G28,コマーシャル!B:B,0),"Y"),"-") -> Y | J28: =SUMIF(コンシューマー!$B:$B,全体!$G28,コンシューマー!D:D) -> 0 | K28: =SUMIF(コンシューマー!$B:$B,全体!$G28,コンシューマー!E:E) -> 0 | L28: =SUMIF(コンシューマー!$B:$B,全体!$G28,コンシューマー!F:F) -> 0 | M28: =SUMIF(コンシューマー!$B:$B,全体!$G28,コンシューマー!G:G) -> 0 | N28: =SUMIF(コンシューマー!$B:$B,全体!$G28,コンシューマー!H:H) -> 0 | O28: =SUMIF(コンシューマー!$B:$B,全体!$G28,コンシューマー!I:I) -> 0 | P28: =SUMIF(コンシューマー!$B:$B,全体!$G28,コンシューマー!J:J) -> 0 | Q28: =SUMIF(コンシューマー!$B:$B,全体!$G28,コンシューマー!K:K) -> 0 | R28: =SUMIF(コンシューマー!$B:$B,全体!$G28,コンシューマー!L:L) -> 0 | S28: =SUMIF(コンシューマー!$B:$B,全体!$G28,コンシューマー!M:M) -> 0 | T28: =SUMIF(コンシューマー!$B:$B,全体!$G28,コンシューマー!N:N) -> 0 | U28: =SUMIF(コンシューマー!$B:$B,全体!$G28,コンシューマー!O:O) -> 0 | V28: =SUMIF(コンシューマー!$B:$B,全体!$G28,コンシューマー!P:P) -> 0 | W28: =SUMIF(コンシューマー!$B:$B,全体!$G28,コンシューマー!Q:Q) -> 0 | X28: =SUMIF(コンシューマー!$B:$B,全体!$G28,コンシューマー!R:R) -> 0 | Y28: =SUMIF(コンシューマー!$B:$B,全体!$G28,コンシューマー!S:S) -> 0 | Z28: =SUMIF(コンシューマー!$B:$B,全体!$G28,コンシューマー!T:T) -> 0 | AA28: =SUMIF(コンシューマー!$B:$B,全体!$G28,コンシューマー!U:U) -> 0 | AB28: =SUMIF(コンシューマー!$B:$B,全体!$G28,コンシューマー!V:V) -> 0 | AC28: =SUMIF(コンシューマー!$B:$B,全体!$G28,コンシューマー!W:W) -> 0 | AD28: =SUMIF(コンシューマー!$B:$B,全体!$G28,コンシューマー!X:X) -> 46 | AE28: =SUMIF(コンシューマー!$B:$B,全体!$G28,コンシューマー!Y:Y) -> 392 | AF28: =SUMIF(コンシューマー!$B:$B,全体!$G28,コンシューマー!Z:Z) -> 489 | AG28: =SUMIF(コンシューマー!$B:$B,全体!$G28,コンシューマー!AA:AA) -> 997 | AI28: 1116 | AK28: 667 | AL28: 1067.4194 | AM28: 807.91167 | AN28: 584 | AO28: 2870 | AP28: 2133 | AQ28: 2381 | AR28: =SUMIF(結果貼付!$A:$A,G28,結果貼付!$D:$D) -> 569 | AS28: =(AR28/AS$2)*AS$1 -> 1219.2857 | AT28: =SUM(SUMIF(コンシューマー!$B:$B,全体!$G28,コンシューマー!AO:AO),SUMIF(コマーシャル!$B:$B,全体!$G28,コマーシャル!AK:AK)) -> 1842 | AU28: =SUM(SUMIF(コンシューマー!$B:$B,全体!$G28,コンシューマー!AP:AP),SUMIF(コマーシャル!$B:$B,全体!$G28,コマーシャル!AL:AL)) -> 2841 | AV28: =SUM(SUMIF(コンシューマー!$B:$B,全体!$G28,コンシューマー!AQ:AQ),SUMIF(コマーシャル!$B:$B,全体!$G28,コマーシャル!AM:AM)) -> 1772 | AW28: =SUM(SUMIF(コンシューマー!$B:$B,全体!$G28,コンシューマー!AR:AR),SUMIF(コマーシャル!$B:$B,全体!$G28,コマーシャル!AN:AN)) -> 1737.9735 | AX28: =SUM(SUMIF(コンシューマー!$B:$B,全体!$G28,コンシューマー!AS:AS),SUMIF(コマーシャル!$B:$B,全体!$G28,コマーシャル!AO:AO)) -> 1522.2768 | AY28: =SUM(SUMIF(コンシューマー!$B:$B,全体!$G28,コンシューマー!AT:AT),SUMIF(コマーシャル!$B:$B,全体!$G28,コマーシャル!AP:AP)) -> 1509.1057
G29: RTX5060 | H29: =IFERROR(IF(MATCH($G29,コンシューマー!B:B,0),"Y"),"-") -> Y | I29: =IFERROR(IF(MATCH($G29,コマーシャル!B:B,0),"Y"),"-") -> Y | N29: =SUMIF(コンシューマー!$B:$B,全体!$G29,コンシューマー!H:H) -> 0 | O29: =SUMIF(コンシューマー!$B:$B,全体!$G29,コンシューマー!I:I) -> 0 | P29: =SUMIF(コンシューマー!$B:$B,全体!$G29,コンシューマー!J:J) -> 0 | Q29: =SUMIF(コンシューマー!$B:$B,全体!$G29,コンシューマー!K:K) -> 0 | R29: =SUMIF(コンシューマー!$B:$B,全体!$G29,コンシューマー!L:L) -> 0 | S29: =SUMIF(コンシューマー!$B:$B,全体!$G29,コンシューマー!M:M) -> 0 | T29: =SUMIF(コンシューマー!$B:$B,全体!$G29,コンシューマー!N:N) -> 0 | U29: =SUMIF(コンシューマー!$B:$B,全体!$G29,コンシューマー!O:O) -> 0 | V29: =SUMIF(コンシューマー!$B:$B,全体!$G29,コンシューマー!P:P) -> 0 | W29: =SUMIF(コンシューマー!$B:$B,全体!$G29,コンシューマー!Q:Q) -> 0 | X29: =SUMIF(コンシューマー!$B:$B,全体!$G29,コンシューマー!R:R) -> 0 | Y29: =SUMIF(コンシューマー!$B:$B,全体!$G29,コンシューマー!S:S) -> 0 | Z29: =SUMIF(コンシューマー!$B:$B,全体!$G29,コンシューマー!T:T) -> 0 | AA29: =SUMIF(コンシューマー!$B:$B,全体!$G29,コンシューマー!U:U) -> 0 | AB29: =SUMIF(コンシューマー!$B:$B,全体!$G29,コンシューマー!V:V) -> 0 | AC29: =SUMIF(コンシューマー!$B:$B,全体!$G29,コンシューマー!W:W) -> 0 | AD29: =SUMIF(コンシューマー!$B:$B,全体!$G29,コンシューマー!X:X) -> 0 | AE29: =SUMIF(コンシューマー!$B:$B,全体!$G29,コンシューマー!Y:Y) -> 75 | AF29: =SUMIF(コンシューマー!$B:$B,全体!$G29,コンシューマー!Z:Z) -> 477 | AG29: =SUMIF(コンシューマー!$B:$B,全体!$G29,コンシューマー!AA:AA) -> 2556 | AI29: 1877 | AK29: 2497 | AL29: 4282.2581 | AM29: 3787.8933 | AN29: 2661 | AO29: 1623 | AP29: 1178 | AQ29: 984 | AR29: =SUMIF(結果貼付!$A:$A,G29,結果貼付!$D:$D) -> 550 | AS29: =(AR29/AS$2)*AS$1 -> 1178.5714 | AT29: =SUM(SUMIF(コンシューマー!$B:$B,全体!$G29,コンシューマー!AO:AO),SUMIF(コマーシャル!$B:$B,全体!$G29,コマーシャル!AK:AK)) -> 1410 | AU29: =SUM(SUMIF(コンシューマー!$B:$B,全体!$G29,コンシューマー!AP:AP),SUMIF(コマーシャル!$B:$B,全体!$G29,コマーシャル!AL:AL)) -> 1214 | AV29: =SUM(SUMIF(コンシューマー!$B:$B,全体!$G29,コンシューマー!AQ:AQ),SUMIF(コマーシャル!$B:$B,全体!$G29,コマーシャル!AM:AM)) -> 1333 | AW29: =SUM(SUMIF(コンシューマー!$B:$B,全体!$G29,コンシューマー!AR:AR),SUMIF(コマーシャル!$B:$B,全体!$G29,コマーシャル!AN:AN)) -> 1307.6481 | AX29: =SUM(SUMIF(コンシューマー!$B:$B,全体!$G29,コンシューマー!AS:AS),SUMIF(コマーシャル!$B:$B,全体!$G29,コマーシャル!AO:AO)) -> 1149.4896 | AY29: =SUM(SUMIF(コンシューマー!$B:$B,全体!$G29,コンシューマー!AT:AT),SUMIF(コマーシャル!$B:$B,全体!$G29,コマーシャル!AP:AP)) -> 1139.6763
G30: RTX5060 WH | H30: =IFERROR(IF(MATCH($G30,コンシューマー!B:B,0),"Y"),"-") -> Y | I30: =IFERROR(IF(MATCH($G30,コマーシャル!B:B,0),"Y"),"-") -> - | N30: =SUMIF(コンシューマー!$B:$B,全体!$G30,コンシューマー!H:H) -> 0 | O30: =SUMIF(コンシューマー!$B:$B,全体!$G30,コンシューマー!I:I) -> 0 | P30: =SUMIF(コンシューマー!$B:$B,全体!$G30,コンシューマー!J:J) -> 0 | Q30: =SUMIF(コンシューマー!$B:$B,全体!$G30,コンシューマー!K:K) -> 0 | R30: =SUMIF(コンシューマー!$B:$B,全体!$G30,コンシューマー!L:L) -> 0 | S30: =SUMIF(コンシューマー!$B:$B,全体!$G30,コンシューマー!M:M) -> 0 | T30: =SUMIF(コンシューマー!$B:$B,全体!$G30,コンシューマー!N:N) -> 0 | U30: =SUMIF(コンシューマー!$B:$B,全体!$G30,コンシューマー!O:O) -> 0 | V30: =SUMIF(コンシューマー!$B:$B,全体!$G30,コンシューマー!P:P) -> 0 | W30: =SUMIF(コンシューマー!$B:$B,全体!$G30,コンシューマー!Q:Q) -> 0 | X30: =SUMIF(コンシューマー!$B:$B,全体!$G30,コンシューマー!R:R) -> 0 | Y30: =SUMIF(コンシューマー!$B:$B,全体!$G30,コンシューマー!S:S) -> 0 | Z30: =SUMIF(コンシューマー!$B:$B,全体!$G30,コンシューマー!T:T) -> 0 | AA30: =SUMIF(コンシューマー!$B:$B,全体!$G30,コンシューマー!U:U) -> 0 | AB30: =SUMIF(コンシューマー!$B:$B,全体!$G30,コンシューマー!V:V) -> 0 | AC30: =SUMIF(コンシューマー!$B:$B,全体!$G30,コンシューマー!W:W) -> 0 | AD30: =SUMIF(コンシューマー!$B:$B,全体!$G30,コンシューマー!X:X) -> 0 | AE30: =SUMIF(コンシューマー!$B:$B,全体!$G30,コンシューマー!Y:Y) -> 0 | AF30: =SUMIF(コンシューマー!$B:$B,全体!$G30,コンシューマー!Z:Z) -> 0 | AG30: =SUMIF(コンシューマー!$B:$B,全体!$G30,コンシューマー!AA:AA) -> 0 | AI30: 0 | AK30: 26 | AL30: 37.741935 | AM30: 15.706667 | AN30: 10 | AO30: 2 | AP30: 12 | AQ30: 11 | AR30: =SUMIF(結果貼付!$A:$A,G30,結果貼付!$D:$D) -> 4 | AS30: =(AR30/AS$2)*AS$1 -> 8.5714286 | AT30: =SUM(SUMIF(コンシューマー!$B:$B,全体!$G30,コンシューマー!AO:AO),SUMIF(コマーシャル!$B:$B,全体!$G30,コマーシャル!AK:AK)) -> 14.927175 | AU30: =SUM(SUMIF(コンシューマー!$B:$B,全体!$G30,コンシューマー!AP:AP),SUMIF(コマーシャル!$B:$B,全体!$G30,コマーシャル!AL:AL)) -> 17.91261 | AV30: =SUM(SUMIF(コンシューマー!$B:$B,全体!$G30,コンシューマー!AQ:AQ),SUMIF(コマーシャル!$B:$B,全体!$G30,コマーシャル!AM:AM)) -> 15.180124 | AW30: =SUM(SUMIF(コンシューマー!$B:$B,全体!$G30,コンシューマー!AR:AR),SUMIF(コマーシャル!$B:$B,全体!$G30,コマーシャル!AN:AN)) -> 14.880166 | AX30: =SUM(SUMIF(コンシューマー!$B:$B,全体!$G30,コンシューマー!AS:AS),SUMIF(コマーシャル!$B:$B,全体!$G30,コマーシャル!AO:AO)) -> 12.890559 | AY30: =SUM(SUMIF(コンシューマー!$B:$B,全体!$G30,コンシューマー!AT:AT),SUMIF(コマーシャル!$B:$B,全体!$G30,コマーシャル!AP:AP)) -> 12.774451
G31: RTX5050 | H31: =IFERROR(IF(MATCH($G31,コンシューマー!B:B,0),"Y"),"-") -> Y | I31: =IFERROR(IF(MATCH($G31,コマーシャル!B:B,0),"Y"),"-") -> Y | N31: =SUMIF(コンシューマー!$B:$B,全体!$G31,コンシューマー!H:H) -> 0 | O31: =SUMIF(コンシューマー!$B:$B,全体!$G31,コンシューマー!I:I) -> 0 | P31: =SUMIF(コンシューマー!$B:$B,全体!$G31,コンシューマー!J:J) -> 0 | Q31: =SUMIF(コンシューマー!$B:$B,全体!$G31,コンシューマー!K:K) -> 0 | R31: =SUMIF(コンシューマー!$B:$B,全体!$G31,コンシューマー!L:L) -> 0 | S31: =SUMIF(コンシューマー!$B:$B,全体!$G31,コンシューマー!M:M) -> 0 | T31: =SUMIF(コンシューマー!$B:$B,全体!$G31,コンシューマー!N:N) -> 0 | U31: =SUMIF(コンシューマー!$B:$B,全体!$G31,コンシューマー!O:O) -> 0 | V31: =SUMIF(コンシューマー!$B:$B,全体!$G31,コンシューマー!P:P) -> 0 | W31: =SUMIF(コンシューマー!$B:$B,全体!$G31,コンシューマー!Q:Q) -> 0 | X31: =SUMIF(コンシューマー!$B:$B,全体!$G31,コンシューマー!R:R) -> 0 | Y31: =SUMIF(コンシューマー!$B:$B,全体!$G31,コンシューマー!S:S) -> 0 | Z31: =SUMIF(コンシューマー!$B:$B,全体!$G31,コンシューマー!T:T) -> 0 | AA31: =SUMIF(コンシューマー!$B:$B,全体!$G31,コンシューマー!U:U) -> 0 | AB31: =SUMIF(コンシューマー!$B:$B,全体!$G31,コンシューマー!V:V) -> 0 | AC31: =SUMIF(コンシューマー!$B:$B,全体!$G31,コンシューマー!W:W) -> 0 | AD31: =SUMIF(コンシューマー!$B:$B,全体!$G31,コンシューマー!X:X) -> 0 | AE31: =SUMIF(コンシューマー!$B:$B,全体!$G31,コンシューマー!Y:Y) -> 0 | AF31: =SUMIF(コンシューマー!$B:$B,全体!$G31,コンシューマー!Z:Z) -> 0 | AG31: =SUMIF(コンシューマー!$B:$B,全体!$G31,コンシューマー!AA:AA) -> 10 | AI31: 34 | AK31: 76 | AL31: 193.54839 | AM31: 5.89 | AN31: 90 | AO31: 118 | AP31: 139 | AQ31: 87 | AR31: =SUMIF(結果貼付!$A:$A,G31,結果貼付!$D:$D) -> 96 | AS31: =(AR31/AS$2)*AS$1 -> 205.71429 | AT31: =SUM(SUMIF(コンシューマー!$B:$B,全体!$G31,コンシューマー!AO:AO),SUMIF(コマーシャル!$B:$B,全体!$G31,コマーシャル!AK:AK)) -> 260 | AU31: =SUM(SUMIF(コンシューマー!$B:$B,全体!$G31,コンシューマー!AP:AP),SUMIF(コマーシャル!$B:$B,全体!$G31,コマーシャル!AL:AL)) -> 310 | AV31: =SUM(SUMIF(コンシューマー!$B:$B,全体!$G31,コンシューマー!AQ:AQ),SUMIF(コマーシャル!$B:$B,全体!$G31,コマーシャル!AM:AM)) -> 264.23638 | AW31: =SUM(SUMIF(コンシューマー!$B:$B,全体!$G31,コンシューマー!AR:AR),SUMIF(コマーシャル!$B:$B,全体!$G31,コマーシャル!AN:AN)) -> 259.2127 | AX31: =SUM(SUMIF(コンシューマー!$B:$B,全体!$G31,コンシューマー!AS:AS),SUMIF(コマーシャル!$B:$B,全体!$G31,コマーシャル!AO:AO)) -> 225.8908 | AY31: =SUM(SUMIF(コンシューマー!$B:$B,全体!$G31,コンシューマー!AT:AT),SUMIF(コマーシャル!$B:$B,全体!$G31,コマーシャル!AP:AP)) -> 223.94622
A32: =SUMIFS(SAP貼付!K:K,SAP貼付!C:C,全体!G32) -> 6859 | B32: =SUMIFS(VGAMBFCST貼付!D:D,VGAMBFCST貼付!B:B,G32,VGAMBFCST貼付!C:C,全体!$B$20) -> 7035 | C32: =SUMIFS(VGAMBFCST貼付!D:D,VGAMBFCST貼付!B:B,G32,VGAMBFCST貼付!C:C,全体!$C$20) -> 0 | D32: =SUM(A32:C32) -> 13894 | E32: =IFERROR(D32-SUM(#REF!)," ") | G32: RTX4060Ti | H32: =IFERROR(IF(MATCH($G32,コンシューマー!B:B,0),"Y"),"-") -> Y | I32: =IFERROR(IF(MATCH($G32,コマーシャル!B:B,0),"Y"),"-") -> - | J32: =SUMIF(コンシューマー!$B:$B,全体!$G32,コンシューマー!D:D) -> 5947 | K32: =SUMIF(コンシューマー!$B:$B,全体!$G32,コンシューマー!E:E) -> 5107 | L32: =SUMIF(コンシューマー!$B:$B,全体!$G32,コンシューマー!F:F) -> 3821 | M32: =SUMIF(コンシューマー!$B:$B,全体!$G32,コンシューマー!G:G) -> 4902 | N32: =SUMIF(コンシューマー!$B:$B,全体!$G32,コンシューマー!H:H) -> 6782 | O32: =SUMIF(コンシューマー!$B:$B,全体!$G32,コンシューマー!I:I) -> 6634 | P32: =SUMIF(コンシューマー!$B:$B,全体!$G32,コンシューマー!J:J) -> 4651 | Q32: =SUMIF(コンシューマー!$B:$B,全体!$G32,コンシューマー!K:K) -> 5233 | R32: =SUMIF(コンシューマー!$B:$B,全体!$G32,コンシューマー!L:L) -> 4041 | S32: =SUMIF(コンシューマー!$B:$B,全体!$G32,コンシューマー!M:M) -> 3442 | T32: =SUMIF(コンシューマー!$B:$B,全体!$G32,コンシューマー!N:N) -> 3586 | U32: =SUMIF(コンシューマー!$B:$B,全体!$G32,コンシューマー!O:O) -> 4650 | V32: =SUMIF(コンシューマー!$B:$B,全体!$G32,コンシューマー!P:P) -> 2681 | W32: =SUMIF(コンシューマー!$B:$B,全体!$G32,コンシューマー!Q:Q) -> 3179 | X32: =SUMIF(コンシューマー!$B:$B,全体!$G32,コンシューマー!R:R) -> 3887 | Y32: =SUMIF(コンシューマー!$B:$B,全体!$G32,コンシューマー!S:S) -> 2269 | Z32: =SUMIF(コンシューマー!$B:$B,全体!$G32,コンシューマー!T:T) -> 4072 | AA32: =SUMIF(コンシューマー!$B:$B,全体!$G32,コンシューマー!U:U) -> 3080 | AB32: =SUMIF(コンシューマー!$B:$B,全体!$G32,コンシューマー!V:V) -> 7614 | AC32: =SUMIF(コンシューマー!$B:$B,全体!$G32,コンシューマー!W:W) -> 7504 | AD32: =SUMIF(コンシューマー!$B:$B,全体!$G32,コンシューマー!X:X) -> 3452 | AE32: =SUMIF(コンシューマー!$B:$B,全体!$G32,コンシューマー!Y:Y) -> 1306 | AF32: =SUMIF(コンシューマー!$B:$B,全体!$G32,コンシューマー!Z:Z) -> 1454 | AG32: =SUMIF(コンシューマー!$B:$B,全体!$G32,コンシューマー!AA:AA) -> 284 | AI32: 311 | AK32: 33 | AL32: 5.8064516 | AM32: 0 | AN32: 0 | AO32: -2 | AP32: 0 | AQ32: 0 | AR32: =SUMIF(結果貼付!$A:$A,G32,結果貼付!$D:$D) -> -1 | AS32: =(AR32/AS$2)*AS$1 -> -2.1428571 | AT32: =SUM(SUMIF(コンシューマー!$B:$B,全体!$G32,コンシューマー!AO:AO),SUMIF(コマーシャル!$B:$B,全体!$G32,コマーシャル!AK:AK)) -> 0 | AU32: =SUM(SUMIF(コンシューマー!$B:$B,全体!$G32,コンシューマー!AP:AP),SUMIF(コマーシャル!$B:$B,全体!$G32,コマーシャル!AL:AL)) -> 0 | AV32: =SUM(SUMIF(コンシューマー!$B:$B,全体!$G32,コンシューマー!AQ:AQ),SUMIF(コマーシャル!$B:$B,全体!$G32,コマーシャル!AM:AM)) -> 0 | AW32: =SUM(SUMIF(コンシューマー!$B:$B,全体!$G32,コンシューマー!AR:AR),SUMIF(コマーシャル!$B:$B,全体!$G32,コマーシャル!AN:AN)) -> 0 | AX32: =SUM(SUMIF(コンシューマー!$B:$B,全体!$G32,コンシューマー!AS:AS),SUMIF(コマーシャル!$B:$B,全体!$G32,コマーシャル!AO:AO)) -> 0 | AY32: =SUM(SUMIF(コンシューマー!$B:$B,全体!$G32,コンシューマー!AT:AT),SUMIF(コマーシャル!$B:$B,全体!$G32,コマーシャル!AP:AP)) -> 0
A33: =SUMIFS(SAP貼付!K:K,SAP貼付!C:C,全体!G33) -> 14779 | B33: =SUMIFS(VGAMBFCST貼付!D:D,VGAMBFCST貼付!B:B,G33,VGAMBFCST貼付!C:C,全体!$B$20) -> 798 | C33: =SUMIFS(VGAMBFCST貼付!D:D,VGAMBFCST貼付!B:B,G33,VGAMBFCST貼付!C:C,全体!$C$20) -> 0 | D33: =SUM(A33:C33) -> 15577 | E33: =IFERROR(D33-SUM(#REF!)," ") | G33: RTX4060 | H33: =IFERROR(IF(MATCH($G33,コンシューマー!B:B,0),"Y"),"-") -> Y | I33: =IFERROR(IF(MATCH($G33,コマーシャル!B:B,0),"Y"),"-") -> - | J33: =SUMIF(コンシューマー!$B:$B,全体!$G33,コンシューマー!D:D) -> 1389 | K33: =SUMIF(コンシューマー!$B:$B,全体!$G33,コンシューマー!E:E) -> 1578 | L33: =SUMIF(コンシューマー!$B:$B,全体!$G33,コンシューマー!F:F) -> 1454 | M33: =SUMIF(コンシューマー!$B:$B,全体!$G33,コンシューマー!G:G) -> 1777 | N33: =SUMIF(コンシューマー!$B:$B,全体!$G33,コンシューマー!H:H) -> 2661 | O33: =SUMIF(コンシューマー!$B:$B,全体!$G33,コンシューマー!I:I) -> 2951 | P33: =SUMIF(コンシューマー!$B:$B,全体!$G33,コンシューマー!J:J) -> 2018 | Q33: =SUMIF(コンシューマー!$B:$B,全体!$G33,コンシューマー!K:K) -> 2292 | R33: =SUMIF(コンシューマー!$B:$B,全体!$G33,コンシューマー!L:L) -> 2401 | S33: =SUMIF(コンシューマー!$B:$B,全体!$G33,コンシューマー!M:M) -> 1944 | T33: =SUMIF(コンシューマー!$B:$B,全体!$G33,コンシューマー!N:N) -> 2259 | U33: =SUMIF(コンシューマー!$B:$B,全体!$G33,コンシューマー!O:O) -> 3579 | V33: =SUMIF(コンシューマー!$B:$B,全体!$G33,コンシューマー!P:P) -> 2639 | W33: =SUMIF(コンシューマー!$B:$B,全体!$G33,コンシューマー!Q:Q) -> 2412 | X33: =SUMIF(コンシューマー!$B:$B,全体!$G33,コンシューマー!R:R) -> 2315 | Y33: =SUMIF(コンシューマー!$B:$B,全体!$G33,コンシューマー!S:S) -> 1664 | Z33: =SUMIF(コンシューマー!$B:$B,全体!$G33,コンシューマー!T:T) -> 3117 | AA33: =SUMIF(コンシューマー!$B:$B,全体!$G33,コンシューマー!U:U) -> 2469 | AB33: =SUMIF(コンシューマー!$B:$B,全体!$G33,コンシューマー!V:V) -> 3675 | AC33: =SUMIF(コンシューマー!$B:$B,全体!$G33,コンシューマー!W:W) -> 7581 | AD33: =SUMIF(コンシューマー!$B:$B,全体!$G33,コンシューマー!X:X) -> 3789 | AE33: =SUMIF(コンシューマー!$B:$B,全体!$G33,コンシューマー!Y:Y) -> 2482 | AF33: =SUMIF(コンシューマー!$B:$B,全体!$G33,コンシューマー!Z:Z) -> 2589 | AG33: =SUMIF(コンシューマー!$B:$B,全体!$G33,コンシューマー!AA:AA) -> 1271 | AI33: 223 | AK33: 19 | AL33: -0.96774194 | AM33: 21.596667 | AN33: 0 | AO33: 51 | AP33: 0 | AQ33: -1 | AR33: =SUMIF(結果貼付!$A:$A,G33,結果貼付!$D:$D) -> 0 | AS33: =(AR33/AS$2)*AS$1 -> 0 | AT33: =SUM(SUMIF(コンシューマー!$B:$B,全体!$G33,コンシューマー!AO:AO),SUMIF(コマーシャル!$B:$B,全体!$G33,コマーシャル!AK:AK)) -> 0 | AU33: =SUM(SUMIF(コンシューマー!$B:$B,全体!$G33,コンシューマー!AP:AP),SUMIF(コマーシャル!$B:$B,全体!$G33,コマーシャル!AL:AL)) -> 0 | AV33: =SUM(SUMIF(コンシューマー!$B:$B,全体!$G33,コンシューマー!AQ:AQ),SUMIF(コマーシャル!$B:$B,全体!$G33,コマーシャル!AM:AM)) -> 0 | AW33: =SUM(SUMIF(コンシューマー!$B:$B,全体!$G33,コンシューマー!AR:AR),SUMIF(コマーシャル!$B:$B,全体!$G33,コマーシャル!AN:AN)) -> 0 | AX33: =SUM(SUMIF(コンシューマー!$B:$B,全体!$G33,コンシューマー!AS:AS),SUMIF(コマーシャル!$B:$B,全体!$G33,コマーシャル!AO:AO)) -> 0 | AY33: =SUM(SUMIF(コンシューマー!$B:$B,全体!$G33,コンシューマー!AT:AT),SUMIF(コマーシャル!$B:$B,全体!$G33,コマーシャル!AP:AP)) -> 0
A34: =SUMIFS(SAP貼付!K:K,SAP貼付!C:C,全体!G34) -> 3835 | B34: =SUMIFS(VGAMBFCST貼付!D:D,VGAMBFCST貼付!B:B,G34,VGAMBFCST貼付!C:C,全体!$B$20) -> 216 | C34: =SUMIFS(VGAMBFCST貼付!D:D,VGAMBFCST貼付!B:B,G34,VGAMBFCST貼付!C:C,全体!$C$20) -> 0 | D34: =SUM(A34:C34) -> 4051 | E34: =IFERROR(D34-SUM(#REF!)," ") | G34: RTX3050 6G | H34: =IFERROR(IF(MATCH($G34,コンシューマー!B:B,0),"Y"),"-") -> Y | I34: =IFERROR(IF(MATCH($G34,コマーシャル!B:B,0),"Y"),"-") -> Y | J34: =SUMIF(コンシューマー!$B:$B,全体!$G34,コンシューマー!D:D) -> 0 | K34: =SUMIF(コンシューマー!$B:$B,全体!$G34,コンシューマー!E:E) -> 0 | L34: =SUMIF(コンシューマー!$B:$B,全体!$G34,コンシューマー!F:F) -> 0 | M34: =SUMIF(コンシューマー!$B:$B,全体!$G34,コンシューマー!G:G) -> 0 | N34: =SUMIF(コンシューマー!$B:$B,全体!$G34,コンシューマー!H:H) -> 0 | O34: =SUMIF(コンシューマー!$B:$B,全体!$G34,コンシューマー!I:I) -> 0 | P34: =SUMIF(コンシューマー!$B:$B,全体!$G34,コンシューマー!J:J) -> 0 | Q34: =SUMIF(コンシューマー!$B:$B,全体!$G34,コンシューマー!K:K) -> 0 | R34: =SUMIF(コンシューマー!$B:$B,全体!$G34,コンシューマー!L:L) -> 0 | S34: =SUMIF(コンシューマー!$B:$B,全体!$G34,コンシューマー!M:M) -> 183 | T34: =SUMIF(コンシューマー!$B:$B,全体!$G34,コンシューマー!N:N) -> 564 | U34: =SUMIF(コンシューマー!$B:$B,全体!$G34,コンシューマー!O:O) -> 705 | V34: =SUMIF(コンシューマー!$B:$B,全体!$G34,コンシューマー!P:P) -> 489 | W34: =SUMIF(コンシューマー!$B:$B,全体!$G34,コンシューマー!Q:Q) -> 564 | X34: =SUMIF(コンシューマー!$B:$B,全体!$G34,コンシューマー!R:R) -> 708 | Y34: =SUMIF(コンシューマー!$B:$B,全体!$G34,コンシューマー!S:S) -> 634 | Z34: =SUMIF(コンシューマー!$B:$B,全体!$G34,コンシューマー!T:T) -> 770 | AA34: =SUMIF(コンシューマー!$B:$B,全体!$G34,コンシューマー!U:U) -> 859 | AB34: =SUMIF(コンシューマー!$B:$B,全体!$G34,コンシューマー!V:V) -> 627 | AC34: =SUMIF(コンシューマー!$B:$B,全体!$G34,コンシューマー!W:W) -> 1031 | AD34: =SUMIF(コンシューマー!$B:$B,全体!$G34,コンシューマー!X:X) -> 574 | AE34: =SUMIF(コンシューマー!$B:$B,全体!$G34,コンシューマー!Y:Y) -> 520 | AF34: =SUMIF(コンシューマー!$B:$B,全体!$G34,コンシューマー!Z:Z) -> 529 | AG34: =SUMIF(コンシューマー!$B:$B,全体!$G34,コンシューマー!AA:AA) -> 816 | AI34: 1198 | AK34: 844 | AL34: 1163.2258 | AM34: 1083.4892 | AN34: 423 | AO34: 526 | AP34: 276 | AQ34: 340 | AR34: =SUMIF(結果貼付!$A:$A,G34,結果貼付!$D:$D) -> 179 | AS34: =(AR34/AS$2)*AS$1 -> 383.57143 | AT34: =SUM(SUMIF(コンシューマー!$B:$B,全体!$G34,コンシューマー!AO:AO),SUMIF(コマーシャル!$B:$B,全体!$G34,コマーシャル!AK:AK)) -> 450 | AU34: =SUM(SUMIF(コンシューマー!$B:$B,全体!$G34,コンシューマー!AP:AP),SUMIF(コマーシャル!$B:$B,全体!$G34,コマーシャル!AL:AL)) -> 561 | AV34: =SUM(SUMIF(コンシューマー!$B:$B,全体!$G34,コンシューマー!AQ:AQ),SUMIF(コマーシャル!$B:$B,全体!$G34,コマーシャル!AM:AM)) -> 456.7782 | AW34: =SUM(SUMIF(コンシューマー!$B:$B,全体!$G34,コンシューマー!AR:AR),SUMIF(コマーシャル!$B:$B,全体!$G34,コマーシャル!AN:AN)) -> 448.74031 | AX34: =SUM(SUMIF(コンシューマー!$B:$B,全体!$G34,コンシューマー!AS:AS),SUMIF(コマーシャル!$B:$B,全体!$G34,コマーシャル!AO:AO)) -> 405.42528 | AY34: =SUM(SUMIF(コンシューマー!$B:$B,全体!$G34,コンシューマー!AT:AT),SUMIF(コマーシャル!$B:$B,全体!$G34,コマーシャル!AP:AP)) -> 402.31395
A35: =SUMIFS(SAP貼付!K:K,SAP貼付!C:C,全体!G35) -> 270 | B35: =SUMIFS(VGAMBFCST貼付!D:D,VGAMBFCST貼付!B:B,G35,VGAMBFCST貼付!C:C,全体!$B$20) -> 16 | C35: =SUMIFS(VGAMBFCST貼付!D:D,VGAMBFCST貼付!B:B,G35,VGAMBFCST貼付!C:C,全体!$C$20) -> 0 | D35: =SUM(A35:C35) -> 286 | E35: =IFERROR(D35-SUM(#REF!)," ") | G35: RTX3050 6G LP | H35: =IFERROR(IF(MATCH($G35,コンシューマー!B:B,0),"Y"),"-") -> Y | I35: =IFERROR(IF(MATCH($G35,コマーシャル!B:B,0),"Y"),"-") -> Y | J35: =SUMIF(コンシューマー!$B:$B,全体!$G35,コンシューマー!D:D) -> 0 | K35: =SUMIF(コンシューマー!$B:$B,全体!$G35,コンシューマー!E:E) -> 0 | L35: =SUMIF(コンシューマー!$B:$B,全体!$G35,コンシューマー!F:F) -> 0 | M35: =SUMIF(コンシューマー!$B:$B,全体!$G35,コンシューマー!G:G) -> 0 | N35: =SUMIF(コンシューマー!$B:$B,全体!$G35,コンシューマー!H:H) -> 0 | O35: =SUMIF(コンシューマー!$B:$B,全体!$G35,コンシューマー!I:I) -> 0 | P35: =SUMIF(コンシューマー!$B:$B,全体!$G35,コンシューマー!J:J) -> 0 | Q35: =SUMIF(コンシューマー!$B:$B,全体!$G35,コンシューマー!K:K) -> 0 | R35: =SUMIF(コンシューマー!$B:$B,全体!$G35,コンシューマー!L:L) -> 0 | S35: =SUMIF(コンシューマー!$B:$B,全体!$G35,コンシューマー!M:M) -> 0 | T35: =SUMIF(コンシューマー!$B:$B,全体!$G35,コンシューマー!N:N) -> 0 | U35: =SUMIF(コンシューマー!$B:$B,全体!$G35,コンシューマー!O:O) -> 0 | V35: =SUMIF(コンシューマー!$B:$B,全体!$G35,コンシューマー!P:P) -> 0 | W35: =SUMIF(コンシューマー!$B:$B,全体!$G35,コンシューマー!Q:Q) -> 0 | X35: =SUMIF(コンシューマー!$B:$B,全体!$G35,コンシューマー!R:R) -> 0 | Y35: =SUMIF(コンシューマー!$B:$B,全体!$G35,コンシューマー!S:S) -> 9 | Z35: =SUMIF(コンシューマー!$B:$B,全体!$G35,コンシューマー!T:T) -> 17 | AA35: =SUMIF(コンシューマー!$B:$B,全体!$G35,コンシューマー!U:U) -> 17 | AB35: =SUMIF(コンシューマー!$B:$B,全体!$G35,コンシューマー!V:V) -> 45 | AC35: =SUMIF(コンシューマー!$B:$B,全体!$G35,コンシューマー!W:W) -> 55 | AD35: =SUMIF(コンシューマー!$B:$B,全体!$G35,コンシューマー!X:X) -> 36 | AE35: =SUMIF(コンシューマー!$B:$B,全体!$G35,コンシューマー!Y:Y) -> 61 | AF35: =SUMIF(コンシューマー!$B:$B,全体!$G35,コンシューマー!Z:Z) -> 53 | AG35: =SUMIF(コンシューマー!$B:$B,全体!$G35,コンシューマー!AA:AA) -> 53 | AI35: 81 | AK35: 54 | AL35: 54.193548 | AM35: 49.574167 | AN35: 85 | AO35: 99 | AP35: 22 | AQ35: 75 | AR35: =SUMIF(結果貼付!$A:$A,G35,結果貼付!$D:$D) -> 3 | AS35: =(AR35/AS$2)*AS$1 -> 6.4285714 | AT35: =SUM(SUMIF(コンシューマー!$B:$B,全体!$G35,コンシューマー!AO:AO),SUMIF(コマーシャル!$B:$B,全体!$G35,コマーシャル!AK:AK)) -> 7.20576 | AU35: =SUM(SUMIF(コンシューマー!$B:$B,全体!$G35,コンシューマー!AP:AP),SUMIF(コマーシャル!$B:$B,全体!$G35,コマーシャル!AL:AL)) -> 0 | AV35: =SUM(SUMIF(コンシューマー!$B:$B,全体!$G35,コンシューマー!AQ:AQ),SUMIF(コマーシャル!$B:$B,全体!$G35,コマーシャル!AM:AM)) -> 0 | AW35: =SUM(SUMIF(コンシューマー!$B:$B,全体!$G35,コンシューマー!AR:AR),SUMIF(コマーシャル!$B:$B,全体!$G35,コマーシャル!AN:AN)) -> 0 | AX35: =SUM(SUMIF(コンシューマー!$B:$B,全体!$G35,コンシューマー!AS:AS),SUMIF(コマーシャル!$B:$B,全体!$G35,コマーシャル!AO:AO)) -> 0 | AY35: =SUM(SUMIF(コンシューマー!$B:$B,全体!$G35,コンシューマー!AT:AT),SUMIF(コマーシャル!$B:$B,全体!$G35,コマーシャル!AP:AP)) -> 0
A36: =SUMIFS(SAP貼付!K:K,SAP貼付!C:C,全体!G36) -> 53 | B36: =SUMIFS(VGAMBFCST貼付!D:D,VGAMBFCST貼付!B:B,G36,VGAMBFCST貼付!C:C,全体!$B$20) -> 0 | C36: =SUMIFS(VGAMBFCST貼付!D:D,VGAMBFCST貼付!B:B,G36,VGAMBFCST貼付!C:C,全体!$C$20) -> 0 | D36: =SUM(A36:C36) -> 53 | E36: =IFERROR(D36-SUM(#REF!)," ") | G36: GT1030 | H36: =IFERROR(IF(MATCH($G36,コンシューマー!B:B,0),"Y"),"-") -> - | I36: =IFERROR(IF(MATCH($G36,コマーシャル!B:B,0),"Y"),"-") -> Y | J36: =SUMIF(コンシューマー!$B:$B,全体!$G36,コンシューマー!D:D) -> 0 | K36: =SUMIF(コンシューマー!$B:$B,全体!$G36,コンシューマー!E:E) -> 0 | L36: =SUMIF(コンシューマー!$B:$B,全体!$G36,コンシューマー!F:F) -> 0 | M36: =SUMIF(コンシューマー!$B:$B,全体!$G36,コンシューマー!G:G) -> 0 | N36: =SUMIF(コンシューマー!$B:$B,全体!$G36,コンシューマー!H:H) -> 0 | O36: =SUMIF(コンシューマー!$B:$B,全体!$G36,コンシューマー!I:I) -> 0 | P36: =SUMIF(コンシューマー!$B:$B,全体!$G36,コンシューマー!J:J) -> 0 | Q36: =SUMIF(コンシューマー!$B:$B,全体!$G36,コンシューマー!K:K) -> 0 | R36: =SUMIF(コンシューマー!$B:$B,全体!$G36,コンシューマー!L:L) -> 0 | S36: =SUMIF(コンシューマー!$B:$B,全体!$G36,コンシューマー!M:M) -> 0 | T36: =SUMIF(コンシューマー!$B:$B,全体!$G36,コンシューマー!N:N) -> 0 | U36: =SUMIF(コンシューマー!$B:$B,全体!$G36,コンシューマー!O:O) -> 0 | V36: =SUMIF(コンシューマー!$B:$B,全体!$G36,コンシューマー!P:P) -> 0 | W36: =SUMIF(コンシューマー!$B:$B,全体!$G36,コンシューマー!Q:Q) -> 0 | X36: =SUMIF(コンシューマー!$B:$B,全体!$G36,コンシューマー!R:R) -> 0 | Y36: =SUMIF(コンシューマー!$B:$B,全体!$G36,コンシューマー!S:S) -> 0 | Z36: =SUMIF(コンシューマー!$B:$B,全体!$G36,コンシューマー!T:T) -> 0 | AA36: =SUMIF(コンシューマー!$B:$B,全体!$G36,コンシューマー!U:U) -> 0 | AB36: =SUMIF(コンシューマー!$B:$B,全体!$G36,コンシューマー!V:V) -> 0 | AC36: =SUMIF(コンシューマー!$B:$B,全体!$G36,コンシューマー!W:W) -> 0 | AD36: =SUMIF(コンシューマー!$B:$B,全体!$G36,コンシューマー!X:X) -> 0 | AE36: =SUMIF(コンシューマー!$B:$B,全体!$G36,コンシューマー!Y:Y) -> 0 | AF36: =SUMIF(コンシューマー!$B:$B,全体!$G36,コンシューマー!Z:Z) -> 0 | AG36: =SUMIF(コンシューマー!$B:$B,全体!$G36,コンシューマー!AA:AA) -> 0 | AI36: 0 | AK36: 0 | AL36: 0 | AM36: 0 | AN36: 0 | AO36: 0 | AP36: 0 | AQ36: 0 | AR36: =SUMIF(結果貼付!$A:$A,G36,結果貼付!$D:$D) -> 0 | AS36: =(AR36/AS$2)*AS$1 -> 0 | AT36: =SUM(SUMIF(コンシューマー!$B:$B,全体!$G36,コンシューマー!AO:AO),SUMIF(コマーシャル!$B:$B,全体!$G36,コマーシャル!AK:AK)) -> 0 | AU36: =SUM(SUMIF(コンシューマー!$B:$B,全体!$G36,コンシューマー!AP:AP),SUMIF(コマーシャル!$B:$B,全体!$G36,コマーシャル!AL:AL)) -> 0 | AV36: =SUM(SUMIF(コンシューマー!$B:$B,全体!$G36,コンシューマー!AQ:AQ),SUMIF(コマーシャル!$B:$B,全体!$G36,コマーシャル!AM:AM)) -> 0 | AW36: =SUM(SUMIF(コンシューマー!$B:$B,全体!$G36,コンシューマー!AR:AR),SUMIF(コマーシャル!$B:$B,全体!$G36,コマーシャル!AN:AN)) -> 0 | AX36: =SUM(SUMIF(コンシューマー!$B:$B,全体!$G36,コンシューマー!AS:AS),SUMIF(コマーシャル!$B:$B,全体!$G36,コマーシャル!AO:AO)) -> 0 | AY36: =SUM(SUMIF(コンシューマー!$B:$B,全体!$G36,コンシューマー!AT:AT),SUMIF(コマーシャル!$B:$B,全体!$G36,コマーシャル!AP:AP)) -> 0
G37: A310 LP | H37: =IFERROR(IF(MATCH($G37,コンシューマー!B:B,0),"Y"),"-") -> Y | I37: =IFERROR(IF(MATCH($G37,コマーシャル!B:B,0),"Y"),"-") -> - | J37: =SUMIF(コンシューマー!$B:$B,全体!$G37,コンシューマー!D:D) -> 0 | K37: =SUMIF(コンシューマー!$B:$B,全体!$G37,コンシューマー!E:E) -> 0 | L37: =SUMIF(コンシューマー!$B:$B,全体!$G37,コンシューマー!F:F) -> 0 | M37: =SUMIF(コンシューマー!$B:$B,全体!$G37,コンシューマー!G:G) -> 0 | N37: =SUMIF(コンシューマー!$B:$B,全体!$G37,コンシューマー!H:H) -> 0 | O37: =SUMIF(コンシューマー!$B:$B,全体!$G37,コンシューマー!I:I) -> 0 | P37: =SUMIF(コンシューマー!$B:$B,全体!$G37,コンシューマー!J:J) -> 0 | Q37: =SUMIF(コンシューマー!$B:$B,全体!$G37,コンシューマー!K:K) -> 0 | R37: =SUMIF(コンシューマー!$B:$B,全体!$G37,コンシューマー!L:L) -> 0 | S37: =SUMIF(コンシューマー!$B:$B,全体!$G37,コンシューマー!M:M) -> 0 | T37: =SUMIF(コンシューマー!$B:$B,全体!$G37,コンシューマー!N:N) -> 0 | U37: =SUMIF(コンシューマー!$B:$B,全体!$G37,コンシューマー!O:O) -> 0 | V37: =SUMIF(コンシューマー!$B:$B,全体!$G37,コンシューマー!P:P) -> 0 | W37: =SUMIF(コンシューマー!$B:$B,全体!$G37,コンシューマー!Q:Q) -> 0 | X37: =SUMIF(コンシューマー!$B:$B,全体!$G37,コンシューマー!R:R) -> 0 | Y37: =SUMIF(コンシューマー!$B:$B,全体!$G37,コンシューマー!S:S) -> 0 | Z37: =SUMIF(コンシューマー!$B:$B,全体!$G37,コンシューマー!T:T) -> 0 | AA37: =SUMIF(コンシューマー!$B:$B,全体!$G37,コンシューマー!U:U) -> 0 | AB37: =SUMIF(コンシューマー!$B:$B,全体!$G37,コンシューマー!V:V) -> 0 | AC37: =SUMIF(コンシューマー!$B:$B,全体!$G37,コンシューマー!W:W) -> 0 | AD37: =SUMIF(コンシューマー!$B:$B,全体!$G37,コンシューマー!X:X) -> 0 | AE37: =SUMIF(コンシューマー!$B:$B,全体!$G37,コンシューマー!Y:Y) -> 0 | AF37: =SUMIF(コンシューマー!$B:$B,全体!$G37,コンシューマー!Z:Z) -> 0 | AG37: =SUMIF(コンシューマー!$B:$B,全体!$G37,コンシューマー!AA:AA) -> 0 | AI37: 0 | AK37: 0 | AL37: 0 | AM37: 0 | AN37: 0 | AO37: 0 | AP37: 0 | AQ37: 0 | AR37: =SUMIF(結果貼付!$A:$A,G37,結果貼付!$D:$D) -> 0 | AS37: =(AR37/AS$2)*AS$1 -> 0 | AT37: =SUM(SUMIF(コンシューマー!$B:$B,全体!$G37,コンシューマー!AO:AO),SUMIF(コマーシャル!$B:$B,全体!$G37,コマーシャル!AK:AK)) -> 7.2 | AU37: =SUM(SUMIF(コンシューマー!$B:$B,全体!$G37,コンシューマー!AP:AP),SUMIF(コマーシャル!$B:$B,全体!$G37,コマーシャル!AL:AL)) -> 5 | AV37: =SUM(SUMIF(コンシューマー!$B:$B,全体!$G37,コンシューマー!AQ:AQ),SUMIF(コマーシャル!$B:$B,全体!$G37,コマーシャル!AM:AM)) -> 5 | AW37: =SUM(SUMIF(コンシューマー!$B:$B,全体!$G37,コンシューマー!AR:AR),SUMIF(コマーシャル!$B:$B,全体!$G37,コマーシャル!AN:AN)) -> 5 | AX37: =SUM(SUMIF(コンシューマー!$B:$B,全体!$G37,コンシューマー!AS:AS),SUMIF(コマーシャル!$B:$B,全体!$G37,コマーシャル!AO:AO)) -> 5 | AY37: =SUM(SUMIF(コンシューマー!$B:$B,全体!$G37,コンシューマー!AT:AT),SUMIF(コマーシャル!$B:$B,全体!$G37,コマーシャル!AP:AP)) -> 4.9549638 | AZ37: 初回発注のみ、追加不要
A38: =SUMIFS(SAP貼付!K:K,SAP貼付!C:C,全体!G38) -> 13 | B38: =SUMIFS(VGAMBFCST貼付!D:D,VGAMBFCST貼付!B:B,G38,VGAMBFCST貼付!C:C,全体!$B$20) -> 0 | C38: =SUMIFS(VGAMBFCST貼付!D:D,VGAMBFCST貼付!B:B,G38,VGAMBFCST貼付!C:C,全体!$C$20) -> 0 | D38: =SUM(A38:C38) -> 13 | E38: =IFERROR(D38-SUM(#REF!)," ") | G38: A380 | H38: =IFERROR(IF(MATCH($G38,コンシューマー!B:B,0),"Y"),"-") -> - | I38: =IFERROR(IF(MATCH($G38,コマーシャル!B:B,0),"Y"),"-") -> - | J38: =SUMIF(コンシューマー!$B:$B,全体!$G38,コンシューマー!D:D) -> 0 | K38: =SUMIF(コンシューマー!$B:$B,全体!$G38,コンシューマー!E:E) -> 0 | L38: =SUMIF(コンシューマー!$B:$B,全体!$G38,コンシューマー!F:F) -> 0 | M38: =SUMIF(コンシューマー!$B:$B,全体!$G38,コンシューマー!G:G) -> 0 | N38: =SUMIF(コンシューマー!$B:$B,全体!$G38,コンシューマー!H:H) -> 0 | O38: =SUMIF(コンシューマー!$B:$B,全体!$G38,コンシューマー!I:I) -> 0 | P38: =SUMIF(コンシューマー!$B:$B,全体!$G38,コンシューマー!J:J) -> 0 | Q38: =SUMIF(コンシューマー!$B:$B,全体!$G38,コンシューマー!K:K) -> 0 | R38: =SUMIF(コンシューマー!$B:$B,全体!$G38,コンシューマー!L:L) -> 0 | S38: =SUMIF(コンシューマー!$B:$B,全体!$G38,コンシューマー!M:M) -> 0 | T38: =SUMIF(コンシューマー!$B:$B,全体!$G38,コンシューマー!N:N) -> 0 | U38: =SUMIF(コンシューマー!$B:$B,全体!$G38,コンシューマー!O:O) -> 0 | V38: =SUMIF(コンシューマー!$B:$B,全体!$G38,コンシューマー!P:P) -> 0 | W38: =SUMIF(コンシューマー!$B:$B,全体!$G38,コンシューマー!Q:Q) -> 0 | X38: =SUMIF(コンシューマー!$B:$B,全体!$G38,コンシューマー!R:R) -> 0 | Y38: =SUMIF(コンシューマー!$B:$B,全体!$G38,コンシューマー!S:S) -> 0 | Z38: =SUMIF(コンシューマー!$B:$B,全体!$G38,コンシューマー!T:T) -> 0 | AA38: =SUMIF(コンシューマー!$B:$B,全体!$G38,コンシューマー!U:U) -> 0 | AB38: =SUMIF(コンシューマー!$B:$B,全体!$G38,コンシューマー!V:V) -> 0 | AC38: =SUMIF(コンシューマー!$B:$B,全体!$G38,コンシューマー!W:W) -> 0 | AD38: =SUMIF(コンシューマー!$B:$B,全体!$G38,コンシューマー!X:X) -> 0 | AE38: =SUMIF(コンシューマー!$B:$B,全体!$G38,コンシューマー!Y:Y) -> 0 | AF38: =SUMIF(コンシューマー!$B:$B,全体!$G38,コンシューマー!Z:Z) -> 0 | AG38: =SUMIF(コンシューマー!$B:$B,全体!$G38,コンシューマー!AA:AA) -> 0 | AI38: 0 | AK38: 0 | AL38: 0 | AM38: 0 | AN38: 0 | AO38: 0 | AP38: 0 | AQ38: 0 | AR38: =SUMIF(結果貼付!$A:$A,G38,結果貼付!$D:$D) -> 0 | AS38: =(AR38/AS$2)*AS$1 -> 0 | AT38: =SUM(SUMIF(コンシューマー!$B:$B,全体!$G38,コンシューマー!AO:AO),SUMIF(コマーシャル!$B:$B,全体!$G38,コマーシャル!AK:AK)) -> 0 | AU38: =SUM(SUMIF(コンシューマー!$B:$B,全体!$G38,コンシューマー!AP:AP),SUMIF(コマーシャル!$B:$B,全体!$G38,コマーシャル!AL:AL)) -> 0 | AV38: =SUM(SUMIF(コンシューマー!$B:$B,全体!$G38,コンシューマー!AQ:AQ),SUMIF(コマーシャル!$B:$B,全体!$G38,コマーシャル!AM:AM)) -> 0 | AW38: =SUM(SUMIF(コンシューマー!$B:$B,全体!$G38,コンシューマー!AR:AR),SUMIF(コマーシャル!$B:$B,全体!$G38,コマーシャル!AN:AN)) -> 0 | AX38: =SUM(SUMIF(コンシューマー!$B:$B,全体!$G38,コンシューマー!AS:AS),SUMIF(コマーシャル!$B:$B,全体!$G38,コマーシャル!AO:AO)) -> 0 | AY38: =SUM(SUMIF(コンシューマー!$B:$B,全体!$G38,コンシューマー!AT:AT),SUMIF(コマーシャル!$B:$B,全体!$G38,コマーシャル!AP:AP)) -> 0
A39: =SUMIFS(SAP貼付!K:K,SAP貼付!C:C,全体!G39) -> 0 | B39: =SUMIFS(VGAMBFCST貼付!D:D,VGAMBFCST貼付!B:B,G39,VGAMBFCST貼付!C:C,全体!$B$20) -> 0 | C39: =SUMIFS(VGAMBFCST貼付!D:D,VGAMBFCST貼付!B:B,G39,VGAMBFCST貼付!C:C,全体!$C$20) -> 0 | D39: =SUM(A39:C39) -> 0 | G39: RX9070XT | H39: =IFERROR(IF(MATCH($G39,コンシューマー!B:B,0),"Y"),"-") -> Y | I39: =IFERROR(IF(MATCH($G39,コマーシャル!B:B,0),"Y"),"-") -> Y | J39: =SUMIF(コンシューマー!$B:$B,全体!$G39,コンシューマー!D:D) -> 0 | K39: =SUMIF(コンシューマー!$B:$B,全体!$G39,コンシューマー!E:E) -> 0 | L39: =SUMIF(コンシューマー!$B:$B,全体!$G39,コンシューマー!F:F) -> 0 | M39: =SUMIF(コンシューマー!$B:$B,全体!$G39,コンシューマー!G:G) -> 0 | N39: =SUMIF(コンシューマー!$B:$B,全体!$G39,コンシューマー!H:H) -> 0 | O39: =SUMIF(コンシューマー!$B:$B,全体!$G39,コンシューマー!I:I) -> 0 | P39: =SUMIF(コンシューマー!$B:$B,全体!$G39,コンシューマー!J:J) -> 0 | Q39: =SUMIF(コンシューマー!$B:$B,全体!$G39,コンシューマー!K:K) -> 0 | R39: =SUMIF(コンシューマー!$B:$B,全体!$G39,コンシューマー!L:L) -> 0 | S39: =SUMIF(コンシューマー!$B:$B,全体!$G39,コンシューマー!M:M) -> 0 | T39: =SUMIF(コンシューマー!$B:$B,全体!$G39,コンシューマー!N:N) -> 0 | U39: =SUMIF(コンシューマー!$B:$B,全体!$G39,コンシューマー!O:O) -> 0 | V39: =SUMIF(コンシューマー!$B:$B,全体!$G39,コンシューマー!P:P) -> 0 | W39: =SUMIF(コンシューマー!$B:$B,全体!$G39,コンシューマー!Q:Q) -> 0 | X39: =SUMIF(コンシューマー!$B:$B,全体!$G39,コンシューマー!R:R) -> 0 | Y39: =SUMIF(コンシューマー!$B:$B,全体!$G39,コンシューマー!S:S) -> 0 | Z39: =SUMIF(コンシューマー!$B:$B,全体!$G39,コンシューマー!T:T) -> 0 | AA39: =SUMIF(コンシューマー!$B:$B,全体!$G39,コンシューマー!U:U) -> 0 | AB39: =SUMIF(コンシューマー!$B:$B,全体!$G39,コンシューマー!V:V) -> 0 | AC39: =SUMIF(コンシューマー!$B:$B,全体!$G39,コンシューマー!W:W) -> 182 | AD39: =SUMIF(コンシューマー!$B:$B,全体!$G39,コンシューマー!X:X) -> 777 | AE39: =SUMIF(コンシューマー!$B:$B,全体!$G39,コンシューマー!Y:Y) -> 379 | AF39: =SUMIF(コンシューマー!$B:$B,全体!$G39,コンシューマー!Z:Z) -> 342 | AG39: =SUMIF(コンシューマー!$B:$B,全体!$G39,コンシューマー!AA:AA) -> 391 | AI39: 201 | AK39: 148 | AL39: 239.03226 | AM39: 137.43333 | AN39: 36 | AO39: 178 | AP39: 578 | AQ39: 25 | AR39: =SUMIF(結果貼付!$A:$A,G39,結果貼付!$D:$D) -> 12 | AS39: =(AR39/AS$2)*AS$1 -> 25.714286 | AT39: =SUM(SUMIF(コンシューマー!$B:$B,全体!$G39,コンシューマー!AO:AO),SUMIF(コマーシャル!$B:$B,全体!$G39,コマーシャル!AK:AK)) -> 36.925397 | AU39: =SUM(SUMIF(コンシューマー!$B:$B,全体!$G39,コンシューマー!AP:AP),SUMIF(コマーシャル!$B:$B,全体!$G39,コマーシャル!AL:AL)) -> 43.710477 | AV39: =SUM(SUMIF(コンシューマー!$B:$B,全体!$G39,コンシューマー!AQ:AQ),SUMIF(コマーシャル!$B:$B,全体!$G39,コマーシャル!AM:AM)) -> 37.500281 | AW39: =SUM(SUMIF(コンシューマー!$B:$B,全体!$G39,コンシューマー!AR:AR),SUMIF(コマーシャル!$B:$B,全体!$G39,コマーシャル!AN:AN)) -> 36.818559 | AX39: =SUM(SUMIF(コンシューマー!$B:$B,全体!$G39,コンシューマー!AS:AS),SUMIF(コマーシャル!$B:$B,全体!$G39,コマーシャル!AO:AO)) -> 32.296725 | AY39: =SUM(SUMIF(コンシューマー!$B:$B,全体!$G39,コンシューマー!AT:AT),SUMIF(コマーシャル!$B:$B,全体!$G39,コマーシャル!AP:AP)) -> 32.032842 | AZ39: 12月ALGSレンタル分130pcs
A40: =SUMIFS(SAP貼付!K:K,SAP貼付!C:C,全体!G40) -> 0 | B40: =SUMIFS(VGAMBFCST貼付!D:D,VGAMBFCST貼付!B:B,G40,VGAMBFCST貼付!C:C,全体!$B$20) -> 0 | C40: =SUMIFS(VGAMBFCST貼付!D:D,VGAMBFCST貼付!B:B,G40,VGAMBFCST貼付!C:C,全体!$C$20) -> 0 | D40: =SUM(A40:C40) -> 0 | G40: RX9070 | H40: =IFERROR(IF(MATCH($G40,コンシューマー!B:B,0),"Y"),"-") -> Y | I40: =IFERROR(IF(MATCH($G40,コマーシャル!B:B,0),"Y"),"-") -> Y | J40: =SUMIF(コンシューマー!$B:$B,全体!$G40,コンシューマー!D:D) -> 0 | K40: =SUMIF(コンシューマー!$B:$B,全体!$G40,コンシューマー!E:E) -> 0 | L40: =SUMIF(コンシューマー!$B:$B,全体!$G40,コンシューマー!F:F) -> 0 | M40: =SUMIF(コンシューマー!$B:$B,全体!$G40,コンシューマー!G:G) -> 0 | N40: =SUMIF(コンシューマー!$B:$B,全体!$G40,コンシューマー!H:H) -> 0 | O40: =SUMIF(コンシューマー!$B:$B,全体!$G40,コンシューマー!I:I) -> 0 | P40: =SUMIF(コンシューマー!$B:$B,全体!$G40,コンシューマー!J:J) -> 0 | Q40: =SUMIF(コンシューマー!$B:$B,全体!$G40,コンシューマー!K:K) -> 0 | R40: =SUMIF(コンシューマー!$B:$B,全体!$G40,コンシューマー!L:L) -> 0 | S40: =SUMIF(コンシューマー!$B:$B,全体!$G40,コンシューマー!M:M) -> 0 | T40: =SUMIF(コンシューマー!$B:$B,全体!$G40,コンシューマー!N:N) -> 0 | U40: =SUMIF(コンシューマー!$B:$B,全体!$G40,コンシューマー!O:O) -> 0 | V40: =SUMIF(コンシューマー!$B:$B,全体!$G40,コンシューマー!P:P) -> 0 | W40: =SUMIF(コンシューマー!$B:$B,全体!$G40,コンシューマー!Q:Q) -> 0 | X40: =SUMIF(コンシューマー!$B:$B,全体!$G40,コンシューマー!R:R) -> 0 | Y40: =SUMIF(コンシューマー!$B:$B,全体!$G40,コンシューマー!S:S) -> 0 | Z40: =SUMIF(コンシューマー!$B:$B,全体!$G40,コンシューマー!T:T) -> 0 | AA40: =SUMIF(コンシューマー!$B:$B,全体!$G40,コンシューマー!U:U) -> 0 | AB40: =SUMIF(コンシューマー!$B:$B,全体!$G40,コンシューマー!V:V) -> 0 | AC40: =SUMIF(コンシューマー!$B:$B,全体!$G40,コンシューマー!W:W) -> 57 | AD40: =SUMIF(コンシューマー!$B:$B,全体!$G40,コンシューマー!X:X) -> 21 | AE40: =SUMIF(コンシューマー!$B:$B,全体!$G40,コンシューマー!Y:Y) -> 8 | AF40: =SUMIF(コンシューマー!$B:$B,全体!$G40,コンシューマー!Z:Z) -> 9 | AG40: =SUMIF(コンシューマー!$B:$B,全体!$G40,コンシューマー!AA:AA) -> 53 | AI40: 30 | AK40: 23 | AL40: 37.741935 | AM40: 17.67 | AN40: 7 | AO40: 3 | AP40: 2 | AQ40: 1 | AR40: =SUMIF(結果貼付!$A:$A,G40,結果貼付!$D:$D) -> 2 | AS40: =(AR40/AS$2)*AS$1 -> 4.2857143 | AT40: =SUM(SUMIF(コンシューマー!$B:$B,全体!$G40,コンシューマー!AO:AO),SUMIF(コマーシャル!$B:$B,全体!$G40,コマーシャル!AK:AK)) -> 4.3570159 | AU40: =SUM(SUMIF(コンシューマー!$B:$B,全体!$G40,コンシューマー!AP:AP),SUMIF(コマーシャル!$B:$B,全体!$G40,コマーシャル!AL:AL)) -> 4.6284191 | AV40: =SUM(SUMIF(コンシューマー!$B:$B,全体!$G40,コンシューマー!AQ:AQ),SUMIF(コマーシャル!$B:$B,全体!$G40,コマーシャル!AM:AM)) -> 4.3800112 | AW40: =SUM(SUMIF(コンシューマー!$B:$B,全体!$G40,コンシューマー!AR:AR),SUMIF(コマーシャル!$B:$B,全体!$G40,コマーシャル!AN:AN)) -> 4.3527424 | AX40: =SUM(SUMIF(コンシューマー!$B:$B,全体!$G40,コンシューマー!AS:AS),SUMIF(コマーシャル!$B:$B,全体!$G40,コマーシャル!AO:AO)) -> 4.171869 | AY40: =SUM(SUMIF(コンシューマー!$B:$B,全体!$G40,コンシューマー!AT:AT),SUMIF(コマーシャル!$B:$B,全体!$G40,コマーシャル!AP:AP)) -> 4.1613137
G41: RX9070GRE | H41: =IFERROR(IF(MATCH($G41,コンシューマー!B:B,0),"Y"),"-") -> Y | I41: =IFERROR(IF(MATCH($G41,コマーシャル!B:B,0),"Y"),"-") -> - | J41: =SUMIF(コンシューマー!$B:$B,全体!$G41,コンシューマー!D:D) -> 0 | K41: =SUMIF(コンシューマー!$B:$B,全体!$G41,コンシューマー!E:E) -> 0 | L41: =SUMIF(コンシューマー!$B:$B,全体!$G41,コンシューマー!F:F) -> 0 | M41: =SUMIF(コンシューマー!$B:$B,全体!$G41,コンシューマー!G:G) -> 0 | N41: =SUMIF(コンシューマー!$B:$B,全体!$G41,コンシューマー!H:H) -> 0 | O41: =SUMIF(コンシューマー!$B:$B,全体!$G41,コンシューマー!I:I) -> 0 | P41: =SUMIF(コンシューマー!$B:$B,全体!$G41,コンシューマー!J:J) -> 0 | Q41: =SUMIF(コンシューマー!$B:$B,全体!$G41,コンシューマー!K:K) -> 0 | R41: =SUMIF(コンシューマー!$B:$B,全体!$G41,コンシューマー!L:L) -> 0 | S41: =SUMIF(コンシューマー!$B:$B,全体!$G41,コンシューマー!M:M) -> 0 | T41: =SUMIF(コンシューマー!$B:$B,全体!$G41,コンシューマー!N:N) -> 0 | U41: =SUMIF(コンシューマー!$B:$B,全体!$G41,コンシューマー!O:O) -> 0 | V41: =SUMIF(コンシューマー!$B:$B,全体!$G41,コンシューマー!P:P) -> 0 | W41: =SUMIF(コンシューマー!$B:$B,全体!$G41,コンシューマー!Q:Q) -> 0 | X41: =SUMIF(コンシューマー!$B:$B,全体!$G41,コンシューマー!R:R) -> 0 | Y41: =SUMIF(コンシューマー!$B:$B,全体!$G41,コンシューマー!S:S) -> 0 | Z41: =SUMIF(コンシューマー!$B:$B,全体!$G41,コンシューマー!T:T) -> 0 | AA41: =SUMIF(コンシューマー!$B:$B,全体!$G41,コンシューマー!U:U) -> 0 | AB41: =SUMIF(コンシューマー!$B:$B,全体!$G41,コンシューマー!V:V) -> 0 | AC41: =SUMIF(コンシューマー!$B:$B,全体!$G41,コンシューマー!W:W) -> 0 | AD41: =SUMIF(コンシューマー!$B:$B,全体!$G41,コンシューマー!X:X) -> 0 | AE41: =SUMIF(コンシューマー!$B:$B,全体!$G41,コンシューマー!Y:Y) -> 0 | AF41: =SUMIF(コンシューマー!$B:$B,全体!$G41,コンシューマー!Z:Z) -> 0 | AG41: =SUMIF(コンシューマー!$B:$B,全体!$G41,コンシューマー!AA:AA) -> 0 | AH41: =SUMIF(コンシューマー!$B:$B,全体!$G41,コンシューマー!AB:AB) -> 0 | AI41: =SUMIF(コンシューマー!$B:$B,全体!$G41,コンシューマー!AC:AC) -> 0 | AJ41: =SUMIF(コンシューマー!$B:$B,全体!$G41,コンシューマー!AD:AD) -> 0 | AK41: =SUMIF(コンシューマー!$B:$B,全体!$G41,コンシューマー!AE:AE) -> 0 | AL41: =SUMIF(コンシューマー!$B:$B,全体!$G41,コンシューマー!AF:AF) -> 0 | AM41: =SUMIF(コンシューマー!$B:$B,全体!$G41,コンシューマー!AG:AG) -> 0 | AN41: =SUMIF(コンシューマー!$B:$B,全体!$G41,コンシューマー!AH:AH) -> 0 | AO41: =SUMIF(コンシューマー!$B:$B,全体!$G41,コンシューマー!AI:AI) -> 0 | AP41: =SUMIF(コンシューマー!$B:$B,全体!$G41,コンシューマー!AJ:AJ) -> 0 | AQ41: 0 | AR41: =SUMIF(コンシューマー!$B:$B,全体!$G41,コンシューマー!AL:AL) -> 0 | AS41: =SUMIF(コンシューマー!$B:$B,全体!$G41,コンシューマー!AM:AM) -> 0 | AT41: =SUM(SUMIF(コンシューマー!$B:$B,全体!$G41,コンシューマー!AO:AO),SUMIF(コマーシャル!$B:$B,全体!$G41,コマーシャル!AK:AK)) -> 6.0048 | AU41: =SUM(SUMIF(コンシューマー!$B:$B,全体!$G41,コンシューマー!AP:AP),SUMIF(コマーシャル!$B:$B,全体!$G41,コマーシャル!AL:AL)) -> 5 | AV41: =SUM(SUMIF(コンシューマー!$B:$B,全体!$G41,コンシューマー!AQ:AQ),SUMIF(コマーシャル!$B:$B,全体!$G41,コマーシャル!AM:AM)) -> 5 | AW41: =SUM(SUMIF(コンシューマー!$B:$B,全体!$G41,コンシューマー!AR:AR),SUMIF(コマーシャル!$B:$B,全体!$G41,コマーシャル!AN:AN)) -> 5 | AX41: =SUM(SUMIF(コンシューマー!$B:$B,全体!$G41,コンシューマー!AS:AS),SUMIF(コマーシャル!$B:$B,全体!$G41,コマーシャル!AO:AO)) -> 5 | AY41: =SUM(SUMIF(コンシューマー!$B:$B,全体!$G41,コンシューマー!AT:AT),SUMIF(コマーシャル!$B:$B,全体!$G41,コマーシャル!AP:AP)) -> 5 | AZ41: 初回10pcs
A42: =SUMIFS(SAP貼付!K:K,SAP貼付!C:C,全体!G42) -> 0 | B42: =SUMIFS(VGAMBFCST貼付!D:D,VGAMBFCST貼付!B:B,G42,VGAMBFCST貼付!C:C,全体!$B$20) -> 0 | C42: =SUMIFS(VGAMBFCST貼付!D:D,VGAMBFCST貼付!B:B,G42,VGAMBFCST貼付!C:C,全体!$C$20) -> 0 | D42: =SUM(A42:C42) -> 0 | G42: RX9060XT 16G | H42: =IFERROR(IF(MATCH($G42,コンシューマー!B:B,0),"Y"),"-") -> Y | I42: =IFERROR(IF(MATCH($G42,コマーシャル!B:B,0),"Y"),"-") -> Y | L42: =SUMIF(コンシューマー!$B:$B,全体!$G42,コンシューマー!F:F) -> 0 | M42: =SUMIF(コンシューマー!$B:$B,全体!$G42,コンシューマー!G:G) -> 0 | N42: =SUMIF(コンシューマー!$B:$B,全体!$G42,コンシューマー!H:H) -> 0 | O42: =SUMIF(コンシューマー!$B:$B,全体!$G42,コンシューマー!I:I) -> 0 | P42: =SUMIF(コンシューマー!$B:$B,全体!$G42,コンシューマー!J:J) -> 0 | Q42: =SUMIF(コンシューマー!$B:$B,全体!$G42,コンシューマー!K:K) -> 0 | R42: =SUMIF(コンシューマー!$B:$B,全体!$G42,コンシューマー!L:L) -> 0 | S42: =SUMIF(コンシューマー!$B:$B,全体!$G42,コンシューマー!M:M) -> 0 | T42: =SUMIF(コンシューマー!$B:$B,全体!$G42,コンシューマー!N:N) -> 0 | U42: =SUMIF(コンシューマー!$B:$B,全体!$G42,コンシューマー!O:O) -> 0 | V42: =SUMIF(コンシューマー!$B:$B,全体!$G42,コンシューマー!P:P) -> 0 | W42: =SUMIF(コンシューマー!$B:$B,全体!$G42,コンシューマー!Q:Q) -> 0 | X42: =SUMIF(コンシューマー!$B:$B,全体!$G42,コンシューマー!R:R) -> 0 | Y42: =SUMIF(コンシューマー!$B:$B,全体!$G42,コンシューマー!S:S) -> 0 | Z42: =SUMIF(コンシューマー!$B:$B,全体!$G42,コンシューマー!T:T) -> 0 | AA42: =SUMIF(コンシューマー!$B:$B,全体!$G42,コンシューマー!U:U) -> 0 | AB42: =SUMIF(コンシューマー!$B:$B,全体!$G42,コンシューマー!V:V) -> 0 | AC42: =SUMIF(コンシューマー!$B:$B,全体!$G42,コンシューマー!W:W) -> 0 | AD42: =SUMIF(コンシューマー!$B:$B,全体!$G42,コンシューマー!X:X) -> 0 | AE42: =SUMIF(コンシューマー!$B:$B,全体!$G42,コンシューマー!Y:Y) -> 0 | AF42: =SUMIF(コンシューマー!$B:$B,全体!$G42,コンシューマー!Z:Z) -> 30 | AG42: =SUMIF(コンシューマー!$B:$B,全体!$G42,コンシューマー!AA:AA) -> 229 | AI42: 145 | AK42: 222 | AL42: 291.29032 | AM42: 255.23333 | AN42: 94 | AO42: 130 | AP42: 292 | AQ42: 179 | AR42: =SUMIF(結果貼付!$A:$A,G42,結果貼付!$D:$D) -> 13 | AS42: =(AR42/AS$2)*AS$1 -> 27.857143 | AT42: =SUM(SUMIF(コンシューマー!$B:$B,全体!$G42,コンシューマー!AO:AO),SUMIF(コマーシャル!$B:$B,全体!$G42,コマーシャル!AK:AK)) -> 150 | AU42: =SUM(SUMIF(コンシューマー!$B:$B,全体!$G42,コンシューマー!AP:AP),SUMIF(コマーシャル!$B:$B,全体!$G42,コマーシャル!AL:AL)) -> 180 | AV42: =SUM(SUMIF(コンシューマー!$B:$B,全体!$G42,コンシューマー!AQ:AQ),SUMIF(コマーシャル!$B:$B,全体!$G42,コマーシャル!AM:AM)) -> 152.54183 | AW42: =SUM(SUMIF(コンシューマー!$B:$B,全体!$G42,コンシューマー!AR:AR),SUMIF(コマーシャル!$B:$B,全体!$G42,コマーシャル!AN:AN)) -> 149.52762 | AX42: =SUM(SUMIF(コンシューマー!$B:$B,全体!$G42,コンシューマー!AS:AS),SUMIF(コマーシャル!$B:$B,全体!$G42,コマーシャル!AO:AO)) -> 129.53448 | AY42: =SUM(SUMIF(コンシューマー!$B:$B,全体!$G42,コンシューマー!AT:AT),SUMIF(コマーシャル!$B:$B,全体!$G42,コマーシャル!AP:AP)) -> 128.36773
A43: =SUMIFS(SAP貼付!K:K,SAP貼付!C:C,全体!G43) -> 0 | B43: =SUMIFS(VGAMBFCST貼付!D:D,VGAMBFCST貼付!B:B,G43,VGAMBFCST貼付!C:C,全体!$B$20) -> 0 | C43: =SUMIFS(VGAMBFCST貼付!D:D,VGAMBFCST貼付!B:B,G43,VGAMBFCST貼付!C:C,全体!$C$20) -> 0 | D43: =SUM(A43:C43) -> 0 | G43: RX9060XT 8G | H43: =IFERROR(IF(MATCH($G43,コンシューマー!B:B,0),"Y"),"-") -> Y | I43: =IFERROR(IF(MATCH($G43,コマーシャル!B:B,0),"Y"),"-") -> Y | L43: =SUMIF(コンシューマー!$B:$B,全体!$G43,コンシューマー!F:F) -> 0 | M43: =SUMIF(コンシューマー!$B:$B,全体!$G43,コンシューマー!G:G) -> 0 | N43: =SUMIF(コンシューマー!$B:$B,全体!$G43,コンシューマー!H:H) -> 0 | O43: =SUMIF(コンシューマー!$B:$B,全体!$G43,コンシューマー!I:I) -> 0 | P43: =SUMIF(コンシューマー!$B:$B,全体!$G43,コンシューマー!J:J) -> 0 | Q43: =SUMIF(コンシューマー!$B:$B,全体!$G43,コンシューマー!K:K) -> 0 | R43: =SUMIF(コンシューマー!$B:$B,全体!$G43,コンシューマー!L:L) -> 0 | S43: =SUMIF(コンシューマー!$B:$B,全体!$G43,コンシューマー!M:M) -> 0 | T43: =SUMIF(コンシューマー!$B:$B,全体!$G43,コンシューマー!N:N) -> 0 | U43: =SUMIF(コンシューマー!$B:$B,全体!$G43,コンシューマー!O:O) -> 0 | V43: =SUMIF(コンシューマー!$B:$B,全体!$G43,コンシューマー!P:P) -> 0 | W43: =SUMIF(コンシューマー!$B:$B,全体!$G43,コンシューマー!Q:Q) -> 0 | X43: =SUMIF(コンシューマー!$B:$B,全体!$G43,コンシューマー!R:R) -> 0 | Y43: =SUMIF(コンシューマー!$B:$B,全体!$G43,コンシューマー!S:S) -> 0 | Z43: =SUMIF(コンシューマー!$B:$B,全体!$G43,コンシューマー!T:T) -> 0 | AA43: =SUMIF(コンシューマー!$B:$B,全体!$G43,コンシューマー!U:U) -> 0 | AB43: =SUMIF(コンシューマー!$B:$B,全体!$G43,コンシューマー!V:V) -> 0 | AC43: =SUMIF(コンシューマー!$B:$B,全体!$G43,コンシューマー!W:W) -> 0 | AD43: =SUMIF(コンシューマー!$B:$B,全体!$G43,コンシューマー!X:X) -> 0 | AE43: =SUMIF(コンシューマー!$B:$B,全体!$G43,コンシューマー!Y:Y) -> 0 | AF43: =SUMIF(コンシューマー!$B:$B,全体!$G43,コンシューマー!Z:Z) -> 3 | AG43: =SUMIF(コンシューマー!$B:$B,全体!$G43,コンシューマー!AA:AA) -> 29 | AI43: 34 | AK43: 15 | AL43: 53.225806 | AM43: 53.01 | AN43: 7 | AO43: 15 | AP43: 6 | AQ43: 1 | AR43: =SUMIF(結果貼付!$A:$A,G43,結果貼付!$D:$D) -> 1 | AS43: =(AR43/AS$2)*AS$1 -> 2.1428571 | AT43: =SUM(SUMIF(コンシューマー!$B:$B,全体!$G43,コンシューマー!AO:AO),SUMIF(コマーシャル!$B:$B,全体!$G43,コマーシャル!AK:AK)) -> 0 | AU43: =SUM(SUMIF(コンシューマー!$B:$B,全体!$G43,コンシューマー!AP:AP),SUMIF(コマーシャル!$B:$B,全体!$G43,コマーシャル!AL:AL)) -> 0 | AV43: =SUM(SUMIF(コンシューマー!$B:$B,全体!$G43,コンシューマー!AQ:AQ),SUMIF(コマーシャル!$B:$B,全体!$G43,コマーシャル!AM:AM)) -> 0 | AW43: =SUM(SUMIF(コンシューマー!$B:$B,全体!$G43,コンシューマー!AR:AR),SUMIF(コマーシャル!$B:$B,全体!$G43,コマーシャル!AN:AN)) -> 0 | AX43: =SUM(SUMIF(コンシューマー!$B:$B,全体!$G43,コンシューマー!AS:AS),SUMIF(コマーシャル!$B:$B,全体!$G43,コマーシャル!AO:AO)) -> 0 | AY43: =SUM(SUMIF(コンシューマー!$B:$B,全体!$G43,コンシューマー!AT:AT),SUMIF(コマーシャル!$B:$B,全体!$G43,コマーシャル!AP:AP)) -> 0 | AZ43: 無くなり次第終了
A44: =SUMIFS(SAP貼付!K:K,SAP貼付!C:C,全体!G44) -> 0 | B44: =SUMIFS(VGAMBFCST貼付!D:D,VGAMBFCST貼付!B:B,G44,VGAMBFCST貼付!C:C,全体!$B$20) -> 0 | C44: =SUMIFS(VGAMBFCST貼付!D:D,VGAMBFCST貼付!B:B,G44,VGAMBFCST貼付!C:C,全体!$C$20) -> 0 | D44: =SUM(A44:C44) -> 0 | G44: RX9060 | H44: =IFERROR(IF(MATCH($G44,コンシューマー!B:B,0),"Y"),"-") -> Y | I44: =IFERROR(IF(MATCH($G44,コマーシャル!B:B,0),"Y"),"-") -> Y | AG44: =SUMIF(コンシューマー!$B:$B,全体!$G44,コンシューマー!AA:AA) -> 29 | AI44: 0 | AK44: 2 | AL44: 35.806452 | AM44: 41.23 | AN44: 2 | AO44: 1 | AP44: 1 | AQ44: 0 | AR44: =SUMIF(結果貼付!$A:$A,G44,結果貼付!$D:$D) -> 0 | AS44: =(AR44/AS$2)*AS$1 -> 0 | AT44: =SUM(SUMIF(コンシューマー!$B:$B,全体!$G44,コンシューマー!AO:AO),SUMIF(コマーシャル!$B:$B,全体!$G44,コマーシャル!AK:AK)) -> 12 | AU44: =SUM(SUMIF(コンシューマー!$B:$B,全体!$G44,コンシューマー!AP:AP),SUMIF(コマーシャル!$B:$B,全体!$G44,コマーシャル!AL:AL)) -> 14.4 | AV44: =SUM(SUMIF(コンシューマー!$B:$B,全体!$G44,コンシューマー!AQ:AQ),SUMIF(コマーシャル!$B:$B,全体!$G44,コマーシャル!AM:AM)) -> 12.203346 | AW44: =SUM(SUMIF(コンシューマー!$B:$B,全体!$G44,コンシューマー!AR:AR),SUMIF(コマーシャル!$B:$B,全体!$G44,コマーシャル!AN:AN)) -> 11.962209 | AX44: =SUM(SUMIF(コンシューマー!$B:$B,全体!$G44,コンシューマー!AS:AS),SUMIF(コマーシャル!$B:$B,全体!$G44,コマーシャル!AO:AO)) -> 10.362758 | AY44: =SUM(SUMIF(コンシューマー!$B:$B,全体!$G44,コンシューマー!AT:AT),SUMIF(コマーシャル!$B:$B,全体!$G44,コマーシャル!AP:AP)) -> 10.269419 | AZ44: 最小必要数のみ発注
A45: =SUMIFS(SAP貼付!K:K,SAP貼付!C:C,全体!G45) -> 0 | B45: =SUMIFS(VGAMBFCST貼付!D:D,VGAMBFCST貼付!B:B,G45,VGAMBFCST貼付!C:C,全体!$B$20) -> 0 | C45: =SUMIFS(VGAMBFCST貼付!D:D,VGAMBFCST貼付!B:B,G45,VGAMBFCST貼付!C:C,全体!$C$20) -> 0 | D45: =SUM(A45:C45) -> 0 | E45: =IFERROR(D45-SUM(#REF!)," ") | G45: RX7900XTX | H45: =IFERROR(IF(MATCH($G45,コンシューマー!B:B,0),"Y"),"-") -> - | I45: =IFERROR(IF(MATCH($G45,コマーシャル!B:B,0),"Y"),"-") -> - | J45: =SUMIF(コンシューマー!$B:$B,全体!$G45,コンシューマー!D:D) -> 0 | K45: =SUMIF(コンシューマー!$B:$B,全体!$G45,コンシューマー!E:E) -> 0 | L45: =SUMIF(コンシューマー!$B:$B,全体!$G45,コンシューマー!F:F) -> 0 | M45: =SUMIF(コンシューマー!$B:$B,全体!$G45,コンシューマー!G:G) -> 0 | N45: =SUMIF(コンシューマー!$B:$B,全体!$G45,コンシューマー!H:H) -> 0 | O45: =SUMIF(コンシューマー!$B:$B,全体!$G45,コンシューマー!I:I) -> 0 | P45: =SUMIF(コンシューマー!$B:$B,全体!$G45,コンシューマー!J:J) -> 0 | Q45: =SUMIF(コンシューマー!$B:$B,全体!$G45,コンシューマー!K:K) -> 0 | R45: =SUMIF(コンシューマー!$B:$B,全体!$G45,コンシューマー!L:L) -> 0 | S45: =SUMIF(コンシューマー!$B:$B,全体!$G45,コンシューマー!M:M) -> 0 | T45: =SUMIF(コンシューマー!$B:$B,全体!$G45,コンシューマー!N:N) -> 0 | U45: =SUMIF(コンシューマー!$B:$B,全体!$G45,コンシューマー!O:O) -> 0 | V45: =SUMIF(コンシューマー!$B:$B,全体!$G45,コンシューマー!P:P) -> 0 | W45: =SUMIF(コンシューマー!$B:$B,全体!$G45,コンシューマー!Q:Q) -> 0 | X45: =SUMIF(コンシューマー!$B:$B,全体!$G45,コンシューマー!R:R) -> 0 | Y45: =SUMIF(コンシューマー!$B:$B,全体!$G45,コンシューマー!S:S) -> 0 | Z45: =SUMIF(コンシューマー!$B:$B,全体!$G45,コンシューマー!T:T) -> 0 | AA45: =SUMIF(コンシューマー!$B:$B,全体!$G45,コンシューマー!U:U) -> 0 | AB45: =SUMIF(コンシューマー!$B:$B,全体!$G45,コンシューマー!V:V) -> 0 | AC45: =SUMIF(コンシューマー!$B:$B,全体!$G45,コンシューマー!W:W) -> 0 | AD45: =SUMIF(コンシューマー!$B:$B,全体!$G45,コンシューマー!X:X) -> 0 | AE45: =SUMIF(コンシューマー!$B:$B,全体!$G45,コンシューマー!Y:Y) -> 0 | AF45: =SUMIF(コンシューマー!$B:$B,全体!$G45,コンシューマー!Z:Z) -> 0 | AG45: =SUMIF(コンシューマー!$B:$B,全体!$G45,コンシューマー!AA:AA) -> 0 | AI45: 0 | AK45: 0 | AL45: 0 | AM45: 0 | AN45: 0 | AO45: 0 | AP45: 0 | AQ45: 0 | AR45: =SUMIF(結果貼付!$A:$A,G45,結果貼付!$D:$D) -> 0 | AS45: =(AR45/AS$2)*AS$1 -> 0 | AT45: =SUM(SUMIF(コンシューマー!$B:$B,全体!$G45,コンシューマー!AO:AO),SUMIF(コマーシャル!$B:$B,全体!$G45,コマーシャル!AK:AK)) -> 0 | AU45: =SUM(SUMIF(コンシューマー!$B:$B,全体!$G45,コンシューマー!AP:AP),SUMIF(コマーシャル!$B:$B,全体!$G45,コマーシャル!AL:AL)) -> 0 | AV45: =SUM(SUMIF(コンシューマー!$B:$B,全体!$G45,コンシューマー!AQ:AQ),SUMIF(コマーシャル!$B:$B,全体!$G45,コマーシャル!AM:AM)) -> 0 | AW45: =SUM(SUMIF(コンシューマー!$B:$B,全体!$G45,コンシューマー!AR:AR),SUMIF(コマーシャル!$B:$B,全体!$G45,コマーシャル!AN:AN)) -> 0 | AX45: =SUM(SUMIF(コンシューマー!$B:$B,全体!$G45,コンシューマー!AS:AS),SUMIF(コマーシャル!$B:$B,全体!$G45,コマーシャル!AO:AO)) -> 0 | AY45: =SUM(SUMIF(コンシューマー!$B:$B,全体!$G45,コンシューマー!AT:AT),SUMIF(コマーシャル!$B:$B,全体!$G45,コマーシャル!AP:AP)) -> 0
A46: =SUMIFS(SAP貼付!K:K,SAP貼付!C:C,全体!G46) -> 6 | B46: =SUMIFS(VGAMBFCST貼付!D:D,VGAMBFCST貼付!B:B,G46,VGAMBFCST貼付!C:C,全体!$B$20) -> 0 | C46: =SUMIFS(VGAMBFCST貼付!D:D,VGAMBFCST貼付!B:B,G46,VGAMBFCST貼付!C:C,全体!$C$20) -> 0 | D46: =SUM(A46:C46) -> 6 | E46: =IFERROR(D46-SUM(#REF!)," ") | G46: RX7900XT | H46: =IFERROR(IF(MATCH($G46,コンシューマー!B:B,0),"Y"),"-") -> - | I46: =IFERROR(IF(MATCH($G46,コマーシャル!B:B,0),"Y"),"-") -> - | J46: =SUMIF(コンシューマー!$B:$B,全体!$G46,コンシューマー!D:D) -> 0 | K46: =SUMIF(コンシューマー!$B:$B,全体!$G46,コンシューマー!E:E) -> 0 | L46: =SUMIF(コンシューマー!$B:$B,全体!$G46,コンシューマー!F:F) -> 0 | M46: =SUMIF(コンシューマー!$B:$B,全体!$G46,コンシューマー!G:G) -> 0 | N46: =SUMIF(コンシューマー!$B:$B,全体!$G46,コンシューマー!H:H) -> 0 | O46: =SUMIF(コンシューマー!$B:$B,全体!$G46,コンシューマー!I:I) -> 0 | P46: =SUMIF(コンシューマー!$B:$B,全体!$G46,コンシューマー!J:J) -> 0 | Q46: =SUMIF(コンシューマー!$B:$B,全体!$G46,コンシューマー!K:K) -> 0 | R46: =SUMIF(コンシューマー!$B:$B,全体!$G46,コンシューマー!L:L) -> 0 | S46: =SUMIF(コンシューマー!$B:$B,全体!$G46,コンシューマー!M:M) -> 0 | T46: =SUMIF(コンシューマー!$B:$B,全体!$G46,コンシューマー!N:N) -> 0 | U46: =SUMIF(コンシューマー!$B:$B,全体!$G46,コンシューマー!O:O) -> 0 | V46: =SUMIF(コンシューマー!$B:$B,全体!$G46,コンシューマー!P:P) -> 0 | W46: =SUMIF(コンシューマー!$B:$B,全体!$G46,コンシューマー!Q:Q) -> 0 | X46: =SUMIF(コンシューマー!$B:$B,全体!$G46,コンシューマー!R:R) -> 0 | Y46: =SUMIF(コンシューマー!$B:$B,全体!$G46,コンシューマー!S:S) -> 0 | Z46: =SUMIF(コンシューマー!$B:$B,全体!$G46,コンシューマー!T:T) -> 0 | AA46: =SUMIF(コンシューマー!$B:$B,全体!$G46,コンシューマー!U:U) -> 0 | AB46: =SUMIF(コンシューマー!$B:$B,全体!$G46,コンシューマー!V:V) -> 0 | AC46: =SUMIF(コンシューマー!$B:$B,全体!$G46,コンシューマー!W:W) -> 0 | AD46: =SUMIF(コンシューマー!$B:$B,全体!$G46,コンシューマー!X:X) -> 0 | AE46: =SUMIF(コンシューマー!$B:$B,全体!$G46,コンシューマー!Y:Y) -> 0 | AF46: =SUMIF(コンシューマー!$B:$B,全体!$G46,コンシューマー!Z:Z) -> 0 | AG46: =SUMIF(コンシューマー!$B:$B,全体!$G46,コンシューマー!AA:AA) -> 0 | AI46: 0 | AK46: 0 | AL46: 0 | AM46: 0 | AN46: 0 | AO46: 0 | AP46: 0 | AQ46: 0 | AR46: =SUMIF(結果貼付!$A:$A,G46,結果貼付!$D:$D) -> 0 | AS46: =(AR46/AS$2)*AS$1 -> 0 | AT46: =SUM(SUMIF(コンシューマー!$B:$B,全体!$G46,コンシューマー!AO:AO),SUMIF(コマーシャル!$B:$B,全体!$G46,コマーシャル!AK:AK)) -> 0 | AU46: =SUM(SUMIF(コンシューマー!$B:$B,全体!$G46,コンシューマー!AP:AP),SUMIF(コマーシャル!$B:$B,全体!$G46,コマーシャル!AL:AL)) -> 0 | AV46: =SUM(SUMIF(コンシューマー!$B:$B,全体!$G46,コンシューマー!AQ:AQ),SUMIF(コマーシャル!$B:$B,全体!$G46,コマーシャル!AM:AM)) -> 0 | AW46: =SUM(SUMIF(コンシューマー!$B:$B,全体!$G46,コンシューマー!AR:AR),SUMIF(コマーシャル!$B:$B,全体!$G46,コマーシャル!AN:AN)) -> 0 | AX46: =SUM(SUMIF(コンシューマー!$B:$B,全体!$G46,コンシューマー!AS:AS),SUMIF(コマーシャル!$B:$B,全体!$G46,コマーシャル!AO:AO)) -> 0 | AY46: =SUM(SUMIF(コンシューマー!$B:$B,全体!$G46,コンシューマー!AT:AT),SUMIF(コマーシャル!$B:$B,全体!$G46,コマーシャル!AP:AP)) -> 0
A47: =SUMIFS(SAP貼付!K:K,SAP貼付!C:C,全体!G47) -> 321 | B47: =SUMIFS(VGAMBFCST貼付!D:D,VGAMBFCST貼付!B:B,G47,VGAMBFCST貼付!C:C,全体!$B$20) -> 1000 | C47: =SUMIFS(VGAMBFCST貼付!D:D,VGAMBFCST貼付!B:B,G47,VGAMBFCST貼付!C:C,全体!$C$20) -> 0 | D47: =SUM(A47:C47) -> 1321 | E47: =IFERROR(D47-SUM(#REF!)," ") | G47: RX7800XT | H47: =IFERROR(IF(MATCH($G47,コンシューマー!B:B,0),"Y"),"-") -> Y | I47: =IFERROR(IF(MATCH($G47,コマーシャル!B:B,0),"Y"),"-") -> - | J47: =SUMIF(コンシューマー!$B:$B,全体!$G47,コンシューマー!D:D) -> 0 | K47: =SUMIF(コンシューマー!$B:$B,全体!$G47,コンシューマー!E:E) -> 0 | L47: =SUMIF(コンシューマー!$B:$B,全体!$G47,コンシューマー!F:F) -> 4 | M47: =SUMIF(コンシューマー!$B:$B,全体!$G47,コンシューマー!G:G) -> 3 | N47: =SUMIF(コンシューマー!$B:$B,全体!$G47,コンシューマー!H:H) -> 2 | O47: =SUMIF(コンシューマー!$B:$B,全体!$G47,コンシューマー!I:I) -> 5 | P47: =SUMIF(コンシューマー!$B:$B,全体!$G47,コンシューマー!J:J) -> 4 | Q47: =SUMIF(コンシューマー!$B:$B,全体!$G47,コンシューマー!K:K) -> 8 | R47: =SUMIF(コンシューマー!$B:$B,全体!$G47,コンシューマー!L:L) -> 5 | S47: =SUMIF(コンシューマー!$B:$B,全体!$G47,コンシューマー!M:M) -> 3 | T47: =SUMIF(コンシューマー!$B:$B,全体!$G47,コンシューマー!N:N) -> 1 | U47: =SUMIF(コンシューマー!$B:$B,全体!$G47,コンシューマー!O:O) -> 4 | V47: =SUMIF(コンシューマー!$B:$B,全体!$G47,コンシューマー!P:P) -> 5 | W47: =SUMIF(コンシューマー!$B:$B,全体!$G47,コンシューマー!Q:Q) -> 4 | X47: =SUMIF(コンシューマー!$B:$B,全体!$G47,コンシューマー!R:R) -> 12 | Y47: =SUMIF(コンシューマー!$B:$B,全体!$G47,コンシューマー!S:S) -> 5 | Z47: =SUMIF(コンシューマー!$B:$B,全体!$G47,コンシューマー!T:T) -> 5 | AA47: =SUMIF(コンシューマー!$B:$B,全体!$G47,コンシューマー!U:U) -> 5 | AB47: =SUMIF(コンシューマー!$B:$B,全体!$G47,コンシューマー!V:V) -> 69 | AC47: =SUMIF(コンシューマー!$B:$B,全体!$G47,コンシューマー!W:W) -> 420 | AD47: =SUMIF(コンシューマー!$B:$B,全体!$G47,コンシューマー!X:X) -> 352 | AE47: =SUMIF(コンシューマー!$B:$B,全体!$G47,コンシューマー!Y:Y) -> 142 | AF47: =SUMIF(コンシューマー!$B:$B,全体!$G47,コンシューマー!Z:Z) -> 114 | AG47: =SUMIF(コンシューマー!$B:$B,全体!$G47,コンシューマー!AA:AA) -> 82 | AI47: 143 | AK47: 45 | AL47: 93.870968 | AM47: 74.606667 | AN47: 6 | AO47: 2 | AP47: 5 | AQ47: 195 | AR47: =SUMIF(結果貼付!$A:$A,G47,結果貼付!$D:$D) -> 8 | AS47: =(AR47/AS$2)*AS$1 -> 17.142857 | AT47: =SUM(SUMIF(コンシューマー!$B:$B,全体!$G47,コンシューマー!AO:AO),SUMIF(コマーシャル!$B:$B,全体!$G47,コマーシャル!AK:AK)) -> 0 | AU47: =SUM(SUMIF(コンシューマー!$B:$B,全体!$G47,コンシューマー!AP:AP),SUMIF(コマーシャル!$B:$B,全体!$G47,コマーシャル!AL:AL)) -> 0 | AV47: =SUM(SUMIF(コンシューマー!$B:$B,全体!$G47,コンシューマー!AQ:AQ),SUMIF(コマーシャル!$B:$B,全体!$G47,コマーシャル!AM:AM)) -> 0 | AW47: =SUM(SUMIF(コンシューマー!$B:$B,全体!$G47,コンシューマー!AR:AR),SUMIF(コマーシャル!$B:$B,全体!$G47,コマーシャル!AN:AN)) -> 0 | AX47: =SUM(SUMIF(コンシューマー!$B:$B,全体!$G47,コンシューマー!AS:AS),SUMIF(コマーシャル!$B:$B,全体!$G47,コマーシャル!AO:AO)) -> 0 | AY47: =SUM(SUMIF(コンシューマー!$B:$B,全体!$G47,コンシューマー!AT:AT),SUMIF(コマーシャル!$B:$B,全体!$G47,コマーシャル!AP:AP)) -> 0
A48: =SUMIFS(SAP貼付!K:K,SAP貼付!C:C,全体!G48) -> 2 | B48: =SUMIFS(VGAMBFCST貼付!D:D,VGAMBFCST貼付!B:B,G48,VGAMBFCST貼付!C:C,全体!$B$20) -> 0 | C48: =SUMIFS(VGAMBFCST貼付!D:D,VGAMBFCST貼付!B:B,G48,VGAMBFCST貼付!C:C,全体!$C$20) -> 0 | D48: =SUM(A48:C48) -> 2 | E48: =IFERROR(D48-SUM(#REF!)," ") | G48: RX7700XT | H48: =IFERROR(IF(MATCH($G48,コンシューマー!B:B,0),"Y"),"-") -> - | I48: =IFERROR(IF(MATCH($G48,コマーシャル!B:B,0),"Y"),"-") -> - | J48: =SUMIF(コンシューマー!$B:$B,全体!$G48,コンシューマー!D:D) -> 0 | K48: =SUMIF(コンシューマー!$B:$B,全体!$G48,コンシューマー!E:E) -> 0 | L48: =SUMIF(コンシューマー!$B:$B,全体!$G48,コンシューマー!F:F) -> 0 | M48: =SUMIF(コンシューマー!$B:$B,全体!$G48,コンシューマー!G:G) -> 0 | N48: =SUMIF(コンシューマー!$B:$B,全体!$G48,コンシューマー!H:H) -> 0 | O48: =SUMIF(コンシューマー!$B:$B,全体!$G48,コンシューマー!I:I) -> 0 | P48: =SUMIF(コンシューマー!$B:$B,全体!$G48,コンシューマー!J:J) -> 0 | Q48: =SUMIF(コンシューマー!$B:$B,全体!$G48,コンシューマー!K:K) -> 0 | R48: =SUMIF(コンシューマー!$B:$B,全体!$G48,コンシューマー!L:L) -> 0 | S48: =SUMIF(コンシューマー!$B:$B,全体!$G48,コンシューマー!M:M) -> 0 | T48: =SUMIF(コンシューマー!$B:$B,全体!$G48,コンシューマー!N:N) -> 0 | U48: =SUMIF(コンシューマー!$B:$B,全体!$G48,コンシューマー!O:O) -> 0 | V48: =SUMIF(コンシューマー!$B:$B,全体!$G48,コンシューマー!P:P) -> 0 | W48: =SUMIF(コンシューマー!$B:$B,全体!$G48,コンシューマー!Q:Q) -> 0 | X48: =SUMIF(コンシューマー!$B:$B,全体!$G48,コンシューマー!R:R) -> 0 | Y48: =SUMIF(コンシューマー!$B:$B,全体!$G48,コンシューマー!S:S) -> 0 | Z48: =SUMIF(コンシューマー!$B:$B,全体!$G48,コンシューマー!T:T) -> 0 | AA48: =SUMIF(コンシューマー!$B:$B,全体!$G48,コンシューマー!U:U) -> 0 | AB48: =SUMIF(コンシューマー!$B:$B,全体!$G48,コンシューマー!V:V) -> 0 | AC48: =SUMIF(コンシューマー!$B:$B,全体!$G48,コンシューマー!W:W) -> 0 | AD48: =SUMIF(コンシューマー!$B:$B,全体!$G48,コンシューマー!X:X) -> 0 | AE48: =SUMIF(コンシューマー!$B:$B,全体!$G48,コンシューマー!Y:Y) -> 0 | AF48: =SUMIF(コンシューマー!$B:$B,全体!$G48,コンシューマー!Z:Z) -> 0 | AG48: =SUMIF(コンシューマー!$B:$B,全体!$G48,コンシューマー!AA:AA) -> 0 | AI48: 0 | AK48: 0 | AL48: 0 | AM48: 0 | AN48: 0 | AO48: 0 | AP48: 0 | AQ48: 0 | AR48: =SUMIF(結果貼付!$A:$A,G48,結果貼付!$D:$D) -> 0 | AS48: =(AR48/AS$2)*AS$1 -> 0 | AT48: =SUM(SUMIF(コンシューマー!$B:$B,全体!$G48,コンシューマー!AO:AO),SUMIF(コマーシャル!$B:$B,全体!$G48,コマーシャル!AK:AK)) -> 0 | AU48: =SUM(SUMIF(コンシューマー!$B:$B,全体!$G48,コンシューマー!AP:AP),SUMIF(コマーシャル!$B:$B,全体!$G48,コマーシャル!AL:AL)) -> 0 | AV48: =SUM(SUMIF(コンシューマー!$B:$B,全体!$G48,コンシューマー!AQ:AQ),SUMIF(コマーシャル!$B:$B,全体!$G48,コマーシャル!AM:AM)) -> 0 | AW48: =SUM(SUMIF(コンシューマー!$B:$B,全体!$G48,コンシューマー!AR:AR),SUMIF(コマーシャル!$B:$B,全体!$G48,コマーシャル!AN:AN)) -> 0 | AX48: =SUM(SUMIF(コンシューマー!$B:$B,全体!$G48,コンシューマー!AS:AS),SUMIF(コマーシャル!$B:$B,全体!$G48,コマーシャル!AO:AO)) -> 0 | AY48: =SUM(SUMIF(コンシューマー!$B:$B,全体!$G48,コンシューマー!AT:AT),SUMIF(コマーシャル!$B:$B,全体!$G48,コマーシャル!AP:AP)) -> 0
A49: =SUMIFS(SAP貼付!K:K,SAP貼付!C:C,全体!G49) -> 7 | B49: =SUMIFS(VGAMBFCST貼付!D:D,VGAMBFCST貼付!B:B,G49,VGAMBFCST貼付!C:C,全体!$B$20) -> 0 | C49: =SUMIFS(VGAMBFCST貼付!D:D,VGAMBFCST貼付!B:B,G49,VGAMBFCST貼付!C:C,全体!$C$20) -> 0 | D49: =SUM(A49:C49) -> 7 | E49: =IFERROR(D49-SUM(#REF!)," ") | G49: RX7600XT | H49: =IFERROR(IF(MATCH($G49,コンシューマー!B:B,0),"Y"),"-") -> - | I49: =IFERROR(IF(MATCH($G49,コマーシャル!B:B,0),"Y"),"-") -> - | J49: =SUMIF(コンシューマー!$B:$B,全体!$G49,コンシューマー!D:D) -> 0 | K49: =SUMIF(コンシューマー!$B:$B,全体!$G49,コンシューマー!E:E) -> 0 | L49: =SUMIF(コンシューマー!$B:$B,全体!$G49,コンシューマー!F:F) -> 0 | M49: =SUMIF(コンシューマー!$B:$B,全体!$G49,コンシューマー!G:G) -> 0 | N49: =SUMIF(コンシューマー!$B:$B,全体!$G49,コンシューマー!H:H) -> 0 | O49: =SUMIF(コンシューマー!$B:$B,全体!$G49,コンシューマー!I:I) -> 0 | P49: =SUMIF(コンシューマー!$B:$B,全体!$G49,コンシューマー!J:J) -> 0 | Q49: =SUMIF(コンシューマー!$B:$B,全体!$G49,コンシューマー!K:K) -> 0 | R49: =SUMIF(コンシューマー!$B:$B,全体!$G49,コンシューマー!L:L) -> 0 | S49: =SUMIF(コンシューマー!$B:$B,全体!$G49,コンシューマー!M:M) -> 0 | T49: =SUMIF(コンシューマー!$B:$B,全体!$G49,コンシューマー!N:N) -> 0 | U49: =SUMIF(コンシューマー!$B:$B,全体!$G49,コンシューマー!O:O) -> 0 | V49: =SUMIF(コンシューマー!$B:$B,全体!$G49,コンシューマー!P:P) -> 0 | W49: =SUMIF(コンシューマー!$B:$B,全体!$G49,コンシューマー!Q:Q) -> 0 | X49: =SUMIF(コンシューマー!$B:$B,全体!$G49,コンシューマー!R:R) -> 0 | Y49: =SUMIF(コンシューマー!$B:$B,全体!$G49,コンシューマー!S:S) -> 0 | Z49: =SUMIF(コンシューマー!$B:$B,全体!$G49,コンシューマー!T:T) -> 0 | AA49: =SUMIF(コンシューマー!$B:$B,全体!$G49,コンシューマー!U:U) -> 0 | AB49: =SUMIF(コンシューマー!$B:$B,全体!$G49,コンシューマー!V:V) -> 0 | AC49: =SUMIF(コンシューマー!$B:$B,全体!$G49,コンシューマー!W:W) -> 0 | AD49: =SUMIF(コンシューマー!$B:$B,全体!$G49,コンシューマー!X:X) -> 0 | AE49: =SUMIF(コンシューマー!$B:$B,全体!$G49,コンシューマー!Y:Y) -> 0 | AF49: =SUMIF(コンシューマー!$B:$B,全体!$G49,コンシューマー!Z:Z) -> 0 | AG49: =SUMIF(コンシューマー!$B:$B,全体!$G49,コンシューマー!AA:AA) -> 0 | AI49: 0 | AK49: 0 | AL49: 0 | AM49: 0 | AN49: 0 | AO49: 0 | AP49: 0 | AQ49: 0 | AR49: =SUMIF(結果貼付!$A:$A,G49,結果貼付!$D:$D) -> 0 | AS49: =(AR49/AS$2)*AS$1 -> 0 | AT49: =SUM(SUMIF(コンシューマー!$B:$B,全体!$G49,コンシューマー!AO:AO),SUMIF(コマーシャル!$B:$B,全体!$G49,コマーシャル!AK:AK)) -> 0 | AU49: =SUM(SUMIF(コンシューマー!$B:$B,全体!$G49,コンシューマー!AP:AP),SUMIF(コマーシャル!$B:$B,全体!$G49,コマーシャル!AL:AL)) -> 0 | AV49: =SUM(SUMIF(コンシューマー!$B:$B,全体!$G49,コンシューマー!AQ:AQ),SUMIF(コマーシャル!$B:$B,全体!$G49,コマーシャル!AM:AM)) -> 0 | AW49: =SUM(SUMIF(コンシューマー!$B:$B,全体!$G49,コンシューマー!AR:AR),SUMIF(コマーシャル!$B:$B,全体!$G49,コマーシャル!AN:AN)) -> 0 | AX49: =SUM(SUMIF(コンシューマー!$B:$B,全体!$G49,コンシューマー!AS:AS),SUMIF(コマーシャル!$B:$B,全体!$G49,コマーシャル!AO:AO)) -> 0 | AY49: =SUM(SUMIF(コンシューマー!$B:$B,全体!$G49,コンシューマー!AT:AT),SUMIF(コマーシャル!$B:$B,全体!$G49,コマーシャル!AP:AP)) -> 0
A50: =SUMIFS(SAP貼付!K:K,SAP貼付!C:C,全体!G50) -> 7 | B50: =SUMIFS(VGAMBFCST貼付!D:D,VGAMBFCST貼付!B:B,G50,VGAMBFCST貼付!C:C,全体!$B$20) -> 0 | C50: =SUMIFS(VGAMBFCST貼付!D:D,VGAMBFCST貼付!B:B,G50,VGAMBFCST貼付!C:C,全体!$C$20) -> 0 | D50: =SUM(A50:C50) -> 7 | E50: =IFERROR(D50-SUM(#REF!)," ") | G50: RX7600 | H50: =IFERROR(IF(MATCH($G50,コンシューマー!B:B,0),"Y"),"-") -> Y | I50: =IFERROR(IF(MATCH($G50,コマーシャル!B:B,0),"Y"),"-") -> - | J50: =SUMIF(コンシューマー!$B:$B,全体!$G50,コンシューマー!D:D) -> 16 | K50: =SUMIF(コンシューマー!$B:$B,全体!$G50,コンシューマー!E:E) -> 8 | L50: =SUMIF(コンシューマー!$B:$B,全体!$G50,コンシューマー!F:F) -> 10 | M50: =SUMIF(コンシューマー!$B:$B,全体!$G50,コンシューマー!G:G) -> 17 | N50: =SUMIF(コンシューマー!$B:$B,全体!$G50,コンシューマー!H:H) -> 26 | O50: =SUMIF(コンシューマー!$B:$B,全体!$G50,コンシューマー!I:I) -> 15 | P50: =SUMIF(コンシューマー!$B:$B,全体!$G50,コンシューマー!J:J) -> 21 | Q50: =SUMIF(コンシューマー!$B:$B,全体!$G50,コンシューマー!K:K) -> 8 | R50: =SUMIF(コンシューマー!$B:$B,全体!$G50,コンシューマー!L:L) -> 4 | S50: =SUMIF(コンシューマー!$B:$B,全体!$G50,コンシューマー!M:M) -> 1 | T50: =SUMIF(コンシューマー!$B:$B,全体!$G50,コンシューマー!N:N) -> 3 | U50: =SUMIF(コンシューマー!$B:$B,全体!$G50,コンシューマー!O:O) -> 4 | V50: =SUMIF(コンシューマー!$B:$B,全体!$G50,コンシューマー!P:P) -> 3 | W50: =SUMIF(コンシューマー!$B:$B,全体!$G50,コンシューマー!Q:Q) -> 5 | X50: =SUMIF(コンシューマー!$B:$B,全体!$G50,コンシューマー!R:R) -> 4 | Y50: =SUMIF(コンシューマー!$B:$B,全体!$G50,コンシューマー!S:S) -> 8 | Z50: =SUMIF(コンシューマー!$B:$B,全体!$G50,コンシューマー!T:T) -> 4 | AA50: =SUMIF(コンシューマー!$B:$B,全体!$G50,コンシューマー!U:U) -> 9 | AB50: =SUMIF(コンシューマー!$B:$B,全体!$G50,コンシューマー!V:V) -> 23 | AC50: =SUMIF(コンシューマー!$B:$B,全体!$G50,コンシューマー!W:W) -> 6 | AD50: =SUMIF(コンシューマー!$B:$B,全体!$G50,コンシューマー!X:X) -> 0 | AE50: =SUMIF(コンシューマー!$B:$B,全体!$G50,コンシューマー!Y:Y) -> 0 | AF50: =SUMIF(コンシューマー!$B:$B,全体!$G50,コンシューマー!Z:Z) -> 2 | AG50: =SUMIF(コンシューマー!$B:$B,全体!$G50,コンシューマー!AA:AA) -> 9 | AI50: 57 | AK50: 36 | AL50: 63.870968 | AM50: 70.68 | AN50: 8 | AO50: 3 | AP50: 0 | AQ50: 39 | AR50: =SUMIF(結果貼付!$A:$A,G50,結果貼付!$D:$D) -> 56 | AS50: =(AR50/AS$2)*AS$1 -> 120 | AT50: =SUM(SUMIF(コンシューマー!$B:$B,全体!$G50,コンシューマー!AO:AO),SUMIF(コマーシャル!$B:$B,全体!$G50,コマーシャル!AK:AK)) -> 60.048 | AU50: =SUM(SUMIF(コンシューマー!$B:$B,全体!$G50,コンシューマー!AP:AP),SUMIF(コマーシャル!$B:$B,全体!$G50,コマーシャル!AL:AL)) -> 0 | AV50: =SUM(SUMIF(コンシューマー!$B:$B,全体!$G50,コンシューマー!AQ:AQ),SUMIF(コマーシャル!$B:$B,全体!$G50,コマーシャル!AM:AM)) -> 0 | AW50: =SUM(SUMIF(コンシューマー!$B:$B,全体!$G50,コンシューマー!AR:AR),SUMIF(コマーシャル!$B:$B,全体!$G50,コマーシャル!AN:AN)) -> 0 | AX50: =SUM(SUMIF(コンシューマー!$B:$B,全体!$G50,コンシューマー!AS:AS),SUMIF(コマーシャル!$B:$B,全体!$G50,コマーシャル!AO:AO)) -> 0 | AY50: =SUM(SUMIF(コンシューマー!$B:$B,全体!$G50,コンシューマー!AT:AT),SUMIF(コマーシャル!$B:$B,全体!$G50,コマーシャル!AP:AP)) -> 0
A51: =SUMIFS(SAP貼付!K:K,SAP貼付!C:C,全体!G51) -> 67 | B51: =SUMIFS(VGAMBFCST貼付!D:D,VGAMBFCST貼付!B:B,G51,VGAMBFCST貼付!C:C,全体!$B$20) -> 0 | C51: =SUMIFS(VGAMBFCST貼付!D:D,VGAMBFCST貼付!B:B,G51,VGAMBFCST貼付!C:C,全体!$C$20) -> 0 | D51: =SUM(A51:C51) -> 67 | E51: =IFERROR(D51-SUM(#REF!)," ") | G51: RX6600 | H51: =IFERROR(IF(MATCH($G51,コンシューマー!B:B,0),"Y"),"-") -> Y | I51: =IFERROR(IF(MATCH($G51,コマーシャル!B:B,0),"Y"),"-") -> - | J51: =SUMIF(コンシューマー!$B:$B,全体!$G51,コンシューマー!D:D) -> 1 | K51: =SUMIF(コンシューマー!$B:$B,全体!$G51,コンシューマー!E:E) -> 1 | L51: =SUMIF(コンシューマー!$B:$B,全体!$G51,コンシューマー!F:F) -> 3 | M51: =SUMIF(コンシューマー!$B:$B,全体!$G51,コンシューマー!G:G) -> 7 | N51: =SUMIF(コンシューマー!$B:$B,全体!$G51,コンシューマー!H:H) -> 6 | O51: =SUMIF(コンシューマー!$B:$B,全体!$G51,コンシューマー!I:I) -> 15 | P51: =SUMIF(コンシューマー!$B:$B,全体!$G51,コンシューマー!J:J) -> 0 | Q51: =SUMIF(コンシューマー!$B:$B,全体!$G51,コンシューマー!K:K) -> 5 | R51: =SUMIF(コンシューマー!$B:$B,全体!$G51,コンシューマー!L:L) -> 13 | S51: =SUMIF(コンシューマー!$B:$B,全体!$G51,コンシューマー!M:M) -> 10 | T51: =SUMIF(コンシューマー!$B:$B,全体!$G51,コンシューマー!N:N) -> 7 | U51: =SUMIF(コンシューマー!$B:$B,全体!$G51,コンシューマー!O:O) -> 16 | V51: =SUMIF(コンシューマー!$B:$B,全体!$G51,コンシューマー!P:P) -> 8 | W51: =SUMIF(コンシューマー!$B:$B,全体!$G51,コンシューマー!Q:Q) -> 3 | X51: =SUMIF(コンシューマー!$B:$B,全体!$G51,コンシューマー!R:R) -> 8 | Y51: =SUMIF(コンシューマー!$B:$B,全体!$G51,コンシューマー!S:S) -> 5 | Z51: =SUMIF(コンシューマー!$B:$B,全体!$G51,コンシューマー!T:T) -> 10 | AA51: =SUMIF(コンシューマー!$B:$B,全体!$G51,コンシューマー!U:U) -> 8 | AB51: =SUMIF(コンシューマー!$B:$B,全体!$G51,コンシューマー!V:V) -> 21 | AC51: =SUMIF(コンシューマー!$B:$B,全体!$G51,コンシューマー!W:W) -> 26 | AD51: =SUMIF(コンシューマー!$B:$B,全体!$G51,コンシューマー!X:X) -> 12 | AE51: =SUMIF(コンシューマー!$B:$B,全体!$G51,コンシューマー!Y:Y) -> 13 | AF51: =SUMIF(コンシューマー!$B:$B,全体!$G51,コンシューマー!Z:Z) -> 28 | AG51: =SUMIF(コンシューマー!$B:$B,全体!$G51,コンシューマー!AA:AA) -> 16 | AI51: 0 | AK51: 0 | AL51: 0 | AM51: 1.9633333 | AN51: 0 | AO51: 0 | AP51: 0 | AQ51: 0 | AR51: =SUMIF(結果貼付!$A:$A,G51,結果貼付!$D:$D) -> 0 | AS51: =(AR51/AS$2)*AS$1 -> 0 | AT51: =SUM(SUMIF(コンシューマー!$B:$B,全体!$G51,コンシューマー!AO:AO),SUMIF(コマーシャル!$B:$B,全体!$G51,コマーシャル!AK:AK)) -> 0 | AU51: =SUM(SUMIF(コンシューマー!$B:$B,全体!$G51,コンシューマー!AP:AP),SUMIF(コマーシャル!$B:$B,全体!$G51,コマーシャル!AL:AL)) -> 0 | AV51: =SUM(SUMIF(コンシューマー!$B:$B,全体!$G51,コンシューマー!AQ:AQ),SUMIF(コマーシャル!$B:$B,全体!$G51,コマーシャル!AM:AM)) -> 0 | AW51: =SUM(SUMIF(コンシューマー!$B:$B,全体!$G51,コンシューマー!AR:AR),SUMIF(コマーシャル!$B:$B,全体!$G51,コマーシャル!AN:AN)) -> 0 | AX51: =SUM(SUMIF(コンシューマー!$B:$B,全体!$G51,コンシューマー!AS:AS),SUMIF(コマーシャル!$B:$B,全体!$G51,コマーシャル!AO:AO)) -> 0 | AY51: =SUM(SUMIF(コンシューマー!$B:$B,全体!$G51,コンシューマー!AT:AT),SUMIF(コマーシャル!$B:$B,全体!$G51,コマーシャル!AP:AP)) -> 0
G52: RX550 | H52: =IFERROR(IF(MATCH($G52,コンシューマー!B:B,0),"Y"),"-") -> Y | I52: =IFERROR(IF(MATCH($G52,コマーシャル!B:B,0),"Y"),"-") -> Y | AI52: 36 | AK52: 29 | AL52: 11.612903 | AM52: 5.89 | AN52: 0 | AO52: 0 | AP52: 0 | AQ52: 0 | AR52: =SUMIF(結果貼付!$A:$A,G52,結果貼付!$D:$D) -> 0 | AS52: =(AR52/AS$2)*AS$1 -> 0 | AT52: =SUM(SUMIF(コンシューマー!$B:$B,全体!$G52,コンシューマー!AO:AO),SUMIF(コマーシャル!$B:$B,全体!$G52,コマーシャル!AK:AK)) -> 0 | AU52: =SUM(SUMIF(コンシューマー!$B:$B,全体!$G52,コンシューマー!AP:AP),SUMIF(コマーシャル!$B:$B,全体!$G52,コマーシャル!AL:AL)) -> 0 | AV52: =SUM(SUMIF(コンシューマー!$B:$B,全体!$G52,コンシューマー!AQ:AQ),SUMIF(コマーシャル!$B:$B,全体!$G52,コマーシャル!AM:AM)) -> 0 | AW52: =SUM(SUMIF(コンシューマー!$B:$B,全体!$G52,コンシューマー!AR:AR),SUMIF(コマーシャル!$B:$B,全体!$G52,コマーシャル!AN:AN)) -> 0 | AX52: =SUM(SUMIF(コンシューマー!$B:$B,全体!$G52,コンシューマー!AS:AS),SUMIF(コマーシャル!$B:$B,全体!$G52,コマーシャル!AO:AO)) -> 0 | AY52: =SUM(SUMIF(コンシューマー!$B:$B,全体!$G52,コンシューマー!AT:AT),SUMIF(コマーシャル!$B:$B,全体!$G52,コマーシャル!AP:AP)) -> 0
G53: 6000BW WS | H53: =IFERROR(IF(MATCH($G53,コンシューマー!B:B,0),"Y"),"-") -> - | I53: =IFERROR(IF(MATCH($G53,コマーシャル!B:B,0),"Y"),"-") -> Y | AK53: 0 | AL53: 0 | AM53: 15 | AN53: 0 | AO53: 0 | AP53: 0 | AQ53: 0 | AR53: =SUMIF(結果貼付!$A:$A,G53,結果貼付!$D:$D) -> 0 | AS53: =(AR53/AS$2)*AS$1 -> 0 | AT53: =SUM(SUMIF(コンシューマー!$B:$B,全体!$G53,コンシューマー!AO:AO),SUMIF(コマーシャル!$B:$B,全体!$G53,コマーシャル!AK:AK)) -> 10 | AU53: =SUM(SUMIF(コンシューマー!$B:$B,全体!$G53,コンシューマー!AP:AP),SUMIF(コマーシャル!$B:$B,全体!$G53,コマーシャル!AL:AL)) -> 7 | AV53: =SUM(SUMIF(コンシューマー!$B:$B,全体!$G53,コンシューマー!AQ:AQ),SUMIF(コマーシャル!$B:$B,全体!$G53,コマーシャル!AM:AM)) -> 6 | AW53: =SUM(SUMIF(コンシューマー!$B:$B,全体!$G53,コンシューマー!AR:AR),SUMIF(コマーシャル!$B:$B,全体!$G53,コマーシャル!AN:AN)) -> 10 | AX53: =SUM(SUMIF(コンシューマー!$B:$B,全体!$G53,コンシューマー!AS:AS),SUMIF(コマーシャル!$B:$B,全体!$G53,コマーシャル!AO:AO)) -> 6 | AY53: =SUM(SUMIF(コンシューマー!$B:$B,全体!$G53,コンシューマー!AT:AT),SUMIF(コマーシャル!$B:$B,全体!$G53,コマーシャル!AP:AP)) -> 6
G54: 6000BW MAX-Q | H54: =IFERROR(IF(MATCH($G54,コンシューマー!B:B,0),"Y"),"-") -> - | I54: =IFERROR(IF(MATCH($G54,コマーシャル!B:B,0),"Y"),"-") -> Y | AK54: 0 | AL54: 0 | AM54: 7 | AN54: 0 | AO54: 0 | AP54: 0 | AQ54: 0 | AR54: =SUMIF(結果貼付!$A:$A,G54,結果貼付!$D:$D) -> 0 | AS54: =(AR54/AS$2)*AS$1 -> 0 | AT54: =SUM(SUMIF(コンシューマー!$B:$B,全体!$G54,コンシューマー!AO:AO),SUMIF(コマーシャル!$B:$B,全体!$G54,コマーシャル!AK:AK)) -> 7 | AU54: =SUM(SUMIF(コンシューマー!$B:$B,全体!$G54,コンシューマー!AP:AP),SUMIF(コマーシャル!$B:$B,全体!$G54,コマーシャル!AL:AL)) -> 3 | AV54: =SUM(SUMIF(コンシューマー!$B:$B,全体!$G54,コンシューマー!AQ:AQ),SUMIF(コマーシャル!$B:$B,全体!$G54,コマーシャル!AM:AM)) -> 4 | AW54: =SUM(SUMIF(コンシューマー!$B:$B,全体!$G54,コンシューマー!AR:AR),SUMIF(コマーシャル!$B:$B,全体!$G54,コマーシャル!AN:AN)) -> 3 | AX54: =SUM(SUMIF(コンシューマー!$B:$B,全体!$G54,コンシューマー!AS:AS),SUMIF(コマーシャル!$B:$B,全体!$G54,コマーシャル!AO:AO)) -> 3 | AY54: =SUM(SUMIF(コンシューマー!$B:$B,全体!$G54,コンシューマー!AT:AT),SUMIF(コマーシャル!$B:$B,全体!$G54,コマーシャル!AP:AP)) -> 4
G55: RTX5000BW | H55: =IFERROR(IF(MATCH($G55,コンシューマー!B:B,0),"Y"),"-") -> - | I55: =IFERROR(IF(MATCH($G55,コマーシャル!B:B,0),"Y"),"-") -> Y | AK55: 0 | AL55: 0 | AM55: 13 | AN55: 0 | AO55: 0 | AP55: 0 | AQ55: 0 | AR55: =SUMIF(結果貼付!$A:$A,G55,結果貼付!$D:$D) -> 0 | AS55: =(AR55/AS$2)*AS$1 -> 0 | AT55: =SUM(SUMIF(コンシューマー!$B:$B,全体!$G55,コンシューマー!AO:AO),SUMIF(コマーシャル!$B:$B,全体!$G55,コマーシャル!AK:AK)) -> 6 | AU55: =SUM(SUMIF(コンシューマー!$B:$B,全体!$G55,コンシューマー!AP:AP),SUMIF(コマーシャル!$B:$B,全体!$G55,コマーシャル!AL:AL)) -> 7 | AV55: =SUM(SUMIF(コンシューマー!$B:$B,全体!$G55,コンシューマー!AQ:AQ),SUMIF(コマーシャル!$B:$B,全体!$G55,コマーシャル!AM:AM)) -> 6 | AW55: =SUM(SUMIF(コンシューマー!$B:$B,全体!$G55,コンシューマー!AR:AR),SUMIF(コマーシャル!$B:$B,全体!$G55,コマーシャル!AN:AN)) -> 7 | AX55: =SUM(SUMIF(コンシューマー!$B:$B,全体!$G55,コンシューマー!AS:AS),SUMIF(コマーシャル!$B:$B,全体!$G55,コマーシャル!AO:AO)) -> 7 | AY55: =SUM(SUMIF(コンシューマー!$B:$B,全体!$G55,コンシューマー!AT:AT),SUMIF(コマーシャル!$B:$B,全体!$G55,コマーシャル!AP:AP)) -> 7
G56: RTX4500BW | H56: =IFERROR(IF(MATCH($G56,コンシューマー!B:B,0),"Y"),"-") -> - | I56: =IFERROR(IF(MATCH($G56,コマーシャル!B:B,0),"Y"),"-") -> Y | AK56: 0 | AL56: 0 | AM56: 11 | AN56: 0 | AO56: 0 | AP56: 0 | AQ56: 0 | AR56: =SUMIF(結果貼付!$A:$A,G56,結果貼付!$D:$D) -> 0 | AS56: =(AR56/AS$2)*AS$1 -> 0 | AT56: =SUM(SUMIF(コンシューマー!$B:$B,全体!$G56,コンシューマー!AO:AO),SUMIF(コマーシャル!$B:$B,全体!$G56,コマーシャル!AK:AK)) -> 5 | AU56: =SUM(SUMIF(コンシューマー!$B:$B,全体!$G56,コンシューマー!AP:AP),SUMIF(コマーシャル!$B:$B,全体!$G56,コマーシャル!AL:AL)) -> 5 | AV56: =SUM(SUMIF(コンシューマー!$B:$B,全体!$G56,コンシューマー!AQ:AQ),SUMIF(コマーシャル!$B:$B,全体!$G56,コマーシャル!AM:AM)) -> 4 | AW56: =SUM(SUMIF(コンシューマー!$B:$B,全体!$G56,コンシューマー!AR:AR),SUMIF(コマーシャル!$B:$B,全体!$G56,コマーシャル!AN:AN)) -> 6 | AX56: =SUM(SUMIF(コンシューマー!$B:$B,全体!$G56,コンシューマー!AS:AS),SUMIF(コマーシャル!$B:$B,全体!$G56,コマーシャル!AO:AO)) -> 5 | AY56: =SUM(SUMIF(コンシューマー!$B:$B,全体!$G56,コンシューマー!AT:AT),SUMIF(コマーシャル!$B:$B,全体!$G56,コマーシャル!AP:AP)) -> 5
G57: RTX4000BW | H57: =IFERROR(IF(MATCH($G57,コンシューマー!B:B,0),"Y"),"-") -> - | I57: =IFERROR(IF(MATCH($G57,コマーシャル!B:B,0),"Y"),"-") -> Y | AK57: 0 | AL57: 0 | AM57: 22 | AN57: 0 | AO57: 0 | AP57: 0 | AQ57: 0 | AR57: =SUMIF(結果貼付!$A:$A,G57,結果貼付!$D:$D) -> 0 | AS57: =(AR57/AS$2)*AS$1 -> 0 | AT57: =SUM(SUMIF(コンシューマー!$B:$B,全体!$G57,コンシューマー!AO:AO),SUMIF(コマーシャル!$B:$B,全体!$G57,コマーシャル!AK:AK)) -> 14 | AU57: =SUM(SUMIF(コンシューマー!$B:$B,全体!$G57,コンシューマー!AP:AP),SUMIF(コマーシャル!$B:$B,全体!$G57,コマーシャル!AL:AL)) -> 10 | AV57: =SUM(SUMIF(コンシューマー!$B:$B,全体!$G57,コンシューマー!AQ:AQ),SUMIF(コマーシャル!$B:$B,全体!$G57,コマーシャル!AM:AM)) -> 9 | AW57: =SUM(SUMIF(コンシューマー!$B:$B,全体!$G57,コンシューマー!AR:AR),SUMIF(コマーシャル!$B:$B,全体!$G57,コマーシャル!AN:AN)) -> 10 | AX57: =SUM(SUMIF(コンシューマー!$B:$B,全体!$G57,コンシューマー!AS:AS),SUMIF(コマーシャル!$B:$B,全体!$G57,コマーシャル!AO:AO)) -> 14 | AY57: =SUM(SUMIF(コンシューマー!$B:$B,全体!$G57,コンシューマー!AT:AT),SUMIF(コマーシャル!$B:$B,全体!$G57,コマーシャル!AP:AP)) -> 14
G58: RTX4000BW-SFF | H58: =IFERROR(IF(MATCH($G58,コンシューマー!B:B,0),"Y"),"-") -> - | I58: =IFERROR(IF(MATCH($G58,コマーシャル!B:B,0),"Y"),"-") -> Y | AK58: 0 | AL58: 0 | AM58: 0 | AN58: 0 | AO58: 0 | AP58: 0 | AQ58: 0 | AR58: =SUMIF(結果貼付!$A:$A,G58,結果貼付!$D:$D) -> 0 | AS58: =(AR58/AS$2)*AS$1 -> 0 | AT58: =SUM(SUMIF(コンシューマー!$B:$B,全体!$G58,コンシューマー!AO:AO),SUMIF(コマーシャル!$B:$B,全体!$G58,コマーシャル!AK:AK)) -> 1 | AU58: =SUM(SUMIF(コンシューマー!$B:$B,全体!$G58,コンシューマー!AP:AP),SUMIF(コマーシャル!$B:$B,全体!$G58,コマーシャル!AL:AL)) -> 1 | AV58: =SUM(SUMIF(コンシューマー!$B:$B,全体!$G58,コンシューマー!AQ:AQ),SUMIF(コマーシャル!$B:$B,全体!$G58,コマーシャル!AM:AM)) -> 1 | AW58: =SUM(SUMIF(コンシューマー!$B:$B,全体!$G58,コンシューマー!AR:AR),SUMIF(コマーシャル!$B:$B,全体!$G58,コマーシャル!AN:AN)) -> 1 | AX58: =SUM(SUMIF(コンシューマー!$B:$B,全体!$G58,コンシューマー!AS:AS),SUMIF(コマーシャル!$B:$B,全体!$G58,コマーシャル!AO:AO)) -> 1 | AY58: =SUM(SUMIF(コンシューマー!$B:$B,全体!$G58,コンシューマー!AT:AT),SUMIF(コマーシャル!$B:$B,全体!$G58,コマーシャル!AP:AP)) -> 1
G59: RTX2000BW | H59: =IFERROR(IF(MATCH($G59,コンシューマー!B:B,0),"Y"),"-") -> - | I59: =IFERROR(IF(MATCH($G59,コマーシャル!B:B,0),"Y"),"-") -> Y | AK59: 0 | AL59: 0 | AM59: 32 | AN59: 0 | AO59: 0 | AP59: 0 | AQ59: 0 | AR59: =SUMIF(結果貼付!$A:$A,G59,結果貼付!$D:$D) -> 0 | AS59: =(AR59/AS$2)*AS$1 -> 0 | AT59: =SUM(SUMIF(コンシューマー!$B:$B,全体!$G59,コンシューマー!AO:AO),SUMIF(コマーシャル!$B:$B,全体!$G59,コマーシャル!AK:AK)) -> 20 | AU59: =SUM(SUMIF(コンシューマー!$B:$B,全体!$G59,コンシューマー!AP:AP),SUMIF(コマーシャル!$B:$B,全体!$G59,コマーシャル!AL:AL)) -> 17 | AV59: =SUM(SUMIF(コンシューマー!$B:$B,全体!$G59,コンシューマー!AQ:AQ),SUMIF(コマーシャル!$B:$B,全体!$G59,コマーシャル!AM:AM)) -> 20 | AW59: =SUM(SUMIF(コンシューマー!$B:$B,全体!$G59,コンシューマー!AR:AR),SUMIF(コマーシャル!$B:$B,全体!$G59,コマーシャル!AN:AN)) -> 37 | AX59: =SUM(SUMIF(コンシューマー!$B:$B,全体!$G59,コンシューマー!AS:AS),SUMIF(コマーシャル!$B:$B,全体!$G59,コマーシャル!AO:AO)) -> 40 | AY59: =SUM(SUMIF(コンシューマー!$B:$B,全体!$G59,コンシューマー!AT:AT),SUMIF(コマーシャル!$B:$B,全体!$G59,コマーシャル!AP:AP)) -> 30
A60: =SUMIFS(SAP貼付!K:K,SAP貼付!C:C,全体!G60) -> 21 | B60: =SUMIFS(VGAMBFCST貼付!D:D,VGAMBFCST貼付!B:B,G60,VGAMBFCST貼付!C:C,全体!$B$20) -> 0 | C60: =SUMIFS(VGAMBFCST貼付!D:D,VGAMBFCST貼付!B:B,G60,VGAMBFCST貼付!C:C,全体!$C$20) -> 0 | D60: =SUM(A60:C60) -> 21 | E60: =IFERROR(D60-SUM(#REF!)," ") | G60: 6000Ada | H60: =IFERROR(IF(MATCH($G60,コンシューマー!B:B,0),"Y"),"-") -> Y | I60: =IFERROR(IF(MATCH($G60,コマーシャル!B:B,0),"Y"),"-") -> Y | J60: =SUMIF(コンシューマー!$B:$B,全体!$G60,コンシューマー!D:D) -> 0 | K60: =SUMIF(コンシューマー!$B:$B,全体!$G60,コンシューマー!E:E) -> 0 | L60: =SUMIF(コンシューマー!$B:$B,全体!$G60,コンシューマー!F:F) -> 0 | M60: =SUMIF(コンシューマー!$B:$B,全体!$G60,コンシューマー!G:G) -> 0 | N60: =SUMIF(コンシューマー!$B:$B,全体!$G60,コンシューマー!H:H) -> 0 | O60: =SUMIF(コンシューマー!$B:$B,全体!$G60,コンシューマー!I:I) -> 0 | P60: =SUMIF(コンシューマー!$B:$B,全体!$G60,コンシューマー!J:J) -> 0 | Q60: =SUMIF(コンシューマー!$B:$B,全体!$G60,コンシューマー!K:K) -> 5 | R60: =SUMIF(コンシューマー!$B:$B,全体!$G60,コンシューマー!L:L) -> 3 | S60: =SUMIF(コンシューマー!$B:$B,全体!$G60,コンシューマー!M:M) -> 0 | T60: =SUMIF(コンシューマー!$B:$B,全体!$G60,コンシューマー!N:N) -> 2 | U60: =SUMIF(コンシューマー!$B:$B,全体!$G60,コンシューマー!O:O) -> 9 | V60: =SUMIF(コンシューマー!$B:$B,全体!$G60,コンシューマー!P:P) -> 12 | W60: =SUMIF(コンシューマー!$B:$B,全体!$G60,コンシューマー!Q:Q) -> 3 | X60: =SUMIF(コンシューマー!$B:$B,全体!$G60,コンシューマー!R:R) -> 2 | Y60: =SUMIF(コンシューマー!$B:$B,全体!$G60,コンシューマー!S:S) -> 1 | Z60: =SUMIF(コンシューマー!$B:$B,全体!$G60,コンシューマー!T:T) -> 1 | AA60: =SUMIF(コンシューマー!$B:$B,全体!$G60,コンシューマー!U:U) -> 1 | AB60: =SUMIF(コンシューマー!$B:$B,全体!$G60,コンシューマー!V:V) -> 3 | AC60: =SUMIF(コンシューマー!$B:$B,全体!$G60,コンシューマー!W:W) -> 4 | AD60: =SUMIF(コンシューマー!$B:$B,全体!$G60,コンシューマー!X:X) -> 5 | AE60: =SUMIF(コンシューマー!$B:$B,全体!$G60,コンシューマー!Y:Y) -> 2 | AF60: =SUMIF(コンシューマー!$B:$B,全体!$G60,コンシューマー!Z:Z) -> 1 | AG60: =SUMIF(コンシューマー!$B:$B,全体!$G60,コンシューマー!AA:AA) -> 2 | AI60: 0 | AK60: 0 | AL60: 0 | AM60: 0 | AN60: 2 | AO60: 0 | AP60: 0 | AQ60: 0 | AR60: =SUMIF(結果貼付!$A:$A,G60,結果貼付!$D:$D) -> 0 | AS60: =(AR60/AS$2)*AS$1 -> 0 | AT60: =SUM(SUMIF(コンシューマー!$B:$B,全体!$G60,コンシューマー!AO:AO),SUMIF(コマーシャル!$B:$B,全体!$G60,コマーシャル!AK:AK)) -> 0 | AU60: =SUM(SUMIF(コンシューマー!$B:$B,全体!$G60,コンシューマー!AP:AP),SUMIF(コマーシャル!$B:$B,全体!$G60,コマーシャル!AL:AL)) -> 0 | AV60: =SUM(SUMIF(コンシューマー!$B:$B,全体!$G60,コンシューマー!AQ:AQ),SUMIF(コマーシャル!$B:$B,全体!$G60,コマーシャル!AM:AM)) -> 0 | AW60: =SUM(SUMIF(コンシューマー!$B:$B,全体!$G60,コンシューマー!AR:AR),SUMIF(コマーシャル!$B:$B,全体!$G60,コマーシャル!AN:AN)) -> 0 | AX60: =SUM(SUMIF(コンシューマー!$B:$B,全体!$G60,コンシューマー!AS:AS),SUMIF(コマーシャル!$B:$B,全体!$G60,コマーシャル!AO:AO)) -> 0 | AY60: =SUM(SUMIF(コンシューマー!$B:$B,全体!$G60,コンシューマー!AT:AT),SUMIF(コマーシャル!$B:$B,全体!$G60,コマーシャル!AP:AP)) -> 0
A61: =SUMIFS(SAP貼付!K:K,SAP貼付!C:C,全体!G61) -> 1 | B61: =SUMIFS(VGAMBFCST貼付!D:D,VGAMBFCST貼付!B:B,G61,VGAMBFCST貼付!C:C,全体!$B$20) -> 5 | C61: =SUMIFS(VGAMBFCST貼付!D:D,VGAMBFCST貼付!B:B,G61,VGAMBFCST貼付!C:C,全体!$C$20) -> 0 | D61: =SUM(A61:C61) -> 6 | E61: =IFERROR(D61-SUM(#REF!)," ") | G61: 5000Ada | H61: =IFERROR(IF(MATCH($G61,コンシューマー!B:B,0),"Y"),"-") -> Y | I61: =IFERROR(IF(MATCH($G61,コマーシャル!B:B,0),"Y"),"-") -> Y | J61: =SUMIF(コンシューマー!$B:$B,全体!$G61,コンシューマー!D:D) -> 0 | K61: =SUMIF(コンシューマー!$B:$B,全体!$G61,コンシューマー!E:E) -> 0 | L61: =SUMIF(コンシューマー!$B:$B,全体!$G61,コンシューマー!F:F) -> 0 | M61: =SUMIF(コンシューマー!$B:$B,全体!$G61,コンシューマー!G:G) -> 0 | N61: =SUMIF(コンシューマー!$B:$B,全体!$G61,コンシューマー!H:H) -> 0 | O61: =SUMIF(コンシューマー!$B:$B,全体!$G61,コンシューマー!I:I) -> 0 | P61: =SUMIF(コンシューマー!$B:$B,全体!$G61,コンシューマー!J:J) -> 2 | Q61: =SUMIF(コンシューマー!$B:$B,全体!$G61,コンシューマー!K:K) -> 1 | R61: =SUMIF(コンシューマー!$B:$B,全体!$G61,コンシューマー!L:L) -> 0 | S61: =SUMIF(コンシューマー!$B:$B,全体!$G61,コンシューマー!M:M) -> 0 | T61: =SUMIF(コンシューマー!$B:$B,全体!$G61,コンシューマー!N:N) -> 1 | U61: =SUMIF(コンシューマー!$B:$B,全体!$G61,コンシューマー!O:O) -> 1 | V61: =SUMIF(コンシューマー!$B:$B,全体!$G61,コンシューマー!P:P) -> 0 | W61: =SUMIF(コンシューマー!$B:$B,全体!$G61,コンシューマー!Q:Q) -> 0 | X61: =SUMIF(コンシューマー!$B:$B,全体!$G61,コンシューマー!R:R) -> 0 | Y61: =SUMIF(コンシューマー!$B:$B,全体!$G61,コンシューマー!S:S) -> 4 | Z61: =SUMIF(コンシューマー!$B:$B,全体!$G61,コンシューマー!T:T) -> 0 | AA61: =SUMIF(コンシューマー!$B:$B,全体!$G61,コンシューマー!U:U) -> 5 | AB61: =SUMIF(コンシューマー!$B:$B,全体!$G61,コンシューマー!V:V) -> 2 | AC61: =SUMIF(コンシューマー!$B:$B,全体!$G61,コンシューマー!W:W) -> 2 | AD61: =SUMIF(コンシューマー!$B:$B,全体!$G61,コンシューマー!X:X) -> 1 | AE61: =SUMIF(コンシューマー!$B:$B,全体!$G61,コンシューマー!Y:Y) -> 5 | AF61: =SUMIF(コンシューマー!$B:$B,全体!$G61,コンシューマー!Z:Z) -> 3 | AG61: =SUMIF(コンシューマー!$B:$B,全体!$G61,コンシューマー!AA:AA) -> 4 | AI61: 0 | AK61: 2 | AL61: 0 | AM61: 0 | AN61: 1 | AO61: 0 | AP61: 0 | AQ61: 0 | AR61: =SUMIF(結果貼付!$A:$A,G61,結果貼付!$D:$D) -> 0 | AS61: =(AR61/AS$2)*AS$1 -> 0 | AT61: =SUM(SUMIF(コンシューマー!$B:$B,全体!$G61,コンシューマー!AO:AO),SUMIF(コマーシャル!$B:$B,全体!$G61,コマーシャル!AK:AK)) -> 0 | AU61: =SUM(SUMIF(コンシューマー!$B:$B,全体!$G61,コンシューマー!AP:AP),SUMIF(コマーシャル!$B:$B,全体!$G61,コマーシャル!AL:AL)) -> 0 | AV61: =SUM(SUMIF(コンシューマー!$B:$B,全体!$G61,コンシューマー!AQ:AQ),SUMIF(コマーシャル!$B:$B,全体!$G61,コマーシャル!AM:AM)) -> 0 | AW61: =SUM(SUMIF(コンシューマー!$B:$B,全体!$G61,コンシューマー!AR:AR),SUMIF(コマーシャル!$B:$B,全体!$G61,コマーシャル!AN:AN)) -> 0 | AX61: =SUM(SUMIF(コンシューマー!$B:$B,全体!$G61,コンシューマー!AS:AS),SUMIF(コマーシャル!$B:$B,全体!$G61,コマーシャル!AO:AO)) -> 0 | AY61: =SUM(SUMIF(コンシューマー!$B:$B,全体!$G61,コンシューマー!AT:AT),SUMIF(コマーシャル!$B:$B,全体!$G61,コマーシャル!AP:AP)) -> 0
A62: =SUMIFS(SAP貼付!K:K,SAP貼付!C:C,全体!G62) -> 11 | B62: =SUMIFS(VGAMBFCST貼付!D:D,VGAMBFCST貼付!B:B,G62,VGAMBFCST貼付!C:C,全体!$B$20) -> 20 | C62: =SUMIFS(VGAMBFCST貼付!D:D,VGAMBFCST貼付!B:B,G62,VGAMBFCST貼付!C:C,全体!$C$20) -> 0 | D62: =SUM(A62:C62) -> 31 | E62: =IFERROR(D62-SUM(#REF!)," ") | G62: 4500Ada | H62: =IFERROR(IF(MATCH($G62,コンシューマー!B:B,0),"Y"),"-") -> Y | I62: =IFERROR(IF(MATCH($G62,コマーシャル!B:B,0),"Y"),"-") -> Y | J62: =SUMIF(コンシューマー!$B:$B,全体!$G62,コンシューマー!D:D) -> 0 | K62: =SUMIF(コンシューマー!$B:$B,全体!$G62,コンシューマー!E:E) -> 0 | L62: =SUMIF(コンシューマー!$B:$B,全体!$G62,コンシューマー!F:F) -> 0 | M62: =SUMIF(コンシューマー!$B:$B,全体!$G62,コンシューマー!G:G) -> 0 | N62: =SUMIF(コンシューマー!$B:$B,全体!$G62,コンシューマー!H:H) -> 0 | O62: =SUMIF(コンシューマー!$B:$B,全体!$G62,コンシューマー!I:I) -> 0 | P62: =SUMIF(コンシューマー!$B:$B,全体!$G62,コンシューマー!J:J) -> 1 | Q62: =SUMIF(コンシューマー!$B:$B,全体!$G62,コンシューマー!K:K) -> 1 | R62: =SUMIF(コンシューマー!$B:$B,全体!$G62,コンシューマー!L:L) -> 0 | S62: =SUMIF(コンシューマー!$B:$B,全体!$G62,コンシューマー!M:M) -> 1 | T62: =SUMIF(コンシューマー!$B:$B,全体!$G62,コンシューマー!N:N) -> 0 | U62: =SUMIF(コンシューマー!$B:$B,全体!$G62,コンシューマー!O:O) -> 3 | V62: =SUMIF(コンシューマー!$B:$B,全体!$G62,コンシューマー!P:P) -> 0 | W62: =SUMIF(コンシューマー!$B:$B,全体!$G62,コンシューマー!Q:Q) -> 9 | X62: =SUMIF(コンシューマー!$B:$B,全体!$G62,コンシューマー!R:R) -> 6 | Y62: =SUMIF(コンシューマー!$B:$B,全体!$G62,コンシューマー!S:S) -> 1 | Z62: =SUMIF(コンシューマー!$B:$B,全体!$G62,コンシューマー!T:T) -> 2 | AA62: =SUMIF(コンシューマー!$B:$B,全体!$G62,コンシューマー!U:U) -> 1 | AB62: =SUMIF(コンシューマー!$B:$B,全体!$G62,コンシューマー!V:V) -> 5 | AC62: =SUMIF(コンシューマー!$B:$B,全体!$G62,コンシューマー!W:W) -> 16 | AD62: =SUMIF(コンシューマー!$B:$B,全体!$G62,コンシューマー!X:X) -> 7 | AE62: =SUMIF(コンシューマー!$B:$B,全体!$G62,コンシューマー!Y:Y) -> 3 | AF62: =SUMIF(コンシューマー!$B:$B,全体!$G62,コンシューマー!Z:Z) -> 4 | AG62: =SUMIF(コンシューマー!$B:$B,全体!$G62,コンシューマー!AA:AA) -> 2 | AI62: 0 | AK62: 0 | AL62: 1.9354839 | AM62: 0 | AN62: 2 | AO62: 4 | AP62: 0 | AQ62: 1 | AR62: =SUMIF(結果貼付!$A:$A,G62,結果貼付!$D:$D) -> 0 | AS62: =(AR62/AS$2)*AS$1 -> 0 | AT62: =SUM(SUMIF(コンシューマー!$B:$B,全体!$G62,コンシューマー!AO:AO),SUMIF(コマーシャル!$B:$B,全体!$G62,コマーシャル!AK:AK)) -> 0 | AU62: =SUM(SUMIF(コンシューマー!$B:$B,全体!$G62,コンシューマー!AP:AP),SUMIF(コマーシャル!$B:$B,全体!$G62,コマーシャル!AL:AL)) -> 0 | AV62: =SUM(SUMIF(コンシューマー!$B:$B,全体!$G62,コンシューマー!AQ:AQ),SUMIF(コマーシャル!$B:$B,全体!$G62,コマーシャル!AM:AM)) -> 0 | AW62: =SUM(SUMIF(コンシューマー!$B:$B,全体!$G62,コンシューマー!AR:AR),SUMIF(コマーシャル!$B:$B,全体!$G62,コマーシャル!AN:AN)) -> 0 | AX62: =SUM(SUMIF(コンシューマー!$B:$B,全体!$G62,コンシューマー!AS:AS),SUMIF(コマーシャル!$B:$B,全体!$G62,コマーシャル!AO:AO)) -> 0 | AY62: =SUM(SUMIF(コンシューマー!$B:$B,全体!$G62,コンシューマー!AT:AT),SUMIF(コマーシャル!$B:$B,全体!$G62,コマーシャル!AP:AP)) -> 0
A63: =SUMIFS(SAP貼付!K:K,SAP貼付!C:C,全体!G63) -> 18 | B63: =SUMIFS(VGAMBFCST貼付!D:D,VGAMBFCST貼付!B:B,G63,VGAMBFCST貼付!C:C,全体!$B$20) -> 0 | C63: =SUMIFS(VGAMBFCST貼付!D:D,VGAMBFCST貼付!B:B,G63,VGAMBFCST貼付!C:C,全体!$C$20) -> 0 | D63: =SUM(A63:C63) -> 18 | E63: =IFERROR(D63-SUM(#REF!)," ") | G63: 4000Ada | H63: =IFERROR(IF(MATCH($G63,コンシューマー!B:B,0),"Y"),"-") -> Y | I63: =IFERROR(IF(MATCH($G63,コマーシャル!B:B,0),"Y"),"-") -> Y | J63: =SUMIF(コンシューマー!$B:$B,全体!$G63,コンシューマー!D:D) -> 0 | K63: =SUMIF(コンシューマー!$B:$B,全体!$G63,コンシューマー!E:E) -> 0 | L63: =SUMIF(コンシューマー!$B:$B,全体!$G63,コンシューマー!F:F) -> 0 | M63: =SUMIF(コンシューマー!$B:$B,全体!$G63,コンシューマー!G:G) -> 0 | N63: =SUMIF(コンシューマー!$B:$B,全体!$G63,コンシューマー!H:H) -> 0 | O63: =SUMIF(コンシューマー!$B:$B,全体!$G63,コンシューマー!I:I) -> 1 | P63: =SUMIF(コンシューマー!$B:$B,全体!$G63,コンシューマー!J:J) -> 0 | Q63: =SUMIF(コンシューマー!$B:$B,全体!$G63,コンシューマー!K:K) -> 6 | R63: =SUMIF(コンシューマー!$B:$B,全体!$G63,コンシューマー!L:L) -> 0 | S63: =SUMIF(コンシューマー!$B:$B,全体!$G63,コンシューマー!M:M) -> 2 | T63: =SUMIF(コンシューマー!$B:$B,全体!$G63,コンシューマー!N:N) -> 2 | U63: =SUMIF(コンシューマー!$B:$B,全体!$G63,コンシューマー!O:O) -> 2 | V63: =SUMIF(コンシューマー!$B:$B,全体!$G63,コンシューマー!P:P) -> 3 | W63: =SUMIF(コンシューマー!$B:$B,全体!$G63,コンシューマー!Q:Q) -> 3 | X63: =SUMIF(コンシューマー!$B:$B,全体!$G63,コンシューマー!R:R) -> 9 | Y63: =SUMIF(コンシューマー!$B:$B,全体!$G63,コンシューマー!S:S) -> 11 | Z63: =SUMIF(コンシューマー!$B:$B,全体!$G63,コンシューマー!T:T) -> 4 | AA63: =SUMIF(コンシューマー!$B:$B,全体!$G63,コンシューマー!U:U) -> 9 | AB63: =SUMIF(コンシューマー!$B:$B,全体!$G63,コンシューマー!V:V) -> 3 | AC63: =SUMIF(コンシューマー!$B:$B,全体!$G63,コンシューマー!W:W) -> 17 | AD63: =SUMIF(コンシューマー!$B:$B,全体!$G63,コンシューマー!X:X) -> 3 | AE63: =SUMIF(コンシューマー!$B:$B,全体!$G63,コンシューマー!Y:Y) -> 8 | AF63: =SUMIF(コンシューマー!$B:$B,全体!$G63,コンシューマー!Z:Z) -> 4 | AG63: =SUMIF(コンシューマー!$B:$B,全体!$G63,コンシューマー!AA:AA) -> 17 | AI63: 11 | AK63: 15 | AL63: 13.548387 | AM63: 0 | AN63: 2 | AO63: 0 | AP63: 0 | AQ63: 0 | AR63: =SUMIF(結果貼付!$A:$A,G63,結果貼付!$D:$D) -> 0 | AS63: =(AR63/AS$2)*AS$1 -> 0 | AT63: =SUM(SUMIF(コンシューマー!$B:$B,全体!$G63,コンシューマー!AO:AO),SUMIF(コマーシャル!$B:$B,全体!$G63,コマーシャル!AK:AK)) -> 0 | AU63: =SUM(SUMIF(コンシューマー!$B:$B,全体!$G63,コンシューマー!AP:AP),SUMIF(コマーシャル!$B:$B,全体!$G63,コマーシャル!AL:AL)) -> 0 | AV63: =SUM(SUMIF(コンシューマー!$B:$B,全体!$G63,コンシューマー!AQ:AQ),SUMIF(コマーシャル!$B:$B,全体!$G63,コマーシャル!AM:AM)) -> 0 | AW63: =SUM(SUMIF(コンシューマー!$B:$B,全体!$G63,コンシューマー!AR:AR),SUMIF(コマーシャル!$B:$B,全体!$G63,コマーシャル!AN:AN)) -> 0 | AX63: =SUM(SUMIF(コンシューマー!$B:$B,全体!$G63,コンシューマー!AS:AS),SUMIF(コマーシャル!$B:$B,全体!$G63,コマーシャル!AO:AO)) -> 0 | AY63: =SUM(SUMIF(コンシューマー!$B:$B,全体!$G63,コンシューマー!AT:AT),SUMIF(コマーシャル!$B:$B,全体!$G63,コマーシャル!AP:AP)) -> 0
A64: =SUMIFS(SAP貼付!K:K,SAP貼付!C:C,全体!G64) -> 0 | B64: =SUMIFS(VGAMBFCST貼付!D:D,VGAMBFCST貼付!B:B,G64,VGAMBFCST貼付!C:C,全体!$B$20) -> 0 | C64: =SUMIFS(VGAMBFCST貼付!D:D,VGAMBFCST貼付!B:B,G64,VGAMBFCST貼付!C:C,全体!$C$20) -> 0 | D64: =SUM(A64:C64) -> 0 | E64: =IFERROR(D64-SUM(#REF!)," ") | G64: 4000 SFF Ada | H64: =IFERROR(IF(MATCH($G64,コンシューマー!B:B,0),"Y"),"-") -> Y | I64: =IFERROR(IF(MATCH($G64,コマーシャル!B:B,0),"Y"),"-") -> Y | J64: =SUMIF(コンシューマー!$B:$B,全体!$G64,コンシューマー!D:D) -> 0 | K64: =SUMIF(コンシューマー!$B:$B,全体!$G64,コンシューマー!E:E) -> 0 | L64: =SUMIF(コンシューマー!$B:$B,全体!$G64,コンシューマー!F:F) -> 0 | M64: =SUMIF(コンシューマー!$B:$B,全体!$G64,コンシューマー!G:G) -> 0 | N64: =SUMIF(コンシューマー!$B:$B,全体!$G64,コンシューマー!H:H) -> 0 | O64: =SUMIF(コンシューマー!$B:$B,全体!$G64,コンシューマー!I:I) -> 0 | P64: =SUMIF(コンシューマー!$B:$B,全体!$G64,コンシューマー!J:J) -> 0 | Q64: =SUMIF(コンシューマー!$B:$B,全体!$G64,コンシューマー!K:K) -> 0 | R64: =SUMIF(コンシューマー!$B:$B,全体!$G64,コンシューマー!L:L) -> 0 | S64: =SUMIF(コンシューマー!$B:$B,全体!$G64,コンシューマー!M:M) -> 0 | T64: =SUMIF(コンシューマー!$B:$B,全体!$G64,コンシューマー!N:N) -> 0 | U64: =SUMIF(コンシューマー!$B:$B,全体!$G64,コンシューマー!O:O) -> 0 | V64: =SUMIF(コンシューマー!$B:$B,全体!$G64,コンシューマー!P:P) -> 0 | W64: =SUMIF(コンシューマー!$B:$B,全体!$G64,コンシューマー!Q:Q) -> 0 | X64: =SUMIF(コンシューマー!$B:$B,全体!$G64,コンシューマー!R:R) -> 0 | Y64: =SUMIF(コンシューマー!$B:$B,全体!$G64,コンシューマー!S:S) -> 1 | Z64: =SUMIF(コンシューマー!$B:$B,全体!$G64,コンシューマー!T:T) -> 0 | AA64: =SUMIF(コンシューマー!$B:$B,全体!$G64,コンシューマー!U:U) -> 0 | AB64: =SUMIF(コンシューマー!$B:$B,全体!$G64,コンシューマー!V:V) -> 0 | AC64: =SUMIF(コンシューマー!$B:$B,全体!$G64,コンシューマー!W:W) -> 5 | AD64: =SUMIF(コンシューマー!$B:$B,全体!$G64,コンシューマー!X:X) -> 0 | AE64: =SUMIF(コンシューマー!$B:$B,全体!$G64,コンシューマー!Y:Y) -> 0 | AF64: =SUMIF(コンシューマー!$B:$B,全体!$G64,コンシューマー!Z:Z) -> 0 | AG64: =SUMIF(コンシューマー!$B:$B,全体!$G64,コンシューマー!AA:AA) -> 0 | AI64: 0 | AK64: 0 | AL64: 0 | AM64: 0 | AN64: 0 | AO64: 0 | AP64: 0 | AQ64: 0 | AR64: =SUMIF(結果貼付!$A:$A,G64,結果貼付!$D:$D) -> 0 | AS64: =(AR64/AS$2)*AS$1 -> 0 | AT64: =SUM(SUMIF(コンシューマー!$B:$B,全体!$G64,コンシューマー!AO:AO),SUMIF(コマーシャル!$B:$B,全体!$G64,コマーシャル!AK:AK)) -> 0 | AU64: =SUM(SUMIF(コンシューマー!$B:$B,全体!$G64,コンシューマー!AP:AP),SUMIF(コマーシャル!$B:$B,全体!$G64,コマーシャル!AL:AL)) -> 0 | AV64: =SUM(SUMIF(コンシューマー!$B:$B,全体!$G64,コンシューマー!AQ:AQ),SUMIF(コマーシャル!$B:$B,全体!$G64,コマーシャル!AM:AM)) -> 0 | AW64: =SUM(SUMIF(コンシューマー!$B:$B,全体!$G64,コンシューマー!AR:AR),SUMIF(コマーシャル!$B:$B,全体!$G64,コマーシャル!AN:AN)) -> 0 | AX64: =SUM(SUMIF(コンシューマー!$B:$B,全体!$G64,コンシューマー!AS:AS),SUMIF(コマーシャル!$B:$B,全体!$G64,コマーシャル!AO:AO)) -> 0 | AY64: =SUM(SUMIF(コンシューマー!$B:$B,全体!$G64,コンシューマー!AT:AT),SUMIF(コマーシャル!$B:$B,全体!$G64,コマーシャル!AP:AP)) -> 0
A65: =SUMIFS(SAP貼付!K:K,SAP貼付!C:C,全体!G65) -> 0 | B65: =SUMIFS(VGAMBFCST貼付!D:D,VGAMBFCST貼付!B:B,G65,VGAMBFCST貼付!C:C,全体!$B$20) -> 0 | C65: =SUMIFS(VGAMBFCST貼付!D:D,VGAMBFCST貼付!B:B,G65,VGAMBFCST貼付!C:C,全体!$C$20) -> 0 | D65: =SUM(A65:C65) -> 0 | E65: =IFERROR(D65-SUM(#REF!)," ") | G65: 2000Ada | H65: =IFERROR(IF(MATCH($G65,コンシューマー!B:B,0),"Y"),"-") -> Y | I65: =IFERROR(IF(MATCH($G65,コマーシャル!B:B,0),"Y"),"-") -> Y | J65: =SUMIF(コンシューマー!$B:$B,全体!$G65,コンシューマー!D:D) -> 0 | K65: =SUMIF(コンシューマー!$B:$B,全体!$G65,コンシューマー!E:E) -> 0 | L65: =SUMIF(コンシューマー!$B:$B,全体!$G65,コンシューマー!F:F) -> 0 | M65: =SUMIF(コンシューマー!$B:$B,全体!$G65,コンシューマー!G:G) -> 0 | N65: =SUMIF(コンシューマー!$B:$B,全体!$G65,コンシューマー!H:H) -> 0 | O65: =SUMIF(コンシューマー!$B:$B,全体!$G65,コンシューマー!I:I) -> 0 | P65: =SUMIF(コンシューマー!$B:$B,全体!$G65,コンシューマー!J:J) -> 0 | Q65: =SUMIF(コンシューマー!$B:$B,全体!$G65,コンシューマー!K:K) -> 0 | R65: =SUMIF(コンシューマー!$B:$B,全体!$G65,コンシューマー!L:L) -> 0 | S65: =SUMIF(コンシューマー!$B:$B,全体!$G65,コンシューマー!M:M) -> 0 | T65: =SUMIF(コンシューマー!$B:$B,全体!$G65,コンシューマー!N:N) -> 0 | U65: =SUMIF(コンシューマー!$B:$B,全体!$G65,コンシューマー!O:O) -> 1 | V65: =SUMIF(コンシューマー!$B:$B,全体!$G65,コンシューマー!P:P) -> 1 | W65: =SUMIF(コンシューマー!$B:$B,全体!$G65,コンシューマー!Q:Q) -> 5 | X65: =SUMIF(コンシューマー!$B:$B,全体!$G65,コンシューマー!R:R) -> 21 | Y65: =SUMIF(コンシューマー!$B:$B,全体!$G65,コンシューマー!S:S) -> 3 | Z65: =SUMIF(コンシューマー!$B:$B,全体!$G65,コンシューマー!T:T) -> 29 | AA65: =SUMIF(コンシューマー!$B:$B,全体!$G65,コンシューマー!U:U) -> 6 | AB65: =SUMIF(コンシューマー!$B:$B,全体!$G65,コンシューマー!V:V) -> 8 | AC65: =SUMIF(コンシューマー!$B:$B,全体!$G65,コンシューマー!W:W) -> 44 | AD65: =SUMIF(コンシューマー!$B:$B,全体!$G65,コンシューマー!X:X) -> 39 | AE65: =SUMIF(コンシューマー!$B:$B,全体!$G65,コンシューマー!Y:Y) -> 19 | AF65: =SUMIF(コンシューマー!$B:$B,全体!$G65,コンシューマー!Z:Z) -> 6 | AG65: =SUMIF(コンシューマー!$B:$B,全体!$G65,コンシューマー!AA:AA) -> 29 | AI65: 0 | AK65: 16 | AL65: 1.9354839 | AM65: 0 | AN65: 0 | AO65: 2 | AP65: 5 | AQ65: 1 | AR65: =SUMIF(結果貼付!$A:$A,G65,結果貼付!$D:$D) -> 4 | AS65: =(AR65/AS$2)*AS$1 -> 8.5714286 | AT65: =SUM(SUMIF(コンシューマー!$B:$B,全体!$G65,コンシューマー!AO:AO),SUMIF(コマーシャル!$B:$B,全体!$G65,コマーシャル!AK:AK)) -> 0 | AU65: =SUM(SUMIF(コンシューマー!$B:$B,全体!$G65,コンシューマー!AP:AP),SUMIF(コマーシャル!$B:$B,全体!$G65,コマーシャル!AL:AL)) -> 0 | AV65: =SUM(SUMIF(コンシューマー!$B:$B,全体!$G65,コンシューマー!AQ:AQ),SUMIF(コマーシャル!$B:$B,全体!$G65,コマーシャル!AM:AM)) -> 0 | AW65: =SUM(SUMIF(コンシューマー!$B:$B,全体!$G65,コンシューマー!AR:AR),SUMIF(コマーシャル!$B:$B,全体!$G65,コマーシャル!AN:AN)) -> 0 | AX65: =SUM(SUMIF(コンシューマー!$B:$B,全体!$G65,コンシューマー!AS:AS),SUMIF(コマーシャル!$B:$B,全体!$G65,コマーシャル!AO:AO)) -> 0 | AY65: =SUM(SUMIF(コンシューマー!$B:$B,全体!$G65,コンシューマー!AT:AT),SUMIF(コマーシャル!$B:$B,全体!$G65,コマーシャル!AP:AP)) -> 0
A66: =SUMIFS(SAP貼付!K:K,SAP貼付!C:C,全体!G66) -> 2 | B66: =SUMIFS(VGAMBFCST貼付!D:D,VGAMBFCST貼付!B:B,G66,VGAMBFCST貼付!C:C,全体!$B$20) -> 0 | C66: =SUMIFS(VGAMBFCST貼付!D:D,VGAMBFCST貼付!B:B,G66,VGAMBFCST貼付!C:C,全体!$C$20) -> 0 | D66: =SUM(A66:C66) -> 2 | E66: =IFERROR(D66-SUM(#REF!)," ") | G66: A6000 | H66: =IFERROR(IF(MATCH($G66,コンシューマー!B:B,0),"Y"),"-") -> Y | I66: =IFERROR(IF(MATCH($G66,コマーシャル!B:B,0),"Y"),"-") -> Y | J66: =SUMIF(コンシューマー!$B:$B,全体!$G66,コンシューマー!D:D) -> 0 | K66: =SUMIF(コンシューマー!$B:$B,全体!$G66,コンシューマー!E:E) -> 0 | L66: =SUMIF(コンシューマー!$B:$B,全体!$G66,コンシューマー!F:F) -> 0 | M66: =SUMIF(コンシューマー!$B:$B,全体!$G66,コンシューマー!G:G) -> 0 | N66: =SUMIF(コンシューマー!$B:$B,全体!$G66,コンシューマー!H:H) -> 0 | O66: =SUMIF(コンシューマー!$B:$B,全体!$G66,コンシューマー!I:I) -> 1 | P66: =SUMIF(コンシューマー!$B:$B,全体!$G66,コンシューマー!J:J) -> 0 | Q66: =SUMIF(コンシューマー!$B:$B,全体!$G66,コンシューマー!K:K) -> 0 | R66: =SUMIF(コンシューマー!$B:$B,全体!$G66,コンシューマー!L:L) -> 0 | S66: =SUMIF(コンシューマー!$B:$B,全体!$G66,コンシューマー!M:M) -> 0 | T66: =SUMIF(コンシューマー!$B:$B,全体!$G66,コンシューマー!N:N) -> 0 | U66: =SUMIF(コンシューマー!$B:$B,全体!$G66,コンシューマー!O:O) -> 0 | V66: =SUMIF(コンシューマー!$B:$B,全体!$G66,コンシューマー!P:P) -> 0 | W66: =SUMIF(コンシューマー!$B:$B,全体!$G66,コンシューマー!Q:Q) -> 1 | X66: =SUMIF(コンシューマー!$B:$B,全体!$G66,コンシューマー!R:R) -> 0 | Y66: =SUMIF(コンシューマー!$B:$B,全体!$G66,コンシューマー!S:S) -> 0 | Z66: =SUMIF(コンシューマー!$B:$B,全体!$G66,コンシューマー!T:T) -> 0 | AA66: =SUMIF(コンシューマー!$B:$B,全体!$G66,コンシューマー!U:U) -> 0 | AB66: =SUMIF(コンシューマー!$B:$B,全体!$G66,コンシューマー!V:V) -> 0 | AC66: =SUMIF(コンシューマー!$B:$B,全体!$G66,コンシューマー!W:W) -> 0 | AD66: =SUMIF(コンシューマー!$B:$B,全体!$G66,コンシューマー!X:X) -> 0 | AE66: =SUMIF(コンシューマー!$B:$B,全体!$G66,コンシューマー!Y:Y) -> 0 | AF66: =SUMIF(コンシューマー!$B:$B,全体!$G66,コンシューマー!Z:Z) -> 0 | AG66: =SUMIF(コンシューマー!$B:$B,全体!$G66,コンシューマー!AA:AA) -> 0 | AI66: 0 | AK66: 0 | AL66: 0 | AM66: 0 | AN66: 0 | AO66: 0 | AP66: 0 | AQ66: 0 | AR66: =SUMIF(結果貼付!$A:$A,G66,結果貼付!$D:$D) -> 0 | AS66: =(AR66/AS$2)*AS$1 -> 0 | AT66: =SUM(SUMIF(コンシューマー!$B:$B,全体!$G66,コンシューマー!AO:AO),SUMIF(コマーシャル!$B:$B,全体!$G66,コマーシャル!AK:AK)) -> 0 | AU66: =SUM(SUMIF(コンシューマー!$B:$B,全体!$G66,コンシューマー!AP:AP),SUMIF(コマーシャル!$B:$B,全体!$G66,コマーシャル!AL:AL)) -> 0 | AV66: =SUM(SUMIF(コンシューマー!$B:$B,全体!$G66,コンシューマー!AQ:AQ),SUMIF(コマーシャル!$B:$B,全体!$G66,コマーシャル!AM:AM)) -> 0 | AW66: =SUM(SUMIF(コンシューマー!$B:$B,全体!$G66,コンシューマー!AR:AR),SUMIF(コマーシャル!$B:$B,全体!$G66,コマーシャル!AN:AN)) -> 0 | AX66: =SUM(SUMIF(コンシューマー!$B:$B,全体!$G66,コンシューマー!AS:AS),SUMIF(コマーシャル!$B:$B,全体!$G66,コマーシャル!AO:AO)) -> 0 | AY66: =SUM(SUMIF(コンシューマー!$B:$B,全体!$G66,コンシューマー!AT:AT),SUMIF(コマーシャル!$B:$B,全体!$G66,コマーシャル!AP:AP)) -> 0
A67: =SUMIFS(SAP貼付!K:K,SAP貼付!C:C,全体!G67) -> 1 | B67: =SUMIFS(VGAMBFCST貼付!D:D,VGAMBFCST貼付!B:B,G67,VGAMBFCST貼付!C:C,全体!$B$20) -> 0 | C67: =SUMIFS(VGAMBFCST貼付!D:D,VGAMBFCST貼付!B:B,G67,VGAMBFCST貼付!C:C,全体!$C$20) -> 0 | D67: =SUM(A67:C67) -> 1 | E67: =IFERROR(D67-SUM(#REF!)," ") | G67: A5500 | H67: =IFERROR(IF(MATCH($G67,コンシューマー!B:B,0),"Y"),"-") -> Y | I67: =IFERROR(IF(MATCH($G67,コマーシャル!B:B,0),"Y"),"-") -> Y | J67: =SUMIF(コンシューマー!$B:$B,全体!$G67,コンシューマー!D:D) -> 0 | K67: =SUMIF(コンシューマー!$B:$B,全体!$G67,コンシューマー!E:E) -> 0 | L67: =SUMIF(コンシューマー!$B:$B,全体!$G67,コンシューマー!F:F) -> 0 | M67: =SUMIF(コンシューマー!$B:$B,全体!$G67,コンシューマー!G:G) -> 0 | N67: =SUMIF(コンシューマー!$B:$B,全体!$G67,コンシューマー!H:H) -> 0 | O67: =SUMIF(コンシューマー!$B:$B,全体!$G67,コンシューマー!I:I) -> 0 | P67: =SUMIF(コンシューマー!$B:$B,全体!$G67,コンシューマー!J:J) -> 1 | Q67: =SUMIF(コンシューマー!$B:$B,全体!$G67,コンシューマー!K:K) -> 1 | R67: =SUMIF(コンシューマー!$B:$B,全体!$G67,コンシューマー!L:L) -> 1 | S67: =SUMIF(コンシューマー!$B:$B,全体!$G67,コンシューマー!M:M) -> 0 | T67: =SUMIF(コンシューマー!$B:$B,全体!$G67,コンシューマー!N:N) -> 0 | U67: =SUMIF(コンシューマー!$B:$B,全体!$G67,コンシューマー!O:O) -> 0 | V67: =SUMIF(コンシューマー!$B:$B,全体!$G67,コンシューマー!P:P) -> 0 | W67: =SUMIF(コンシューマー!$B:$B,全体!$G67,コンシューマー!Q:Q) -> 0 | X67: =SUMIF(コンシューマー!$B:$B,全体!$G67,コンシューマー!R:R) -> 0 | Y67: =SUMIF(コンシューマー!$B:$B,全体!$G67,コンシューマー!S:S) -> 0 | Z67: =SUMIF(コンシューマー!$B:$B,全体!$G67,コンシューマー!T:T) -> 0 | AA67: =SUMIF(コンシューマー!$B:$B,全体!$G67,コンシューマー!U:U) -> 0 | AB67: =SUMIF(コンシューマー!$B:$B,全体!$G67,コンシューマー!V:V) -> 0 | AC67: =SUMIF(コンシューマー!$B:$B,全体!$G67,コンシューマー!W:W) -> 1 | AD67: =SUMIF(コンシューマー!$B:$B,全体!$G67,コンシューマー!X:X) -> 0 | AE67: =SUMIF(コンシューマー!$B:$B,全体!$G67,コンシューマー!Y:Y) -> 0 | AF67: =SUMIF(コンシューマー!$B:$B,全体!$G67,コンシューマー!Z:Z) -> 0 | AG67: =SUMIF(コンシューマー!$B:$B,全体!$G67,コンシューマー!AA:AA) -> 0 | AI67: 0 | AK67: 0 | AL67: 0 | AM67: 0 | AN67: 0 | AO67: 0 | AP67: 0 | AQ67: 0 | AR67: =SUMIF(結果貼付!$A:$A,G67,結果貼付!$D:$D) -> 0 | AS67: =(AR67/AS$2)*AS$1 -> 0 | AT67: =SUM(SUMIF(コンシューマー!$B:$B,全体!$G67,コンシューマー!AO:AO),SUMIF(コマーシャル!$B:$B,全体!$G67,コマーシャル!AK:AK)) -> 0 | AU67: =SUM(SUMIF(コンシューマー!$B:$B,全体!$G67,コンシューマー!AP:AP),SUMIF(コマーシャル!$B:$B,全体!$G67,コマーシャル!AL:AL)) -> 0 | AV67: =SUM(SUMIF(コンシューマー!$B:$B,全体!$G67,コンシューマー!AQ:AQ),SUMIF(コマーシャル!$B:$B,全体!$G67,コマーシャル!AM:AM)) -> 0 | AW67: =SUM(SUMIF(コンシューマー!$B:$B,全体!$G67,コンシューマー!AR:AR),SUMIF(コマーシャル!$B:$B,全体!$G67,コマーシャル!AN:AN)) -> 0 | AX67: =SUM(SUMIF(コンシューマー!$B:$B,全体!$G67,コンシューマー!AS:AS),SUMIF(コマーシャル!$B:$B,全体!$G67,コマーシャル!AO:AO)) -> 0 | AY67: =SUM(SUMIF(コンシューマー!$B:$B,全体!$G67,コンシューマー!AT:AT),SUMIF(コマーシャル!$B:$B,全体!$G67,コマーシャル!AP:AP)) -> 0
A68: =SUMIFS(SAP貼付!K:K,SAP貼付!C:C,全体!G68) -> 6 | B68: =SUMIFS(VGAMBFCST貼付!D:D,VGAMBFCST貼付!B:B,G68,VGAMBFCST貼付!C:C,全体!$B$20) -> 0 | C68: =SUMIFS(VGAMBFCST貼付!D:D,VGAMBFCST貼付!B:B,G68,VGAMBFCST貼付!C:C,全体!$C$20) -> 0 | D68: =SUM(A68:C68) -> 6 | E68: =IFERROR(D68-SUM(#REF!)," ") | G68: A4500 | H68: =IFERROR(IF(MATCH($G68,コンシューマー!B:B,0),"Y"),"-") -> Y | I68: =IFERROR(IF(MATCH($G68,コマーシャル!B:B,0),"Y"),"-") -> Y | J68: =SUMIF(コンシューマー!$B:$B,全体!$G68,コンシューマー!D:D) -> 0 | K68: =SUMIF(コンシューマー!$B:$B,全体!$G68,コンシューマー!E:E) -> 0 | L68: =SUMIF(コンシューマー!$B:$B,全体!$G68,コンシューマー!F:F) -> 0 | M68: =SUMIF(コンシューマー!$B:$B,全体!$G68,コンシューマー!G:G) -> 0 | N68: =SUMIF(コンシューマー!$B:$B,全体!$G68,コンシューマー!H:H) -> 0 | O68: =SUMIF(コンシューマー!$B:$B,全体!$G68,コンシューマー!I:I) -> 0 | P68: =SUMIF(コンシューマー!$B:$B,全体!$G68,コンシューマー!J:J) -> 1 | Q68: =SUMIF(コンシューマー!$B:$B,全体!$G68,コンシューマー!K:K) -> 3 | R68: =SUMIF(コンシューマー!$B:$B,全体!$G68,コンシューマー!L:L) -> 1 | S68: =SUMIF(コンシューマー!$B:$B,全体!$G68,コンシューマー!M:M) -> 1 | T68: =SUMIF(コンシューマー!$B:$B,全体!$G68,コンシューマー!N:N) -> 0 | U68: =SUMIF(コンシューマー!$B:$B,全体!$G68,コンシューマー!O:O) -> 3 | V68: =SUMIF(コンシューマー!$B:$B,全体!$G68,コンシューマー!P:P) -> 1 | W68: =SUMIF(コンシューマー!$B:$B,全体!$G68,コンシューマー!Q:Q) -> 2 | X68: =SUMIF(コンシューマー!$B:$B,全体!$G68,コンシューマー!R:R) -> 0 | Y68: =SUMIF(コンシューマー!$B:$B,全体!$G68,コンシューマー!S:S) -> 1 | Z68: =SUMIF(コンシューマー!$B:$B,全体!$G68,コンシューマー!T:T) -> 2 | AA68: =SUMIF(コンシューマー!$B:$B,全体!$G68,コンシューマー!U:U) -> 3 | AB68: =SUMIF(コンシューマー!$B:$B,全体!$G68,コンシューマー!V:V) -> 2 | AC68: =SUMIF(コンシューマー!$B:$B,全体!$G68,コンシューマー!W:W) -> 3 | AD68: =SUMIF(コンシューマー!$B:$B,全体!$G68,コンシューマー!X:X) -> 0 | AE68: =SUMIF(コンシューマー!$B:$B,全体!$G68,コンシューマー!Y:Y) -> 1 | AF68: =SUMIF(コンシューマー!$B:$B,全体!$G68,コンシューマー!Z:Z) -> 1 | AG68: =SUMIF(コンシューマー!$B:$B,全体!$G68,コンシューマー!AA:AA) -> 0 | AI68: 0 | AK68: 0 | AL68: 0 | AM68: 0 | AN68: 0 | AO68: 0 | AP68: 0 | AQ68: 0 | AR68: =SUMIF(結果貼付!$A:$A,G68,結果貼付!$D:$D) -> 0 | AS68: =(AR68/AS$2)*AS$1 -> 0 | AT68: =SUM(SUMIF(コンシューマー!$B:$B,全体!$G68,コンシューマー!AO:AO),SUMIF(コマーシャル!$B:$B,全体!$G68,コマーシャル!AK:AK)) -> 0 | AU68: =SUM(SUMIF(コンシューマー!$B:$B,全体!$G68,コンシューマー!AP:AP),SUMIF(コマーシャル!$B:$B,全体!$G68,コマーシャル!AL:AL)) -> 0 | AV68: =SUM(SUMIF(コンシューマー!$B:$B,全体!$G68,コンシューマー!AQ:AQ),SUMIF(コマーシャル!$B:$B,全体!$G68,コマーシャル!AM:AM)) -> 0 | AW68: =SUM(SUMIF(コンシューマー!$B:$B,全体!$G68,コンシューマー!AR:AR),SUMIF(コマーシャル!$B:$B,全体!$G68,コマーシャル!AN:AN)) -> 0 | AX68: =SUM(SUMIF(コンシューマー!$B:$B,全体!$G68,コンシューマー!AS:AS),SUMIF(コマーシャル!$B:$B,全体!$G68,コマーシャル!AO:AO)) -> 0 | AY68: =SUM(SUMIF(コンシューマー!$B:$B,全体!$G68,コンシューマー!AT:AT),SUMIF(コマーシャル!$B:$B,全体!$G68,コマーシャル!AP:AP)) -> 0
A69: =SUMIFS(SAP貼付!K:K,SAP貼付!C:C,全体!G69) -> 9 | B69: =SUMIFS(VGAMBFCST貼付!D:D,VGAMBFCST貼付!B:B,G69,VGAMBFCST貼付!C:C,全体!$B$20) -> 0 | C69: =SUMIFS(VGAMBFCST貼付!D:D,VGAMBFCST貼付!B:B,G69,VGAMBFCST貼付!C:C,全体!$C$20) -> 0 | D69: =SUM(A69:C69) -> 9 | E69: =IFERROR(D69-SUM(#REF!)," ") | G69: A4000 | H69: =IFERROR(IF(MATCH($G69,コンシューマー!B:B,0),"Y"),"-") -> Y | I69: =IFERROR(IF(MATCH($G69,コマーシャル!B:B,0),"Y"),"-") -> Y | J69: =SUMIF(コンシューマー!$B:$B,全体!$G69,コンシューマー!D:D) -> 0 | K69: =SUMIF(コンシューマー!$B:$B,全体!$G69,コンシューマー!E:E) -> 1 | L69: =SUMIF(コンシューマー!$B:$B,全体!$G69,コンシューマー!F:F) -> 2 | M69: =SUMIF(コンシューマー!$B:$B,全体!$G69,コンシューマー!G:G) -> 0 | N69: =SUMIF(コンシューマー!$B:$B,全体!$G69,コンシューマー!H:H) -> 1 | O69: =SUMIF(コンシューマー!$B:$B,全体!$G69,コンシューマー!I:I) -> 3 | P69: =SUMIF(コンシューマー!$B:$B,全体!$G69,コンシューマー!J:J) -> 4 | Q69: =SUMIF(コンシューマー!$B:$B,全体!$G69,コンシューマー!K:K) -> 10 | R69: =SUMIF(コンシューマー!$B:$B,全体!$G69,コンシューマー!L:L) -> 2 | S69: =SUMIF(コンシューマー!$B:$B,全体!$G69,コンシューマー!M:M) -> 1 | T69: =SUMIF(コンシューマー!$B:$B,全体!$G69,コンシューマー!N:N) -> 3 | U69: =SUMIF(コンシューマー!$B:$B,全体!$G69,コンシューマー!O:O) -> 1 | V69: =SUMIF(コンシューマー!$B:$B,全体!$G69,コンシューマー!P:P) -> 3 | W69: =SUMIF(コンシューマー!$B:$B,全体!$G69,コンシューマー!Q:Q) -> 2 | X69: =SUMIF(コンシューマー!$B:$B,全体!$G69,コンシューマー!R:R) -> 0 | Y69: =SUMIF(コンシューマー!$B:$B,全体!$G69,コンシューマー!S:S) -> 0 | Z69: =SUMIF(コンシューマー!$B:$B,全体!$G69,コンシューマー!T:T) -> 1 | AA69: =SUMIF(コンシューマー!$B:$B,全体!$G69,コンシューマー!U:U) -> 0 | AB69: =SUMIF(コンシューマー!$B:$B,全体!$G69,コンシューマー!V:V) -> 0 | AC69: =SUMIF(コンシューマー!$B:$B,全体!$G69,コンシューマー!W:W) -> 0 | AD69: =SUMIF(コンシューマー!$B:$B,全体!$G69,コンシューマー!X:X) -> 0 | AE69: =SUMIF(コンシューマー!$B:$B,全体!$G69,コンシューマー!Y:Y) -> 0 | AF69: =SUMIF(コンシューマー!$B:$B,全体!$G69,コンシューマー!Z:Z) -> 0 | AG69: =SUMIF(コンシューマー!$B:$B,全体!$G69,コンシューマー!AA:AA) -> 0 | AI69: 0 | AK69: 0 | AL69: 0 | AM69: 0 | AN69: 0 | AO69: 0 | AP69: 0 | AQ69: 0 | AR69: =SUMIF(結果貼付!$A:$A,G69,結果貼付!$D:$D) -> 0 | AS69: =(AR69/AS$2)*AS$1 -> 0 | AT69: =SUM(SUMIF(コンシューマー!$B:$B,全体!$G69,コンシューマー!AO:AO),SUMIF(コマーシャル!$B:$B,全体!$G69,コマーシャル!AK:AK)) -> 0 | AU69: =SUM(SUMIF(コンシューマー!$B:$B,全体!$G69,コンシューマー!AP:AP),SUMIF(コマーシャル!$B:$B,全体!$G69,コマーシャル!AL:AL)) -> 0 | AV69: =SUM(SUMIF(コンシューマー!$B:$B,全体!$G69,コンシューマー!AQ:AQ),SUMIF(コマーシャル!$B:$B,全体!$G69,コマーシャル!AM:AM)) -> 0 | AW69: =SUM(SUMIF(コンシューマー!$B:$B,全体!$G69,コンシューマー!AR:AR),SUMIF(コマーシャル!$B:$B,全体!$G69,コマーシャル!AN:AN)) -> 0 | AX69: =SUM(SUMIF(コンシューマー!$B:$B,全体!$G69,コンシューマー!AS:AS),SUMIF(コマーシャル!$B:$B,全体!$G69,コマーシャル!AO:AO)) -> 0 | AY69: =SUM(SUMIF(コンシューマー!$B:$B,全体!$G69,コンシューマー!AT:AT),SUMIF(コマーシャル!$B:$B,全体!$G69,コマーシャル!AP:AP)) -> 0
A70: =SUMIFS(SAP貼付!K:K,SAP貼付!C:C,全体!G70) -> 72 | B70: =SUMIFS(VGAMBFCST貼付!D:D,VGAMBFCST貼付!B:B,G70,VGAMBFCST貼付!C:C,全体!$B$20) -> 0 | C70: =SUMIFS(VGAMBFCST貼付!D:D,VGAMBFCST貼付!B:B,G70,VGAMBFCST貼付!C:C,全体!$C$20) -> 0 | D70: =SUM(A70:C70) -> 72 | E70: =IFERROR(D70-SUM(#REF!)," ") | G70: A2000 | H70: =IFERROR(IF(MATCH($G70,コンシューマー!B:B,0),"Y"),"-") -> Y | I70: =IFERROR(IF(MATCH($G70,コマーシャル!B:B,0),"Y"),"-") -> Y | J70: =SUMIF(コンシューマー!$B:$B,全体!$G70,コンシューマー!D:D) -> 5 | K70: =SUMIF(コンシューマー!$B:$B,全体!$G70,コンシューマー!E:E) -> 10 | L70: =SUMIF(コンシューマー!$B:$B,全体!$G70,コンシューマー!F:F) -> 5 | M70: =SUMIF(コンシューマー!$B:$B,全体!$G70,コンシューマー!G:G) -> 3 | N70: =SUMIF(コンシューマー!$B:$B,全体!$G70,コンシューマー!H:H) -> 7 | O70: =SUMIF(コンシューマー!$B:$B,全体!$G70,コンシューマー!I:I) -> 11 | P70: =SUMIF(コンシューマー!$B:$B,全体!$G70,コンシューマー!J:J) -> 7 | Q70: =SUMIF(コンシューマー!$B:$B,全体!$G70,コンシューマー!K:K) -> 23 | R70: =SUMIF(コンシューマー!$B:$B,全体!$G70,コンシューマー!L:L) -> 8 | S70: =SUMIF(コンシューマー!$B:$B,全体!$G70,コンシューマー!M:M) -> 4 | T70: =SUMIF(コンシューマー!$B:$B,全体!$G70,コンシューマー!N:N) -> 8 | U70: =SUMIF(コンシューマー!$B:$B,全体!$G70,コンシューマー!O:O) -> 2 | V70: =SUMIF(コンシューマー!$B:$B,全体!$G70,コンシューマー!P:P) -> 1 | W70: =SUMIF(コンシューマー!$B:$B,全体!$G70,コンシューマー!Q:Q) -> 6 | X70: =SUMIF(コンシューマー!$B:$B,全体!$G70,コンシューマー!R:R) -> 3 | Y70: =SUMIF(コンシューマー!$B:$B,全体!$G70,コンシューマー!S:S) -> 0 | Z70: =SUMIF(コンシューマー!$B:$B,全体!$G70,コンシューマー!T:T) -> 0 | AA70: =SUMIF(コンシューマー!$B:$B,全体!$G70,コンシューマー!U:U) -> 0 | AB70: =SUMIF(コンシューマー!$B:$B,全体!$G70,コンシューマー!V:V) -> 0 | AC70: =SUMIF(コンシューマー!$B:$B,全体!$G70,コンシューマー!W:W) -> 0 | AD70: =SUMIF(コンシューマー!$B:$B,全体!$G70,コンシューマー!X:X) -> 0 | AE70: =SUMIF(コンシューマー!$B:$B,全体!$G70,コンシューマー!Y:Y) -> 0 | AF70: =SUMIF(コンシューマー!$B:$B,全体!$G70,コンシューマー!Z:Z) -> 0 | AG70: =SUMIF(コンシューマー!$B:$B,全体!$G70,コンシューマー!AA:AA) -> 0 | AI70: 0 | AK70: 0 | AL70: 0 | AM70: 0 | AN70: 0 | AO70: 0 | AP70: 0 | AQ70: 0 | AR70: =SUMIF(結果貼付!$A:$A,G70,結果貼付!$D:$D) -> 0 | AS70: =(AR70/AS$2)*AS$1 -> 0 | AT70: =SUM(SUMIF(コンシューマー!$B:$B,全体!$G70,コンシューマー!AO:AO),SUMIF(コマーシャル!$B:$B,全体!$G70,コマーシャル!AK:AK)) -> 0 | AU70: =SUM(SUMIF(コンシューマー!$B:$B,全体!$G70,コンシューマー!AP:AP),SUMIF(コマーシャル!$B:$B,全体!$G70,コマーシャル!AL:AL)) -> 0 | AV70: =SUM(SUMIF(コンシューマー!$B:$B,全体!$G70,コンシューマー!AQ:AQ),SUMIF(コマーシャル!$B:$B,全体!$G70,コマーシャル!AM:AM)) -> 0 | AW70: =SUM(SUMIF(コンシューマー!$B:$B,全体!$G70,コンシューマー!AR:AR),SUMIF(コマーシャル!$B:$B,全体!$G70,コマーシャル!AN:AN)) -> 0 | AX70: =SUM(SUMIF(コンシューマー!$B:$B,全体!$G70,コンシューマー!AS:AS),SUMIF(コマーシャル!$B:$B,全体!$G70,コマーシャル!AO:AO)) -> 0 | AY70: =SUM(SUMIF(コンシューマー!$B:$B,全体!$G70,コンシューマー!AT:AT),SUMIF(コマーシャル!$B:$B,全体!$G70,コマーシャル!AP:AP)) -> 0
A71: =SUMIFS(SAP貼付!K:K,SAP貼付!C:C,全体!G71) -> 33 | B71: =SUMIFS(VGAMBFCST貼付!D:D,VGAMBFCST貼付!B:B,G71,VGAMBFCST貼付!C:C,全体!$B$20) -> 29 | C71: =SUMIFS(VGAMBFCST貼付!D:D,VGAMBFCST貼付!B:B,G71,VGAMBFCST貼付!C:C,全体!$C$20) -> 0 | D71: =SUM(A71:C71) -> 62 | E71: =IFERROR(D71-SUM(#REF!)," ") | G71: A1000 | H71: =IFERROR(IF(MATCH($G71,コンシューマー!B:B,0),"Y"),"-") -> Y | I71: =IFERROR(IF(MATCH($G71,コマーシャル!B:B,0),"Y"),"-") -> Y | J71: =SUMIF(コンシューマー!$B:$B,全体!$G71,コンシューマー!D:D) -> 0 | K71: =SUMIF(コンシューマー!$B:$B,全体!$G71,コンシューマー!E:E) -> 0 | L71: =SUMIF(コンシューマー!$B:$B,全体!$G71,コンシューマー!F:F) -> 0 | M71: =SUMIF(コンシューマー!$B:$B,全体!$G71,コンシューマー!G:G) -> 0 | N71: =SUMIF(コンシューマー!$B:$B,全体!$G71,コンシューマー!H:H) -> 0 | O71: =SUMIF(コンシューマー!$B:$B,全体!$G71,コンシューマー!I:I) -> 0 | P71: =SUMIF(コンシューマー!$B:$B,全体!$G71,コンシューマー!J:J) -> 0 | Q71: =SUMIF(コンシューマー!$B:$B,全体!$G71,コンシューマー!K:K) -> 0 | R71: =SUMIF(コンシューマー!$B:$B,全体!$G71,コンシューマー!L:L) -> 0 | S71: =SUMIF(コンシューマー!$B:$B,全体!$G71,コンシューマー!M:M) -> 0 | T71: =SUMIF(コンシューマー!$B:$B,全体!$G71,コンシューマー!N:N) -> 0 | U71: =SUMIF(コンシューマー!$B:$B,全体!$G71,コンシューマー!O:O) -> 0 | V71: =SUMIF(コンシューマー!$B:$B,全体!$G71,コンシューマー!P:P) -> 0 | W71: =SUMIF(コンシューマー!$B:$B,全体!$G71,コンシューマー!Q:Q) -> 1 | X71: =SUMIF(コンシューマー!$B:$B,全体!$G71,コンシューマー!R:R) -> 2 | Y71: =SUMIF(コンシューマー!$B:$B,全体!$G71,コンシューマー!S:S) -> 7 | Z71: =SUMIF(コンシューマー!$B:$B,全体!$G71,コンシューマー!T:T) -> 3 | AA71: =SUMIF(コンシューマー!$B:$B,全体!$G71,コンシューマー!U:U) -> 8 | AB71: =SUMIF(コンシューマー!$B:$B,全体!$G71,コンシューマー!V:V) -> 43 | AC71: =SUMIF(コンシューマー!$B:$B,全体!$G71,コンシューマー!W:W) -> 6 | AD71: =SUMIF(コンシューマー!$B:$B,全体!$G71,コンシューマー!X:X) -> 66 | AE71: =SUMIF(コンシューマー!$B:$B,全体!$G71,コンシューマー!Y:Y) -> 16 | AF71: =SUMIF(コンシューマー!$B:$B,全体!$G71,コンシューマー!Z:Z) -> 17 | AG71: =SUMIF(コンシューマー!$B:$B,全体!$G71,コンシューマー!AA:AA) -> 32 | AI71: 0 | AK71: 27 | AL71: 12.580645 | AM71: 28 | AN71: 1 | AO71: 11 | AP71: 10 | AQ71: 3 | AR71: =SUMIF(結果貼付!$A:$A,G71,結果貼付!$D:$D) -> 5 | AS71: =(AR71/AS$2)*AS$1 -> 10.714286 | AT71: =SUM(SUMIF(コンシューマー!$B:$B,全体!$G71,コンシューマー!AO:AO),SUMIF(コマーシャル!$B:$B,全体!$G71,コマーシャル!AK:AK)) -> 20 | AU71: =SUM(SUMIF(コンシューマー!$B:$B,全体!$G71,コンシューマー!AP:AP),SUMIF(コマーシャル!$B:$B,全体!$G71,コマーシャル!AL:AL)) -> 20 | AV71: =SUM(SUMIF(コンシューマー!$B:$B,全体!$G71,コンシューマー!AQ:AQ),SUMIF(コマーシャル!$B:$B,全体!$G71,コマーシャル!AM:AM)) -> 20 | AW71: =SUM(SUMIF(コンシューマー!$B:$B,全体!$G71,コンシューマー!AR:AR),SUMIF(コマーシャル!$B:$B,全体!$G71,コマーシャル!AN:AN)) -> 20 | AX71: =SUM(SUMIF(コンシューマー!$B:$B,全体!$G71,コンシューマー!AS:AS),SUMIF(コマーシャル!$B:$B,全体!$G71,コマーシャル!AO:AO)) -> 20 | AY71: =SUM(SUMIF(コンシューマー!$B:$B,全体!$G71,コンシューマー!AT:AT),SUMIF(コマーシャル!$B:$B,全体!$G71,コマーシャル!AP:AP)) -> 30
... A75: =SUMIFS(SAP貼付!K:K,SAP貼付!C:C,全体!G75) -> 2 | B75: =SUMIFS(VGAMBFCST貼付!D:D,VGAMBFCST貼付!B:B,G75,VGAMBFCST貼付!C:C,全体!$B$20) -> 0 | C75: =SUMIFS(VGAMBFCST貼付!D:D,VGAMBFCST貼付!B:B,G75,VGAMBFCST貼付!C:C,全体!$C$20) -> 0 | D75: =SUM(A75:C75) -> 2 | E75: =IFERROR(D75-SUM(#REF!)," ") | G75: T400 | H75: =IFERROR(IF(MATCH($G75,コンシューマー!B:B,0),"Y"),"-") -> Y | I75: =IFERROR(IF(MATCH($G75,コマーシャル!B:B,0),"Y"),"-") -> Y | J75: =SUMIF(コンシューマー!$B:$B,全体!$G75,コンシューマー!D:D) -> 3 | K75: =SUMIF(コンシューマー!$B:$B,全体!$G75,コンシューマー!E:E) -> 6 | L75: =SUMIF(コンシューマー!$B:$B,全体!$G75,コンシューマー!F:F) -> 1 | M75: =SUMIF(コンシューマー!$B:$B,全体!$G75,コンシューマー!G:G) -> 6 | N75: =SUMIF(コンシューマー!$B:$B,全体!$G75,コンシューマー!H:H) -> 7 | O75: =SUMIF(コンシューマー!$B:$B,全体!$G75,コンシューマー!I:I) -> 2 | P75: =SUMIF(コンシューマー!$B:$B,全体!$G75,コンシューマー!J:J) -> 1 | Q75: =SUMIF(コンシューマー!$B:$B,全体!$G75,コンシューマー!K:K) -> 16 | R75: =SUMIF(コンシューマー!$B:$B,全体!$G75,コンシューマー!L:L) -> 4 | S75: =SUMIF(コンシューマー!$B:$B,全体!$G75,コンシューマー!M:M) -> 0 | T75: =SUMIF(コンシューマー!$B:$B,全体!$G75,コンシューマー!N:N) -> 7 | U75: =SUMIF(コンシューマー!$B:$B,全体!$G75,コンシューマー!O:O) -> 4 | V75: =SUMIF(コンシューマー!$B:$B,全体!$G75,コンシューマー!P:P) -> 3 | W75: =SUMIF(コンシューマー!$B:$B,全体!$G75,コンシューマー!Q:Q) -> 3 | X75: =SUMIF(コンシューマー!$B:$B,全体!$G75,コンシューマー!R:R) -> 2 | Y75: =SUMIF(コンシューマー!$B:$B,全体!$G75,コンシューマー!S:S) -> 0 | Z75: =SUMIF(コンシューマー!$B:$B,全体!$G75,コンシューマー!T:T) -> 0 | AA75: =SUMIF(コンシューマー!$B:$B,全体!$G75,コンシューマー!U:U) -> 0 | AB75: =SUMIF(コンシューマー!$B:$B,全体!$G75,コンシューマー!V:V) -> 0 | AC75: =SUMIF(コンシューマー!$B:$B,全体!$G75,コンシューマー!W:W) -> 0 | AD75: =SUMIF(コンシューマー!$B:$B,全体!$G75,コンシューマー!X:X) -> 0 | AE75: =SUMIF(コンシューマー!$B:$B,全体!$G75,コンシューマー!Y:Y) -> 0 | AF75: =SUMIF(コンシューマー!$B:$B,全体!$G75,コンシューマー!Z:Z) -> 0 | AG75: =SUMIF(コンシューマー!$B:$B,全体!$G75,コンシューマー!AA:AA) -> 0 | AI75: 0 | AK75: 0 | AL75: 0 | AM75: 0 | AN75: 0 | AO75: 0 | AP75: 0 | AQ75: 0 | AR75: =SUMIF(結果貼付!$A:$A,G75,結果貼付!$D:$D) -> 0 | AS75: =(AR75/AS$2)*AS$1 -> 0 | AT75: =SUM(SUMIF(コンシューマー!$B:$B,全体!$G75,コンシューマー!AO:AO),SUMIF(コマーシャル!$B:$B,全体!$G75,コマーシャル!AK:AK)) -> 0 | AU75: =SUM(SUMIF(コンシューマー!$B:$B,全体!$G75,コンシューマー!AP:AP),SUMIF(コマーシャル!$B:$B,全体!$G75,コマーシャル!AL:AL)) -> 0 | AV75: =SUM(SUMIF(コンシューマー!$B:$B,全体!$G75,コンシューマー!AQ:AQ),SUMIF(コマーシャル!$B:$B,全体!$G75,コマーシャル!AM:AM)) -> 0 | AW75: =SUM(SUMIF(コンシューマー!$B:$B,全体!$G75,コンシューマー!AR:AR),SUMIF(コマーシャル!$B:$B,全体!$G75,コマーシャル!AN:AN)) -> 0 | AX75: =SUM(SUMIF(コンシューマー!$B:$B,全体!$G75,コンシューマー!AS:AS),SUMIF(コマーシャル!$B:$B,全体!$G75,コマーシャル!AO:AO)) -> 0 | AY75: =SUM(SUMIF(コンシューマー!$B:$B,全体!$G75,コンシューマー!AT:AT),SUMIF(コマーシャル!$B:$B,全体!$G75,コマーシャル!AP:AP)) -> 0
A76: =SUM(A23:A75) -> 27547 | B76: =SUM(B23:B75) -> 24489 | C76: =SUM(C23:C75) -> 11743 | D76: =SUM(A76:C76) -> 63779 | E76: =SUM(E23:E75) -> 6660.029 | G76: VGA合計 | J76: =SUM(J21:J75) -> 7361 | K76: =SUM(K21:K75) -> 6711 | L76: =SUM(L21:L75) -> 5300 | M76: =SUM(M21:M75) -> 6715 | N76: =SUM(N21:N75) -> 9492 | O76: =SUM(O21:O75) -> 9638 | P76: =SUM(P21:P75) -> 6711 | Q76: =SUM(Q21:Q75) -> 7612 | ... AB76: =SUM(AB21:AB75) -> 13354 | AC76: =SUM(SUMIF(コンシューマー!$B:$B,全体!$G76,コンシューマー!W:W),SUMIF(コマーシャル!$B:$B,全体!$G76,コマーシャル!W:W)) -> 28885 | AD76: =SUM(SUMIF(コンシューマー!$B:$B,全体!$G76,コンシューマー!X:X),SUMIF(コマーシャル!$B:$B,全体!$G76,コマーシャル!X:X)) -> 17582 | AE76: =SUM(SUMIF(コンシューマー!$B:$B,全体!$G76,コンシューマー!Y:Y),SUMIF(コマーシャル!$B:$B,全体!$G76,コマーシャル!Y:Y)) -> 12867 | AF76: =SUM(SUMIF(コンシューマー!$B:$B,全体!$G76,コンシューマー!Z:Z),SUMIF(コマーシャル!$B:$B,全体!$G76,コマーシャル!Z:Z)) -> 13834 | AG76: =SUM(SUMIF(コンシューマー!$B:$B,全体!$G76,コンシューマー!AA:AA),SUMIF(コマーシャル!$B:$B,全体!$G76,コマーシャル!AA:AA)) -> 18695 | AH76: =SUM(SUMIF(コンシューマー!$B:$B,全体!$G76,コンシューマー!AB:AB),SUMIF(コマーシャル!$B:$B,全体!$G76,コマーシャル!AB:AB)) -> 13272 | AI76: =SUM(SUMIF(コンシューマー!$B:$B,全体!$G76,コンシューマー!AC:AC),SUMIF(コマーシャル!$B:$B,全体!$G76,コマーシャル!AC:AC)) -> 12338 | AJ76: =SUM(SUMIF(コンシューマー!$B:$B,全体!$G76,コンシューマー!AD:AD),SUMIF(コマーシャル!$B:$B,全体!$G76,コマーシャル!AD:AD)) -> 13870.376 | AK76: =SUM(SUMIF(コンシューマー!$B:$B,全体!$G76,コンシューマー!AE:AE),SUMIF(コマーシャル!$B:$B,全体!$G76,コマーシャル!AE:AE)) -> 11068 | AL76: =SUM(SUMIF(コンシューマー!$B:$B,全体!$G76,コンシューマー!AF:AF),SUMIF(コマーシャル!$B:$B,全体!$G76,コマーシャル!AF:AF)) -> 21193 | AM76: =SUM(SUMIF(コンシューマー!$B:$B,全体!$G76,コンシューマー!AG:AG),SUMIF(コマーシャル!$B:$B,全体!$G76,コマーシャル!AG:AG)) -> 12199 | AN76: =SUM(SUMIF(コンシューマー!$B:$B,全体!$G76,コンシューマー!AH:AH),SUMIF(コマーシャル!$B:$B,全体!$G76,コマーシャル!AH:AH)) -> 7447.5652 | AO76: =SUM(SUMIF(コンシューマー!$B:$B,全体!$G76,コンシューマー!AL:AL),SUMIF(コマーシャル!$B:$B,全体!$G76,コマーシャル!AI:AI)) -> 3736 | AP76: 9624 | AQ76: 11021 | AR76: =SUM(SUMIF(コンシューマー!$B:$B,全体!$G76,コンシューマー!AM:AM),SUMIF(コマーシャル!$B:$B,全体!$G76,コマーシャル!AJ:AJ)) -> 8227.5 | AS76: =SUM(SUMIF(コンシューマー!$B:$B,全体!$G76,コンシューマー!AN:AN),SUMIF(コマーシャル!$B:$B,全体!$G76,コマーシャル!AK:AK)) -> 7658.5 | AT76: =SUM(SUMIF(コンシューマー!$B:$B,全体!$G76,コンシューマー!AO:AO),SUMIF(コマーシャル!$B:$B,全体!$G76,コマーシャル!AK:AK)) -> 10062.855 | AU76: =SUM(SUMIF(コンシューマー!$B:$B,全体!$G76,コンシューマー!AP:AP),SUMIF(コマーシャル!$B:$B,全体!$G76,コマーシャル!AL:AL)) -> 12033.276 | AV76: =SUM(SUMIF(コンシューマー!$B:$B,全体!$G76,コンシューマー!AQ:AQ),SUMIF(コマーシャル!$B:$B,全体!$G76,コマーシャル!AM:AM)) -> 9689.2245 | AW76: =SUM(SUMIF(コンシューマー!$B:$B,全体!$G76,コンシューマー!AR:AR),SUMIF(コマーシャル!$B:$B,全体!$G76,コマーシャル!AN:AN)) -> 9465.0664 | AX76: =SUM(SUMIF(コンシューマー!$B:$B,全体!$G76,コンシューマー!AS:AS),SUMIF(コマーシャル!$B:$B,全体!$G76,コマーシャル!AO:AO)) -> 8349.6201 | AY76: =SUM(SUMIF(コンシューマー!$B:$B,全体!$G76,コンシューマー!AT:AT),SUMIF(コマーシャル!$B:$B,全体!$G76,コマーシャル!AP:AP)) -> 8279.9528
AT77: =SUM(SUMIF(コンシューマー!$B:$B,全体!$G77,コンシューマー!AO:AO),SUMIF(コマーシャル!$B:$B,全体!$G77,コマーシャル!AK:AK)) -> 0 | AU77: =SUM(SUMIF(コンシューマー!$B:$B,全体!$G77,コンシューマー!AP:AP),SUMIF(コマーシャル!$B:$B,全体!$G77,コマーシャル!AL:AL)) -> 0 | AV77: =SUM(SUMIF(コンシューマー!$B:$B,全体!$G77,コンシューマー!AQ:AQ),SUMIF(コマーシャル!$B:$B,全体!$G77,コマーシャル!AM:AM)) -> 0 | AW77: =SUM(SUMIF(コンシューマー!$B:$B,全体!$G77,コンシューマー!AR:AR),SUMIF(コマーシャル!$B:$B,全体!$G77,コマーシャル!AN:AN)) -> 0 | AX77: =SUM(SUMIF(コンシューマー!$B:$B,全体!$G77,コンシューマー!AS:AS),SUMIF(コマーシャル!$B:$B,全体!$G77,コマーシャル!AO:AO)) -> 0 | AY77: =SUM(SUMIF(コンシューマー!$B:$B,全体!$G77,コンシューマー!AT:AT),SUMIF(コマーシャル!$B:$B,全体!$G77,コマーシャル!AP:AP)) -> 0
A78: =SUMIFS(SAP貼付!K:K,SAP貼付!C:C,全体!#REF!) -> 0 | D78: =SUM(A78:C78) -> 0 | E78: =IFERROR(D78-SUM(#REF!)," ") | G78: U7-270K Plus | H78: =IFERROR(IF(MATCH($G78,コンシューマー!B:B,0),"Y"),"-") -> Y | I78: =IFERROR(IF(MATCH($G78,コマーシャル!B:B,0),"Y"),"-") -> Y | N78: =SUMIF(コンシューマー!$B:$B,全体!#REF!,コンシューマー!H:H) -> 0 | O78: =SUMIF(コンシューマー!$B:$B,全体!#REF!,コンシューマー!I:I) -> 0 | P78: =SUMIF(コンシューマー!$B:$B,全体!#REF!,コンシューマー!J:J) -> 0 | Q78: =SUMIF(コンシューマー!$B:$B,全体!#REF!,コンシューマー!K:K) -> 0 | R78: =SUMIF(コンシューマー!$B:$B,全体!#REF!,コンシューマー!L:L) -> 0 | S78: =SUMIF(コンシューマー!$B:$B,全体!#REF!,コンシューマー!M:M) -> 0 | T78: =SUMIF(コンシューマー!$B:$B,全体!#REF!,コンシューマー!N:N) -> 0 | U78: =SUMIF(コンシューマー!$B:$B,全体!#REF!,コンシューマー!O:O) -> 0 | V78: =SUMIF(コンシューマー!$B:$B,全体!#REF!,コンシューマー!P:P) -> 0 | W78: =SUMIF(コンシューマー!$B:$B,全体!#REF!,コンシューマー!Q:Q) -> 0 | X78: =SUMIF(コンシューマー!$B:$B,全体!#REF!,コンシューマー!R:R) -> 0 | Y78: =SUMIF(コンシューマー!$B:$B,全体!#REF!,コンシューマー!S:S) -> 0 | Z78: =SUMIF(コンシューマー!$B:$B,全体!#REF!,コンシューマー!T:T) -> 0 | AA78: =SUMIF(コンシューマー!$B:$B,全体!#REF!,コンシューマー!U:U) -> 0 | AB78: =SUMIF(コンシューマー!$B:$B,全体!#REF!,コンシューマー!V:V) -> 0 | AC78: =SUMIF(コンシューマー!$B:$B,全体!#REF!,コンシューマー!W:W) -> 0 | AD78: =SUMIF(コンシューマー!$B:$B,全体!#REF!,コンシューマー!X:X) -> 0 | AE78: =SUMIF(コンシューマー!$B:$B,全体!#REF!,コンシューマー!Y:Y) -> 0 | AF78: =SUMIF(コンシューマー!$B:$B,全体!#REF!,コンシューマー!Z:Z) -> 0 | AG78: =SUM(SUMIF(コンシューマー!$B:$B,全体!$G78,コンシューマー!AL:AL),SUMIF(コマーシャル!$B:$B,全体!$G78,コマーシャル!AA:AA)) -> 16 | AI78: =SUM(SUMIF(コンシューマー!$B:$B,全体!$G78,コンシューマー!AM:AM),SUMIF(コマーシャル!$B:$B,全体!$G78,コマーシャル!AI:AI)) -> 37.285714 | AK78: 0 | AL78: 0 | AM78: 0 | AN78: 0 | AO78: 1 | AP78: 24 | AQ78: 48 | AR78: =SUM(SUMIF(コンシューマー!$B:$B,全体!$G78,コンシューマー!AM:AM),SUMIF(コマーシャル!$B:$B,全体!$G78,コマーシャル!AI:AI)) -> 37.285714 | AS78: =SUM(SUMIF(コンシューマー!$B:$B,全体!$G78,コンシューマー!AN:AN),SUMIF(コマーシャル!$B:$B,全体!$G78,コマーシャル!AJ:AJ)) -> 34.285714 | AT78: =SUM(SUMIF(コンシューマー!$B:$B,全体!$G78,コンシューマー!AO:AO),SUMIF(コマーシャル!$B:$B,全体!$G78,コマーシャル!AK:AK)) -> 100 | AU78: =SUM(SUMIF(コンシューマー!$B:$B,全体!$G78,コンシューマー!AP:AP),SUMIF(コマーシャル!$B:$B,全体!$G78,コマーシャル!AL:AL)) -> 300 | AV78: =SUM(SUMIF(コンシューマー!$B:$B,全体!$G78,コンシューマー!AQ:AQ),SUMIF(コマーシャル!$B:$B,全体!$G78,コマーシャル!AM:AM)) -> 254.23638 | AW78: =SUM(SUMIF(コンシューマー!$B:$B,全体!$G78,コンシューマー!AR:AR),SUMIF(コマーシャル!$B:$B,全体!$G78,コマーシャル!AN:AN)) -> 249.2127 | AX78: =SUM(SUMIF(コンシューマー!$B:$B,全体!$G78,コンシューマー!AS:AS),SUMIF(コマーシャル!$B:$B,全体!$G78,コマーシャル!AO:AO)) -> 215.8908 | AY78: =SUM(SUMIF(コンシューマー!$B:$B,全体!$G78,コンシューマー!AT:AT),SUMIF(コマーシャル!$B:$B,全体!$G78,コマーシャル!AP:AP)) -> 213.94622 | AZ78: 性能次第ではU9の入れ替え先として検討
G79: U5-250K Plus | H79: =IFERROR(IF(MATCH($G79,コンシューマー!B:B,0),"Y"),"-") -> - | I79: =IFERROR(IF(MATCH($G79,コマーシャル!B:B,0),"Y"),"-") -> Y | N79: =SUMIF(コンシューマー!$B:$B,全体!#REF!,コンシューマー!H:H) -> 0 | O79: =SUMIF(コンシューマー!$B:$B,全体!#REF!,コンシューマー!I:I) -> 0 | P79: =SUMIF(コンシューマー!$B:$B,全体!#REF!,コンシューマー!J:J) -> 0 | Q79: =SUMIF(コンシューマー!$B:$B,全体!#REF!,コンシューマー!K:K) -> 0 | R79: =SUMIF(コンシューマー!$B:$B,全体!#REF!,コンシューマー!L:L) -> 0 | S79: =SUMIF(コンシューマー!$B:$B,全体!#REF!,コンシューマー!M:M) -> 0 | T79: =SUMIF(コンシューマー!$B:$B,全体!#REF!,コンシューマー!N:N) -> 0 | U79: =SUMIF(コンシューマー!$B:$B,全体!#REF!,コンシューマー!O:O) -> 0 | V79: =SUMIF(コンシューマー!$B:$B,全体!#REF!,コンシューマー!P:P) -> 0 | W79: =SUMIF(コンシューマー!$B:$B,全体!#REF!,コンシューマー!Q:Q) -> 0 | X79: =SUMIF(コンシューマー!$B:$B,全体!#REF!,コンシューマー!R:R) -> 0 | Y79: =SUMIF(コンシューマー!$B:$B,全体!#REF!,コンシューマー!S:S) -> 0 | Z79: =SUMIF(コンシューマー!$B:$B,全体!#REF!,コンシューマー!T:T) -> 0 | AA79: =SUMIF(コンシューマー!$B:$B,全体!#REF!,コンシューマー!U:U) -> 0 | AB79: =SUMIF(コンシューマー!$B:$B,全体!#REF!,コンシューマー!V:V) -> 0 | AC79: =SUMIF(コンシューマー!$B:$B,全体!#REF!,コンシューマー!W:W) -> 0 | AD79: =SUMIF(コンシューマー!$B:$B,全体!#REF!,コンシューマー!X:X) -> 0 | AE79: =SUMIF(コンシューマー!$B:$B,全体!#REF!,コンシューマー!Y:Y) -> 0 | AF79: =SUMIF(コンシューマー!$B:$B,全体!#REF!,コンシューマー!Z:Z) -> 0 | AG79: =SUM(SUMIF(コンシューマー!$B:$B,全体!$G79,コンシューマー!AL:AL),SUMIF(コマーシャル!$B:$B,全体!$G79,コマーシャル!AA:AA)) -> 0 | AI79: =SUM(SUMIF(コンシューマー!$B:$B,全体!$G79,コンシューマー!AM:AM),SUMIF(コマーシャル!$B:$B,全体!$G79,コマーシャル!AI:AI)) -> 0 | AK79: 0 | AL79: 0 | AM79: 0 | AN79: 0 | AO79: 0 | AP79: 0 | AQ79: 0 | AR79: =SUM(SUMIF(コンシューマー!$B:$B,全体!$G79,コンシューマー!AM:AM),SUMIF(コマーシャル!$B:$B,全体!$G79,コマーシャル!AI:AI)) -> 0 | AS79: =SUM(SUMIF(コンシューマー!$B:$B,全体!$G79,コンシューマー!AN:AN),SUMIF(コマーシャル!$B:$B,全体!$G79,コマーシャル!AJ:AJ)) -> 0 | AT79: =SUM(SUMIF(コンシューマー!$B:$B,全体!$G79,コンシューマー!AO:AO),SUMIF(コマーシャル!$B:$B,全体!$G79,コマーシャル!AK:AK)) -> 0 | AU79: =SUM(SUMIF(コンシューマー!$B:$B,全体!$G79,コンシューマー!AP:AP),SUMIF(コマーシャル!$B:$B,全体!$G79,コマーシャル!AL:AL)) -> 0 | AV79: =SUM(SUMIF(コンシューマー!$B:$B,全体!$G79,コンシューマー!AQ:AQ),SUMIF(コマーシャル!$B:$B,全体!$G79,コマーシャル!AM:AM)) -> 0 | AW79: =SUM(SUMIF(コンシューマー!$B:$B,全体!$G79,コンシューマー!AR:AR),SUMIF(コマーシャル!$B:$B,全体!$G79,コマーシャル!AN:AN)) -> 0 | AX79: =SUM(SUMIF(コンシューマー!$B:$B,全体!$G79,コンシューマー!AS:AS),SUMIF(コマーシャル!$B:$B,全体!$G79,コマーシャル!AO:AO)) -> 0 | AY79: =SUM(SUMIF(コンシューマー!$B:$B,全体!$G79,コンシューマー!AT:AT),SUMIF(コマーシャル!$B:$B,全体!$G79,コマーシャル!AP:AP)) -> 0 | AZ79: 性能次第ではU7の入れ替え先として検討
A80: =SUMIFS(SAP貼付!K:K,SAP貼付!C:C,全体!G80) -> 0 | D80: =SUM(A80:C80) -> 0 | E80: =IFERROR(D80-SUM(#REF!)," ") | G80: U9-285K | H80: =IFERROR(IF(MATCH($G80,コンシューマー!B:B,0),"Y"),"-") -> Y | I80: =IFERROR(IF(MATCH($G80,コマーシャル!B:B,0),"Y"),"-") -> Y | N80: =SUMIF(コンシューマー!$B:$B,全体!$G80,コンシューマー!H:H) -> 0 | O80: =SUMIF(コンシューマー!$B:$B,全体!$G80,コンシューマー!I:I) -> 0 | P80: =SUMIF(コンシューマー!$B:$B,全体!$G80,コンシューマー!J:J) -> 0 | Q80: =SUMIF(コンシューマー!$B:$B,全体!$G80,コンシューマー!K:K) -> 0 | R80: =SUMIF(コンシューマー!$B:$B,全体!$G80,コンシューマー!L:L) -> 0 | S80: =SUMIF(コンシューマー!$B:$B,全体!$G80,コンシューマー!M:M) -> 0 | T80: =SUMIF(コンシューマー!$B:$B,全体!$G80,コンシューマー!N:N) -> 0 | U80: =SUMIF(コンシューマー!$B:$B,全体!$G80,コンシューマー!O:O) -> 0 | V80: =SUMIF(コンシューマー!$B:$B,全体!$G80,コンシューマー!P:P) -> 0 | W80: =SUMIF(コンシューマー!$B:$B,全体!$G80,コンシューマー!Q:Q) -> 0 | X80: =SUMIF(コンシューマー!$B:$B,全体!$G80,コンシューマー!R:R) -> 0 | Y80: =SUMIF(コンシューマー!$B:$B,全体!$G80,コンシューマー!S:S) -> 55 | Z80: =SUMIF(コンシューマー!$B:$B,全体!$G80,コンシューマー!T:T) -> 105 | AA80: =SUMIF(コンシューマー!$B:$B,全体!$G80,コンシューマー!U:U) -> 98 | AB80: =SUMIF(コンシューマー!$B:$B,全体!$G80,コンシューマー!V:V) -> 307 | AC80: =SUMIF(コンシューマー!$B:$B,全体!$G80,コンシューマー!W:W) -> 454 | AD80: =SUMIF(コンシューマー!$B:$B,全体!$G80,コンシューマー!X:X) -> 233 | AE80: =SUMIF(コンシューマー!$B:$B,全体!$G80,コンシューマー!Y:Y) -> 226 | AF80: =SUMIF(コンシューマー!$B:$B,全体!$G80,コンシューマー!Z:Z) -> 306 | AG80: =SUM(SUMIF(コンシューマー!$B:$B,全体!$G80,コンシューマー!AL:AL),SUMIF(コマーシャル!$B:$B,全体!$G80,コマーシャル!AA:AA)) -> 132 | AI80: 260 | AK80: 292 | AL80: 322.25806 | AM80: 231 | AN80: 170 | AO80: 148 | AP80: 132 | AQ80: 173 | AR80: =SUM(SUMIF(コンシューマー!$B:$B,全体!$G80,コンシューマー!AM:AM),SUMIF(コマーシャル!$B:$B,全体!$G80,コマーシャル!AI:AI)) -> 156.57143 | AS80: =SUM(SUMIF(コンシューマー!$B:$B,全体!$G80,コンシューマー!AN:AN),SUMIF(コマーシャル!$B:$B,全体!$G80,コマーシャル!AJ:AJ)) -> 143.57143 | AT80: =SUM(SUMIF(コンシューマー!$B:$B,全体!$G80,コンシューマー!AO:AO),SUMIF(コマーシャル!$B:$B,全体!$G80,コマーシャル!AK:AK)) -> 150 | AU80: =SUM(SUMIF(コンシューマー!$B:$B,全体!$G80,コンシューマー!AP:AP),SUMIF(コマーシャル!$B:$B,全体!$G80,コマーシャル!AL:AL)) -> 170 | AV80: =SUM(SUMIF(コンシューマー!$B:$B,全体!$G80,コンシューマー!AQ:AQ),SUMIF(コマーシャル!$B:$B,全体!$G80,コマーシャル!AM:AM)) -> 151.69455 | AW80: =SUM(SUMIF(コンシューマー!$B:$B,全体!$G80,コンシューマー!AR:AR),SUMIF(コマーシャル!$B:$B,全体!$G80,コマーシャル!AN:AN)) -> 149.68508 | AX80: =SUM(SUMIF(コンシューマー!$B:$B,全体!$G80,コンシューマー!AS:AS),SUMIF(コマーシャル!$B:$B,全体!$G80,コマーシャル!AO:AO)) -> 146.35632 | AY80: =SUM(SUMIF(コンシューマー!$B:$B,全体!$G80,コンシューマー!AT:AT),SUMIF(コマーシャル!$B:$B,全体!$G80,コマーシャル!AP:AP)) -> 145.57849
A81: =SUMIFS(SAP貼付!K:K,SAP貼付!C:C,全体!G81) -> 0 | D81: =SUM(A81:C81) -> 0 | E81: =IFERROR(D81-SUM(#REF!)," ") | G81: U9-285 | H81: =IFERROR(IF(MATCH($G81,コンシューマー!B:B,0),"Y"),"-") -> Y | I81: =IFERROR(IF(MATCH($G81,コマーシャル!B:B,0),"Y"),"-") -> Y | J81: =SUMIF(コンシューマー!$B:$B,全体!$G81,コンシューマー!D:D) -> 0 | K81: =SUMIF(コンシューマー!$B:$B,全体!$G81,コンシューマー!E:E) -> 0 | L81: =SUMIF(コンシューマー!$B:$B,全体!$G81,コンシューマー!F:F) -> 0 | M81: =SUMIF(コンシューマー!$B:$B,全体!$G81,コンシューマー!G:G) -> 0 | N81: =SUMIF(コンシューマー!$B:$B,全体!$G81,コンシューマー!H:H) -> 0 | O81: =SUMIF(コンシューマー!$B:$B,全体!$G81,コンシューマー!I:I) -> 0 | P81: =SUMIF(コンシューマー!$B:$B,全体!$G81,コンシューマー!J:J) -> 0 | Q81: =SUMIF(コンシューマー!$B:$B,全体!$G81,コンシューマー!K:K) -> 0 | R81: =SUMIF(コンシューマー!$B:$B,全体!$G81,コンシューマー!L:L) -> 0 | S81: =SUMIF(コンシューマー!$B:$B,全体!$G81,コンシューマー!M:M) -> 0 | T81: =SUMIF(コンシューマー!$B:$B,全体!$G81,コンシューマー!N:N) -> 0 | U81: =SUMIF(コンシューマー!$B:$B,全体!$G81,コンシューマー!O:O) -> 0 | V81: =SUMIF(コンシューマー!$B:$B,全体!$G81,コンシューマー!P:P) -> 0 | W81: =SUMIF(コンシューマー!$B:$B,全体!$G81,コンシューマー!Q:Q) -> 0 | X81: =SUMIF(コンシューマー!$B:$B,全体!$G81,コンシューマー!R:R) -> 0 | Y81: =SUMIF(コンシューマー!$B:$B,全体!$G81,コンシューマー!S:S) -> 0 | Z81: =SUMIF(コンシューマー!$B:$B,全体!$G81,コンシューマー!T:T) -> 0 | AA81: =SUMIF(コンシューマー!$B:$B,全体!$G81,コンシューマー!U:U) -> 0 | AB81: =SUMIF(コンシューマー!$B:$B,全体!$G81,コンシューマー!V:V) -> 0 | AC81: =SUMIF(コンシューマー!$B:$B,全体!$G81,コンシューマー!W:W) -> 37 | AD81: =SUMIF(コンシューマー!$B:$B,全体!$G81,コンシューマー!X:X) -> 61 | AE81: =SUMIF(コンシューマー!$B:$B,全体!$G81,コンシューマー!Y:Y) -> 118 | AF81: =SUMIF(コンシューマー!$B:$B,全体!$G81,コンシューマー!Z:Z) -> 100 | AG81: =SUMIF(コンシューマー!$B:$B,全体!$G81,コンシューマー!AA:AA) -> 169 | AI81: 94 | AK81: 57 | AL81: 54.193548 | AM81: 43.904167 | AN81: 27 | AO81: 22 | AP81: 14 | AQ81: 17 | AR81: =SUMIF(結果貼付!$A:$A,G81,結果貼付!$D:$D) -> 14 | AS81: =(AR81/AS$2)*AS$1 -> 30 | AT81: =SUM(SUMIF(コンシューマー!$B:$B,全体!$G81,コンシューマー!AO:AO),SUMIF(コマーシャル!$B:$B,全体!$G81,コマーシャル!AK:AK)) -> 23.39254 | AU81: =SUM(SUMIF(コンシューマー!$B:$B,全体!$G81,コンシューマー!AP:AP),SUMIF(コマーシャル!$B:$B,全体!$G81,コマーシャル!AL:AL)) -> 24.071048 | AV81: =SUM(SUMIF(コンシューマー!$B:$B,全体!$G81,コンシューマー!AQ:AQ),SUMIF(コマーシャル!$B:$B,全体!$G81,コマーシャル!AM:AM)) -> 23.450028 | AW81: =SUM(SUMIF(コンシューマー!$B:$B,全体!$G81,コンシューマー!AR:AR),SUMIF(コマーシャル!$B:$B,全体!$G81,コマーシャル!AN:AN)) -> 23.381856 | AX81: =SUM(SUMIF(コンシューマー!$B:$B,全体!$G81,コンシューマー!AS:AS),SUMIF(コマーシャル!$B:$B,全体!$G81,コマーシャル!AO:AO)) -> 32.929672 | AY81: =SUM(SUMIF(コンシューマー!$B:$B,全体!$G81,コンシューマー!AT:AT),SUMIF(コマーシャル!$B:$B,全体!$G81,コマーシャル!AP:AP)) -> 32.903284
A82: =SUMIFS(SAP貼付!K:K,SAP貼付!C:C,全体!G82) -> 0 | D82: =SUM(A82:C82) -> 0 | E82: =IFERROR(D82-SUM(#REF!)," ") | G82: U9-285T | H82: =IFERROR(IF(MATCH($G82,コンシューマー!B:B,0),"Y"),"-") -> Y | I82: =IFERROR(IF(MATCH($G82,コマーシャル!B:B,0),"Y"),"-") -> Y | J82: =SUMIF(コンシューマー!$B:$B,全体!$G82,コンシューマー!D:D) -> 0 | K82: =SUMIF(コンシューマー!$B:$B,全体!$G82,コンシューマー!E:E) -> 0 | L82: =SUMIF(コンシューマー!$B:$B,全体!$G82,コンシューマー!F:F) -> 0 | M82: =SUMIF(コンシューマー!$B:$B,全体!$G82,コンシューマー!G:G) -> 0 | N82: =SUMIF(コンシューマー!$B:$B,全体!$G82,コンシューマー!H:H) -> 0 | O82: =SUMIF(コンシューマー!$B:$B,全体!$G82,コンシューマー!I:I) -> 0 | P82: =SUMIF(コンシューマー!$B:$B,全体!$G82,コンシューマー!J:J) -> 0 | Q82: =SUMIF(コンシューマー!$B:$B,全体!$G82,コンシューマー!K:K) -> 0 | R82: =SUMIF(コンシューマー!$B:$B,全体!$G82,コンシューマー!L:L) -> 0 | S82: =SUMIF(コンシューマー!$B:$B,全体!$G82,コンシューマー!M:M) -> 0 | T82: =SUMIF(コンシューマー!$B:$B,全体!$G82,コンシューマー!N:N) -> 0 | U82: =SUMIF(コンシューマー!$B:$B,全体!$G82,コンシューマー!O:O) -> 0 | V82: =SUMIF(コンシューマー!$B:$B,全体!$G82,コンシューマー!P:P) -> 0 | W82: =SUMIF(コンシューマー!$B:$B,全体!$G82,コンシューマー!Q:Q) -> 0 | X82: =SUMIF(コンシューマー!$B:$B,全体!$G82,コンシューマー!R:R) -> 0 | Y82: =SUMIF(コンシューマー!$B:$B,全体!$G82,コンシューマー!S:S) -> 0 | Z82: =SUMIF(コンシューマー!$B:$B,全体!$G82,コンシューマー!T:T) -> 0 | AA82: =SUMIF(コンシューマー!$B:$B,全体!$G82,コンシューマー!U:U) -> 0 | AB82: =SUMIF(コンシューマー!$B:$B,全体!$G82,コンシューマー!V:V) -> 0 | AC82: =SUMIF(コンシューマー!$B:$B,全体!$G82,コンシューマー!W:W) -> 0 | AD82: =SUMIF(コンシューマー!$B:$B,全体!$G82,コンシューマー!X:X) -> 0 | AE82: =SUMIF(コンシューマー!$B:$B,全体!$G82,コンシューマー!Y:Y) -> 0 | AF82: =SUMIF(コンシューマー!$B:$B,全体!$G82,コンシューマー!Z:Z) -> 0 | AG82: =SUMIF(コンシューマー!$B:$B,全体!$G82,コンシューマー!AA:AA) -> 0 | AI82: 0 | AK82: 0 | AL82: 0 | AM82: 0 | AN82: 0 | AO82: 0 | AP82: 0 | AQ82: 0 | AR82: =SUMIF(結果貼付!$A:$A,G82,結果貼付!$D:$D) -> 0 | AS82: =(AR82/AS$2)*AS$1 -> 0 | AT82: =SUM(SUMIF(コンシューマー!$B:$B,全体!$G82,コンシューマー!AO:AO),SUMIF(コマーシャル!$B:$B,全体!$G82,コマーシャル!AK:AK)) -> 0 | AU82: =SUM(SUMIF(コンシューマー!$B:$B,全体!$G82,コンシューマー!AP:AP),SUMIF(コマーシャル!$B:$B,全体!$G82,コマーシャル!AL:AL)) -> 0 | AV82: =SUM(SUMIF(コンシューマー!$B:$B,全体!$G82,コンシューマー!AQ:AQ),SUMIF(コマーシャル!$B:$B,全体!$G82,コマーシャル!AM:AM)) -> 0 | AW82: =SUM(SUMIF(コンシューマー!$B:$B,全体!$G82,コンシューマー!AR:AR),SUMIF(コマーシャル!$B:$B,全体!$G82,コマーシャル!AN:AN)) -> 0 | AX82: =SUM(SUMIF(コンシューマー!$B:$B,全体!$G82,コンシューマー!AS:AS),SUMIF(コマーシャル!$B:$B,全体!$G82,コマーシャル!AO:AO)) -> 0 | AY82: =SUM(SUMIF(コンシューマー!$B:$B,全体!$G82,コンシューマー!AT:AT),SUMIF(コマーシャル!$B:$B,全体!$G82,コマーシャル!AP:AP)) -> 0
A83: =SUMIFS(SAP貼付!K:K,SAP貼付!C:C,全体!G83) -> 0 | D83: =SUM(A83:C83) -> 0 | E83: =IFERROR(D83-SUM(#REF!)," ") | G83: U7-265KF | H83: =IFERROR(IF(MATCH($G83,コンシューマー!B:B,0),"Y"),"-") -> Y | I83: =IFERROR(IF(MATCH($G83,コマーシャル!B:B,0),"Y"),"-") -> Y | J83: =SUMIF(コンシューマー!$B:$B,全体!$G83,コンシューマー!D:D) -> 0 | K83: =SUMIF(コンシューマー!$B:$B,全体!$G83,コンシューマー!E:E) -> 0 | L83: =SUMIF(コンシューマー!$B:$B,全体!$G83,コンシューマー!F:F) -> 0 | M83: =SUMIF(コンシューマー!$B:$B,全体!$G83,コンシューマー!G:G) -> 0 | N83: =SUMIF(コンシューマー!$B:$B,全体!$G83,コンシューマー!H:H) -> 0 | O83: =SUMIF(コンシューマー!$B:$B,全体!$G83,コンシューマー!I:I) -> 0 | P83: =SUMIF(コンシューマー!$B:$B,全体!$G83,コンシューマー!J:J) -> 0 | Q83: =SUMIF(コンシューマー!$B:$B,全体!$G83,コンシューマー!K:K) -> 0 | R83: =SUMIF(コンシューマー!$B:$B,全体!$G83,コンシューマー!L:L) -> 0 | S83: =SUMIF(コンシューマー!$B:$B,全体!$G83,コンシューマー!M:M) -> 0 | T83: =SUMIF(コンシューマー!$B:$B,全体!$G83,コンシューマー!N:N) -> 0 | U83: =SUMIF(コンシューマー!$B:$B,全体!$G83,コンシューマー!O:O) -> 0 | V83: =SUMIF(コンシューマー!$B:$B,全体!$G83,コンシューマー!P:P) -> 0 | W83: =SUMIF(コンシューマー!$B:$B,全体!$G83,コンシューマー!Q:Q) -> 0 | X83: =SUMIF(コンシューマー!$B:$B,全体!$G83,コンシューマー!R:R) -> 0 | Y83: =SUMIF(コンシューマー!$B:$B,全体!$G83,コンシューマー!S:S) -> 71 | Z83: =SUMIF(コンシューマー!$B:$B,全体!$G83,コンシューマー!T:T) -> 115 | AA83: =SUMIF(コンシューマー!$B:$B,全体!$G83,コンシューマー!U:U) -> 90 | AB83: =SUMIF(コンシューマー!$B:$B,全体!$G83,コンシューマー!V:V) -> 64 | AC83: =SUMIF(コンシューマー!$B:$B,全体!$G83,コンシューマー!W:W) -> 104 | AD83: =SUMIF(コンシューマー!$B:$B,全体!$G83,コンシューマー!X:X) -> 80 | AE83: =SUMIF(コンシューマー!$B:$B,全体!$G83,コンシューマー!Y:Y) -> 41 | AF83: =SUMIF(コンシューマー!$B:$B,全体!$G83,コンシューマー!Z:Z) -> 82 | AG83: =SUMIF(コンシューマー!$B:$B,全体!$G83,コンシューマー!AA:AA) -> 117 | AI83: 181 | AK83: 243 | AL83: 354.19355 | AM83: 511.09 | AN83: 196 | AO83: 124 | AP83: 162 | AQ83: 84 | AR83: =SUMIF(結果貼付!$A:$A,G83,結果貼付!$D:$D) -> 35 | AS83: =(AR83/AS$2)*AS$1 -> 75 | AT83: =SUM(SUMIF(コンシューマー!$B:$B,全体!$G83,コンシューマー!AO:AO),SUMIF(コマーシャル!$B:$B,全体!$G83,コマーシャル!AK:AK)) -> 80 | AU83: =SUM(SUMIF(コンシューマー!$B:$B,全体!$G83,コンシューマー!AP:AP),SUMIF(コマーシャル!$B:$B,全体!$G83,コマーシャル!AL:AL)) -> 10 | AV83: =SUM(SUMIF(コンシューマー!$B:$B,全体!$G83,コンシューマー!AQ:AQ),SUMIF(コマーシャル!$B:$B,全体!$G83,コマーシャル!AM:AM)) -> 10 | AW83: =SUM(SUMIF(コンシューマー!$B:$B,全体!$G83,コンシューマー!AR:AR),SUMIF(コマーシャル!$B:$B,全体!$G83,コマーシャル!AN:AN)) -> 10 | AX83: =SUM(SUMIF(コンシューマー!$B:$B,全体!$G83,コンシューマー!AS:AS),SUMIF(コマーシャル!$B:$B,全体!$G83,コマーシャル!AO:AO)) -> 20 | AY83: =SUM(SUMIF(コンシューマー!$B:$B,全体!$G83,コンシューマー!AT:AT),SUMIF(コマーシャル!$B:$B,全体!$G83,コマーシャル!AP:AP)) -> 20
A84: =SUMIFS(SAP貼付!K:K,SAP貼付!C:C,全体!G84) -> 0 | D84: =SUM(A84:C84) -> 0 | E84: =IFERROR(D84-SUM(#REF!)," ") | G84: U7-265K | H84: =IFERROR(IF(MATCH($G84,コンシューマー!B:B,0),"Y"),"-") -> Y | I84: =IFERROR(IF(MATCH($G84,コマーシャル!B:B,0),"Y"),"-") -> Y | J84: =SUMIF(コンシューマー!$B:$B,全体!$G84,コンシューマー!D:D) -> 0 | K84: =SUMIF(コンシューマー!$B:$B,全体!$G84,コンシューマー!E:E) -> 0 | L84: =SUMIF(コンシューマー!$B:$B,全体!$G84,コンシューマー!F:F) -> 0 | M84: =SUMIF(コンシューマー!$B:$B,全体!$G84,コンシューマー!G:G) -> 0 | N84: =SUMIF(コンシューマー!$B:$B,全体!$G84,コンシューマー!H:H) -> 0 | O84: =SUMIF(コンシューマー!$B:$B,全体!$G84,コンシューマー!I:I) -> 0 | P84: =SUMIF(コンシューマー!$B:$B,全体!$G84,コンシューマー!J:J) -> 0 | Q84: =SUMIF(コンシューマー!$B:$B,全体!$G84,コンシューマー!K:K) -> 0 | R84: =SUMIF(コンシューマー!$B:$B,全体!$G84,コンシューマー!L:L) -> 0 | S84: =SUMIF(コンシューマー!$B:$B,全体!$G84,コンシューマー!M:M) -> 0 | T84: =SUMIF(コンシューマー!$B:$B,全体!$G84,コンシューマー!N:N) -> 0 | U84: =SUMIF(コンシューマー!$B:$B,全体!$G84,コンシューマー!O:O) -> 0 | V84: =SUMIF(コンシューマー!$B:$B,全体!$G84,コンシューマー!P:P) -> 0 | W84: =SUMIF(コンシューマー!$B:$B,全体!$G84,コンシューマー!Q:Q) -> 0 | X84: =SUMIF(コンシューマー!$B:$B,全体!$G84,コンシューマー!R:R) -> 0 | Y84: =SUMIF(コンシューマー!$B:$B,全体!$G84,コンシューマー!S:S) -> 12 | Z84: =SUMIF(コンシューマー!$B:$B,全体!$G84,コンシューマー!T:T) -> 24 | AA84: =SUMIF(コンシューマー!$B:$B,全体!$G84,コンシューマー!U:U) -> 16 | AB84: =SUMIF(コンシューマー!$B:$B,全体!$G84,コンシューマー!V:V) -> 41 | AC84: =SUMIF(コンシューマー!$B:$B,全体!$G84,コンシューマー!W:W) -> 47 | AD84: =SUMIF(コンシューマー!$B:$B,全体!$G84,コンシューマー!X:X) -> 10 | AE84: =SUMIF(コンシューマー!$B:$B,全体!$G84,コンシューマー!Y:Y) -> 18 | AF84: =SUMIF(コンシューマー!$B:$B,全体!$G84,コンシューマー!Z:Z) -> 48 | AG84: =SUMIF(コンシューマー!$B:$B,全体!$G84,コンシューマー!AA:AA) -> 58 | AI84: 31 | AK84: 92 | AL84: 152.90323 | AM84: 58.973333 | AN84: 53 | AO84: 61 | AP84: 60 | AQ84: 15 | AR84: =SUMIF(結果貼付!$A:$A,G84,結果貼付!$D:$D) -> 3 | AS84: =(AR84/AS$2)*AS$1 -> 6.4285714 | AT84: =SUM(SUMIF(コンシューマー!$B:$B,全体!$G84,コンシューマー!AO:AO),SUMIF(コマーシャル!$B:$B,全体!$G84,コマーシャル!AK:AK)) -> 7.0048 | AU84: =SUM(SUMIF(コンシューマー!$B:$B,全体!$G84,コンシューマー!AP:AP),SUMIF(コマーシャル!$B:$B,全体!$G84,コマーシャル!AL:AL)) -> 0 | AV84: =SUM(SUMIF(コンシューマー!$B:$B,全体!$G84,コンシューマー!AQ:AQ),SUMIF(コマーシャル!$B:$B,全体!$G84,コマーシャル!AM:AM)) -> 0 | AW84: =SUM(SUMIF(コンシューマー!$B:$B,全体!$G84,コンシューマー!AR:AR),SUMIF(コマーシャル!$B:$B,全体!$G84,コマーシャル!AN:AN)) -> 0 | AX84: =SUM(SUMIF(コンシューマー!$B:$B,全体!$G84,コンシューマー!AS:AS),SUMIF(コマーシャル!$B:$B,全体!$G84,コマーシャル!AO:AO)) -> 0 | AY84: =SUM(SUMIF(コンシューマー!$B:$B,全体!$G84,コンシューマー!AT:AT),SUMIF(コマーシャル!$B:$B,全体!$G84,コマーシャル!AP:AP)) -> 0
A85: =SUMIFS(SAP貼付!K:K,SAP貼付!C:C,全体!G85) -> 0 | D85: =SUM(A85:C85) -> 0 | E85: =IFERROR(D85-SUM(#REF!)," ") | G85: U7-265F | H85: =IFERROR(IF(MATCH($G85,コンシューマー!B:B,0),"Y"),"-") -> Y | I85: =IFERROR(IF(MATCH($G85,コマーシャル!B:B,0),"Y"),"-") -> Y | J85: =SUMIF(コンシューマー!$B:$B,全体!$G85,コンシューマー!D:D) -> 0 | K85: =SUMIF(コンシューマー!$B:$B,全体!$G85,コンシューマー!E:E) -> 0 | L85: =SUMIF(コンシューマー!$B:$B,全体!$G85,コンシューマー!F:F) -> 0 | M85: =SUMIF(コンシューマー!$B:$B,全体!$G85,コンシューマー!G:G) -> 0 | N85: =SUMIF(コンシューマー!$B:$B,全体!$G85,コンシューマー!H:H) -> 0 | O85: =SUMIF(コンシューマー!$B:$B,全体!$G85,コンシューマー!I:I) -> 0 | P85: =SUMIF(コンシューマー!$B:$B,全体!$G85,コンシューマー!J:J) -> 0 | Q85: =SUMIF(コンシューマー!$B:$B,全体!$G85,コンシューマー!K:K) -> 0 | R85: =SUMIF(コンシューマー!$B:$B,全体!$G85,コンシューマー!L:L) -> 0 | S85: =SUMIF(コンシューマー!$B:$B,全体!$G85,コンシューマー!M:M) -> 0 | T85: =SUMIF(コンシューマー!$B:$B,全体!$G85,コンシューマー!N:N) -> 0 | U85: =SUMIF(コンシューマー!$B:$B,全体!$G85,コンシューマー!O:O) -> 0 | V85: =SUMIF(コンシューマー!$B:$B,全体!$G85,コンシューマー!P:P) -> 0 | W85: =SUMIF(コンシューマー!$B:$B,全体!$G85,コンシューマー!Q:Q) -> 0 | X85: =SUMIF(コンシューマー!$B:$B,全体!$G85,コンシューマー!R:R) -> 0 | Y85: =SUMIF(コンシューマー!$B:$B,全体!$G85,コンシューマー!S:S) -> 0 | Z85: =SUMIF(コンシューマー!$B:$B,全体!$G85,コンシューマー!T:T) -> 0 | AA85: =SUMIF(コンシューマー!$B:$B,全体!$G85,コンシューマー!U:U) -> 0 | AB85: =SUMIF(コンシューマー!$B:$B,全体!$G85,コンシューマー!V:V) -> 55 | AC85: =SUMIF(コンシューマー!$B:$B,全体!$G85,コンシューマー!W:W) -> 1566 | AD85: =SUMIF(コンシューマー!$B:$B,全体!$G85,コンシューマー!X:X) -> 1987 | AE85: =SUMIF(コンシューマー!$B:$B,全体!$G85,コンシューマー!Y:Y) -> 986 | AF85: =SUMIF(コンシューマー!$B:$B,全体!$G85,コンシューマー!Z:Z) -> 1204 | AG85: =SUMIF(コンシューマー!$B:$B,全体!$G85,コンシューマー!AA:AA) -> 1829 | AI85: 1220 | AK85: 1810 | AL85: 3306.7742 | AM85: 2551.1242 | AN85: 1205 | AO85: 890 | AP85: 945 | AQ85: 1571 | AR85: =SUMIF(結果貼付!$A:$A,G85,結果貼付!$D:$D) -> 506 | AS85: =(AR85/AS$2)*AS$1 -> 1084.2857 | AT85: =SUM(SUMIF(コンシューマー!$B:$B,全体!$G85,コンシューマー!AO:AO),SUMIF(コマーシャル!$B:$B,全体!$G85,コマーシャル!AK:AK)) -> 1173.8184 | AU85: =SUM(SUMIF(コンシューマー!$B:$B,全体!$G85,コンシューマー!AP:AP),SUMIF(コマーシャル!$B:$B,全体!$G85,コマーシャル!AL:AL)) -> 1378.5821 | AV85: =SUM(SUMIF(コンシューマー!$B:$B,全体!$G85,コンシューマー!AQ:AQ),SUMIF(コマーシャル!$B:$B,全体!$G85,コマーシャル!AM:AM)) -> 1191.1675 | AW85: =SUM(SUMIF(コンシューマー!$B:$B,全体!$G85,コンシューマー!AR:AR),SUMIF(コマーシャル!$B:$B,全体!$G85,コマーシャル!AN:AN)) -> 1084 | AX85: =SUM(SUMIF(コンシューマー!$B:$B,全体!$G85,コンシューマー!AS:AS),SUMIF(コマーシャル!$B:$B,全体!$G85,コマーシャル!AO:AO)) -> 1035 | AY85: =SUM(SUMIF(コンシューマー!$B:$B,全体!$G85,コンシューマー!AT:AT),SUMIF(コマーシャル!$B:$B,全体!$G85,コマーシャル!AP:AP)) -> 1027.1187
A86: =SUMIFS(SAP貼付!K:K,SAP貼付!C:C,全体!G86) -> 0 | D86: =SUM(A86:C86) -> 0 | E86: =IFERROR(D86-SUM(#REF!)," ") | G86: U7-265 | H86: =IFERROR(IF(MATCH($G86,コンシューマー!B:B,0),"Y"),"-") -> Y | I86: =IFERROR(IF(MATCH($G86,コマーシャル!B:B,0),"Y"),"-") -> Y | J86: =SUMIF(コンシューマー!$B:$B,全体!$G86,コンシューマー!D:D) -> 0 | K86: =SUMIF(コンシューマー!$B:$B,全体!$G86,コンシューマー!E:E) -> 0 | L86: =SUMIF(コンシューマー!$B:$B,全体!$G86,コンシューマー!F:F) -> 0 | M86: =SUMIF(コンシューマー!$B:$B,全体!$G86,コンシューマー!G:G) -> 0 | N86: =SUMIF(コンシューマー!$B:$B,全体!$G86,コンシューマー!H:H) -> 0 | O86: =SUMIF(コンシューマー!$B:$B,全体!$G86,コンシューマー!I:I) -> 0 | P86: =SUMIF(コンシューマー!$B:$B,全体!$G86,コンシューマー!J:J) -> 0 | Q86: =SUMIF(コンシューマー!$B:$B,全体!$G86,コンシューマー!K:K) -> 0 | R86: =SUMIF(コンシューマー!$B:$B,全体!$G86,コンシューマー!L:L) -> 0 | S86: =SUMIF(コンシューマー!$B:$B,全体!$G86,コンシューマー!M:M) -> 0 | T86: =SUMIF(コンシューマー!$B:$B,全体!$G86,コンシューマー!N:N) -> 0 | U86: =SUMIF(コンシューマー!$B:$B,全体!$G86,コンシューマー!O:O) -> 0 | V86: =SUMIF(コンシューマー!$B:$B,全体!$G86,コンシューマー!P:P) -> 0 | W86: =SUMIF(コンシューマー!$B:$B,全体!$G86,コンシューマー!Q:Q) -> 0 | X86: =SUMIF(コンシューマー!$B:$B,全体!$G86,コンシューマー!R:R) -> 0 | Y86: =SUMIF(コンシューマー!$B:$B,全体!$G86,コンシューマー!S:S) -> 0 | Z86: =SUMIF(コンシューマー!$B:$B,全体!$G86,コンシューマー!T:T) -> 0 | AA86: =SUMIF(コンシューマー!$B:$B,全体!$G86,コンシューマー!U:U) -> 0 | AB86: =SUMIF(コンシューマー!$B:$B,全体!$G86,コンシューマー!V:V) -> 0 | AC86: =SUMIF(コンシューマー!$B:$B,全体!$G86,コンシューマー!W:W) -> 160 | AD86: =SUMIF(コンシューマー!$B:$B,全体!$G86,コンシューマー!X:X) -> 337 | AE86: =SUMIF(コンシューマー!$B:$B,全体!$G86,コンシューマー!Y:Y) -> 446 | AF86: =SUMIF(コンシューマー!$B:$B,全体!$G86,コンシューマー!Z:Z) -> 520 | AG86: =SUMIF(コンシューマー!$B:$B,全体!$G86,コンシューマー!AA:AA) -> 669 | AI86: 407 | AK86: 618 | AL86: 1071.2903 | AM86: 776.42917 | AN86: 318 | AO86: 316 | AP86: 367 | AQ86: 609 | AR86: =SUMIF(結果貼付!$A:$A,G86,結果貼付!$D:$D) -> 306 | AS86: =(AR86/AS$2)*AS$1 -> 655.71429 | AT86: =SUM(SUMIF(コンシューマー!$B:$B,全体!$G86,コンシューマー!AO:AO),SUMIF(コマーシャル!$B:$B,全体!$G86,コマーシャル!AK:AK)) -> 551 | AU86: =SUM(SUMIF(コンシューマー!$B:$B,全体!$G86,コンシューマー!AP:AP),SUMIF(コマーシャル!$B:$B,全体!$G86,コマーシャル!AL:AL)) -> 651.2 | AV86: =SUM(SUMIF(コンシューマー!$B:$B,全体!$G86,コンシューマー!AQ:AQ),SUMIF(コマーシャル!$B:$B,全体!$G86,コマーシャル!AM:AM)) -> 559.4897 | AW86: =SUM(SUMIF(コンシューマー!$B:$B,全体!$G86,コンシューマー!AR:AR),SUMIF(コマーシャル!$B:$B,全体!$G86,コマーシャル!AN:AN)) -> 549.42224 | AX86: =SUM(SUMIF(コンシューマー!$B:$B,全体!$G86,コンシューマー!AS:AS),SUMIF(コマーシャル!$B:$B,全体!$G86,コマーシャル!AO:AO)) -> 492.64516 | AY86: =SUM(SUMIF(コンシューマー!$B:$B,全体!$G86,コンシューマー!AT:AT),SUMIF(コマーシャル!$B:$B,全体!$G86,コマーシャル!AP:AP)) -> 488.74823
A87: =SUMIFS(SAP貼付!K:K,SAP貼付!C:C,全体!G87) -> 0 | D87: =SUM(A87:C87) -> 0 | E87: =IFERROR(D87-SUM(#REF!)," ") | G87: U7-265T | H87: =IFERROR(IF(MATCH($G87,コンシューマー!B:B,0),"Y"),"-") -> Y | I87: =IFERROR(IF(MATCH($G87,コマーシャル!B:B,0),"Y"),"-") -> Y | J87: =SUMIF(コンシューマー!$B:$B,全体!$G87,コンシューマー!D:D) -> 0 | K87: =SUMIF(コンシューマー!$B:$B,全体!$G87,コンシューマー!E:E) -> 0 | L87: =SUMIF(コンシューマー!$B:$B,全体!$G87,コンシューマー!F:F) -> 0 | M87: =SUMIF(コンシューマー!$B:$B,全体!$G87,コンシューマー!G:G) -> 0 | N87: =SUMIF(コンシューマー!$B:$B,全体!$G87,コンシューマー!H:H) -> 0 | O87: =SUMIF(コンシューマー!$B:$B,全体!$G87,コンシューマー!I:I) -> 0 | P87: =SUMIF(コンシューマー!$B:$B,全体!$G87,コンシューマー!J:J) -> 0 | Q87: =SUMIF(コンシューマー!$B:$B,全体!$G87,コンシューマー!K:K) -> 0 | R87: =SUMIF(コンシューマー!$B:$B,全体!$G87,コンシューマー!L:L) -> 0 | S87: =SUMIF(コンシューマー!$B:$B,全体!$G87,コンシューマー!M:M) -> 0 | T87: =SUMIF(コンシューマー!$B:$B,全体!$G87,コンシューマー!N:N) -> 0 | U87: =SUMIF(コンシューマー!$B:$B,全体!$G87,コンシューマー!O:O) -> 0 | V87: =SUMIF(コンシューマー!$B:$B,全体!$G87,コンシューマー!P:P) -> 0 | W87: =SUMIF(コンシューマー!$B:$B,全体!$G87,コンシューマー!Q:Q) -> 0 | X87: =SUMIF(コンシューマー!$B:$B,全体!$G87,コンシューマー!R:R) -> 0 | Y87: =SUMIF(コンシューマー!$B:$B,全体!$G87,コンシューマー!S:S) -> 0 | Z87: =SUMIF(コンシューマー!$B:$B,全体!$G87,コンシューマー!T:T) -> 0 | AA87: =SUMIF(コンシューマー!$B:$B,全体!$G87,コンシューマー!U:U) -> 0 | AB87: =SUMIF(コンシューマー!$B:$B,全体!$G87,コンシューマー!V:V) -> 3 | AC87: =SUMIF(コンシューマー!$B:$B,全体!$G87,コンシューマー!W:W) -> 2 | AD87: =SUMIF(コンシューマー!$B:$B,全体!$G87,コンシューマー!X:X) -> 6 | AE87: =SUMIF(コンシューマー!$B:$B,全体!$G87,コンシューマー!Y:Y) -> 3 | AF87: =SUMIF(コンシューマー!$B:$B,全体!$G87,コンシューマー!Z:Z) -> 3 | AG87: =SUMIF(コンシューマー!$B:$B,全体!$G87,コンシューマー!AA:AA) -> 3 | AI87: 35 | AK87: 39 | AL87: 44.516129 | AM87: 9.8533333 | AN87: 7 | AO87: 21 | AP87: 5 | AQ87: 6 | AR87: =SUMIF(結果貼付!$A:$A,G87,結果貼付!$D:$D) -> 1 | AS87: =(AR87/AS$2)*AS$1 -> 2.1428571 | AT87: =SUM(SUMIF(コンシューマー!$B:$B,全体!$G87,コンシューマー!AO:AO),SUMIF(コマーシャル!$B:$B,全体!$G87,コマーシャル!AK:AK)) -> 5.0016 | AU87: =SUM(SUMIF(コンシューマー!$B:$B,全体!$G87,コンシューマー!AP:AP),SUMIF(コマーシャル!$B:$B,全体!$G87,コマーシャル!AL:AL)) -> 3 | AV87: =SUM(SUMIF(コンシューマー!$B:$B,全体!$G87,コンシューマー!AQ:AQ),SUMIF(コマーシャル!$B:$B,全体!$G87,コマーシャル!AM:AM)) -> 3 | AW87: =SUM(SUMIF(コンシューマー!$B:$B,全体!$G87,コンシューマー!AR:AR),SUMIF(コマーシャル!$B:$B,全体!$G87,コマーシャル!AN:AN)) -> 3 | AX87: =SUM(SUMIF(コンシューマー!$B:$B,全体!$G87,コンシューマー!AS:AS),SUMIF(コマーシャル!$B:$B,全体!$G87,コマーシャル!AO:AO)) -> 3 | AY87: =SUM(SUMIF(コンシューマー!$B:$B,全体!$G87,コンシューマー!AT:AT),SUMIF(コマーシャル!$B:$B,全体!$G87,コマーシャル!AP:AP)) -> 3
A88: =SUMIFS(SAP貼付!K:K,SAP貼付!C:C,全体!G88) -> 0 | D88: =SUM(A88:C88) -> 0 | E88: =IFERROR(D88-SUM(#REF!)," ") | G88: U5-245KF | H88: =IFERROR(IF(MATCH($G88,コンシューマー!B:B,0),"Y"),"-") -> Y | I88: =IFERROR(IF(MATCH($G88,コマーシャル!B:B,0),"Y"),"-") -> Y | J88: =SUMIF(コンシューマー!$B:$B,全体!$G88,コンシューマー!D:D) -> 0 | K88: =SUMIF(コンシューマー!$B:$B,全体!$G88,コンシューマー!E:E) -> 0 | L88: =SUMIF(コンシューマー!$B:$B,全体!$G88,コンシューマー!F:F) -> 0 | M88: =SUMIF(コンシューマー!$B:$B,全体!$G88,コンシューマー!G:G) -> 0 | N88: =SUMIF(コンシューマー!$B:$B,全体!$G88,コンシューマー!H:H) -> 0 | O88: =SUMIF(コンシューマー!$B:$B,全体!$G88,コンシューマー!I:I) -> 0 | P88: =SUMIF(コンシューマー!$B:$B,全体!$G88,コンシューマー!J:J) -> 0 | Q88: =SUMIF(コンシューマー!$B:$B,全体!$G88,コンシューマー!K:K) -> 0 | R88: =SUMIF(コンシューマー!$B:$B,全体!$G88,コンシューマー!L:L) -> 0 | S88: =SUMIF(コンシューマー!$B:$B,全体!$G88,コンシューマー!M:M) -> 0 | T88: =SUMIF(コンシューマー!$B:$B,全体!$G88,コンシューマー!N:N) -> 0 | U88: =SUMIF(コンシューマー!$B:$B,全体!$G88,コンシューマー!O:O) -> 0 | V88: =SUMIF(コンシューマー!$B:$B,全体!$G88,コンシューマー!P:P) -> 0 | W88: =SUMIF(コンシューマー!$B:$B,全体!$G88,コンシューマー!Q:Q) -> 0 | X88: =SUMIF(コンシューマー!$B:$B,全体!$G88,コンシューマー!R:R) -> 0 | Y88: =SUMIF(コンシューマー!$B:$B,全体!$G88,コンシューマー!S:S) -> 12 | Z88: =SUMIF(コンシューマー!$B:$B,全体!$G88,コンシューマー!T:T) -> 24 | AA88: =SUMIF(コンシューマー!$B:$B,全体!$G88,コンシューマー!U:U) -> 0 | AB88: =SUMIF(コンシューマー!$B:$B,全体!$G88,コンシューマー!V:V) -> 0 | AC88: =SUMIF(コンシューマー!$B:$B,全体!$G88,コンシューマー!W:W) -> 0 | AD88: =SUMIF(コンシューマー!$B:$B,全体!$G88,コンシューマー!X:X) -> 0 | AE88: =SUMIF(コンシューマー!$B:$B,全体!$G88,コンシューマー!Y:Y) -> 0 | AF88: =SUMIF(コンシューマー!$B:$B,全体!$G88,コンシューマー!Z:Z) -> 0 | AG88: =SUMIF(コンシューマー!$B:$B,全体!$G88,コンシューマー!AA:AA) -> 0 | AI88: 0 | AK88: 0 | AL88: 87.096774 | AM88: 3.9266667 | AN88: 11 | AO88: 40 | AP88: 19 | AQ88: 12 | AR88: =SUMIF(結果貼付!$A:$A,G88,結果貼付!$D:$D) -> 3 | AS88: =(AR88/AS$2)*AS$1 -> 6.4285714 | AT88: =SUM(SUMIF(コンシューマー!$B:$B,全体!$G88,コンシューマー!AO:AO),SUMIF(コマーシャル!$B:$B,全体!$G88,コマーシャル!AK:AK)) -> 40.032 | AU88: =SUM(SUMIF(コンシューマー!$B:$B,全体!$G88,コンシューマー!AP:AP),SUMIF(コマーシャル!$B:$B,全体!$G88,コマーシャル!AL:AL)) -> 48.0384 | AV88: =SUM(SUMIF(コンシューマー!$B:$B,全体!$G88,コンシューマー!AQ:AQ),SUMIF(コマーシャル!$B:$B,全体!$G88,コマーシャル!AM:AM)) -> 40.710363 | AW88: =SUM(SUMIF(コンシューマー!$B:$B,全体!$G88,コンシューマー!AR:AR),SUMIF(コマーシャル!$B:$B,全体!$G88,コマーシャル!AN:AN)) -> 39.90593 | AX88: =SUM(SUMIF(コンシューマー!$B:$B,全体!$G88,コンシューマー!AS:AS),SUMIF(コマーシャル!$B:$B,全体!$G88,コマーシャル!AO:AO)) -> 0 | AY88: =SUM(SUMIF(コンシューマー!$B:$B,全体!$G88,コンシューマー!AT:AT),SUMIF(コマーシャル!$B:$B,全体!$G88,コマーシャル!AP:AP)) -> 0
A89: =SUMIFS(SAP貼付!K:K,SAP貼付!C:C,全体!G89) -> 0 | D89: =SUM(A89:C89) -> 0 | E89: =IFERROR(D89-SUM(#REF!)," ") | G89: U5-245K | H89: =IFERROR(IF(MATCH($G89,コンシューマー!B:B,0),"Y"),"-") -> - | I89: =IFERROR(IF(MATCH($G89,コマーシャル!B:B,0),"Y"),"-") -> Y | J89: =SUMIF(コンシューマー!$B:$B,全体!$G89,コンシューマー!D:D) -> 0 | K89: =SUMIF(コンシューマー!$B:$B,全体!$G89,コンシューマー!E:E) -> 0 | L89: =SUMIF(コンシューマー!$B:$B,全体!$G89,コンシューマー!F:F) -> 0 | M89: =SUMIF(コンシューマー!$B:$B,全体!$G89,コンシューマー!G:G) -> 0 | N89: =SUMIF(コンシューマー!$B:$B,全体!$G89,コンシューマー!H:H) -> 0 | O89: =SUMIF(コンシューマー!$B:$B,全体!$G89,コンシューマー!I:I) -> 0 | P89: =SUMIF(コンシューマー!$B:$B,全体!$G89,コンシューマー!J:J) -> 0 | Q89: =SUMIF(コンシューマー!$B:$B,全体!$G89,コンシューマー!K:K) -> 0 | R89: =SUMIF(コンシューマー!$B:$B,全体!$G89,コンシューマー!L:L) -> 0 | S89: =SUMIF(コンシューマー!$B:$B,全体!$G89,コンシューマー!M:M) -> 0 | T89: =SUMIF(コンシューマー!$B:$B,全体!$G89,コンシューマー!N:N) -> 0 | U89: =SUMIF(コンシューマー!$B:$B,全体!$G89,コンシューマー!O:O) -> 0 | V89: =SUMIF(コンシューマー!$B:$B,全体!$G89,コンシューマー!P:P) -> 0 | W89: =SUMIF(コンシューマー!$B:$B,全体!$G89,コンシューマー!Q:Q) -> 0 | X89: =SUMIF(コンシューマー!$B:$B,全体!$G89,コンシューマー!R:R) -> 0 | Y89: =SUMIF(コンシューマー!$B:$B,全体!$G89,コンシューマー!S:S) -> 0 | Z89: =SUMIF(コンシューマー!$B:$B,全体!$G89,コンシューマー!T:T) -> 0 | AA89: =SUMIF(コンシューマー!$B:$B,全体!$G89,コンシューマー!U:U) -> 0 | AB89: =SUMIF(コンシューマー!$B:$B,全体!$G89,コンシューマー!V:V) -> 0 | AC89: =SUMIF(コンシューマー!$B:$B,全体!$G89,コンシューマー!W:W) -> 0 | AD89: =SUMIF(コンシューマー!$B:$B,全体!$G89,コンシューマー!X:X) -> 0 | AE89: =SUMIF(コンシューマー!$B:$B,全体!$G89,コンシューマー!Y:Y) -> 0 | AF89: =SUMIF(コンシューマー!$B:$B,全体!$G89,コンシューマー!Z:Z) -> 0 | AG89: =SUMIF(コンシューマー!$B:$B,全体!$G89,コンシューマー!AA:AA) -> 0 | AI89: 0 | AK89: 0 | AL89: 0 | AM89: 0 | AN89: 0 | AO89: 0 | AP89: 0 | AQ89: 0 | AR89: =SUMIF(結果貼付!$A:$A,G89,結果貼付!$D:$D) -> 0 | AS89: =(AR89/AS$2)*AS$1 -> 0 | AT89: =SUM(SUMIF(コンシューマー!$B:$B,全体!$G89,コンシューマー!AO:AO),SUMIF(コマーシャル!$B:$B,全体!$G89,コマーシャル!AK:AK)) -> 0 | AU89: =SUM(SUMIF(コンシューマー!$B:$B,全体!$G89,コンシューマー!AP:AP),SUMIF(コマーシャル!$B:$B,全体!$G89,コマーシャル!AL:AL)) -> 0 | AV89: =SUM(SUMIF(コンシューマー!$B:$B,全体!$G89,コンシューマー!AQ:AQ),SUMIF(コマーシャル!$B:$B,全体!$G89,コマーシャル!AM:AM)) -> 0 | AW89: =SUM(SUMIF(コンシューマー!$B:$B,全体!$G89,コンシューマー!AR:AR),SUMIF(コマーシャル!$B:$B,全体!$G89,コマーシャル!AN:AN)) -> 0 | AX89: =SUM(SUMIF(コンシューマー!$B:$B,全体!$G89,コンシューマー!AS:AS),SUMIF(コマーシャル!$B:$B,全体!$G89,コマーシャル!AO:AO)) -> 0 | AY89: =SUM(SUMIF(コンシューマー!$B:$B,全体!$G89,コンシューマー!AT:AT),SUMIF(コマーシャル!$B:$B,全体!$G89,コマーシャル!AP:AP)) -> 0
A90: =SUMIFS(SAP貼付!K:K,SAP貼付!C:C,全体!G90) -> 0 | D90: =SUM(A90:C90) -> 0 | E90: =IFERROR(D90-SUM(#REF!)," ") | G90: U5-245 | H90: =IFERROR(IF(MATCH($G90,コンシューマー!B:B,0),"Y"),"-") -> Y | I90: =IFERROR(IF(MATCH($G90,コマーシャル!B:B,0),"Y"),"-") -> Y | J90: =SUMIF(コンシューマー!$B:$B,全体!$G90,コンシューマー!D:D) -> 0 | K90: =SUMIF(コンシューマー!$B:$B,全体!$G90,コンシューマー!E:E) -> 0 | L90: =SUMIF(コンシューマー!$B:$B,全体!$G90,コンシューマー!F:F) -> 0 | M90: =SUMIF(コンシューマー!$B:$B,全体!$G90,コンシューマー!G:G) -> 0 | N90: =SUMIF(コンシューマー!$B:$B,全体!$G90,コンシューマー!H:H) -> 0 | O90: =SUMIF(コンシューマー!$B:$B,全体!$G90,コンシューマー!I:I) -> 0 | P90: =SUMIF(コンシューマー!$B:$B,全体!$G90,コンシューマー!J:J) -> 0 | Q90: =SUMIF(コンシューマー!$B:$B,全体!$G90,コンシューマー!K:K) -> 0 | R90: =SUMIF(コンシューマー!$B:$B,全体!$G90,コンシューマー!L:L) -> 0 | S90: =SUMIF(コンシューマー!$B:$B,全体!$G90,コンシューマー!M:M) -> 0 | T90: =SUMIF(コンシューマー!$B:$B,全体!$G90,コンシューマー!N:N) -> 0 | U90: =SUMIF(コンシューマー!$B:$B,全体!$G90,コンシューマー!O:O) -> 0 | V90: =SUMIF(コンシューマー!$B:$B,全体!$G90,コンシューマー!P:P) -> 0 | W90: =SUMIF(コンシューマー!$B:$B,全体!$G90,コンシューマー!Q:Q) -> 0 | X90: =SUMIF(コンシューマー!$B:$B,全体!$G90,コンシューマー!R:R) -> 0 | Y90: =SUMIF(コンシューマー!$B:$B,全体!$G90,コンシューマー!S:S) -> 0 | Z90: =SUMIF(コンシューマー!$B:$B,全体!$G90,コンシューマー!T:T) -> 0 | AA90: =SUMIF(コンシューマー!$B:$B,全体!$G90,コンシューマー!U:U) -> 0 | AB90: =SUMIF(コンシューマー!$B:$B,全体!$G90,コンシューマー!V:V) -> 0 | AC90: =SUMIF(コンシューマー!$B:$B,全体!$G90,コンシューマー!W:W) -> 0 | AD90: =SUMIF(コンシューマー!$B:$B,全体!$G90,コンシューマー!X:X) -> 0 | AE90: =SUMIF(コンシューマー!$B:$B,全体!$G90,コンシューマー!Y:Y) -> 0 | AF90: =SUMIF(コンシューマー!$B:$B,全体!$G90,コンシューマー!Z:Z) -> 0 | AG90: =SUMIF(コンシューマー!$B:$B,全体!$G90,コンシューマー!AA:AA) -> 0 | AI90: 0 | AK90: 0 | AL90: 0 | AM90: 0 | AN90: 0 | AO90: 0 | AP90: 0 | AQ90: 0 | AR90: =SUMIF(結果貼付!$A:$A,G90,結果貼付!$D:$D) -> 0 | AS90: =(AR90/AS$2)*AS$1 -> 0 | AT90: =SUM(SUMIF(コンシューマー!$B:$B,全体!$G90,コンシューマー!AO:AO),SUMIF(コマーシャル!$B:$B,全体!$G90,コマーシャル!AK:AK)) -> 0 | AU90: =SUM(SUMIF(コンシューマー!$B:$B,全体!$G90,コンシューマー!AP:AP),SUMIF(コマーシャル!$B:$B,全体!$G90,コマーシャル!AL:AL)) -> 0 | AV90: =SUM(SUMIF(コンシューマー!$B:$B,全体!$G90,コンシューマー!AQ:AQ),SUMIF(コマーシャル!$B:$B,全体!$G90,コマーシャル!AM:AM)) -> 0 | AW90: =SUM(SUMIF(コンシューマー!$B:$B,全体!$G90,コンシューマー!AR:AR),SUMIF(コマーシャル!$B:$B,全体!$G90,コマーシャル!AN:AN)) -> 0 | AX90: =SUM(SUMIF(コンシューマー!$B:$B,全体!$G90,コンシューマー!AS:AS),SUMIF(コマーシャル!$B:$B,全体!$G90,コマーシャル!AO:AO)) -> 0 | AY90: =SUM(SUMIF(コンシューマー!$B:$B,全体!$G90,コンシューマー!AT:AT),SUMIF(コマーシャル!$B:$B,全体!$G90,コマーシャル!AP:AP)) -> 0
A91: =SUMIFS(SAP貼付!K:K,SAP貼付!C:C,全体!G91) -> 0 | D91: =SUM(A91:C91) -> 0 | E91: =IFERROR(D91-SUM(#REF!)," ") | G91: U5-235 | H91: =IFERROR(IF(MATCH($G91,コンシューマー!B:B,0),"Y"),"-") -> Y | I91: =IFERROR(IF(MATCH($G91,コマーシャル!B:B,0),"Y"),"-") -> Y | J91: =SUMIF(コンシューマー!$B:$B,全体!$G91,コンシューマー!D:D) -> 0 | K91: =SUMIF(コンシューマー!$B:$B,全体!$G91,コンシューマー!E:E) -> 0 | L91: =SUMIF(コンシューマー!$B:$B,全体!$G91,コンシューマー!F:F) -> 0 | M91: =SUMIF(コンシューマー!$B:$B,全体!$G91,コンシューマー!G:G) -> 0 | N91: =SUMIF(コンシューマー!$B:$B,全体!$G91,コンシューマー!H:H) -> 0 | O91: =SUMIF(コンシューマー!$B:$B,全体!$G91,コンシューマー!I:I) -> 0 | P91: =SUMIF(コンシューマー!$B:$B,全体!$G91,コンシューマー!J:J) -> 0 | Q91: =SUMIF(コンシューマー!$B:$B,全体!$G91,コンシューマー!K:K) -> 0 | R91: =SUMIF(コンシューマー!$B:$B,全体!$G91,コンシューマー!L:L) -> 0 | S91: =SUMIF(コンシューマー!$B:$B,全体!$G91,コンシューマー!M:M) -> 0 | T91: =SUMIF(コンシューマー!$B:$B,全体!$G91,コンシューマー!N:N) -> 0 | U91: =SUMIF(コンシューマー!$B:$B,全体!$G91,コンシューマー!O:O) -> 0 | V91: =SUMIF(コンシューマー!$B:$B,全体!$G91,コンシューマー!P:P) -> 0 | W91: =SUMIF(コンシューマー!$B:$B,全体!$G91,コンシューマー!Q:Q) -> 0 | X91: =SUMIF(コンシューマー!$B:$B,全体!$G91,コンシューマー!R:R) -> 0 | Y91: =SUMIF(コンシューマー!$B:$B,全体!$G91,コンシューマー!S:S) -> 0 | Z91: =SUMIF(コンシューマー!$B:$B,全体!$G91,コンシューマー!T:T) -> 0 | AA91: =SUMIF(コンシューマー!$B:$B,全体!$G91,コンシューマー!U:U) -> 0 | AB91: =SUMIF(コンシューマー!$B:$B,全体!$G91,コンシューマー!V:V) -> 0 | AC91: =SUMIF(コンシューマー!$B:$B,全体!$G91,コンシューマー!W:W) -> 25 | AD91: =SUMIF(コンシューマー!$B:$B,全体!$G91,コンシューマー!X:X) -> 24 | AE91: =SUMIF(コンシューマー!$B:$B,全体!$G91,コンシューマー!Y:Y) -> 18 | AF91: =SUMIF(コンシューマー!$B:$B,全体!$G91,コンシューマー!Z:Z) -> 36 | AG91: =SUMIF(コンシューマー!$B:$B,全体!$G91,コンシューマー!AA:AA) -> 57 | AI91: 85 | AK91: 9 | AL91: 125.80645 | AM91: 40.739167 | AN91: 34 | AO91: 97 | AP91: 28 | AQ91: 54 | AR91: =SUMIF(結果貼付!$A:$A,G91,結果貼付!$D:$D) -> 30 | AS91: =(AR91/AS$2)*AS$1 -> 64.285714 | AT91: =SUM(SUMIF(コンシューマー!$B:$B,全体!$G91,コンシューマー!AO:AO),SUMIF(コマーシャル!$B:$B,全体!$G91,コマーシャル!AK:AK)) -> 85.064 | AU91: =SUM(SUMIF(コンシューマー!$B:$B,全体!$G91,コンシューマー!AP:AP),SUMIF(コマーシャル!$B:$B,全体!$G91,コマーシャル!AL:AL)) -> 101.0768 | AV91: =SUM(SUMIF(コンシューマー!$B:$B,全体!$G91,コンシューマー!AQ:AQ),SUMIF(コマーシャル!$B:$B,全体!$G91,コマーシャル!AM:AM)) -> 86.420725 | AW91: =SUM(SUMIF(コンシューマー!$B:$B,全体!$G91,コンシューマー!AR:AR),SUMIF(コマーシャル!$B:$B,全体!$G91,コマーシャル!AN:AN)) -> 84.811861 | AX91: =SUM(SUMIF(コンシューマー!$B:$B,全体!$G91,コンシューマー!AS:AS),SUMIF(コマーシャル!$B:$B,全体!$G91,コマーシャル!AO:AO)) -> 74.140324 | AY91: =SUM(SUMIF(コンシューマー!$B:$B,全体!$G91,コンシューマー!AT:AT),SUMIF(コマーシャル!$B:$B,全体!$G91,コマーシャル!AP:AP)) -> 73.517561
A92: =SUMIFS(SAP貼付!K:K,SAP貼付!C:C,全体!G92) -> 0 | D92: =SUM(A92:C92) -> 0 | E92: =IFERROR(D92-SUM(#REF!)," ") | G92: U5-225F | H92: =IFERROR(IF(MATCH($G92,コンシューマー!B:B,0),"Y"),"-") -> Y | I92: =IFERROR(IF(MATCH($G92,コマーシャル!B:B,0),"Y"),"-") -> Y | J92: =SUMIF(コンシューマー!$B:$B,全体!$G92,コンシューマー!D:D) -> 0 | K92: =SUMIF(コンシューマー!$B:$B,全体!$G92,コンシューマー!E:E) -> 0 | L92: =SUMIF(コンシューマー!$B:$B,全体!$G92,コンシューマー!F:F) -> 0 | M92: =SUMIF(コンシューマー!$B:$B,全体!$G92,コンシューマー!G:G) -> 0 | N92: =SUMIF(コンシューマー!$B:$B,全体!$G92,コンシューマー!H:H) -> 0 | O92: =SUMIF(コンシューマー!$B:$B,全体!$G92,コンシューマー!I:I) -> 0 | P92: =SUMIF(コンシューマー!$B:$B,全体!$G92,コンシューマー!J:J) -> 0 | Q92: =SUMIF(コンシューマー!$B:$B,全体!$G92,コンシューマー!K:K) -> 0 | R92: =SUMIF(コンシューマー!$B:$B,全体!$G92,コンシューマー!L:L) -> 0 | S92: =SUMIF(コンシューマー!$B:$B,全体!$G92,コンシューマー!M:M) -> 0 | T92: =SUMIF(コンシューマー!$B:$B,全体!$G92,コンシューマー!N:N) -> 0 | U92: =SUMIF(コンシューマー!$B:$B,全体!$G92,コンシューマー!O:O) -> 0 | V92: =SUMIF(コンシューマー!$B:$B,全体!$G92,コンシューマー!P:P) -> 0 | W92: =SUMIF(コンシューマー!$B:$B,全体!$G92,コンシューマー!Q:Q) -> 0 | X92: =SUMIF(コンシューマー!$B:$B,全体!$G92,コンシューマー!R:R) -> 0 | Y92: =SUMIF(コンシューマー!$B:$B,全体!$G92,コンシューマー!S:S) -> 0 | Z92: =SUMIF(コンシューマー!$B:$B,全体!$G92,コンシューマー!T:T) -> 0 | AA92: =SUMIF(コンシューマー!$B:$B,全体!$G92,コンシューマー!U:U) -> 0 | AB92: =SUMIF(コンシューマー!$B:$B,全体!$G92,コンシューマー!V:V) -> 0 | AC92: =SUMIF(コンシューマー!$B:$B,全体!$G92,コンシューマー!W:W) -> 4 | AD92: =SUMIF(コンシューマー!$B:$B,全体!$G92,コンシューマー!X:X) -> 5 | AE92: =SUMIF(コンシューマー!$B:$B,全体!$G92,コンシューマー!Y:Y) -> 7 | AF92: =SUMIF(コンシューマー!$B:$B,全体!$G92,コンシューマー!Z:Z) -> 8 | AG92: =SUMIF(コンシューマー!$B:$B,全体!$G92,コンシューマー!AA:AA) -> 128 | AI92: 218 | AK92: 490 | AL92: 1055.8065 | AM92: 355.1475 | AN92: 329 | AO92: 372 | AP92: 327 | AQ92: 432 | AR92: =SUMIF(結果貼付!$A:$A,G92,結果貼付!$D:$D) -> 371 | AS92: =(AR92/AS$2)*AS$1 -> 795 | AT92: =SUM(SUMIF(コンシューマー!$B:$B,全体!$G92,コンシューマー!AO:AO),SUMIF(コマーシャル!$B:$B,全体!$G92,コマーシャル!AK:AK)) -> 906.7008 | AU92: =SUM(SUMIF(コンシューマー!$B:$B,全体!$G92,コンシューマー!AP:AP),SUMIF(コマーシャル!$B:$B,全体!$G92,コマーシャル!AL:AL)) -> 1092.041 | AV92: =SUM(SUMIF(コンシューマー!$B:$B,全体!$G92,コンシューマー!AQ:AQ),SUMIF(コマーシャル!$B:$B,全体!$G92,コマーシャル!AM:AM)) -> 921.55694 | AW92: =SUM(SUMIF(コンシューマー!$B:$B,全体!$G92,コンシューマー!AR:AR),SUMIF(コマーシャル!$B:$B,全体!$G92,コマーシャル!AN:AN)) -> 903.93988 | AX92: =SUM(SUMIF(コンシューマー!$B:$B,全体!$G92,コンシューマー!AS:AS),SUMIF(コマーシャル!$B:$B,全体!$G92,コマーシャル!AO:AO)) -> 797.08655 | AY92: =SUM(SUMIF(コンシューマー!$B:$B,全体!$G92,コンシューマー!AT:AT),SUMIF(コマーシャル!$B:$B,全体!$G92,コマーシャル!AP:AP)) -> 790.26729
A93: =SUMIFS(SAP貼付!K:K,SAP貼付!C:C,全体!G93) -> 0 | D93: =SUM(A93:C93) -> 0 | E93: =IFERROR(D93-SUM(#REF!)," ") | G93: U5-225 | H93: =IFERROR(IF(MATCH($G93,コンシューマー!B:B,0),"Y"),"-") -> Y | I93: =IFERROR(IF(MATCH($G93,コマーシャル!B:B,0),"Y"),"-") -> Y | J93: =SUMIF(コンシューマー!$B:$B,全体!$G93,コンシューマー!D:D) -> 0 | K93: =SUMIF(コンシューマー!$B:$B,全体!$G93,コンシューマー!E:E) -> 0 | L93: =SUMIF(コンシューマー!$B:$B,全体!$G93,コンシューマー!F:F) -> 0 | M93: =SUMIF(コンシューマー!$B:$B,全体!$G93,コンシューマー!G:G) -> 0 | N93: =SUMIF(コンシューマー!$B:$B,全体!$G93,コンシューマー!H:H) -> 0 | O93: =SUMIF(コンシューマー!$B:$B,全体!$G93,コンシューマー!I:I) -> 0 | P93: =SUMIF(コンシューマー!$B:$B,全体!$G93,コンシューマー!J:J) -> 0 | Q93: =SUMIF(コンシューマー!$B:$B,全体!$G93,コンシューマー!K:K) -> 0 | R93: =SUMIF(コンシューマー!$B:$B,全体!$G93,コンシューマー!L:L) -> 0 | S93: =SUMIF(コンシューマー!$B:$B,全体!$G93,コンシューマー!M:M) -> 0 | T93: =SUMIF(コンシューマー!$B:$B,全体!$G93,コンシューマー!N:N) -> 0 | U93: =SUMIF(コンシューマー!$B:$B,全体!$G93,コンシューマー!O:O) -> 0 | V93: =SUMIF(コンシューマー!$B:$B,全体!$G93,コンシューマー!P:P) -> 0 | W93: =SUMIF(コンシューマー!$B:$B,全体!$G93,コンシューマー!Q:Q) -> 0 | X93: =SUMIF(コンシューマー!$B:$B,全体!$G93,コンシューマー!R:R) -> 0 | Y93: =SUMIF(コンシューマー!$B:$B,全体!$G93,コンシューマー!S:S) -> 0 | Z93: =SUMIF(コンシューマー!$B:$B,全体!$G93,コンシューマー!T:T) -> 0 | AA93: =SUMIF(コンシューマー!$B:$B,全体!$G93,コンシューマー!U:U) -> 0 | AB93: =SUMIF(コンシューマー!$B:$B,全体!$G93,コンシューマー!V:V) -> 0 | AC93: =SUMIF(コンシューマー!$B:$B,全体!$G93,コンシューマー!W:W) -> 7 | AD93: =SUMIF(コンシューマー!$B:$B,全体!$G93,コンシューマー!X:X) -> 23 | AE93: =SUMIF(コンシューマー!$B:$B,全体!$G93,コンシューマー!Y:Y) -> 20 | AF93: =SUMIF(コンシューマー!$B:$B,全体!$G93,コンシューマー!Z:Z) -> 31 | AG93: =SUMIF(コンシューマー!$B:$B,全体!$G93,コンシューマー!AA:AA) -> 62 | AI93: 213 | AK93: 1089 | AL93: 1465.1613 | AM93: 1425.1458 | AN93: 520 | AO93: 567 | AP93: 471 | AQ93: 421 | AR93: =SUMIF(結果貼付!$A:$A,G93,結果貼付!$D:$D) -> 585 | AS93: =(AR93/AS$2)*AS$1 -> 1253.5714 | AT93: =SUM(SUMIF(コンシューマー!$B:$B,全体!$G93,コンシューマー!AO:AO),SUMIF(コマーシャル!$B:$B,全体!$G93,コマーシャル!AK:AK)) -> 2437.9896 | AU93: =SUM(SUMIF(コンシューマー!$B:$B,全体!$G93,コンシューマー!AP:AP),SUMIF(コマーシャル!$B:$B,全体!$G93,コマーシャル!AL:AL)) -> 1486 | AV93: =SUM(SUMIF(コンシューマー!$B:$B,全体!$G93,コンシューマー!AQ:AQ),SUMIF(コマーシャル!$B:$B,全体!$G93,コマーシャル!AM:AM)) -> 1289.8266 | AW93: =SUM(SUMIF(コンシューマー!$B:$B,全体!$G93,コンシューマー!AR:AR),SUMIF(コマーシャル!$B:$B,全体!$G93,コマーシャル!AN:AN)) -> 1268.2918 | AX93: =SUM(SUMIF(コンシューマー!$B:$B,全体!$G93,コンシューマー!AS:AS),SUMIF(コマーシャル!$B:$B,全体!$G93,コマーシャル!AO:AO)) -> 1135.4519 | AY93: =SUM(SUMIF(コンシューマー!$B:$B,全体!$G93,コンシューマー!AT:AT),SUMIF(コマーシャル!$B:$B,全体!$G93,コマーシャル!AP:AP)) -> 1127.1161
A94: =SUMIFS(SAP貼付!K:K,SAP貼付!C:C,全体!G94) -> 390 | D94: =SUM(A94:C94) -> 390 | E94: =IFERROR(D94-SUM(#REF!)," ") | G94: i9-14900KF | H94: =IFERROR(IF(MATCH($G94,コンシューマー!B:B,0),"Y"),"-") -> Y | I94: =IFERROR(IF(MATCH($G94,コマーシャル!B:B,0),"Y"),"-") -> Y | J94: =SUMIF(コンシューマー!$B:$B,全体!$G94,コンシューマー!D:D) -> 0 | K94: =SUMIF(コンシューマー!$B:$B,全体!$G94,コンシューマー!E:E) -> 0 | L94: =SUMIF(コンシューマー!$B:$B,全体!$G94,コンシューマー!F:F) -> 0 | M94: =SUMIF(コンシューマー!$B:$B,全体!$G94,コンシューマー!G:G) -> 365 | N94: =SUMIF(コンシューマー!$B:$B,全体!$G94,コンシューマー!H:H) -> 439 | O94: =SUMIF(コンシューマー!$B:$B,全体!$G94,コンシューマー!I:I) -> 412 | P94: =SUMIF(コンシューマー!$B:$B,全体!$G94,コンシューマー!J:J) -> 443 | Q94: =SUMIF(コンシューマー!$B:$B,全体!$G94,コンシューマー!K:K) -> 363 | R94: =SUMIF(コンシューマー!$B:$B,全体!$G94,コンシューマー!L:L) -> 487 | S94: =SUMIF(コンシューマー!$B:$B,全体!$G94,コンシューマー!M:M) -> 427 | T94: =SUMIF(コンシューマー!$B:$B,全体!$G94,コンシューマー!N:N) -> 270 | U94: =SUMIF(コンシューマー!$B:$B,全体!$G94,コンシューマー!O:O) -> 301 | V94: =SUMIF(コンシューマー!$B:$B,全体!$G94,コンシューマー!P:P) -> 199 | W94: =SUMIF(コンシューマー!$B:$B,全体!$G94,コンシューマー!Q:Q) -> 298 | X94: =SUMIF(コンシューマー!$B:$B,全体!$G94,コンシューマー!R:R) -> 301 | Y94: =SUMIF(コンシューマー!$B:$B,全体!$G94,コンシューマー!S:S) -> 219 | Z94: =SUMIF(コンシューマー!$B:$B,全体!$G94,コンシューマー!T:T) -> 339 | AA94: =SUMIF(コンシューマー!$B:$B,全体!$G94,コンシューマー!U:U) -> 308 | AB94: =SUMIF(コンシューマー!$B:$B,全体!$G94,コンシューマー!V:V) -> 332 | AC94: =SUMIF(コンシューマー!$B:$B,全体!$G94,コンシューマー!W:W) -> 601 | AD94: =SUMIF(コンシューマー!$B:$B,全体!$G94,コンシューマー!X:X) -> 222 | AE94: =SUMIF(コンシューマー!$B:$B,全体!$G94,コンシューマー!Y:Y) -> 44 | AF94: =SUMIF(コンシューマー!$B:$B,全体!$G94,コンシューマー!Z:Z) -> 63 | AG94: =SUMIF(コンシューマー!$B:$B,全体!$G94,コンシューマー!AA:AA) -> 58 | AI94: 4 | AK94: 3 | AL94: 4.8387097 | AM94: 0 | AN94: 0 | AO94: -1 | AP94: 0 | AQ94: 0 | AR94: =SUMIF(結果貼付!$A:$A,G94,結果貼付!$D:$D) -> 0 | AS94: =(AR94/AS$2)*AS$1 -> 0 | AT94: =SUM(SUMIF(コンシューマー!$B:$B,全体!$G94,コンシューマー!AO:AO),SUMIF(コマーシャル!$B:$B,全体!$G94,コマーシャル!AK:AK)) -> 0 | AU94: =SUM(SUMIF(コンシューマー!$B:$B,全体!$G94,コンシューマー!AP:AP),SUMIF(コマーシャル!$B:$B,全体!$G94,コマーシャル!AL:AL)) -> 0 | AV94: =SUM(SUMIF(コンシューマー!$B:$B,全体!$G94,コンシューマー!AQ:AQ),SUMIF(コマーシャル!$B:$B,全体!$G94,コマーシャル!AM:AM)) -> 0 | AW94: =SUM(SUMIF(コンシューマー!$B:$B,全体!$G94,コンシューマー!AR:AR),SUMIF(コマーシャル!$B:$B,全体!$G94,コマーシャル!AN:AN)) -> 0 | AX94: =SUM(SUMIF(コンシューマー!$B:$B,全体!$G94,コンシューマー!AS:AS),SUMIF(コマーシャル!$B:$B,全体!$G94,コマーシャル!AO:AO)) -> 0 | AY94: =SUM(SUMIF(コンシューマー!$B:$B,全体!$G94,コンシューマー!AT:AT),SUMIF(コマーシャル!$B:$B,全体!$G94,コマーシャル!AP:AP)) -> 0 | AZ94: 不要な14世代消す
A95: =SUMIFS(SAP貼付!K:K,SAP貼付!C:C,全体!G95) -> 13 | D95: =SUM(A95:C95) -> 13 | E95: =IFERROR(D95-SUM(#REF!)," ") | G95: i9-14900K | H95: =IFERROR(IF(MATCH($G95,コンシューマー!B:B,0),"Y"),"-") -> Y | I95: =IFERROR(IF(MATCH($G95,コマーシャル!B:B,0),"Y"),"-") -> - | J95: =SUMIF(コンシューマー!$B:$B,全体!$G95,コンシューマー!D:D) -> 0 | K95: =SUMIF(コンシューマー!$B:$B,全体!$G95,コンシューマー!E:E) -> 0 | L95: =SUMIF(コンシューマー!$B:$B,全体!$G95,コンシューマー!F:F) -> 0 | M95: =SUMIF(コンシューマー!$B:$B,全体!$G95,コンシューマー!G:G) -> 68 | N95: =SUMIF(コンシューマー!$B:$B,全体!$G95,コンシューマー!H:H) -> 148 | O95: =SUMIF(コンシューマー!$B:$B,全体!$G95,コンシューマー!I:I) -> 191 | P95: =SUMIF(コンシューマー!$B:$B,全体!$G95,コンシューマー!J:J) -> 198 | Q95: =SUMIF(コンシューマー!$B:$B,全体!$G95,コンシューマー!K:K) -> 129 | R95: =SUMIF(コンシューマー!$B:$B,全体!$G95,コンシューマー!L:L) -> 124 | S95: =SUMIF(コンシューマー!$B:$B,全体!$G95,コンシューマー!M:M) -> 100 | T95: =SUMIF(コンシューマー!$B:$B,全体!$G95,コンシューマー!N:N) -> 164 | U95: =SUMIF(コンシューマー!$B:$B,全体!$G95,コンシューマー!O:O) -> 136 | V95: =SUMIF(コンシューマー!$B:$B,全体!$G95,コンシューマー!P:P) -> 74 | W95: =SUMIF(コンシューマー!$B:$B,全体!$G95,コンシューマー!Q:Q) -> 114 | X95: =SUMIF(コンシューマー!$B:$B,全体!$G95,コンシューマー!R:R) -> 100 | Y95: =SUMIF(コンシューマー!$B:$B,全体!$G95,コンシューマー!S:S) -> 3 | Z95: =SUMIF(コンシューマー!$B:$B,全体!$G95,コンシューマー!T:T) -> 61 | AA95: =SUMIF(コンシューマー!$B:$B,全体!$G95,コンシューマー!U:U) -> 5 | AB95: =SUMIF(コンシューマー!$B:$B,全体!$G95,コンシューマー!V:V) -> 1 | AC95: =SUMIF(コンシューマー!$B:$B,全体!$G95,コンシューマー!W:W) -> 2 | AD95: =SUMIF(コンシューマー!$B:$B,全体!$G95,コンシューマー!X:X) -> 0 | AE95: =SUMIF(コンシューマー!$B:$B,全体!$G95,コンシューマー!Y:Y) -> 0 | AF95: =SUMIF(コンシューマー!$B:$B,全体!$G95,コンシューマー!Z:Z) -> 0 | AG95: =SUMIF(コンシューマー!$B:$B,全体!$G95,コンシューマー!AA:AA) -> 0 | AI95: 0 | AK95: 0 | AL95: 0 | AM95: 0 | AN95: 0 | AO95: 0 | AP95: 0 | AQ95: 0 | AR95: =SUMIF(結果貼付!$A:$A,G95,結果貼付!$D:$D) -> 0 | AS95: =(AR95/AS$2)*AS$1 -> 0 | AT95: =SUM(SUMIF(コンシューマー!$B:$B,全体!$G95,コンシューマー!AO:AO),SUMIF(コマーシャル!$B:$B,全体!$G95,コマーシャル!AK:AK)) -> 0 | AU95: =SUM(SUMIF(コンシューマー!$B:$B,全体!$G95,コンシューマー!AP:AP),SUMIF(コマーシャル!$B:$B,全体!$G95,コマーシャル!AL:AL)) -> 0 | AV95: =SUM(SUMIF(コンシューマー!$B:$B,全体!$G95,コンシューマー!AQ:AQ),SUMIF(コマーシャル!$B:$B,全体!$G95,コマーシャル!AM:AM)) -> 0 | AW95: =SUM(SUMIF(コンシューマー!$B:$B,全体!$G95,コンシューマー!AR:AR),SUMIF(コマーシャル!$B:$B,全体!$G95,コマーシャル!AN:AN)) -> 0 | AX95: =SUM(SUMIF(コンシューマー!$B:$B,全体!$G95,コンシューマー!AS:AS),SUMIF(コマーシャル!$B:$B,全体!$G95,コマーシャル!AO:AO)) -> 0 | AY95: =SUM(SUMIF(コンシューマー!$B:$B,全体!$G95,コンシューマー!AT:AT),SUMIF(コマーシャル!$B:$B,全体!$G95,コマーシャル!AP:AP)) -> 0
A96: =SUMIFS(SAP貼付!K:K,SAP貼付!C:C,全体!G96) -> 22 | D96: =SUM(A96:C96) -> 22 | E96: =IFERROR(D96-SUM(#REF!)," ") | G96: i9-14900F | H96: =IFERROR(IF(MATCH($G96,コンシューマー!B:B,0),"Y"),"-") -> Y | I96: =IFERROR(IF(MATCH($G96,コマーシャル!B:B,0),"Y"),"-") -> - | J96: =SUMIF(コンシューマー!$B:$B,全体!$G96,コンシューマー!D:D) -> 0 | K96: =SUMIF(コンシューマー!$B:$B,全体!$G96,コンシューマー!E:E) -> 0 | L96: =SUMIF(コンシューマー!$B:$B,全体!$G96,コンシューマー!F:F) -> 0 | M96: =SUMIF(コンシューマー!$B:$B,全体!$G96,コンシューマー!G:G) -> 0 | N96: =SUMIF(コンシューマー!$B:$B,全体!$G96,コンシューマー!H:H) -> 0 | O96: =SUMIF(コンシューマー!$B:$B,全体!$G96,コンシューマー!I:I) -> 2 | P96: =SUMIF(コンシューマー!$B:$B,全体!$G96,コンシューマー!J:J) -> 44 | Q96: =SUMIF(コンシューマー!$B:$B,全体!$G96,コンシューマー!K:K) -> 64 | R96: =SUMIF(コンシューマー!$B:$B,全体!$G96,コンシューマー!L:L) -> 53 | S96: =SUMIF(コンシューマー!$B:$B,全体!$G96,コンシューマー!M:M) -> 32 | T96: =SUMIF(コンシューマー!$B:$B,全体!$G96,コンシューマー!N:N) -> 31 | U96: =SUMIF(コンシューマー!$B:$B,全体!$G96,コンシューマー!O:O) -> 32 | V96: =SUMIF(コンシューマー!$B:$B,全体!$G96,コンシューマー!P:P) -> 19 | W96: =SUMIF(コンシューマー!$B:$B,全体!$G96,コンシューマー!Q:Q) -> 60 | X96: =SUMIF(コンシューマー!$B:$B,全体!$G96,コンシューマー!R:R) -> 51 | Y96: =SUMIF(コンシューマー!$B:$B,全体!$G96,コンシューマー!S:S) -> 0 | Z96: =SUMIF(コンシューマー!$B:$B,全体!$G96,コンシューマー!T:T) -> 17 | AA96: =SUMIF(コンシューマー!$B:$B,全体!$G96,コンシューマー!U:U) -> 2 | AB96: =SUMIF(コンシューマー!$B:$B,全体!$G96,コンシューマー!V:V) -> 21 | AC96: =SUMIF(コンシューマー!$B:$B,全体!$G96,コンシューマー!W:W) -> 3 | AD96: =SUMIF(コンシューマー!$B:$B,全体!$G96,コンシューマー!X:X) -> 6 | AE96: =SUMIF(コンシューマー!$B:$B,全体!$G96,コンシューマー!Y:Y) -> 2 | AF96: =SUMIF(コンシューマー!$B:$B,全体!$G96,コンシューマー!Z:Z) -> 6 | AG96: =SUMIF(コンシューマー!$B:$B,全体!$G96,コンシューマー!AA:AA) -> 0 | AI96: 0 | AK96: 0 | AL96: 0 | AM96: 0 | AN96: 0 | AO96: 0 | AP96: 0 | AQ96: 0 | AR96: =SUMIF(結果貼付!$A:$A,G96,結果貼付!$D:$D) -> 0 | AS96: =(AR96/AS$2)*AS$1 -> 0 | AT96: =SUM(SUMIF(コンシューマー!$B:$B,全体!$G96,コンシューマー!AO:AO),SUMIF(コマーシャル!$B:$B,全体!$G96,コマーシャル!AK:AK)) -> 0 | AU96: =SUM(SUMIF(コンシューマー!$B:$B,全体!$G96,コンシューマー!AP:AP),SUMIF(コマーシャル!$B:$B,全体!$G96,コマーシャル!AL:AL)) -> 0 | AV96: =SUM(SUMIF(コンシューマー!$B:$B,全体!$G96,コンシューマー!AQ:AQ),SUMIF(コマーシャル!$B:$B,全体!$G96,コマーシャル!AM:AM)) -> 0 | AW96: =SUM(SUMIF(コンシューマー!$B:$B,全体!$G96,コンシューマー!AR:AR),SUMIF(コマーシャル!$B:$B,全体!$G96,コマーシャル!AN:AN)) -> 0 | AX96: =SUM(SUMIF(コンシューマー!$B:$B,全体!$G96,コンシューマー!AS:AS),SUMIF(コマーシャル!$B:$B,全体!$G96,コマーシャル!AO:AO)) -> 0 | AY96: =SUM(SUMIF(コンシューマー!$B:$B,全体!$G96,コンシューマー!AT:AT),SUMIF(コマーシャル!$B:$B,全体!$G96,コマーシャル!AP:AP)) -> 0
A97: =SUMIFS(SAP貼付!K:K,SAP貼付!C:C,全体!G97) -> 36 | D97: =SUM(A97:C97) -> 36 | E97: =IFERROR(D97-SUM(#REF!)," ") | G97: i9-14900 | H97: =IFERROR(IF(MATCH($G97,コンシューマー!B:B,0),"Y"),"-") -> Y | I97: =IFERROR(IF(MATCH($G97,コマーシャル!B:B,0),"Y"),"-") -> - | J97: =SUMIF(コンシューマー!$B:$B,全体!$G97,コンシューマー!D:D) -> 0 | K97: =SUMIF(コンシューマー!$B:$B,全体!$G97,コンシューマー!E:E) -> 0 | L97: =SUMIF(コンシューマー!$B:$B,全体!$G97,コンシューマー!F:F) -> 0 | M97: =SUMIF(コンシューマー!$B:$B,全体!$G97,コンシューマー!G:G) -> 0 | N97: =SUMIF(コンシューマー!$B:$B,全体!$G97,コンシューマー!H:H) -> 0 | O97: =SUMIF(コンシューマー!$B:$B,全体!$G97,コンシューマー!I:I) -> 40 | P97: =SUMIF(コンシューマー!$B:$B,全体!$G97,コンシューマー!J:J) -> 74 | Q97: =SUMIF(コンシューマー!$B:$B,全体!$G97,コンシューマー!K:K) -> 88 | R97: =SUMIF(コンシューマー!$B:$B,全体!$G97,コンシューマー!L:L) -> 38 | S97: =SUMIF(コンシューマー!$B:$B,全体!$G97,コンシューマー!M:M) -> 27 | T97: =SUMIF(コンシューマー!$B:$B,全体!$G97,コンシューマー!N:N) -> 30 | U97: =SUMIF(コンシューマー!$B:$B,全体!$G97,コンシューマー!O:O) -> 88 | V97: =SUMIF(コンシューマー!$B:$B,全体!$G97,コンシューマー!P:P) -> 48 | W97: =SUMIF(コンシューマー!$B:$B,全体!$G97,コンシューマー!Q:Q) -> 37 | X97: =SUMIF(コンシューマー!$B:$B,全体!$G97,コンシューマー!R:R) -> 31 | Y97: =SUMIF(コンシューマー!$B:$B,全体!$G97,コンシューマー!S:S) -> 76 | Z97: =SUMIF(コンシューマー!$B:$B,全体!$G97,コンシューマー!T:T) -> 45 | AA97: =SUMIF(コンシューマー!$B:$B,全体!$G97,コンシューマー!U:U) -> 83 | AB97: =SUMIF(コンシューマー!$B:$B,全体!$G97,コンシューマー!V:V) -> 31 | AC97: =SUMIF(コンシューマー!$B:$B,全体!$G97,コンシューマー!W:W) -> 14 | AD97: =SUMIF(コンシューマー!$B:$B,全体!$G97,コンシューマー!X:X) -> 1 | AE97: =SUMIF(コンシューマー!$B:$B,全体!$G97,コンシューマー!Y:Y) -> 3 | AF97: =SUMIF(コンシューマー!$B:$B,全体!$G97,コンシューマー!Z:Z) -> 27 | AG97: =SUMIF(コンシューマー!$B:$B,全体!$G97,コンシューマー!AA:AA) -> 20 | AI97: 1 | AK97: 0 | AL97: 0 | AM97: 0 | AN97: 0 | AO97: 0 | AP97: 0 | AQ97: 0 | AR97: =SUMIF(結果貼付!$A:$A,G97,結果貼付!$D:$D) -> 0 | AS97: =(AR97/AS$2)*AS$1 -> 0 | AT97: =SUM(SUMIF(コンシューマー!$B:$B,全体!$G97,コンシューマー!AO:AO),SUMIF(コマーシャル!$B:$B,全体!$G97,コマーシャル!AK:AK)) -> 0 | AU97: =SUM(SUMIF(コンシューマー!$B:$B,全体!$G97,コンシューマー!AP:AP),SUMIF(コマーシャル!$B:$B,全体!$G97,コマーシャル!AL:AL)) -> 0 | AV97: =SUM(SUMIF(コンシューマー!$B:$B,全体!$G97,コンシューマー!AQ:AQ),SUMIF(コマーシャル!$B:$B,全体!$G97,コマーシャル!AM:AM)) -> 0 | AW97: =SUM(SUMIF(コンシューマー!$B:$B,全体!$G97,コンシューマー!AR:AR),SUMIF(コマーシャル!$B:$B,全体!$G97,コマーシャル!AN:AN)) -> 0 | AX97: =SUM(SUMIF(コンシューマー!$B:$B,全体!$G97,コンシューマー!AS:AS),SUMIF(コマーシャル!$B:$B,全体!$G97,コマーシャル!AO:AO)) -> 0 | AY97: =SUM(SUMIF(コンシューマー!$B:$B,全体!$G97,コンシューマー!AT:AT),SUMIF(コマーシャル!$B:$B,全体!$G97,コマーシャル!AP:AP)) -> 0
A98: =SUMIFS(SAP貼付!K:K,SAP貼付!C:C,全体!G98) -> 40 | D98: =SUM(A98:C98) -> 40 | E98: =IFERROR(D98-SUM(#REF!)," ") | G98: i7-14700KF | H98: =IFERROR(IF(MATCH($G98,コンシューマー!B:B,0),"Y"),"-") -> Y | I98: =IFERROR(IF(MATCH($G98,コマーシャル!B:B,0),"Y"),"-") -> - | J98: =SUMIF(コンシューマー!$B:$B,全体!$G98,コンシューマー!D:D) -> 0 | K98: =SUMIF(コンシューマー!$B:$B,全体!$G98,コンシューマー!E:E) -> 0 | L98: =SUMIF(コンシューマー!$B:$B,全体!$G98,コンシューマー!F:F) -> 0 | M98: =SUMIF(コンシューマー!$B:$B,全体!$G98,コンシューマー!G:G) -> 432 | N98: =SUMIF(コンシューマー!$B:$B,全体!$G98,コンシューマー!H:H) -> 476 | O98: =SUMIF(コンシューマー!$B:$B,全体!$G98,コンシューマー!I:I) -> 509 | P98: =SUMIF(コンシューマー!$B:$B,全体!$G98,コンシューマー!J:J) -> 617 | Q98: =SUMIF(コンシューマー!$B:$B,全体!$G98,コンシューマー!K:K) -> 292 | R98: =SUMIF(コンシューマー!$B:$B,全体!$G98,コンシューマー!L:L) -> 317 | S98: =SUMIF(コンシューマー!$B:$B,全体!$G98,コンシューマー!M:M) -> 223 | T98: =SUMIF(コンシューマー!$B:$B,全体!$G98,コンシューマー!N:N) -> 262 | U98: =SUMIF(コンシューマー!$B:$B,全体!$G98,コンシューマー!O:O) -> 231 | V98: =SUMIF(コンシューマー!$B:$B,全体!$G98,コンシューマー!P:P) -> 118 | W98: =SUMIF(コンシューマー!$B:$B,全体!$G98,コンシューマー!Q:Q) -> 226 | X98: =SUMIF(コンシューマー!$B:$B,全体!$G98,コンシューマー!R:R) -> 231 | Y98: =SUMIF(コンシューマー!$B:$B,全体!$G98,コンシューマー!S:S) -> 36 | Z98: =SUMIF(コンシューマー!$B:$B,全体!$G98,コンシューマー!T:T) -> 60 | AA98: =SUMIF(コンシューマー!$B:$B,全体!$G98,コンシューマー!U:U) -> 72 | AB98: =SUMIF(コンシューマー!$B:$B,全体!$G98,コンシューマー!V:V) -> 99 | AC98: =SUMIF(コンシューマー!$B:$B,全体!$G98,コンシューマー!W:W) -> 30 | AD98: =SUMIF(コンシューマー!$B:$B,全体!$G98,コンシューマー!X:X) -> 0 | AE98: =SUMIF(コンシューマー!$B:$B,全体!$G98,コンシューマー!Y:Y) -> -1 | AF98: =SUMIF(コンシューマー!$B:$B,全体!$G98,コンシューマー!Z:Z) -> 0 | AG98: =SUMIF(コンシューマー!$B:$B,全体!$G98,コンシューマー!AA:AA) -> 0 | AI98: 0 | AK98: 0 | AL98: 0 | AM98: 0 | AN98: 0 | AO98: 0 | AP98: 0 | AQ98: -1 | AR98: =SUMIF(結果貼付!$A:$A,G98,結果貼付!$D:$D) -> 0 | AS98: =(AR98/AS$2)*AS$1 -> 0 | AT98: =SUM(SUMIF(コンシューマー!$B:$B,全体!$G98,コンシューマー!AO:AO),SUMIF(コマーシャル!$B:$B,全体!$G98,コマーシャル!AK:AK)) -> 0 | AU98: =SUM(SUMIF(コンシューマー!$B:$B,全体!$G98,コンシューマー!AP:AP),SUMIF(コマーシャル!$B:$B,全体!$G98,コマーシャル!AL:AL)) -> 0 | AV98: =SUM(SUMIF(コンシューマー!$B:$B,全体!$G98,コンシューマー!AQ:AQ),SUMIF(コマーシャル!$B:$B,全体!$G98,コマーシャル!AM:AM)) -> 0 | AW98: =SUM(SUMIF(コンシューマー!$B:$B,全体!$G98,コンシューマー!AR:AR),SUMIF(コマーシャル!$B:$B,全体!$G98,コマーシャル!AN:AN)) -> 0 | AX98: =SUM(SUMIF(コンシューマー!$B:$B,全体!$G98,コンシューマー!AS:AS),SUMIF(コマーシャル!$B:$B,全体!$G98,コマーシャル!AO:AO)) -> 0 | AY98: =SUM(SUMIF(コンシューマー!$B:$B,全体!$G98,コンシューマー!AT:AT),SUMIF(コマーシャル!$B:$B,全体!$G98,コマーシャル!AP:AP)) -> 0
A99: =SUMIFS(SAP貼付!K:K,SAP貼付!C:C,全体!G99) -> 1 | D99: =SUM(A99:C99) -> 1 | E99: =IFERROR(D99-SUM(#REF!)," ") | G99: i7-14700K | H99: =IFERROR(IF(MATCH($G99,コンシューマー!B:B,0),"Y"),"-") -> Y | I99: =IFERROR(IF(MATCH($G99,コマーシャル!B:B,0),"Y"),"-") -> - | J99: =SUMIF(コンシューマー!$B:$B,全体!$G99,コンシューマー!D:D) -> 0 | K99: =SUMIF(コンシューマー!$B:$B,全体!$G99,コンシューマー!E:E) -> 0 | L99: =SUMIF(コンシューマー!$B:$B,全体!$G99,コンシューマー!F:F) -> 0 | M99: =SUMIF(コンシューマー!$B:$B,全体!$G99,コンシューマー!G:G) -> 53 | N99: =SUMIF(コンシューマー!$B:$B,全体!$G99,コンシューマー!H:H) -> 133 | O99: =SUMIF(コンシューマー!$B:$B,全体!$G99,コンシューマー!I:I) -> 100 | P99: =SUMIF(コンシューマー!$B:$B,全体!$G99,コンシューマー!J:J) -> 91 | Q99: =SUMIF(コンシューマー!$B:$B,全体!$G99,コンシューマー!K:K) -> 75 | R99: =SUMIF(コンシューマー!$B:$B,全体!$G99,コンシューマー!L:L) -> 69 | S99: =SUMIF(コンシューマー!$B:$B,全体!$G99,コンシューマー!M:M) -> 62 | T99: =SUMIF(コンシューマー!$B:$B,全体!$G99,コンシューマー!N:N) -> 56 | U99: =SUMIF(コンシューマー!$B:$B,全体!$G99,コンシューマー!O:O) -> 40 | V99: =SUMIF(コンシューマー!$B:$B,全体!$G99,コンシューマー!P:P) -> 32 | W99: =SUMIF(コンシューマー!$B:$B,全体!$G99,コンシューマー!Q:Q) -> 51 | X99: =SUMIF(コンシューマー!$B:$B,全体!$G99,コンシューマー!R:R) -> 59 | Y99: =SUMIF(コンシューマー!$B:$B,全体!$G99,コンシューマー!S:S) -> 1 | Z99: =SUMIF(コンシューマー!$B:$B,全体!$G99,コンシューマー!T:T) -> 8 | AA99: =SUMIF(コンシューマー!$B:$B,全体!$G99,コンシューマー!U:U) -> 3 | AB99: =SUMIF(コンシューマー!$B:$B,全体!$G99,コンシューマー!V:V) -> 2 | AC99: =SUMIF(コンシューマー!$B:$B,全体!$G99,コンシューマー!W:W) -> 10 | AD99: =SUMIF(コンシューマー!$B:$B,全体!$G99,コンシューマー!X:X) -> 0 | AE99: =SUMIF(コンシューマー!$B:$B,全体!$G99,コンシューマー!Y:Y) -> 0 | AF99: =SUMIF(コンシューマー!$B:$B,全体!$G99,コンシューマー!Z:Z) -> 0 | AG99: =SUMIF(コンシューマー!$B:$B,全体!$G99,コンシューマー!AA:AA) -> 0 | AI99: 0 | AK99: 0 | AL99: 0 | AM99: 0 | AN99: 0 | AO99: 0 | AP99: 0 | AQ99: 0 | AR99: =SUMIF(結果貼付!$A:$A,G99,結果貼付!$D:$D) -> 0 | AS99: =(AR99/AS$2)*AS$1 -> 0 | AT99: =SUM(SUMIF(コンシューマー!$B:$B,全体!$G99,コンシューマー!AO:AO),SUMIF(コマーシャル!$B:$B,全体!$G99,コマーシャル!AK:AK)) -> 0 | AU99: =SUM(SUMIF(コンシューマー!$B:$B,全体!$G99,コンシューマー!AP:AP),SUMIF(コマーシャル!$B:$B,全体!$G99,コマーシャル!AL:AL)) -> 0 | AV99: =SUM(SUMIF(コンシューマー!$B:$B,全体!$G99,コンシューマー!AQ:AQ),SUMIF(コマーシャル!$B:$B,全体!$G99,コマーシャル!AM:AM)) -> 0 | AW99: =SUM(SUMIF(コンシューマー!$B:$B,全体!$G99,コンシューマー!AR:AR),SUMIF(コマーシャル!$B:$B,全体!$G99,コマーシャル!AN:AN)) -> 0 | AX99: =SUM(SUMIF(コンシューマー!$B:$B,全体!$G99,コンシューマー!AS:AS),SUMIF(コマーシャル!$B:$B,全体!$G99,コマーシャル!AO:AO)) -> 0 | AY99: =SUM(SUMIF(コンシューマー!$B:$B,全体!$G99,コンシューマー!AT:AT),SUMIF(コマーシャル!$B:$B,全体!$G99,コマーシャル!AP:AP)) -> 0
A100: =SUMIFS(SAP貼付!K:K,SAP貼付!C:C,全体!G100) -> 2238 | D100: =SUM(A100:C100) -> 2238 | E100: =IFERROR(D100-SUM(#REF!)," ") | G100: i7-14700F | H100: =IFERROR(IF(MATCH($G100,コンシューマー!B:B,0),"Y"),"-") -> Y | I100: =IFERROR(IF(MATCH($G100,コマーシャル!B:B,0),"Y"),"-") -> Y | J100: =SUMIF(コンシューマー!$B:$B,全体!$G100,コンシューマー!D:D) -> 0 | K100: =SUMIF(コンシューマー!$B:$B,全体!$G100,コンシューマー!E:E) -> 0 | L100: =SUMIF(コンシューマー!$B:$B,全体!$G100,コンシューマー!F:F) -> 0 | M100: =SUMIF(コンシューマー!$B:$B,全体!$G100,コンシューマー!G:G) -> 0 | N100: =SUMIF(コンシューマー!$B:$B,全体!$G100,コンシューマー!H:H) -> 0 | O100: =SUMIF(コンシューマー!$B:$B,全体!$G100,コンシューマー!I:I) -> 1705 | P100: =SUMIF(コンシューマー!$B:$B,全体!$G100,コンシューマー!J:J) -> 5698 | Q100: =SUMIF(コンシューマー!$B:$B,全体!$G100,コンシューマー!K:K) -> 5954 | R100: =SUMIF(コンシューマー!$B:$B,全体!$G100,コンシューマー!L:L) -> 5821 | S100: =SUMIF(コンシューマー!$B:$B,全体!$G100,コンシューマー!M:M) -> 4824 | T100: =SUMIF(コンシューマー!$B:$B,全体!$G100,コンシューマー!N:N) -> 4887 | U100: =SUMIF(コンシューマー!$B:$B,全体!$G100,コンシューマー!O:O) -> 6648 | V100: =SUMIF(コンシューマー!$B:$B,全体!$G100,コンシューマー!P:P) -> 3573 | W100: =SUMIF(コンシューマー!$B:$B,全体!$G100,コンシューマー!Q:Q) -> 4561 | X100: =SUMIF(コンシューマー!$B:$B,全体!$G100,コンシューマー!R:R) -> 5986 | Y100: =SUMIF(コンシューマー!$B:$B,全体!$G100,コンシューマー!S:S) -> 5158 | Z100: =SUMIF(コンシューマー!$B:$B,全体!$G100,コンシューマー!T:T) -> 8660 | AA100: =SUMIF(コンシューマー!$B:$B,全体!$G100,コンシューマー!U:U) -> 7377 | AB100: =SUMIF(コンシューマー!$B:$B,全体!$G100,コンシューマー!V:V) -> 8679 | AC100: =SUMIF(コンシューマー!$B:$B,全体!$G100,コンシューマー!W:W) -> 9754 | AD100: =SUMIF(コンシューマー!$B:$B,全体!$G100,コンシューマー!X:X) -> 4117 | AE100: =SUMIF(コンシューマー!$B:$B,全体!$G100,コンシューマー!Y:Y) -> 3218 | AF100: =SUMIF(コンシューマー!$B:$B,全体!$G100,コンシューマー!Z:Z) -> 3245 | AG100: =SUMIF(コンシューマー!$B:$B,全体!$G100,コンシューマー!AA:AA) -> 3730 | AI100: 1674 | AK100: 581 | AL100: 742.25806 | AM100: 364.7075 | AN100: 147 | AO100: 804 | AP100: 652 | AQ100: 454 | AR100: =SUMIF(結果貼付!$A:$A,G100,結果貼付!$D:$D) -> 95 | AS100: =(AR100/AS$2)*AS$1 -> 203.57143 | AT100: =SUM(SUMIF(コンシューマー!$B:$B,全体!$G100,コンシューマー!AO:AO),SUMIF(コマーシャル!$B:$B,全体!$G100,コマーシャル!AK:AK)) -> 250 | AU100: =SUM(SUMIF(コンシューマー!$B:$B,全体!$G100,コンシューマー!AP:AP),SUMIF(コマーシャル!$B:$B,全体!$G100,コマーシャル!AL:AL)) -> 298 | AV100: =SUM(SUMIF(コンシューマー!$B:$B,全体!$G100,コンシューマー!AQ:AQ),SUMIF(コマーシャル!$B:$B,全体!$G100,コマーシャル!AM:AM)) -> 254.06692 | AW100: =SUM(SUMIF(コンシューマー!$B:$B,全体!$G100,コンシューマー!AR:AR),SUMIF(コマーシャル!$B:$B,全体!$G100,コマーシャル!AN:AN)) -> 249.24419 | AX100: =SUM(SUMIF(コンシューマー!$B:$B,全体!$G100,コンシューマー!AS:AS),SUMIF(コマーシャル!$B:$B,全体!$G100,コマーシャル!AO:AO)) -> 217.25517 | AY100: =SUM(SUMIF(コンシューマー!$B:$B,全体!$G100,コンシューマー!AT:AT),SUMIF(コマーシャル!$B:$B,全体!$G100,コマーシャル!AP:AP)) -> 215.38837
A101: =SUMIFS(SAP貼付!K:K,SAP貼付!C:C,全体!G101) -> 2304 | D101: =SUM(A101:C101) -> 2304 | E101: =IFERROR(D101-SUM(#REF!)," ") | G101: i7-14700 | H101: =IFERROR(IF(MATCH($G101,コンシューマー!B:B,0),"Y"),"-") -> Y | I101: =IFERROR(IF(MATCH($G101,コマーシャル!B:B,0),"Y"),"-") -> Y | J101: =SUMIF(コンシューマー!$B:$B,全体!$G101,コンシューマー!D:D) -> 0 | K101: =SUMIF(コンシューマー!$B:$B,全体!$G101,コンシューマー!E:E) -> 0 | L101: =SUMIF(コンシューマー!$B:$B,全体!$G101,コンシューマー!F:F) -> 0 | M101: =SUMIF(コンシューマー!$B:$B,全体!$G101,コンシューマー!G:G) -> 0 | N101: =SUMIF(コンシューマー!$B:$B,全体!$G101,コンシューマー!H:H) -> 0 | O101: =SUMIF(コンシューマー!$B:$B,全体!$G101,コンシューマー!I:I) -> 370 | P101: =SUMIF(コンシューマー!$B:$B,全体!$G101,コンシューマー!J:J) -> 990 | Q101: =SUMIF(コンシューマー!$B:$B,全体!$G101,コンシューマー!K:K) -> 1255 | R101: =SUMIF(コンシューマー!$B:$B,全体!$G101,コンシューマー!L:L) -> 1435 | S101: =SUMIF(コンシューマー!$B:$B,全体!$G101,コンシューマー!M:M) -> 1201 | T101: =SUMIF(コンシューマー!$B:$B,全体!$G101,コンシューマー!N:N) -> 1132 | U101: =SUMIF(コンシューマー!$B:$B,全体!$G101,コンシューマー!O:O) -> 1616 | V101: =SUMIF(コンシューマー!$B:$B,全体!$G101,コンシューマー!P:P) -> 843 | W101: =SUMIF(コンシューマー!$B:$B,全体!$G101,コンシューマー!Q:Q) -> 1127 | X101: =SUMIF(コンシューマー!$B:$B,全体!$G101,コンシューマー!R:R) -> 1352 | Y101: =SUMIF(コンシューマー!$B:$B,全体!$G101,コンシューマー!S:S) -> 1309 | Z101: =SUMIF(コンシューマー!$B:$B,全体!$G101,コンシューマー!T:T) -> 2363 | AA101: =SUMIF(コンシューマー!$B:$B,全体!$G101,コンシューマー!U:U) -> 2008 | AB101: =SUMIF(コンシューマー!$B:$B,全体!$G101,コンシューマー!V:V) -> 1867 | AC101: =SUMIF(コンシューマー!$B:$B,全体!$G101,コンシューマー!W:W) -> 565 | AD101: =SUMIF(コンシューマー!$B:$B,全体!$G101,コンシューマー!X:X) -> 662 | AE101: =SUMIF(コンシューマー!$B:$B,全体!$G101,コンシューマー!Y:Y) -> 780 | AF101: =SUMIF(コンシューマー!$B:$B,全体!$G101,コンシューマー!Z:Z) -> 865 | AG101: =SUMIF(コンシューマー!$B:$B,全体!$G101,コンシューマー!AA:AA) -> 1004 | AI101: 717 | AK101: 269 | AL101: 267.09677 | AM101: 240.03583 | AN101: 148 | AO101: 126 | AP101: 0 | AQ101: 10 | AR101: =SUMIF(結果貼付!$A:$A,G101,結果貼付!$D:$D) -> 0 | AS101: =(AR101/AS$2)*AS$1 -> 0 | AT101: =SUM(SUMIF(コンシューマー!$B:$B,全体!$G101,コンシューマー!AO:AO),SUMIF(コマーシャル!$B:$B,全体!$G101,コマーシャル!AK:AK)) -> 10 | AU101: =SUM(SUMIF(コンシューマー!$B:$B,全体!$G101,コンシューマー!AP:AP),SUMIF(コマーシャル!$B:$B,全体!$G101,コマーシャル!AL:AL)) -> 10 | AV101: =SUM(SUMIF(コンシューマー!$B:$B,全体!$G101,コンシューマー!AQ:AQ),SUMIF(コマーシャル!$B:$B,全体!$G101,コマーシャル!AM:AM)) -> 10 | AW101: =SUM(SUMIF(コンシューマー!$B:$B,全体!$G101,コンシューマー!AR:AR),SUMIF(コマーシャル!$B:$B,全体!$G101,コマーシャル!AN:AN)) -> 10 | AX101: =SUM(SUMIF(コンシューマー!$B:$B,全体!$G101,コンシューマー!AS:AS),SUMIF(コマーシャル!$B:$B,全体!$G101,コマーシャル!AO:AO)) -> 10 | AY101: =SUM(SUMIF(コンシューマー!$B:$B,全体!$G101,コンシューマー!AT:AT),SUMIF(コマーシャル!$B:$B,全体!$G101,コマーシャル!AP:AP)) -> 10
A102: =SUMIFS(SAP貼付!K:K,SAP貼付!C:C,全体!G102) -> 102 | D102: =SUM(A102:C102) -> 102 | E102: =IFERROR(D102-SUM(#REF!)," ") | G102: i7-14700T | H102: =IFERROR(IF(MATCH($G102,コンシューマー!B:B,0),"Y"),"-") -> Y | I102: =IFERROR(IF(MATCH($G102,コマーシャル!B:B,0),"Y"),"-") -> - | J102: =SUMIF(コンシューマー!$B:$B,全体!$G102,コンシューマー!D:D) -> 0 | K102: =SUMIF(コンシューマー!$B:$B,全体!$G102,コンシューマー!E:E) -> 0 | L102: =SUMIF(コンシューマー!$B:$B,全体!$G102,コンシューマー!F:F) -> 0 | M102: =SUMIF(コンシューマー!$B:$B,全体!$G102,コンシューマー!G:G) -> 0 | N102: =SUMIF(コンシューマー!$B:$B,全体!$G102,コンシューマー!H:H) -> 0 | O102: =SUMIF(コンシューマー!$B:$B,全体!$G102,コンシューマー!I:I) -> 42 | P102: =SUMIF(コンシューマー!$B:$B,全体!$G102,コンシューマー!J:J) -> 65 | Q102: =SUMIF(コンシューマー!$B:$B,全体!$G102,コンシューマー!K:K) -> 108 | R102: =SUMIF(コンシューマー!$B:$B,全体!$G102,コンシューマー!L:L) -> 80 | S102: =SUMIF(コンシューマー!$B:$B,全体!$G102,コンシューマー!M:M) -> 93 | T102: =SUMIF(コンシューマー!$B:$B,全体!$G102,コンシューマー!N:N) -> 99 | U102: =SUMIF(コンシューマー!$B:$B,全体!$G102,コンシューマー!O:O) -> 98 | V102: =SUMIF(コンシューマー!$B:$B,全体!$G102,コンシューマー!P:P) -> 11 | W102: =SUMIF(コンシューマー!$B:$B,全体!$G102,コンシューマー!Q:Q) -> 14 | X102: =SUMIF(コンシューマー!$B:$B,全体!$G102,コンシューマー!R:R) -> 14 | Y102: =SUMIF(コンシューマー!$B:$B,全体!$G102,コンシューマー!S:S) -> 14 | Z102: =SUMIF(コンシューマー!$B:$B,全体!$G102,コンシューマー!T:T) -> 14 | AA102: =SUMIF(コンシューマー!$B:$B,全体!$G102,コンシューマー!U:U) -> 14 | AB102: =SUMIF(コンシューマー!$B:$B,全体!$G102,コンシューマー!V:V) -> 14 | AC102: =SUMIF(コンシューマー!$B:$B,全体!$G102,コンシューマー!W:W) -> 14 | AD102: =SUMIF(コンシューマー!$B:$B,全体!$G102,コンシューマー!X:X) -> 14 | AE102: =SUMIF(コンシューマー!$B:$B,全体!$G102,コンシューマー!Y:Y) -> 14 | AF102: =SUMIF(コンシューマー!$B:$B,全体!$G102,コンシューマー!Z:Z) -> 14 | AG102: =SUMIF(コンシューマー!$B:$B,全体!$G102,コンシューマー!AA:AA) -> 14 | AI102: 20 | AK102: 0 | AL102: 0 | AM102: 0 | AN102: 0 | AO102: 0 | AP102: 0 | AQ102: 0 | AR102: =SUMIF(結果貼付!$A:$A,G102,結果貼付!$D:$D) -> 0 | AS102: =(AR102/AS$2)*AS$1 -> 0 | AT102: =SUM(SUMIF(コンシューマー!$B:$B,全体!$G102,コンシューマー!AO:AO),SUMIF(コマーシャル!$B:$B,全体!$G102,コマーシャル!AK:AK)) -> 0 | AU102: =SUM(SUMIF(コンシューマー!$B:$B,全体!$G102,コンシューマー!AP:AP),SUMIF(コマーシャル!$B:$B,全体!$G102,コマーシャル!AL:AL)) -> 0 | AV102: =SUM(SUMIF(コンシューマー!$B:$B,全体!$G102,コンシューマー!AQ:AQ),SUMIF(コマーシャル!$B:$B,全体!$G102,コマーシャル!AM:AM)) -> 0 | AW102: =SUM(SUMIF(コンシューマー!$B:$B,全体!$G102,コンシューマー!AR:AR),SUMIF(コマーシャル!$B:$B,全体!$G102,コマーシャル!AN:AN)) -> 0 | AX102: =SUM(SUMIF(コンシューマー!$B:$B,全体!$G102,コンシューマー!AS:AS),SUMIF(コマーシャル!$B:$B,全体!$G102,コマーシャル!AO:AO)) -> 0 | AY102: =SUM(SUMIF(コンシューマー!$B:$B,全体!$G102,コンシューマー!AT:AT),SUMIF(コマーシャル!$B:$B,全体!$G102,コマーシャル!AP:AP)) -> 0
A103: =SUMIFS(SAP貼付!K:K,SAP貼付!C:C,全体!G103) -> 73 | D103: =SUM(A103:C103) -> 73 | E103: =IFERROR(D103-SUM(#REF!)," ") | G103: i5-14500 | H103: =IFERROR(IF(MATCH($G103,コンシューマー!B:B,0),"Y"),"-") -> Y | I103: =IFERROR(IF(MATCH($G103,コマーシャル!B:B,0),"Y"),"-") -> - | J103: =SUMIF(コンシューマー!$B:$B,全体!$G103,コンシューマー!D:D) -> 0 | K103: =SUMIF(コンシューマー!$B:$B,全体!$G103,コンシューマー!E:E) -> 0 | L103: =SUMIF(コンシューマー!$B:$B,全体!$G103,コンシューマー!F:F) -> 0 | M103: =SUMIF(コンシューマー!$B:$B,全体!$G103,コンシューマー!G:G) -> 0 | N103: =SUMIF(コンシューマー!$B:$B,全体!$G103,コンシューマー!H:H) -> 0 | O103: =SUMIF(コンシューマー!$B:$B,全体!$G103,コンシューマー!I:I) -> 75 | P103: =SUMIF(コンシューマー!$B:$B,全体!$G103,コンシューマー!J:J) -> 289 | Q103: =SUMIF(コンシューマー!$B:$B,全体!$G103,コンシューマー!K:K) -> 459 | R103: =SUMIF(コンシューマー!$B:$B,全体!$G103,コンシューマー!L:L) -> 480 | S103: =SUMIF(コンシューマー!$B:$B,全体!$G103,コンシューマー!M:M) -> 432 | T103: =SUMIF(コンシューマー!$B:$B,全体!$G103,コンシューマー!N:N) -> 389 | U103: =SUMIF(コンシューマー!$B:$B,全体!$G103,コンシューマー!O:O) -> 467 | V103: =SUMIF(コンシューマー!$B:$B,全体!$G103,コンシューマー!P:P) -> 309 | W103: =SUMIF(コンシューマー!$B:$B,全体!$G103,コンシューマー!Q:Q) -> 279 | X103: =SUMIF(コンシューマー!$B:$B,全体!$G103,コンシューマー!R:R) -> 32 | Y103: =SUMIF(コンシューマー!$B:$B,全体!$G103,コンシューマー!S:S) -> 0 | Z103: =SUMIF(コンシューマー!$B:$B,全体!$G103,コンシューマー!T:T) -> 22 | AA103: =SUMIF(コンシューマー!$B:$B,全体!$G103,コンシューマー!U:U) -> 0 | AB103: =SUMIF(コンシューマー!$B:$B,全体!$G103,コンシューマー!V:V) -> 0 | AC103: =SUMIF(コンシューマー!$B:$B,全体!$G103,コンシューマー!W:W) -> 2 | AD103: =SUMIF(コンシューマー!$B:$B,全体!$G103,コンシューマー!X:X) -> 3 | AE103: =SUMIF(コンシューマー!$B:$B,全体!$G103,コンシューマー!Y:Y) -> 6 | AF103: =SUMIF(コンシューマー!$B:$B,全体!$G103,コンシューマー!Z:Z) -> 39 | AG103: =SUMIF(コンシューマー!$B:$B,全体!$G103,コンシューマー!AA:AA) -> 17 | AI103: 0 | AK103: 0 | AL103: 0 | AM103: 0 | AN103: 0 | AO103: 0 | AP103: 0 | AQ103: 0 | AR103: =SUMIF(結果貼付!$A:$A,G103,結果貼付!$D:$D) -> 0 | AS103: =(AR103/AS$2)*AS$1 -> 0 | AT103: =SUM(SUMIF(コンシューマー!$B:$B,全体!$G103,コンシューマー!AO:AO),SUMIF(コマーシャル!$B:$B,全体!$G103,コマーシャル!AK:AK)) -> 0 | AU103: =SUM(SUMIF(コンシューマー!$B:$B,全体!$G103,コンシューマー!AP:AP),SUMIF(コマーシャル!$B:$B,全体!$G103,コマーシャル!AL:AL)) -> 0 | AV103: =SUM(SUMIF(コンシューマー!$B:$B,全体!$G103,コンシューマー!AQ:AQ),SUMIF(コマーシャル!$B:$B,全体!$G103,コマーシャル!AM:AM)) -> 0 | AW103: =SUM(SUMIF(コンシューマー!$B:$B,全体!$G103,コンシューマー!AR:AR),SUMIF(コマーシャル!$B:$B,全体!$G103,コマーシャル!AN:AN)) -> 0 | AX103: =SUM(SUMIF(コンシューマー!$B:$B,全体!$G103,コンシューマー!AS:AS),SUMIF(コマーシャル!$B:$B,全体!$G103,コマーシャル!AO:AO)) -> 0 | AY103: =SUM(SUMIF(コンシューマー!$B:$B,全体!$G103,コンシューマー!AT:AT),SUMIF(コマーシャル!$B:$B,全体!$G103,コマーシャル!AP:AP)) -> 0
...

Sheet コラボ販売予測
A1: 印刷面 | B1: 金具 | E1: 45901 | F1: 45931 | G1: 45962 | H1: 45992 | I1: 46023 | J1: 46054 | K1: 46082 | L1: 46113 | M1: 46143 | N1: 46174 | O1: 46204 | P1: 46235 | Q1: 46266 | R1: 46296 | S1: 46327 | T1: 46357 | U1: 46388 | V1: 46419 | W1: 46447 | X1: 46478 | Y1: 46508 | Z1: 46539 | AA1: 46569 | AB1: 46600 | AC1: 46631 | AD1: 46661 | AE1: 46692 | AF1: 46722 | AG1: 46753
A2: 表 | B2: あり | C2: SF 黒 コラボ 表 | D2: SF黒コラボ 渋ハル | E2: 100 | F2: 50 | G2: 30 | H2: 30 | I2: 20 | J2: 20 | K2: 20 | L2: 20 | M2: 20 | N2: 20 | O2: 10 | P2: 10 | Q2: 10 | R2: 10 | S2: 10 | T2: 10 | U2: 10 | V2: 10 | W2: 10 | X2: 10 | Y2: 10 | Z2: 10 | AA2: 10
A3: 表 | B3: あり | C3: SF 黒 コラボ 表 | D3: SF黒コラボ 葛葉 | F3: 1300 | G3: 500 | H3: 500 | I3: 400 | J3: 200 | K3: 200 | L3: 200 | M3: 200 | N3: 80 | O3: 80 | P3: 80 | Q3: 80 | R3: 80 | S3: 80 | T3: 80 | U3: 80 | V3: 80 | W3: 80 | X3: 80 | Y3: 80 | Z3: 80 | AA3: 80 | AB3: 80 | AC3: 80 | AD3: 80
A4: 表 | B4: あり | C4: SF 白 コラボ | D4: SF白コラボ Nachoneko | G4: 200 | H4: 100 | I4: 60 | J4: 100 | K4: 100 | L4: 100 | M4: 100 | N4: 50 | O4: 50 | P4: 50 | Q4: 50 | R4: 50 | S4: 50 | T4: 50 | U4: 50 | V4: 50 | W4: 50 | X4: 50 | Y4: 50 | Z4: 50 | AA4: 50 | AB4: 50 | AC4: 50 | AD4: 50
A5: 表 | B5: あり | C5: SF 黒 コラボ 表 | D5: SF黒コラボ REJECT | H5: 50 | I5: 50 | J5: 10 | K5: 10 | L5: 10 | M5: 10 | N5: 10 | O5: 10 | P5: 10 | Q5: 10 | R5: 10 | S5: 10 | T5: 10 | U5: 10 | V5: 10 | W5: 10 | X5: 10 | Y5: 10 | Z5: 10 | AA5: 10 | AB5: 10 | AC5: 10 | AD5: 10 | AE5: 10
A6: 裏 | B6: 無 | C6: SF 白 コラボ | D6: SF白コラボ 猫麦とろろ | L6: 400 | M6: 200 | N6: 30 | O6: 30 | P6: 30 | Q6: 30 | R6: 30 | S6: 30 | T6: 30 | U6: 30 | V6: 30 | W6: 30 | X6: 30 | Y6: 30 | Z6: 30 | AA6: 30 | AB6: 30 | AC6: 30 | AD6: 30
A7: 裏 | B7: 無 | C7: SF 黒 コラボ | D7: SF黒コラボ 藤ちょこ | L7: 500 | M7: 250 | N7: 30 | O7: 30 | P7: 30 | Q7: 30 | R7: 30 | S7: 30 | T7: 30 | U7: 30 | V7: 30 | W7: 30
A8: 裏 | B8: 無 | C8: SF 白 コラボ | D8: SF白コラボ シャニマス | L8: 300 | M8: 180 | N8: 20 | O8: 20 | P8: 20 | Q8: 20 | R8: 20 | S8: 20 | T8: 20 | U8: 20 | V8: 20
A9: 表 | B9: あり | C9: SF 黒 コラボ 表 | D9: SF黒コラボ MHWs | J9: 100 | K9: 50 | L9: 50 | M9: 50 | N9: 10 | O9: 10 | P9: 10 | Q9: 10 | R9: 10 | S9: 10 | T9: 10 | U9: 10
A10: 裏 | B10: 無 | C10: SF 白 コラボ | D10: SF白コラボ カグラナナ | O10: 80 | P10: 30 | Q10: 20 | R10: 20 | S10: 20 | T10: 20 | U10: 20 | V10: 20 | W10: 20 | X10: 20 | Y10: 20 | Z10: 20
A11: 裏 | B11: 無 | C11: SF 白 コラボ | D11: 寺田てら | P11: 60 | Q11: 30 | R11: 30 | S11: 30 | T11: 30 | U11: 20 | V11: 20 | W11: 20 | X11: 20 | Y11: 20 | Z11: 20 | AA11: 20
A12: 裏 | B12: 無 | C12: SF 黒 コラボ | D12: スタレ | M12: 200 | N12: 200 | O12: 200 | P12: 200 | Q12: 200 | R12: 200 | S12: 200 | T12: 200 | U12: 200 | V12: 200 | W12: 200 | X12: 200 | Y12: 200
A13: 裏 | B13: 無 | C13: SF 黒 コラボ | D13: SF黒コラボ ぶいすぽ① | L13: 800 | M13: 400 | N13: 150 | O13: 150 | P13: 150 | Q13: 150 | R13: 100 | S13: 100 | T13: 100 | U13: 100 | V13: 80 | W13: 80
A14: 表 | B14: あり | C14: SF 黒 コラボ 表 | D14: SF黒コラボ ローレン | M14: 400 | N14: 150 | O14: 150 | P14: 150 | Q14: 150 | R14: 80 | S14: 80 | T14: 80 | U14: 80 | V14: 80 | W14: 80 | X14: 80
A15: 表 | B15: あり | C15: SF 白 コラボ 表 | D15: SF白コラボ イブラヒム | M15: 300 | N15: 100 | O15: 100 | P15: 100 | Q15: 150 | R15: 80 | S15: 80 | T15: 80 | U15: 80 | V15: 80 | W15: 80 | X15: 80
A16: 裏 | B16: 無 | C16: SF 黒 コラボ | D16: SF黒コラボ ぶいすぽ② | N16: 500 | O16: 400 | P16: 150 | Q16: 150 | R16: 150 | S16: 100 | T16: 100 | U16: 100 | V16: 100 | W16: 100 | X16: 80 | Y16: 80
A17: 裏 | B17: 無 | C17: SF 白 コラボ | D17: しぐれうい | O17: 200 | P17: 150 | Q17: 150 | R17: 100 | S17: 50 | T17: 50 | U17: 50 | V17: 50 | W17: 50 | X17: 50 | Y17: 50 | Z17: 50
A18: 裏 | B18: 無 | C18: SF 白 コラボ | D18: ライト 販売見送り
A19: 裏 | B19: 無 | C19: SF 白 コラボ | D19: 天鬼ぷるる | P19: 100 | Q19: 50 | R19: 50 | S19: 50 | T19: 30 | U19: 30 | V19: 30 | W19: 30 | X19: 30 | Y19: 30 | Z19: 30 | AA19: 30
A20: 裏 | B20: 無 | C20: SF 白 コラボ | D20: SF6 | Q20: 150 | R20: 100 | S20: 100 | T20: 100 | U20: 50 | V20: 50 | W20: 100 | X20: 50 | Y20: 50 | Z20: 50 | AA20: 50 | AB20: 50
A21: 裏 | B21: 無 | C21: SF 白 コラボ | D21: 因幡はねる | Q21: 100 | R21: 50 | S21: 50 | T21: 50 | U21: 30 | V21: 30 | W21: 30 | X21: 30 | Y21: 30 | Z21: 30 | AA21: 30 | AB21: 30
A22: 裏 | B22: 無 | C22: SF 黒 コラボ | D22: ALGS | Q22: 150 | R22: 100 | S22: 100 | T22: 100 | U22: 100 | V22: 100 | W22: 50 | X22: 50 | Y22: 50 | Z22: 50 | AA22: 50 | AB22: 50
A23: 裏 | B23: 無 | C23: SF 白 コラボ | D23: 寺田てら | Q23: 60 | R23: 30 | S23: 30 | T23: 30 | U23: 30 | V23: 20 | W23: 20 | X23: 20 | Y23: 20 | Z23: 20 | AA23: 20 | AB23: 20
A24: 裏 | B24: 無 | C24: SF 白 コラボ | D24: カグラナナ | R24: 80 | S24: 30 | T24: 20 | U24: 20 | V24: 20 | W24: 20 | X24: 20 | Y24: 20 | Z24: 20 | AA24: 20 | AB24: 20 | AC24: 20
A25: 裏 | B25: 無 | C25: SF 黒 コラボ | D25: VARREL | R25: 50 | S25: 20 | T25: 20 | U25: 10 | V25: 10 | W25: 10 | X25: 10 | Y25: 10 | Z25: 10 | AA25: 10 | AB25: 10 | AC25: 10
C26: 未定 | D26: ぽこピー | R26: 80 | S26: 30 | T26: 20 | U26: 20 | V26: 20 | W26: 20 | X26: 20 | Y26: 20 | Z26: 20 | AA26: 20 | AB26: 20 | AC26: 20
C27: 未定 | D27: LAM | S27: 70 | T27: 60 | U27: 60 | V27: 50 | W27: 50 | X27: 50 | Y27: 50 | Z27: 50 | AA27: 50 | AB27: 30 | AC27: 30 | AD27: 30
C28: 未定 | D28: 結城さくな | S28: 150 | T28: 100 | U28: 50 | V28: 30 | W28: 30 | X28: 30 | Y28: 30 | Z28: 30 | AA28: 30 | AB28: 30 | AC28: 30 | AD28: 30
C29: 未定 | D29: 碧依さくら | S29: 100 | T29: 50 | U29: 50 | V29: 10 | W29: 10 | X29: 10 | Y29: 10 | Z29: 10 | AA29: 10 | AB29: 10 | AC29: 10 | AD29: 10
C30: 未定 | D30: 鳴潮 | S30: 300 | T30: 200 | U30: 200 | V30: 100 | W30: 100 | X30: 100 | Y30: 100 | Z30: 100 | AA30: 100 | AB30: 100 | AC30: 100 | AD30: 100
C31: 未定 | D31: エースコンバット | T31: 50 | U31: 30 | V31: 20 | W31: 20 | X31: 20 | Y31: 20 | Z31: 20 | AA31: 20 | AB31: 20 | AC31: 20 | AD31: 20 | AE31: 20
A32: 裏 | B32: 無 | C32: SF 白 コラボ | D32: FF | U32: 500 | V32: 200 | W32: 200 | X32: 150 | Y32: 150 | Z32: 150 | AA32: 100 | AB32: 100 | AC32: 100 | AD32: 100 | AE32: 100 | AF32: 100
D33: 合計 | E33: =SUM(E2:E32) -> 100 | F33: =SUM(F2:F32) -> 1350 | G33: =SUM(G2:G32) -> 730 | H33: =SUM(H2:H32) -> 680 | I33: =SUM(I2:I32) -> 530 | J33: =SUM(J2:J32) -> 430 | K33: =SUM(K2:K32) -> 380 | L33: =SUM(L2:L32) -> 2380 | ... AG33: =SUM(AG2:AG32) -> 0
E35: =E1 -> 45901 | F35: =F1 -> 45931 | G35: =G1 -> 45962 | H35: =H1 -> 45992 | I35: =I1 -> 46023 | J35: =J1 -> 46054 | K35: =K1 -> 46082 | L35: =L1 -> 46113 | ... AG35: =AG1 -> 46753
C36: SF 黒 コラボ | E36: =_xlfn.LET( _xlpm.targetDate, E$35, _xlpm.col, _xlfn.XMATCH(_xlpm.targetDate, $E$1:$AA$1, 0), _xlpm.rng, INDEX($E$2:$AA$32, 0, _xlpm.col), SUMIFS(_xlpm.rng, $C$2:$C$32, $C36) ) -> 0 | F36: =_xlfn.LET( _xlpm.targetDate, F$35, _xlpm.col, _xlfn.XMATCH(_xlpm.targetDate, $E$1:$AA$1, 0), _xlpm.rng, INDEX($E$2:$AA$32, 0, _xlpm.col), SUMIFS(_xlpm.rng, $C$2:$C$32, $C36) ) -> 0 | G36: =_xlfn.LET( _xlpm.targetDate, G$35, _xlpm.col, _xlfn.XMATCH(_xlpm.targetDate, $E$1:$AA$1, 0), _xlpm.rng, INDEX($E$2:$AA$32, 0, _xlpm.col), SUMIFS(_xlpm.rng, $C$2:$C$32, $C36) ) -> 0 | H36: =_xlfn.LET( _xlpm.targetDate, H$35, _xlpm.col, _xlfn.XMATCH(_xlpm.targetDate, $E$1:$AA$1, 0), _xlpm.rng, INDEX($E$2:$AA$32, 0, _xlpm.col), SUMIFS(_xlpm.rng, $C$2:$C$32, $C36) ) -> 0 | I36: =_xlfn.LET( _xlpm.targetDate, I$35, _xlpm.col, _xlfn.XMATCH(_xlpm.targetDate, $E$1:$AA$1, 0), _xlpm.rng, INDEX($E$2:$AA$32, 0, _xlpm.col), SUMIFS(_xlpm.rng, $C$2:$C$32, $C36) ) -> 0 | J36: =_xlfn.LET( _xlpm.targetDate, J$35, _xlpm.col, _xlfn.XMATCH(_xlpm.targetDate, $E$1:$AA$1, 0), _xlpm.rng, INDEX($E$2:$AA$32, 0, _xlpm.col), SUMIFS(_xlpm.rng, $C$2:$C$32, $C36) ) -> 0 | K36: =_xlfn.LET( _xlpm.targetDate, K$35, _xlpm.col, _xlfn.XMATCH(_xlpm.targetDate, $E$1:$AA$1, 0), _xlpm.rng, INDEX($E$2:$AA$32, 0, _xlpm.col), SUMIFS(_xlpm.rng, $C$2:$C$32, $C36) ) -> 0 | L36: =_xlfn.LET( _xlpm.targetDate, L$35, _xlpm.col, _xlfn.XMATCH(_xlpm.targetDate, $E$1:$AA$1, 0), _xlpm.rng, INDEX($E$2:$AA$32, 0, _xlpm.col), SUMIFS(_xlpm.rng, $C$2:$C$32, $C36) ) -> 1300 | ... AA36: =_xlfn.LET( _xlpm.targetDate, AA$35, _xlpm.col, _xlfn.XMATCH(_xlpm.targetDate, $E$1:$AA$1, 0), _xlpm.rng, INDEX($E$2:$AA$32, 0, _xlpm.col), SUMIFS(_xlpm.rng, $C$2:$C$32, $C36) ) -> 60 | AB36: =_xlfn.LET( _xlpm.targetDate, AB$35, _xlpm.col, _xlfn.XMATCH(_xlpm.targetDate, $E$1:$AG$1, 0), _xlpm.rng, INDEX($E$2:$AG$32, 0, _xlpm.col), SUMIFS(_xlpm.rng, $C$2:$C$32, $C36) ) -> 60 | AC36: =_xlfn.LET( _xlpm.targetDate, AC$35, _xlpm.col, _xlfn.XMATCH(_xlpm.targetDate, $E$1:$AG$1, 0), _xlpm.rng, INDEX($E$2:$AG$32, 0, _xlpm.col), SUMIFS(_xlpm.rng, $C$2:$C$32, $C36) ) -> 10 | AD36: =_xlfn.LET( _xlpm.targetDate, AD$35, _xlpm.col, _xlfn.XMATCH(_xlpm.targetDate, $E$1:$AG$1, 0), _xlpm.rng, INDEX($E$2:$AG$32, 0, _xlpm.col), SUMIFS(_xlpm.rng, $C$2:$C$32, $C36) ) -> 0 | AE36: =_xlfn.LET( _xlpm.targetDate, AE$35, _xlpm.col, _xlfn.XMATCH(_xlpm.targetDate, $E$1:$AG$1, 0), _xlpm.rng, INDEX($E$2:$AG$32, 0, _xlpm.col), SUMIFS(_xlpm.rng, $C$2:$C$32, $C36) ) -> 0 | AF36: =_xlfn.LET( _xlpm.targetDate, AF$35, _xlpm.col, _xlfn.XMATCH(_xlpm.targetDate, $E$1:$AG$1, 0), _xlpm.rng, INDEX($E$2:$AG$32, 0, _xlpm.col), SUMIFS(_xlpm.rng, $C$2:$C$32, $C36) ) -> 0 | AG36: =_xlfn.LET( _xlpm.targetDate, AG$35, _xlpm.col, _xlfn.XMATCH(_xlpm.targetDate, $E$1:$AG$1, 0), _xlpm.rng, INDEX($E$2:$AG$32, 0, _xlpm.col), SUMIFS(_xlpm.rng, $C$2:$C$32, $C36) ) -> 0
