Workbook

Sheet 表の見方と入力について
A5: ↓インチ+ブランド | G5: ↓当月月初の在庫（SAP貼り付けから計算） | K5: ↓各月の計画
B6: ↓購買の名称 | C6: ↓販売モデル名＝定格銘板 | D6: ↓搭載CPU | E6: 搭載GPU | F6: メモリ種別 | H6: ↓今月～翌々月（向う4か月の販売計画 在庫＜販売計画の場合赤文字）
B7: GALLERIA | C7: model名 | D7: CPU | E7: GPU | F7: メモリ | G7: 在庫残 | H7: 4か月計画 | I7: 45292 | J7: 45323 | K7: 45352 | L7: 45383 | M7: 45413 | N7: 45444 | O7: 45474 | P7: 45505 | Q7: 45536 | R7: 45566 | S7: 45597 | T7: 45627 | U7: 45658 | V7: 45689 | W7: 45717 | X7: 45748 | Y7: 45778
A8: 17"-G | B8: CLE-X370-13900HX-4090-L6 | C8: UL9C-R49 | D8: RPL-i9-13900HX | E8: 4090 | F8: DDR5 | G8: 101 | H8: 98 | I8: 48 | J8: 41 | K8: 49 | M8: 49 | N8: 49
H9: 0
A10: 16”-G | B10: ID-B 14900HX-4090-creator-L6 | C10: UL9C-R49-6 | D10: RPL-R i9-14900HX | E10: 4090 | F10: DDR5 | G10: 166 | H10: 128.46447 | M10: 41.56267 | N10: 42.967437 | O10: 43.934367 | P10: 37.162537 | Q10: 34.416967 | R10: 30.705081 | S10: 32.475825 | T10: 51.467864 | U10: 34.913113 | V10: 29.879111 | W10: 43.758397 | X10: 37.756631
B11: ID-B 14900HX-4070-L6 | C11: ZL9C-R47-6B | D11: RPL-R i9-14900HX | E11: 4070 | F11: DDR5 | G11: 300 | H11: 194.02279 | N11: 97 | O11: 97.02279 | P11: 87.43885 | Q11: 77.32581 | R11: 69.003718 | S11: 73.784727 | T11: 102.20604
B12: ID-U-155H-4070-gaming | C12: ZL7C-R47-6 | D12: MTL-UL9-185H | E12: 4070 | F12: DDR5 | G12: 0 | H12: 10 | O12: 10 | P12: 10 | Q12: 102.45938 | R12: 84.967783 | S12: 91.165387 | T12: 154.13753 | U12: 122.1959 | V12: 104.57689 | W12: 153.15439 | X12: 132.14821
B13: ID-B 14900HX-4060-L6 | C13: ZL9C-R46-6 | D13: RPL-R i9-14900HX | E13: 4060 | F13: DDR5 | G13: 200 | H13: 132.2034 | N13: 43.960924 | O13: 88.24248 | P13: 75.390089 | Q13: 66.40072 | R13: 58.892194 | S13: 63.14198 | T13: 44.960924
B14: CLE-V56-155H-4060-L6 | C14: XL7C-R46-6 | D14: MTL-UL7-155H | E14: 4060 | F14: DDR5 | H14: 0 | P14: 668.57582 | Q14: 591.17326 | R14: 526.51178 | S14: 565.46815 | T14: 966.29302 | U14: 768.08848 | V14: 657.34044 | W14: 962.68474 | X14: 830.64588
B15: UNW-6H2-13700H-4060-L6 | C15: XL7C-R46H(L6) | D15: RPL-i7-13700H | E15: 4060 | F15: DDR5 | G15: 657 | H15: 404 | I15: 95 | J15: 85 | K15: 130 | L15: 108 | M15: 128 | N15: 123 | O15: 153 | P15: 153 | Q15: 133
B16: CLE-V56-155H-4050-L6 | C16: XL7C-R45-6 | D16: MTL-UL7-155H | E16: 4050 | H16: 0 | P16: 403.14549 | Q16: 353.70396 | R16: 317.90707 | S16: 341.28089 | T16: 580.77581 | U16: 460.85309 | V16: 394.40426 | W16: 577.61085 | X16: 498.38753
B17: UNW-6H2-13700H-4050-L9 | C17: XL7C-R45H(L9) | D17: RPL-i7-13700H | E17: 4050 | G17: 17 | H17: 6 | I17: 28 | J17: 85 | K17: 74 | L17: 22 | M17: 2 | N17: 2 | O17: 2
B18: CLE-NV45-13700H-4050-L6 | C18: RM7C-R45 | D18: RPL-i7-13700H | E18: 4050 | F18: DDR5 | G18: 1 | H18: 25 | I18: 105 | J18: 105 | K18: 205 | L18: 155 | M18: 25
H19: 0
B20: GALLERIA 合計 | K20: 3046 | L20: 1820 | M20: 2143.0703 | N20: 2586.7887 | O20: 3011.9025 | P20: 3117.4016 | Q20: 2611.0739 | R20: 2239.6654 | S20: 2475.9708 | T20: 3779.2164 | U20: 2608.0095 | V20: 1559.6896 | W20: 2284.1883 | X20: 1970.8961 | Y20: 0
B21: GALLERIA 予算 | G21: 0 | H21: 0 | P21: 2919.1792 | Q21: 2806.0207 | R21: 2719.4459 | S21: 2912.4681 | T21: 4805.0359 | U21: 4440.2634
Q22: ↑台数計画合計＜予算の場合赤文字
B27: EOL製品
B28: 計画製品（未発注もしくは未確定）
B29: ブランド別の合計
B31: 変更必須（在庫不足） | C31: ←納期変更や、販売過剰などによる在庫不足（販売不可）
B32: 前回（最新日付のシート）から変更 | C32: ←ONE未反映の状態。最新シートが作成された時点で白地に変更します
B44: ■ノート担当用
B45: 販売計画の更新について
B47: 計画更新が発生したら、
B48: ツールバーから 数式→再計算実行を選択（一般 + 法人 の計算実行）
A49: 1 | B49: 一般 + 法人 = 全体 になっていることを確認
B50: ① 新規に更新されたモデルを確認
B51: ② 他 3点ほどランダムでモデルピックアップをして確認
B52: 問題ある場合、計算式を確認、またモデル追加がある場合はモデルを追加
B53: （一般、法人双方に同じモデルがないと集計されない可能性あり）
A54: 2 | B54: 在庫使用計画（ノート全体試算）をコピー、コピーしたシート名を在庫使用計画（当日日付）に変更
A55: 3 | B55: 2.でコピーしたシート全体をCtrl+A、Crtl +C で全体コピーして、数字で貼り付け
B56: （計算式を残さないで数字としてデータ化）
A57: 4 | B57: 3.でコピーした結果が、全体試算のシートと変わらないか確認
A58: 5 | B58: \\172.25.20.11\サードウェーブグループ\41上期\サードウェーブ\購買本部\【通常業務】\ONE
B59: ↑ONEファイルから、『NoteONE計画』のファイルを開く
A60: 6 | B60: 販売計画_yymmdd（一番新しい日付のもの）を全体コピーして、yymmdd（ひとつ前）のシートに貼り付け
B61: ひとつ前のシート名を更新
A62: 7 | B62: 3.で作成したシート全体をコピーして、販売計画_yymmdd（一番新しい日付のもの）に貼り付け。
B63: 日付けを更新した日（3.のシート名と同じ日付）に更新
A64: 8 | B64: 『NoteONE計画』の部品予測のシートを確認

Sheet マスタ
A1: 在庫使用計画にあるか | B1: EOL連絡 | C1: ブランド | D1: 製品型番 | E1: 商品コード | F1: ベア名称 | G1: ID通称 | H1: 綽名 | I1: 画面サイズ | J1: Copilot OS | K1: CPU | L1: GPU | M1: 在庫 | N1: 在庫+注残 | O1: MP出荷 | P1: 販売開始 | Q1: 終息予定 | R1: 備考 | S1: 移動数 | T1: 完了日 | U1: 備考2 | V1: 計画 | W1: 総発注数 | X1: 販売数 | Y1: 最終入荷 | Z1: 代替製品CD | AA1: 名称 | AB1: 代替品CD 2 | AC1: 列3 | AD1: 移動累計 | AE1: リペア比率 | AF1: 販売比率 | AG1: 在庫4 | AH1: その他 | AI1: 代替提案CD | AJ1: 代替提案ベア | AK1: 対応マニュアル | AL1: 納品日 | AM1: 納品数 | AN1: AC容量 | AO1: V | AP1: A | AQ1: AC形状 | AR1: AC商品CD | AS1: ケーブル | AT1: ケーブルCD | AU1: USB-PD対応 | AV1: 備考3 | AW1: ONE計画との整合 | AX1: SAPとの整合 | AY1: TGP | AZ1: Aカバー | BA1: Aカバー7 | BB1: Bカバー | BC1: C | BD1: D | BE1: サイズ | BF1: 重量(kg) | BG1: ACアダプタ | BH1: 箱サイズ | BI1: 重量(kg)2 | BJ1: 後継・代替 | BK1: 直近30日販売台数 | BL1: 列1 | BM1: 全体 | BN1: 一般 | BO1: 法人 | BP1: 全体実績+予測 | BQ1: 計画 予測 | BR1: 在庫確認 | BS1: 部品予測
A2: {=_xlfn.XLOOKUP(マスタ_EOLリスト[製品型番],'在庫使用計画 (ノート全体試算)'!C:C,'在庫使用計画 (ノート全体試算)'!C:C)} -> 0 | B2: 4EOL(完全終息) | E2: 161647 | F2: 組TVS 8023D法(8 WXGA Z8350 4+64 3165 DC PD | M2: 0 | N2: 0 | AX2: 在庫無し | BM2: =IF(COUNTIFS('在庫使用計画 (ノート全体試算)'!C:C,マスタ_EOLリスト[[#This Row],[製品型番]])=0,"記載なし","") -> 記載なし | BN2: =IF(COUNTIFS('在庫使用計画 (一般)'!C:C,マスタ_EOLリスト[[#This Row],[製品型番]])=0,"記載なし","") -> 記載なし | BO2: =IF(COUNTIFS('在庫使用計画 (法人)'!C:C,マスタ_EOLリスト[[#This Row],[製品型番]])=0,"記載なし","") -> 記載なし | BP2: =IF(COUNTIFS('在庫使用計画 (全体実績+予測）0701'!C:C,マスタ_EOLリスト[[#This Row],[製品型番]])=0,"記載なし","") -> 記載なし | BQ2: =IF(COUNTIFS('在庫使用計画 (計画 予測)'!C:C,マスタ_EOLリスト[[#This Row],[製品型番]])=0,"記載なし","") -> 記載なし | BR2: =IF(COUNTIFS(在庫確認!B:B,マスタ_EOLリスト[[#This Row],[製品型番]])=0,"記載なし","") -> 記載なし | BS2: =COUNTIF(#REF!,マスタ_EOLリスト[[#This Row],[製品型番]]) -> #REF!
A3: 0 | B3: 4EOL(完全終息) | E3: 168654 | F3: 組TVS TVE8016E-A法(8inch WXGA N4120 8G128G 9461) | M3: 0 | N3: 0 | AX3: 在庫無し | BM3: =IF(COUNTIFS('在庫使用計画 (ノート全体試算)'!C:C,マスタ_EOLリスト[[#This Row],[製品型番]])=0,"記載なし","") -> 記載なし | BN3: =IF(COUNTIFS('在庫使用計画 (一般)'!C:C,マスタ_EOLリスト[[#This Row],[製品型番]])=0,"記載なし","") -> 記載なし | BO3: =IF(COUNTIFS('在庫使用計画 (法人)'!C:C,マスタ_EOLリスト[[#This Row],[製品型番]])=0,"記載なし","") -> 記載なし | BP3: =IF(COUNTIFS('在庫使用計画 (全体実績+予測）0701'!C:C,マスタ_EOLリスト[[#This Row],[製品型番]])=0,"記載なし","") -> 記載なし | BQ3: =IF(COUNTIFS('在庫使用計画 (計画 予測)'!C:C,マスタ_EOLリスト[[#This Row],[製品型番]])=0,"記載なし","") -> 記載なし | BR3: =IF(COUNTIFS(在庫確認!B:B,マスタ_EOLリスト[[#This Row],[製品型番]])=0,"記載なし","") -> 記載なし | BS3: =COUNTIF(#REF!,マスタ_EOLリスト[[#This Row],[製品型番]]) -> #REF!
A4: 0 | B4: 4EOL(完全終息) | E4: 174103 | F4: 組TVS 8016E-A(法R1 8 WXGA N4120 8G128G 9461 | M4: 0 | N4: 0 | AX4: 在庫無し | BM4: =IF(COUNTIFS('在庫使用計画 (ノート全体試算)'!C:C,マスタ_EOLリスト[[#This Row],[製品型番]])=0,"記載なし","") -> 記載なし | BN4: =IF(COUNTIFS('在庫使用計画 (一般)'!C:C,マスタ_EOLリスト[[#This Row],[製品型番]])=0,"記載なし","") -> 記載なし | BO4: =IF(COUNTIFS('在庫使用計画 (法人)'!C:C,マスタ_EOLリスト[[#This Row],[製品型番]])=0,"記載なし","") -> 記載なし | BP4: =IF(COUNTIFS('在庫使用計画 (全体実績+予測）0701'!C:C,マスタ_EOLリスト[[#This Row],[製品型番]])=0,"記載なし","") -> 記載なし | BQ4: =IF(COUNTIFS('在庫使用計画 (計画 予測)'!C:C,マスタ_EOLリスト[[#This Row],[製品型番]])=0,"記載なし","") -> 記載なし | BR4: =IF(COUNTIFS(在庫確認!B:B,マスタ_EOLリスト[[#This Row],[製品型番]])=0,"記載なし","") -> 記載なし | BS4: =COUNTIF(#REF!,マスタ_EOLリスト[[#This Row],[製品型番]]) -> #REF!
A5: UL9C-R59-8A | B5: 2発売中 | C5: 1GALLERIA-G | D5: UL9C-R59-8A | E5: 212347 | F5: 組CLE X58WNT-G(GG 18QHD+ 275HX 5090 330W L6) | G5: X58 | H5: CLE-X58-275HX-5090-L6 | I5: 18 | K5: u9-275HX | L5: 5090 | M5: 66 | N5: 66 | O5: 45717 | P5: 45747 | Q5: 2026年4月頃 | V5: 600 | W5: 476 | AN5: 330W | AO5: 20 | AP5: 16.5 | AQ5: 5525+ | AU5: 100W | AV5: 100W以上 | AW5: TRUE | AX5: 組CLE X58WNT-G(GG 18QHD+ 275HX 5090 330W | AY5: 175 | BA5: S60 鐵灰 | BB5: S60 鐵灰 | BC5: S60 鐵灰 | BD5: S60 鐵灰 | BJ5: NMC9L-R59-G8 | BM5: =IF(COUNTIFS('在庫使用計画 (ノート全体試算)'!C:C,マスタ_EOLリスト[[#This Row],[製品型番]])=0,"記載なし","") | BN5: =IF(COUNTIFS('在庫使用計画 (一般)'!C:C,マスタ_EOLリスト[[#This Row],[製品型番]])=0,"記載なし","") | BO5: =IF(COUNTIFS('在庫使用計画 (法人)'!C:C,マスタ_EOLリスト[[#This Row],[製品型番]])=0,"記載なし","") | BP5: =IF(COUNTIFS('在庫使用計画 (全体実績+予測）0701'!C:C,マスタ_EOLリスト[[#This Row],[製品型番]])=0,"記載なし","") | BQ5: =IF(COUNTIFS('在庫使用計画 (計画 予測)'!C:C,マスタ_EOLリスト[[#This Row],[製品型番]])=0,"記載なし","") | BR5: =IF(COUNTIFS(在庫確認!B:B,マスタ_EOLリスト[[#This Row],[製品型番]])=0,"記載なし","") | BS5: =COUNTIF(#REF!,マスタ_EOLリスト[[#This Row],[製品型番]]) -> #REF!
A6: UL9C-R49-6 | B6: 4EOL(完全終息) | C6: 1GALLERIA-G | D6: UL9C-R49-6 | E6: 193182 | F6: 組UNW GM6IX9B(GG 16WQXGA 14900HX 4090 280W L6) | G6: ID-B | H6: ID-B 14900HX-4090-gaming-L6 | K6: i9-14900HX | L6: 4090 | M6: 0 | N6: 0 | O6: 45414 | P6: 45414 | Q6: 終息 | U6: Copilot keyモデルにスライド | V6: 150 | W6: 216 | Z6: 199017 | AB6: 212347 | AC6: 5090 価格差あり | AK6: 194883 | AL6: 45481 | AM6: 35 | AN6: 280W | AX6: 在庫無し | BA6: Light Gray | BB6: Black | BC6: Light Gray | BD6: Light Gray | BM6: =IF(COUNTIFS('在庫使用計画 (ノート全体試算)'!C:C,マスタ_EOLリスト[[#This Row],[製品型番]])=0,"記載なし","") | BN6: =IF(COUNTIFS('在庫使用計画 (一般)'!C:C,マスタ_EOLリスト[[#This Row],[製品型番]])=0,"記載なし","") | BO6: =IF(COUNTIFS('在庫使用計画 (法人)'!C:C,マスタ_EOLリスト[[#This Row],[製品型番]])=0,"記載なし","") | BP6: =IF(COUNTIFS('在庫使用計画 (全体実績+予測）0701'!C:C,マスタ_EOLリスト[[#This Row],[製品型番]])=0,"記載なし","") | BQ6: =IF(COUNTIFS('在庫使用計画 (計画 予測)'!C:C,マスタ_EOLリスト[[#This Row],[製品型番]])=0,"記載なし","") -> 記載なし | BR6: =IF(COUNTIFS(在庫確認!B:B,マスタ_EOLリスト[[#This Row],[製品型番]])=0,"記載なし","") | BS6: =COUNTIF(#REF!,マスタ_EOLリスト[[#This Row],[製品型番]]) -> #REF!
A7: UL9C-R49-6 | B7: 4EOL(完全終息) | C7: 1GALLERIA-G | D7: UL9C-R49-6 | E7: 199017 | F7: 組UNW GM6IX9B(R1 GG 16WQXGA 14900HX 4090 280W L6) | G7: ID-B | H7: ID-B 14900HX-4090-gaming-L6 | K7: i9-14900HX | L7: 4090 | M7: 0 | N7: 0 | Q7: 2025年3月頃 | R7: Copilot key対応版 | W7: 235 | AB7: 212347 | AC7: 5090 価格差あり | AK7: 207653 | AL7: 45483 | AM7: 125 | AN7: 280W | AX7: 在庫無し | BA7: Aurora Black | BB7: Black | BC7: Aurora Black | BD7: Black | BM7: =IF(COUNTIFS('在庫使用計画 (ノート全体試算)'!C:C,マスタ_EOLリスト[[#This Row],[製品型番]])=0,"記載なし","") | BN7: =IF(COUNTIFS('在庫使用計画 (一般)'!C:C,マスタ_EOLリスト[[#This Row],[製品型番]])=0,"記載なし","") | BO7: =IF(COUNTIFS('在庫使用計画 (法人)'!C:C,マスタ_EOLリスト[[#This Row],[製品型番]])=0,"記載なし","") | BP7: =IF(COUNTIFS('在庫使用計画 (全体実績+予測）0701'!C:C,マスタ_EOLリスト[[#This Row],[製品型番]])=0,"記載なし","") | BQ7: =IF(COUNTIFS('在庫使用計画 (計画 予測)'!C:C,マスタ_EOLリスト[[#This Row],[製品型番]])=0,"記載なし","") -> 記載なし | BR7: =IF(COUNTIFS(在庫確認!B:B,マスタ_EOLリスト[[#This Row],[製品型番]])=0,"記載なし","") | BS7: =COUNTIF(#REF!,マスタ_EOLリスト[[#This Row],[製品型番]]) -> #REF!
A8: UL9C-R49 | B8: 4EOL(完全終息) | C8: 1GALLERIA-G | D8: UL9C-R49 | E8: 184056 | F8: 組CLE X370SNW-G(17.3QHD 13900HX 4090 330W L6) | G8: X370 | H8: CLE-X370-13900HX-4090-L6 | K8: i9-13900HX | L8: 4090 | M8: 0 | N8: 0 | P8: 45197 | Q8: 2024年5月頃 | R8: 代替候補はID別 | V8: 300 | W8: 400 | Z8: 193182 | AC8: 2024/6頃 RPL-Rに変更 | AH8: 後継IDは変更 →ID-B | AI8: 193182 | AJ8: 組UNW GM6IX9B(GG 16WQXGA 14900HX 4090 280W L6) | AL8: 45471 | AM8: 80 | AQ8: 特殊 | AX8: 在庫無し | BM8: =IF(COUNTIFS('在庫使用計画 (ノート全体試算)'!C:C,マスタ_EOLリスト[[#This Row],[製品型番]])=0,"記載なし","") | BN8: =IF(COUNTIFS('在庫使用計画 (一般)'!C:C,マスタ_EOLリスト[[#This Row],[製品型番]])=0,"記載なし","") -> 記載なし | BO8: =IF(COUNTIFS('在庫使用計画 (法人)'!C:C,マスタ_EOLリスト[[#This Row],[製品型番]])=0,"記載なし","") | BP8: =IF(COUNTIFS('在庫使用計画 (全体実績+予測）0701'!C:C,マスタ_EOLリスト[[#This Row],[製品型番]])=0,"記載なし","") | BQ8: =IF(COUNTIFS('在庫使用計画 (計画 予測)'!C:C,マスタ_EOLリスト[[#This Row],[製品型番]])=0,"記載なし","") -> 記載なし | BR8: =IF(COUNTIFS(在庫確認!B:B,マスタ_EOLリスト[[#This Row],[製品型番]])=0,"記載なし","") | BS8: =COUNTIF(#REF!,マスタ_EOLリスト[[#This Row],[製品型番]]) -> #REF!
A9: NMC9L-R59-G8 | B9: 2発売中 | C9: 1GALLERIA-G | D9: NMC9L-R59-G8 | E9: 318440 | F9: 組CLE X58WNT-G(GG 18QHD+290HXP5090 330W L6) | G9: X58 | H9: CLE-X58-290HXP-5090-L6-GG | I9: 18 | K9: u9-290HX Plus | L9: 5090 | M9: 107 | N9: 107 | AW9: TRUE | AX9: 組CLE X58WNT-G(GG 18QHD+290HXP5090 330W L | BJ9: x | BM9: =IF(COUNTIFS('在庫使用計画 (ノート全体試算)'!C:C,マスタ_EOLリスト[[#This Row],[製品型番]])=0,"記載なし","") | BN9: =IF(COUNTIFS('在庫使用計画 (一般)'!C:C,マスタ_EOLリスト[[#This Row],[製品型番]])=0,"記載なし","") | BO9: =IF(COUNTIFS('在庫使用計画 (法人)'!C:C,マスタ_EOLリスト[[#This Row],[製品型番]])=0,"記載なし","") | BP9: =IF(COUNTIFS('在庫使用計画 (全体実績+予測）0701'!C:C,マスタ_EOLリスト[[#This Row],[製品型番]])=0,"記載なし","") | BQ9: =IF(COUNTIFS('在庫使用計画 (計画 予測)'!C:C,マスタ_EOLリスト[[#This Row],[製品型番]])=0,"記載なし","") | BR9: =IF(COUNTIFS(在庫確認!B:B,マスタ_EOLリスト[[#This Row],[製品型番]])=0,"記載なし","") -> 記載なし | BS9: =COUNTIF(#REF!,マスタ_EOLリスト[[#This Row],[製品型番]]) -> #REF!
A10: NMC9L-R59-G8 | B10: 2発売中 | C10: 1GALLERIA-G | D10: NMC9L-R59-G8 | E10: 366294 | F10: 組CLE X58WNT-G(R1GG 18QHD+290HXP5090 330WL6) | G10: X58 | H10: CLE-X58-290HXP-5090-L6-GG | I10: 18 | K10: u9-290HX Plus | L10: 5090 | M10: 0 | N10: 30 | AW10: TRUE | AX10: 在庫無し | BJ10: x | BM10: =IF(COUNTIFS('在庫使用計画 (ノート全体試算)'!C:C,マスタ_EOLリスト[[#This Row],[製品型番]])=0,"記載なし","") | BN10: =IF(COUNTIFS('在庫使用計画 (一般)'!C:C,マスタ_EOLリスト[[#This Row],[製品型番]])=0,"記載なし","") | BO10: =IF(COUNTIFS('在庫使用計画 (法人)'!C:C,マスタ_EOLリスト[[#This Row],[製品型番]])=0,"記載なし","") | BP10: =IF(COUNTIFS('在庫使用計画 (全体実績+予測）0701'!C:C,マスタ_EOLリスト[[#This Row],[製品型番]])=0,"記載なし","") | BQ10: =IF(COUNTIFS('在庫使用計画 (計画 予測)'!C:C,マスタ_EOLリスト[[#This Row],[製品型番]])=0,"記載なし","") | BR10: =IF(COUNTIFS(在庫確認!B:B,マスタ_EOLリスト[[#This Row],[製品型番]])=0,"記載なし","") -> 記載なし | BS10: =COUNTIF(#REF!,マスタ_EOLリスト[[#This Row],[製品型番]]) -> #REF!
A11: NMC9L-R58-H6 | B11: 2発売中 | C11: 1GALLERIA-G | D11: NMC9L-R58-H6 | E11: 326941 | F11: 組UNW X6AF558Y(GC 16WQXGA 290HXP 5080 330W L6) | G11: ID-Y | H11: UNW-Y-290HXP-5080-L6-GC | I11: 16 | K11: u9-290HX Plus | L11: 5080 | M11: 269 | N11: 341 | AW11: TRUE | AX11: 組UNW X6AF558Y(GC 16WQXGA 290HXP 5080 330 | BM11: =IF(COUNTIFS('在庫使用計画 (ノート全体試算)'!C:C,マスタ_EOLリスト[[#This Row],[製品型番]])=0,"記載なし","") | BN11: =IF(COUNTIFS('在庫使用計画 (一般)'!C:C,マスタ_EOLリスト[[#This Row],[製品型番]])=0,"記載なし","") | BO11: =IF(COUNTIFS('在庫使用計画 (法人)'!C:C,マスタ_EOLリスト[[#This Row],[製品型番]])=0,"記載なし","") | BP11: =IF(COUNTIFS('在庫使用計画 (全体実績+予測）0701'!C:C,マスタ_EOLリスト[[#This Row],[製品型番]])=0,"記載なし","") | BQ11: =IF(COUNTIFS('在庫使用計画 (計画 予測)'!C:C,マスタ_EOLリスト[[#This Row],[製品型番]])=0,"記載なし","") | BR11: =IF(COUNTIFS(在庫確認!B:B,マスタ_EOLリスト[[#This Row],[製品型番]])=0,"記載なし","") -> 記載なし | BS11: =COUNTIF(#REF!,マスタ_EOLリスト[[#This Row],[製品型番]]) -> #REF!
A12: ZL9R-R57T-6 | B12: 3EOL(在庫あり) | C12: 1GALLERIA-G | D12: ZL9R-R57T-6 | E12: 212476 | F12: 組UNW X6FR57TK(GG 16WQXGA 9955HX 5070Ti 240W L6) | G12: ID-K | H12: UNW-K-9955HX-5070Ti-L6 | I12: 16 | K12: R9-9955X | L12: 5070Ti | M12: 11 | N12: 11 | O12: 45717 | P12: 45793 | Q12: 2026年4月頃 | R12: 在庫+注残限り | V12: 240 | W12: 1306 | AN12: 240W | AO12: 20 | AP12: 12 | AQ12: 5525+ | AR12: 199685 | AS12: C5-C6 | AT12: 171480 | AU12: 100W/140W | AV12: 140W未検証 | AW12: TRUE | AX12: 組UNW X6FR57TK(GG 16WQXGA 9955HX 5070Ti 2 | AY12: 115 | BA12: Ink Stone Black | BB12: Ink Stone Black | BC12: Ink Stone Black | BD12: Ink Stone Black | BJ12: ZL9C-R57T-6A | BM12: =IF(COUNTIFS('在庫使用計画 (ノート全体試算)'!C:C,マスタ_EOLリスト[[#This Row],[製品型番]])=0,"記載なし","") | BN12: =IF(COUNTIFS('在庫使用計画 (一般)'!C:C,マスタ_EOLリスト[[#This Row],[製品型番]])=0,"記載なし","") | BO12: =IF(COUNTIFS('在庫使用計画 (法人)'!C:C,マスタ_EOLリスト[[#This Row],[製品型番]])=0,"記載なし","") | BP12: =IF(COUNTIFS('在庫使用計画 (全体実績+予測）0701'!C:C,マスタ_EOLリスト[[#This Row],[製品型番]])=0,"記載なし","") | BQ12: =IF(COUNTIFS('在庫使用計画 (計画 予測)'!C:C,マスタ_EOLリスト[[#This Row],[製品型番]])=0,"記載なし","") | BR12: =IF(COUNTIFS(在庫確認!B:B,マスタ_EOLリスト[[#This Row],[製品型番]])=0,"記載なし","") | BS12: =COUNTIF(#REF!,マスタ_EOLリスト[[#This Row],[製品型番]]) -> #REF!
A13: ZL9C-R57T-6A | B13: 2発売中 | C13: 1GALLERIA-G | D13: ZL9C-R57T-6A | E13: 220801 | F13: 組UNW X6AR57TK(GG 16WQXGA 275HX 5070Ti 240W L6) | G13: ID-K | H13: UNW-K-275HX-5070Ti-L6 | I13: 16 | K13: u9-275HX | L13: 5070Ti | M13: 74 | N13: 74 | O13: 45848 | P13: 45876 | Q13: 2026年4月頃 | R13: 在庫+注残限り | V13: 580 | W13: 696 | AN13: 240W | AO13: 20 | AP13: 12 | AQ13: 5525+ | AR13: 199685 | AS13: C5-C6 | AT13: 171480 | AU13: 100W/140W | AV13: 140W未検証 | AW13: TRUE | AX13: 組UNW X6AR57TK(GG 16WQXGA 275HX 5070Ti 24 | AY13: 115 | BA13: Light Gray | BB13: Black | BC13: Light Gray | BD13: Light Gray | BJ13: x | BM13: =IF(COUNTIFS('在庫使用計画 (ノート全体試算)'!C:C,マスタ_EOLリスト[[#This Row],[製品型番]])=0,"記載なし","") | BN13: =IF(COUNTIFS('在庫使用計画 (一般)'!C:C,マスタ_EOLリスト[[#This Row],[製品型番]])=0,"記載なし","") | BO13: =IF(COUNTIFS('在庫使用計画 (法人)'!C:C,マスタ_EOLリスト[[#This Row],[製品型番]])=0,"記載なし","") | BP13: =IF(COUNTIFS('在庫使用計画 (全体実績+予測）0701'!C:C,マスタ_EOLリスト[[#This Row],[製品型番]])=0,"記載なし","") | BQ13: =IF(COUNTIFS('在庫使用計画 (計画 予測)'!C:C,マスタ_EOLリスト[[#This Row],[製品型番]])=0,"記載なし","") | BR13: =IF(COUNTIFS(在庫確認!B:B,マスタ_EOLリスト[[#This Row],[製品型番]])=0,"記載なし","") | BS13: =COUNTIF(#REF!,マスタ_EOLリスト[[#This Row],[製品型番]]) -> #REF!
A14: ZL9C-R57T-6A | B14: 2発売中 | C14: 1GALLERIA-G | D14: ZL9C-R57T-6A | E14: 349140 | F14: 組UNW X6AR57TK(R1 GG 16WQXGA 275HX 5070Ti 240W L6) | G14: ID-K | H14: UNW-K-275HX-5070Ti-L6 | I14: 16 | K14: u9-275HX | L14: 5070Ti | M14: 119 | N14: 479 | O14: 45848 | P14: 45876 | Q14: 2026年4月頃 | R14: 在庫+注残限り。箱変更 | V14: 580 | W14: 0 | AN14: 240W | AO14: 20 | AP14: 12 | AQ14: 5525+ | AR14: 199685 | AS14: C5-C6 | AT14: 171480 | AU14: 100W/140W | AV14: 140W未検証 | AW14: TRUE | AX14: 組UNW X6AR57TK(R1 GG 16WQXGA 275HX 5070Ti | AY14: 115 | BA14: Light Gray | BB14: Black | BC14: Light Gray | BD14: Light Gray | BJ14: x | BM14: =IF(COUNTIFS('在庫使用計画 (ノート全体試算)'!C:C,マスタ_EOLリスト[[#This Row],[製品型番]])=0,"記載なし","") | BN14: =IF(COUNTIFS('在庫使用計画 (一般)'!C:C,マスタ_EOLリスト[[#This Row],[製品型番]])=0,"記載なし","") | BO14: =IF(COUNTIFS('在庫使用計画 (法人)'!C:C,マスタ_EOLリスト[[#This Row],[製品型番]])=0,"記載なし","") | BP14: =IF(COUNTIFS('在庫使用計画 (全体実績+予測）0701'!C:C,マスタ_EOLリスト[[#This Row],[製品型番]])=0,"記載なし","") | BQ14: =IF(COUNTIFS('在庫使用計画 (計画 予測)'!C:C,マスタ_EOLリスト[[#This Row],[製品型番]])=0,"記載なし","") | BR14: =IF(COUNTIFS(在庫確認!B:B,マスタ_EOLリスト[[#This Row],[製品型番]])=0,"記載なし","") | BS14: =COUNTIF(#REF!,マスタ_EOLリスト[[#This Row],[製品型番]]) -> #REF!
A15: ZL7C-R57-6A | B15: 2発売中 | C15: 1GALLERIA-G | D15: ZL7C-R57-6A | E15: 220803 | F15: 組UNW X6AR557K(GG 16WQXGA 255HX 5070 240W L6) | G15: ID-K | H15: UNW-K-255HX-5070-L6 | I15: 16 | K15: u7-255HX | L15: 5070 | M15: 128 | N15: 128 | O15: 45856 | P15: 45876 | Q15: 2026年4月頃 | R15: 在庫+注残限り | V15: 1180 | W15: 926 | AN15: 240W | AO15: 20 | AP15: 12 | AQ15: 5525+ | AR15: 199685 | AS15: C5-C6 | AT15: 171480 | AU15: 100W/140W | AV15: 140W未検証 | AW15: TRUE | AX15: 組UNW X6AR557K(GG 16WQXGA 255HX 5070 240W | AY15: 115 | BA15: Light Gray | BB15: Black | BC15: Light Gray | BD15: Light Gray | BJ15: ID-7? | BM15: =IF(COUNTIFS('在庫使用計画 (ノート全体試算)'!C:C,マスタ_EOLリスト[[#This Row],[製品型番]])=0,"記載なし","") | BN15: =IF(COUNTIFS('在庫使用計画 (一般)'!C:C,マスタ_EOLリスト[[#This Row],[製品型番]])=0,"記載なし","") | BO15: =IF(COUNTIFS('在庫使用計画 (法人)'!C:C,マスタ_EOLリスト[[#This Row],[製品型番]])=0,"記載なし","") | BP15: =IF(COUNTIFS('在庫使用計画 (全体実績+予測）0701'!C:C,マスタ_EOLリスト[[#This Row],[製品型番]])=0,"記載なし","") | BQ15: =IF(COUNTIFS('在庫使用計画 (計画 予測)'!C:C,マスタ_EOLリスト[[#This Row],[製品型番]])=0,"記載なし","") | BR15: =IF(COUNTIFS(在庫確認!B:B,マスタ_EOLリスト[[#This Row],[製品型番]])=0,"記載なし","") | BS15: =COUNTIF(#REF!,マスタ_EOLリスト[[#This Row],[製品型番]]) -> #REF!
A16: ZL7C-R57-6A | B16: 2発売中 | C16: 1GALLERIA-G | D16: ZL7C-R57-6A | E16: 366295 | F16: 組UNW X6AR557K(R1GG 16WQXGA 255HX 5070 240W L6) | G16: ID-K | H16: UNW-K-255HX-5070-L6 | I16: 16 | K16: u7-255HX | L16: 5070 | M16: 0 | N16: 140 | O16: 45856 | P16: 45876 | Q16: 2026年4月頃 | R16: 在庫+注残限り | V16: 1180 | W16: 0 | AN16: 240W | AO16: 20 | AP16: 12 | AQ16: 5525+ | AR16: 199685 | AS16: C5-C6 | AT16: 171480 | AU16: 100W/140W | AV16: 140W未検証 | AW16: TRUE | AX16: 在庫無し | AY16: 115 | BA16: Light Gray | BB16: Black | BC16: Light Gray | BD16: Light Gray | BJ16: ID-7? | BM16: =IF(COUNTIFS('在庫使用計画 (ノート全体試算)'!C:C,マスタ_EOLリスト[[#This Row],[製品型番]])=0,"記載なし","") | BN16: =IF(COUNTIFS('在庫使用計画 (一般)'!C:C,マスタ_EOLリスト[[#This Row],[製品型番]])=0,"記載なし","") | BO16: =IF(COUNTIFS('在庫使用計画 (法人)'!C:C,マスタ_EOLリスト[[#This Row],[製品型番]])=0,"記載なし","") | BP16: =IF(COUNTIFS('在庫使用計画 (全体実績+予測）0701'!C:C,マスタ_EOLリスト[[#This Row],[製品型番]])=0,"記載なし","") | BQ16: =IF(COUNTIFS('在庫使用計画 (計画 予測)'!C:C,マスタ_EOLリスト[[#This Row],[製品型番]])=0,"記載なし","") | BR16: =IF(COUNTIFS(在庫確認!B:B,マスタ_EOLリスト[[#This Row],[製品型番]])=0,"記載なし","") | BS16: =COUNTIF(#REF!,マスタ_EOLリスト[[#This Row],[製品型番]]) -> #REF!
A17: ZL9C-R47-6B | B17: 4EOL(完全終息) | C17: 1GALLERIA-G | D17: ZL9C-R47-6B | E17: 196068 | F17: 組UNW_GM6IX7B(GG 16WQXGA 14900HX 4070 240W L6) | G17: ID-B | H17: ID-B 14900HX-4070-L6 | K17: i9-14900HX | L17: 4070 | M17: 0 | N17: 0 | O17: 45423 | P17: 45449 | U17: Copilot keyモデルにスライド | V17: 500 | W17: 400 | Z17: 199019 | AK17: 199325 | AL17: 45525 | AM17: 70 | AN17: 240W | AX17: 在庫無し | BA17: Thunder Black | BB17: Black | BC17: Thunder Black | BD17: Stellar Black | BM17: =IF(COUNTIFS('在庫使用計画 (ノート全体試算)'!C:C,マスタ_EOLリスト[[#This Row],[製品型番]])=0,"記載なし","") | BN17: =IF(COUNTIFS('在庫使用計画 (一般)'!C:C,マスタ_EOLリスト[[#This Row],[製品型番]])=0,"記載なし","") | BO17: =IF(COUNTIFS('在庫使用計画 (法人)'!C:C,マスタ_EOLリスト[[#This Row],[製品型番]])=0,"記載なし","") | BP17: =IF(COUNTIFS('在庫使用計画 (全体実績+予測）0701'!C:C,マスタ_EOLリスト[[#This Row],[製品型番]])=0,"記載なし","") | BQ17: =IF(COUNTIFS('在庫使用計画 (計画 予測)'!C:C,マスタ_EOLリスト[[#This Row],[製品型番]])=0,"記載なし","") -> 記載なし | BR17: =IF(COUNTIFS(在庫確認!B:B,マスタ_EOLリスト[[#This Row],[製品型番]])=0,"記載なし","") | BS17: =COUNTIF(#REF!,マスタ_EOLリスト[[#This Row],[製品型番]]) -> #REF!
A18: ZL9C-R47-6B | B18: 4EOL(完全終息) | C18: 1GALLERIA-G | D18: ZL9C-R47-6B | E18: 199019 | F18: 組UNW GM6IX7B(R1 GG 16WQXGA 14900HX 4070 240W L6) | G18: ID-B | H18: ID-B 14900HX-4070-L6 | K18: i9-14900HX | L18: 4070 | M18: 0 | N18: 0 | Q18: 2025年3月頃 | R18: Copilot key対応版 | W18: 890 | Z18: 212476,212347 | AB18: 212476 | AK18: 207654 | AL18: 45483 | AM18: 125 | AN18: 240W | AX18: 在庫無し | BA18: S17S 暮石灰 | BB18: S72 暮石灰 | BC18: S72 暮石灰 | BD18: S72 暮石灰 | BM18: =IF(COUNTIFS('在庫使用計画 (ノート全体試算)'!C:C,マスタ_EOLリスト[[#This Row],[製品型番]])=0,"記載なし","") | BN18: =IF(COUNTIFS('在庫使用計画 (一般)'!C:C,マスタ_EOLリスト[[#This Row],[製品型番]])=0,"記載なし","") | BO18: =IF(COUNTIFS('在庫使用計画 (法人)'!C:C,マスタ_EOLリスト[[#This Row],[製品型番]])=0,"記載なし","") | BP18: =IF(COUNTIFS('在庫使用計画 (全体実績+予測）0701'!C:C,マスタ_EOLリスト[[#This Row],[製品型番]])=0,"記載なし","") | BQ18: =IF(COUNTIFS('在庫使用計画 (計画 予測)'!C:C,マスタ_EOLリスト[[#This Row],[製品型番]])=0,"記載なし","") -> 記載なし | BR18: =IF(COUNTIFS(在庫確認!B:B,マスタ_EOLリスト[[#This Row],[製品型番]])=0,"記載なし","") | BS18: =COUNTIF(#REF!,マスタ_EOLリスト[[#This Row],[製品型番]]) -> #REF!
A19: ZL9C-R46-6 | B19: 4EOL(完全終息) | C19: 1GALLERIA-G | D19: ZL9C-R46-6 | E19: 196066 | F19: 組UNW GM6IX0B(16WQXGA 14900HX 4060 240W L6) | G19: ID-B | H19: ID-B 14900HX-4060-L6 | K19: i9-14900HX | L19: 4060 | M19: 0 | N19: 0 | P19: 45449 | U19: 在庫限りで終息予定 | V19: 500 | W19: 380 | Z19: 199020 | AC19: ZL9C-R47-6B | AL19: 45481 | AM19: 10 | AX19: 在庫無し | BA19: B11S 瀾夜黑 | BB19: B77 瀾夜黑 | BC19: B77 瀾夜黑 | BD19: B77 瀾夜黑 | BM19: =IF(COUNTIFS('在庫使用計画 (ノート全体試算)'!C:C,マスタ_EOLリスト[[#This Row],[製品型番]])=0,"記載なし","") | BN19: =IF(COUNTIFS('在庫使用計画 (一般)'!C:C,マスタ_EOLリスト[[#This Row],[製品型番]])=0,"記載なし","") | BO19: =IF(COUNTIFS('在庫使用計画 (法人)'!C:C,マスタ_EOLリスト[[#This Row],[製品型番]])=0,"記載なし","") | BP19: =IF(COUNTIFS('在庫使用計画 (全体実績+予測）0701'!C:C,マスタ_EOLリスト[[#This Row],[製品型番]])=0,"記載なし","") | BQ19: =IF(COUNTIFS('在庫使用計画 (計画 予測)'!C:C,マスタ_EOLリスト[[#This Row],[製品型番]])=0,"記載なし","") -> 記載なし | BR19: =IF(COUNTIFS(在庫確認!B:B,マスタ_EOLリスト[[#This Row],[製品型番]])=0,"記載なし","") | BS19: =COUNTIF(#REF!,マスタ_EOLリスト[[#This Row],[製品型番]]) -> #REF!
A20: ZL9C-R46-6 | B20: 4EOL(完全終息) | C20: 1GALLERIA-G | D20: ZL9C-R46-6 | E20: 199020 | F20: 組UNW GM6IX0B(R1 GG 16WQXGA 14900HX 4060 240W L6) | G20: ID-B | H20: ID-B 14900HX-4060-L6 | K20: i9-14900HX | L20: 4060 | M20: 0 | N20: 0 | R20: Copilot key対応版 | W20: 0 | Z20: なし | AL20: 45483 | AM20: 125 | AX20: 在庫無し | BA20: B11S 瀾夜黑 | BB20: B77 瀾夜黑 | BC20: B77 瀾夜黑 | BD20: B77 瀾夜黑 | BM20: =IF(COUNTIFS('在庫使用計画 (ノート全体試算)'!C:C,マスタ_EOLリスト[[#This Row],[製品型番]])=0,"記載なし","") | BN20: =IF(COUNTIFS('在庫使用計画 (一般)'!C:C,マスタ_EOLリスト[[#This Row],[製品型番]])=0,"記載なし","") | BO20: =IF(COUNTIFS('在庫使用計画 (法人)'!C:C,マスタ_EOLリスト[[#This Row],[製品型番]])=0,"記載なし","") | BP20: =IF(COUNTIFS('在庫使用計画 (全体実績+予測）0701'!C:C,マスタ_EOLリスト[[#This Row],[製品型番]])=0,"記載なし","") | BQ20: =IF(COUNTIFS('在庫使用計画 (計画 予測)'!C:C,マスタ_EOLリスト[[#This Row],[製品型番]])=0,"記載なし","") -> 記載なし | BR20: =IF(COUNTIFS(在庫確認!B:B,マスタ_EOLリスト[[#This Row],[製品型番]])=0,"記載なし","") | BS20: =COUNTIF(#REF!,マスタ_EOLリスト[[#This Row],[製品型番]]) -> #REF!
A21: ZL7C-R47 | B21: 4EOL(完全終息) | C21: 1GALLERIA-G | D21: ZL7C-R47 | E21: 184057 | F21: 組CLE PD51SNE-GTD(15.6FHD 13700HX 4070 280W L6) | G21: PD51 | H21: CLE-PD51-13700HX-4070-L6 | K21: i7-13700HX | L21: 4070 | M21: 0 | N21: 0 | P21: 45197 | Q21: 2024年6月頃 | R21: 代替候補はID別 | V21: 1200 | W21: 1250 | Z21: 196068 | AC21: ラインとしての後継 | AH21: 後継IDは変更 | AI21: 196068 | AJ21: 組UNW_GM6IX7B(GG 16WQXGA 14900HX 4070 240W L6) | AL21: 45413 | AM21: 40 | AX21: 在庫無し | BA21: Light Gray | BB21: Black | BC21: Light Gray | BD21: Light Gray | BM21: =IF(COUNTIFS('在庫使用計画 (ノート全体試算)'!C:C,マスタ_EOLリスト[[#This Row],[製品型番]])=0,"記載なし","") | BN21: =IF(COUNTIFS('在庫使用計画 (一般)'!C:C,マスタ_EOLリスト[[#This Row],[製品型番]])=0,"記載なし","") -> 記載なし | BO21: =IF(COUNTIFS('在庫使用計画 (法人)'!C:C,マスタ_EOLリスト[[#This Row],[製品型番]])=0,"記載なし","") | BP21: =IF(COUNTIFS('在庫使用計画 (全体実績+予測）0701'!C:C,マスタ_EOLリスト[[#This Row],[製品型番]])=0,"記載なし","") | BQ21: =IF(COUNTIFS('在庫使用計画 (計画 予測)'!C:C,マスタ_EOLリスト[[#This Row],[製品型番]])=0,"記載なし","") -> 記載なし | BR21: =IF(COUNTIFS(在庫確認!B:B,マスタ_EOLリスト[[#This Row],[製品型番]])=0,"記載なし","") | BS21: =COUNTIF(#REF!,マスタ_EOLリスト[[#This Row],[製品型番]]) -> #REF!
A22: XL7R-R56-6A | B22: 4EOL(完全終息) | C22: 1GALLERIA-G | D22: XL7R-R56-6A | E22: 212469 | F22: 組CLE V561KNN-TD(GG 16QHD+ 350 5060 180W L6) | G22: V56 | H22: CLE-V56-350-5060-L6 | I22: 16 | J22: 必須 | K22: R AI 7 350 | L22: 5060 | M22: 0 | N22: 0 | O22: 2025年4月末 | P22: 45793 | Q22: 2026年4月頃 | V22: 1050 | W22: 506 | Z22: 251110 | AN22: 180W | AO22: 20 | AP22: 9 | AQ22: 5525+ | AR22: 188009 | AS22: C5-C6 | AT22: 188010 | AU22: 45-100W | AX22: 在庫無し | AY22: 115 | BA22: S60 鐵灰 | BB22: S60 鐵灰 | BC22: S60 鐵灰 | BD22: S60 鐵灰 | BJ22: x | BM22: =IF(COUNTIFS('在庫使用計画 (ノート全体試算)'!C:C,マスタ_EOLリスト[[#This Row],[製品型番]])=0,"記載なし","") | BN22: =IF(COUNTIFS('在庫使用計画 (一般)'!C:C,マスタ_EOLリスト[[#This Row],[製品型番]])=0,"記載なし","") | BO22: =IF(COUNTIFS('在庫使用計画 (法人)'!C:C,マスタ_EOLリスト[[#This Row],[製品型番]])=0,"記載なし","") | BP22: =IF(COUNTIFS('在庫使用計画 (全体実績+予測）0701'!C:C,マスタ_EOLリスト[[#This Row],[製品型番]])=0,"記載なし","") | BQ22: =IF(COUNTIFS('在庫使用計画 (計画 予測)'!C:C,マスタ_EOLリスト[[#This Row],[製品型番]])=0,"記載なし","") | BR22: =IF(COUNTIFS(在庫確認!B:B,マスタ_EOLリスト[[#This Row],[製品型番]])=0,"記載なし","") | BS22: =COUNTIF(#REF!,マスタ_EOLリスト[[#This Row],[製品型番]]) -> #REF!
A23: XL7R-R56-6A | B23: 4EOL(完全終息) | C23: 1GALLERIA-G | D23: XL7R-R56-6A | E23: 251110 | F23: 組CLE V561KNN-TD(R1 GG 16QHD+300Hz 350 5060 180WL6 | G23: V56 | H23: CLE-V56-350-5060-L6 | I23: 16 | J23: 必須 | K23: R AI 7 350 | L23: 5060 | M23: 0 | N23: 0 | P23: 45793 | Q23: 2026年4月頃 | R23: 液晶変更版 2nd sorce | W23: 384 | AB23: 295634 | AN23: 180W | AO23: 20 | AP23: 9 | AQ23: 5525+ | AR23: 188009 | AS23: C5-C6 | AT23: 188010 | AU23: 45-100W | AX23: 在庫無し | AY23: 115 | BA23: Light Gray | BB23: Black | BC23: Light Gray | BD23: Light Gray | BJ23: NDC7L-R57-G6 | BM23: =IF(COUNTIFS('在庫使用計画 (ノート全体試算)'!C:C,マスタ_EOLリスト[[#This Row],[製品型番]])=0,"記載なし","") | BN23: =IF(COUNTIFS('在庫使用計画 (一般)'!C:C,マスタ_EOLリスト[[#This Row],[製品型番]])=0,"記載なし","") | BO23: =IF(COUNTIFS('在庫使用計画 (法人)'!C:C,マスタ_EOLリスト[[#This Row],[製品型番]])=0,"記載なし","") | BP23: =IF(COUNTIFS('在庫使用計画 (全体実績+予測）0701'!C:C,マスタ_EOLリスト[[#This Row],[製品型番]])=0,"記載なし","") | BQ23: =IF(COUNTIFS('在庫使用計画 (計画 予測)'!C:C,マスタ_EOLリスト[[#This Row],[製品型番]])=0,"記載なし","") | BR23: =IF(COUNTIFS(在庫確認!B:B,マスタ_EOLリスト[[#This Row],[製品型番]])=0,"記載なし","") | BS23: =COUNTIF(#REF!,マスタ_EOLリスト[[#This Row],[製品型番]]) -> #REF!
A24: XL7C-R56-6A | B24: 3EOL(在庫あり) | C24: 1GALLERIA-G | D24: XL7C-R56-6A | E24: 214073 | F24: 組UNW X6AR556U(GG 16WQXGA 255HX 5060 240W L6) | G24: ID-U | H24: UNW-U-255HX-5060-L6 | I24: 16 | K24: u7-255HX | L24: 5060 | M24: 5 | N24: 5 | P24: 45925 | Q24: 2026年5月頃？ | V24: 1950 | W24: 786 | AN24: 240W | AO24: 20 | AP24: 12 | AQ24: 5525+ | AR24: 199685 | AS24: C5-C6 | AT24: 171480 | AW24: TRUE | AX24: 組UNW X6AR556U(GG 16WQXGA 255HX 5060 240W | AY24: 115 | BA24: S17S 暮石灰 | BB24: S17S 暮石灰 | BC24: S17S 暮石灰 | BD24: S17S 暮石灰 | BJ24: x | BM24: =IF(COUNTIFS('在庫使用計画 (ノート全体試算)'!C:C,マスタ_EOLリスト[[#This Row],[製品型番]])=0,"記載なし","") | BN24: =IF(COUNTIFS('在庫使用計画 (一般)'!C:C,マスタ_EOLリスト[[#This Row],[製品型番]])=0,"記載なし","") | BO24: =IF(COUNTIFS('在庫使用計画 (法人)'!C:C,マスタ_EOLリスト[[#This Row],[製品型番]])=0,"記載なし","") | BP24: =IF(COUNTIFS('在庫使用計画 (全体実績+予測）0701'!C:C,マスタ_EOLリスト[[#This Row],[製品型番]])=0,"記載なし","") | BQ24: =IF(COUNTIFS('在庫使用計画 (計画 予測)'!C:C,マスタ_EOLリスト[[#This Row],[製品型番]])=0,"記載なし","") | BR24: =IF(COUNTIFS(在庫確認!B:B,マスタ_EOLリスト[[#This Row],[製品型番]])=0,"記載なし","") | BS24: =COUNTIF(#REF!,マスタ_EOLリスト[[#This Row],[製品型番]]) -> #REF!
A25: #N/A | B25: 4EOL(完全終息) | C25: 1GALLERIA-G | D25: XL7C-R46H | E25: 186236 | F25: 組UNW PH6PG02(16WUXGA 13700H 4060 150W L6) | G25: 6H2 | M25: 0 | N25: 0 | Q25: 2024年6月頃 | R25: 代替候補はID別 | W25: 1248 | AC25: 2024/7頃 | AI25: 199408 | AL25: 45422 | AM25: 250 | AN25: 150W | AO25: 19 | AP25: 7.89 | AQ25: 5525+ | AX25: 在庫無し | BM25: =IF(COUNTIFS('在庫使用計画 (ノート全体試算)'!C:C,マスタ_EOLリスト[[#This Row],[製品型番]])=0,"記載なし","") -> 記載なし | BN25: =IF(COUNTIFS('在庫使用計画 (一般)'!C:C,マスタ_EOLリスト[[#This Row],[製品型番]])=0,"記載なし","") -> 記載なし | BO25: =IF(COUNTIFS('在庫使用計画 (法人)'!C:C,マスタ_EOLリスト[[#This Row],[製品型番]])=0,"記載なし","") -> 記載なし | BP25: =IF(COUNTIFS('在庫使用計画 (全体実績+予測）0701'!C:C,マスタ_EOLリスト[[#This Row],[製品型番]])=0,"記載なし","") -> 記載なし | BQ25: =IF(COUNTIFS('在庫使用計画 (計画 予測)'!C:C,マスタ_EOLリスト[[#This Row],[製品型番]])=0,"記載なし","") -> 記載なし | BR25: =IF(COUNTIFS(在庫確認!B:B,マスタ_EOLリスト[[#This Row],[製品型番]])=0,"記載なし","") -> 記載なし | BS25: =COUNTIF(#REF!,マスタ_EOLリスト[[#This Row],[製品型番]]) -> #REF!
A26: XL7C-R46-6 | B26: 4EOL(完全終息) | C26: 1GALLERIA-G | D26: XL7C-R46-6 | E26: 199408 | F26: 組CLE V561TND-TD(GG 16QHD+240Hz 155H 4060 180W L6) | G26: V56 | H26: CLE-V56-155H-4060-L6 | K26: u7-155H | L26: 4060 | M26: 0 | N26: 0 | P26: 45526 | Q26: 2025年4-5月 | U26: 2000で終了見込み | V26: 5010 | W26: 2000 | Z26: 212347 | AB26: 212469,214073 | AC26: intel/AMD +5060 | AL26: 45510 | AM26: 300 | AN26: 180W | AX26: 在庫無し | BA26: S17S 暮石灰 | BB26: S17S 暮石灰 | BC26: S17S 暮石灰 | BD26: S17S 暮石灰 | BM26: =IF(COUNTIFS('在庫使用計画 (ノート全体試算)'!C:C,マスタ_EOLリスト[[#This Row],[製品型番]])=0,"記載なし","") | BN26: =IF(COUNTIFS('在庫使用計画 (一般)'!C:C,マスタ_EOLリスト[[#This Row],[製品型番]])=0,"記載なし","") | BO26: =IF(COUNTIFS('在庫使用計画 (法人)'!C:C,マスタ_EOLリスト[[#This Row],[製品型番]])=0,"記載なし","") | BP26: =IF(COUNTIFS('在庫使用計画 (全体実績+予測）0701'!C:C,マスタ_EOLリスト[[#This Row],[製品型番]])=0,"記載なし","") | BQ26: =IF(COUNTIFS('在庫使用計画 (計画 予測)'!C:C,マスタ_EOLリスト[[#This Row],[製品型番]])=0,"記載なし","") -> 記載なし | BR26: =IF(COUNTIFS(在庫確認!B:B,マスタ_EOLリスト[[#This Row],[製品型番]])=0,"記載なし","") | BS26: =COUNTIF(#REF!,マスタ_EOLリスト[[#This Row],[製品型番]]) -> #REF!
A27: #N/A | B27: 4EOL(完全終息) | C27: 1GALLERIA-G | D27: XL7C-R46 | E27: 186232 | F27: 組TFH GM5PG0O(15FHD 13700H 4060 230W L6) | G27: ID-O3 | M27: 0 | N27: 0 | P27: 10月予定 | Q27: 2024年6月頃 | R27: 代替候補はID別 | W27: 3240 | Z27: 201898 | AC27: 2024/7頃 | AI27: 201898,199408 | AJ27: 201898は廉価、199408は16”MTL | AX27: 在庫無し | BA27: Galaxy Black | BB27: Black | BC27: Galaxy Black | BD27: Black | BM27: =IF(COUNTIFS('在庫使用計画 (ノート全体試算)'!C:C,マスタ_EOLリスト[[#This Row],[製品型番]])=0,"記載なし","") -> 記載なし | BN27: =IF(COUNTIFS('在庫使用計画 (一般)'!C:C,マスタ_EOLリスト[[#This Row],[製品型番]])=0,"記載なし","") -> 記載なし | BO27: =IF(COUNTIFS('在庫使用計画 (法人)'!C:C,マスタ_EOLリスト[[#This Row],[製品型番]])=0,"記載なし","") -> 記載なし | BP27: =IF(COUNTIFS('在庫使用計画 (全体実績+予測）0701'!C:C,マスタ_EOLリスト[[#This Row],[製品型番]])=0,"記載なし","") -> 記載なし | BQ27: =IF(COUNTIFS('在庫使用計画 (計画 予測)'!C:C,マスタ_EOLリスト[[#This Row],[製品型番]])=0,"記載なし","") -> 記載なし | BR27: =IF(COUNTIFS(在庫確認!B:B,マスタ_EOLリスト[[#This Row],[製品型番]])=0,"記載なし","") -> 記載なし | BS27: =COUNTIF(#REF!,マスタ_EOLリスト[[#This Row],[製品型番]]) -> #REF!
A28: #N/A | B28: 4EOL(完全終息) | C28: 1GALLERIA-G | D28: XL7C-R45H | E28: 181640 | F28: 組UNW PH6PG52(16WUXGA 13700H 4050 150W L9) | G28: 6H2 | M28: 0 | N28: 0 | P28: 45106 | R28: 代替候補はID別 | V28: 2000 | W28: 700 | X28: 71 | AC28: ↓L6に移行 | AN28: 150W | AO28: 19 | AP28: 7.89 | AQ28: 5525+ | AX28: 在庫無し | BA28: Galaxy Black | BB28: Black | BC28: Galaxy Black | BD28: Black | BM28: =IF(COUNTIFS('在庫使用計画 (ノート全体試算)'!C:C,マスタ_EOLリスト[[#This Row],[製品型番]])=0,"記載なし","") -> 記載なし | BN28: =IF(COUNTIFS('在庫使用計画 (一般)'!C:C,マスタ_EOLリスト[[#This Row],[製品型番]])=0,"記載なし","") -> 記載なし | BO28: =IF(COUNTIFS('在庫使用計画 (法人)'!C:C,マスタ_EOLリスト[[#This Row],[製品型番]])=0,"記載なし","") -> 記載なし | BP28: =IF(COUNTIFS('在庫使用計画 (全体実績+予測）0701'!C:C,マスタ_EOLリスト[[#This Row],[製品型番]])=0,"記載なし","") -> 記載なし | BQ28: =IF(COUNTIFS('在庫使用計画 (計画 予測)'!C:C,マスタ_EOLリスト[[#This Row],[製品型番]])=0,"記載なし","") -> 記載なし | BR28: =IF(COUNTIFS(在庫確認!B:B,マスタ_EOLリスト[[#This Row],[製品型番]])=0,"記載なし","") -> 記載なし | BS28: =COUNTIF(#REF!,マスタ_EOLリスト[[#This Row],[製品型番]]) -> #REF!
A29: XL7C-R45-6 | B29: 4EOL(完全終息) | C29: 1GALLERIA-G | D29: XL7C-R45-6 | E29: 199409 | F29: 組CLE V561TNC-TD(GG 16QHD+240Hz 155H 4050 180W L6) | G29: V56 | H29: CLE-V56-155H-4050-L6 | K29: u7-155H | L29: 4060 | M29: 0 | N29: 0 | P29: 45526 | Q29: 2025年4-5月 | U29: 1500で終了見込み | V29: 3350 | W29: 1500 | Z29: 216515 | AA29: 5050モデル | AB29: 212469,214073 | AC29: intel/AMD +5060 | AL29: 45530 | AM29: 240 | AN29: 180W | AX29: 在庫無し | BA29: S60 鐵灰 | BB29: S60 鐵灰 | BC29: S60 鐵灰 | BD29: S60 鐵灰 | BM29: =IF(COUNTIFS('在庫使用計画 (ノート全体試算)'!C:C,マスタ_EOLリスト[[#This Row],[製品型番]])=0,"記載なし","") | BN29: =IF(COUNTIFS('在庫使用計画 (一般)'!C:C,マスタ_EOLリスト[[#This Row],[製品型番]])=0,"記載なし","") | BO29: =IF(COUNTIFS('在庫使用計画 (法人)'!C:C,マスタ_EOLリスト[[#This Row],[製品型番]])=0,"記載なし","") | BP29: =IF(COUNTIFS('在庫使用計画 (全体実績+予測）0701'!C:C,マスタ_EOLリスト[[#This Row],[製品型番]])=0,"記載なし","") | BQ29: =IF(COUNTIFS('在庫使用計画 (計画 予測)'!C:C,マスタ_EOLリスト[[#This Row],[製品型番]])=0,"記載なし","") -> 記載なし | BR29: =IF(COUNTIFS(在庫確認!B:B,マスタ_EOLリスト[[#This Row],[製品型番]])=0,"記載なし","") | BS29: =COUNTIF(#REF!,マスタ_EOLリスト[[#This Row],[製品型番]]) -> #REF!
A30: #N/A | B30: 4EOL(完全終息) | C30: 1GALLERIA-G | D30: XL7C-R45 | E30: 179160 | F30: 組TFH GM5PG5O(15FHD 13700H 4050 230W L9) | G30: ID-O3 | K30: i7-13700H | L30: 4050 | M30: 0 | N30: 0 | P30: 45056 | R30: 代替候補はID別 | V30: 6780 | W30: 4350 | X30: 2397 | Z30: 201900 | AC30: ↓L6に移行 | AH30: 後継IDは変更 →ID-U | AI30: 201900,199409 | AJ30: 201900は廉価 | AX30: 在庫無し | BA30: S60 鐵灰 | BB30: S60 鐵灰 | BC30: S60 鐵灰 | BD30: S60 鐵灰 | BM30: =IF(COUNTIFS('在庫使用計画 (ノート全体試算)'!C:C,マスタ_EOLリスト[[#This Row],[製品型番]])=0,"記載なし","") -> 記載なし | BN30: =IF(COUNTIFS('在庫使用計画 (一般)'!C:C,マスタ_EOLリスト[[#This Row],[製品型番]])=0,"記載なし","") -> 記載なし | BO30: =IF(COUNTIFS('在庫使用計画 (法人)'!C:C,マスタ_EOLリスト[[#This Row],[製品型番]])=0,"記載なし","") -> 記載なし | BP30: =IF(COUNTIFS('在庫使用計画 (全体実績+予測）0701'!C:C,マスタ_EOLリスト[[#This Row],[製品型番]])=0,"記載なし","") -> 記載なし | BQ30: =IF(COUNTIFS('在庫使用計画 (計画 予測)'!C:C,マスタ_EOLリスト[[#This Row],[製品型番]])=0,"記載なし","") -> 記載なし | BR30: =IF(COUNTIFS(在庫確認!B:B,マスタ_EOLリスト[[#This Row],[製品型番]])=0,"記載なし","") -> 記載なし | BS30: =COUNTIF(#REF!,マスタ_EOLリスト[[#This Row],[製品型番]]) -> #REF!
A31: #N/A | B31: 4EOL(完全終息) | C31: 1GALLERIA-G | D31: XL7C-R45 | E31: 186233 | F31: 組TFH GM5PG5O(15FHD 13700H 4050 230W L6) | G31: ID-O3 | K31: i7-13700H | L31: 4050 | M31: 0 | N31: 0 | Q31: 2024年6月頃 | R31: 代替候補はID別 | W31: 5120 | Z31: 201900 | AC31: 2024/7頃 | AI31: 201900,199409 | AJ31: 201900は廉価 | AL31: 45422 | AM31: 60 | AX31: 在庫無し | BA31: S60 鐵灰 | BB31: S60 鐵灰 | BC31: S60 鐵灰 | BD31: S60 鐵灰 | BM31: =IF(COUNTIFS('在庫使用計画 (ノート全体試算)'!C:C,マスタ_EOLリスト[[#This Row],[製品型番]])=0,"記載なし","") -> 記載なし | BN31: =IF(COUNTIFS('在庫使用計画 (一般)'!C:C,マスタ_EOLリスト[[#This Row],[製品型番]])=0,"記載なし","") -> 記載なし | BO31: =IF(COUNTIFS('在庫使用計画 (法人)'!C:C,マスタ_EOLリスト[[#This Row],[製品型番]])=0,"記載なし","") -> 記載なし | BP31: =IF(COUNTIFS('在庫使用計画 (全体実績+予測）0701'!C:C,マスタ_EOLリスト[[#This Row],[製品型番]])=0,"記載なし","") -> 記載なし | BQ31: =IF(COUNTIFS('在庫使用計画 (計画 予測)'!C:C,マスタ_EOLリスト[[#This Row],[製品型番]])=0,"記載なし","") -> 記載なし | BR31: =IF(COUNTIFS(在庫確認!B:B,マスタ_EOLリスト[[#This Row],[製品型番]])=0,"記載なし","") -> 記載なし | BS31: =COUNTIF(#REF!,マスタ_EOLリスト[[#This Row],[製品型番]]) -> #REF!
A32: #N/A | B32: 5開発中止 | C32: 1GALLERIA-G | D32: NDC9L-R57T-G6 | G32: ID-K | H32: UNW-K-290HXP-5070Ti-L6 | I32: 16 | K32: ARL-HX R U9-290HX Plus | L32: 5070Ti | M32: 0 | N32: 0 | AX32: 在庫無し | BM32: =IF(COUNTIFS('在庫使用計画 (ノート全体試算)'!C:C,マスタ_EOLリスト[[#This Row],[製品型番]])=0,"記載なし","") -> 記載なし | BN32: =IF(COUNTIFS('在庫使用計画 (一般)'!C:C,マスタ_EOLリスト[[#This Row],[製品型番]])=0,"記載なし","") -> 記載なし | BO32: =IF(COUNTIFS('在庫使用計画 (法人)'!C:C,マスタ_EOLリスト[[#This Row],[製品型番]])=0,"記載なし","") -> 記載なし | BP32: =IF(COUNTIFS('在庫使用計画 (全体実績+予測）0701'!C:C,マスタ_EOLリスト[[#This Row],[製品型番]])=0,"記載なし","") -> 記載なし | BQ32: =IF(COUNTIFS('在庫使用計画 (計画 予測)'!C:C,マスタ_EOLリスト[[#This Row],[製品型番]])=0,"記載なし","") -> 記載なし | BR32: =IF(COUNTIFS(在庫確認!B:B,マスタ_EOLリスト[[#This Row],[製品型番]])=0,"記載なし","") -> 記載なし | BS32: =COUNTIF(#REF!,マスタ_EOLリスト[[#This Row],[製品型番]]) -> #REF!
A33: #N/A | B33: 5開発中止 | C33: 1GALLERIA-G | D33: NDC7L-R57-G6 | G33: ID-K | H33: UNW-K-270HXP-5070-L6 | I33: 16 | K33: ARL-HX U7-270HX Plus(仮) | L33: 5070 | M33: 0 | N33: 0 | AX33: 在庫無し | BM33: =IF(COUNTIFS('在庫使用計画 (ノート全体試算)'!C:C,マスタ_EOLリスト[[#This Row],[製品型番]])=0,"記載なし","") -> 記載なし | BN33: =IF(COUNTIFS('在庫使用計画 (一般)'!C:C,マスタ_EOLリスト[[#This Row],[製品型番]])=0,"記載なし","") -> 記載なし | BO33: =IF(COUNTIFS('在庫使用計画 (法人)'!C:C,マスタ_EOLリスト[[#This Row],[製品型番]])=0,"記載なし","") -> 記載なし | BP33: =IF(COUNTIFS('在庫使用計画 (全体実績+予測）0701'!C:C,マスタ_EOLリスト[[#This Row],[製品型番]])=0,"記載なし","") -> 記載なし | BQ33: =IF(COUNTIFS('在庫使用計画 (計画 予測)'!C:C,マスタ_EOLリスト[[#This Row],[製品型番]])=0,"記載なし","") -> 記載なし | BR33: =IF(COUNTIFS(在庫確認!B:B,マスタ_EOLリスト[[#This Row],[製品型番]])=0,"記載なし","") -> 記載なし | BS33: =COUNTIF(#REF!,マスタ_EOLリスト[[#This Row],[製品型番]]) -> #REF!
A34: RL7C-R56-5N | B34: 2発売中 | C34: 1GALLERIA-G | D34: RL7C-R56-5N | E34: 222818 | F34: 組CLE V350SNNQ(GG 15.6FHD 14650HX 5060 180W L6) | G34: V35 | H34: CLE-V35-14650HX-5060-L6 | I34: 15 | K34: i7-14650HX | L34: 5060 | M34: 53 | N34: 53 | P34: 45939 | R34: 7-8月にID-2に切替 | W34: 2726 | AU34: 65W-100W | AW34: TRUE | AX34: 組CLE V350SNNQ(GG 15.6FHD 14650HX 5060 18 | AY34: 115 | BA34: S17S 暮石灰 | BB34: S17S 暮石灰 | BC34: S17S 暮石灰 | BD34: S17S 暮石灰 | BJ34: NPC7L-R56-G5 | BM34: =IF(COUNTIFS('在庫使用計画 (ノート全体試算)'!C:C,マスタ_EOLリスト[[#This Row],[製品型番]])=0,"記載なし","") | BN34: =IF(COUNTIFS('在庫使用計画 (一般)'!C:C,マスタ_EOLリスト[[#This Row],[製品型番]])=0,"記載なし","") | BO34: =IF(COUNTIFS('在庫使用計画 (法人)'!C:C,マスタ_EOLリスト[[#This Row],[製品型番]])=0,"記載なし","") | BP34: =IF(COUNTIFS('在庫使用計画 (全体実績+予測）0701'!C:C,マスタ_EOLリスト[[#This Row],[製品型番]])=0,"記載なし","") | BQ34: =IF(COUNTIFS('在庫使用計画 (計画 予測)'!C:C,マスタ_EOLリスト[[#This Row],[製品型番]])=0,"記載なし","") | BR34: =IF(COUNTIFS(在庫確認!B:B,マスタ_EOLリスト[[#This Row],[製品型番]])=0,"記載なし","") | BS34: =COUNTIF(#REF!,マスタ_EOLリスト[[#This Row],[製品型番]]) -> #REF!
A35: RL7C-R56-5N | B35: 2発売中 | C35: 1GALLERIA-G | D35: RL7C-R56-5N | E35: 317460 | F35: 組CLE V350SNNQ(R1 GG 15.6FHD 14650HX 5060 180W L6) | G35: V35 | H35: CLE-V35-14650HX-5060-L6 | I35: 15 | K35: i7-14650HX | L35: 5060 | M35: 99 | N35: 99 | R35: 7-8月にID-2に切替 | AW35: TRUE | AX35: 組CLE V350SNNQ(R1 GG 15.6FHD 14650HX 5060 | BJ35: NPC7L-R56-G5 | BM35: =IF(COUNTIFS('在庫使用計画 (ノート全体試算)'!C:C,マスタ_EOLリスト[[#This Row],[製品型番]])=0,"記載なし","") | BN35: =IF(COUNTIFS('在庫使用計画 (一般)'!C:C,マスタ_EOLリスト[[#This Row],[製品型番]])=0,"記載なし","") | BO35: =IF(COUNTIFS('在庫使用計画 (法人)'!C:C,マスタ_EOLリスト[[#This Row],[製品型番]])=0,"記載なし","") | BP35: =IF(COUNTIFS('在庫使用計画 (全体実績+予測）0701'!C:C,マスタ_EOLリスト[[#This Row],[製品型番]])=0,"記載なし","") | BQ35: =IF(COUNTIFS('在庫使用計画 (計画 予測)'!C:C,マスタ_EOLリスト[[#This Row],[製品型番]])=0,"記載なし","") | BR35: =IF(COUNTIFS(在庫確認!B:B,マスタ_EOLリスト[[#This Row],[製品型番]])=0,"記載なし","") | BS35: =COUNTIF(#REF!,マスタ_EOLリスト[[#This Row],[製品型番]]) -> #REF!
A36: RL7C-R55-5N | B36: 2発売中 | C36: 1GALLERIA-G | D36: RL7C-R55-5N | E36: 216515 | F36: 組CLE V350SNMQ(GG 15.6FHD 14650HX 5050 180W L6) | G36: V35 | H36: CLE-V35-14650HX-5050-L6 | I36: 15 | K36: i7-14650HX | L36: 5050 | M36: 702 | N36: 702 | O36: 2025年5月末 | P36: 45832 | R36: 7-8月にID-2に切替 | V36: 6000 | W36: 3596 | AN36: 180W | AU36: 65W-100W | AW36: TRUE | AX36: 組CLE V350SNMQ(GG 15.6FHD 14650HX 5050 18 | AY36: 115 | BA36: S17S 暮石灰 | BB36: S17S 暮石灰 | BC36: S17S 暮石灰 | BD36: S17S 暮石灰 | BJ36: NPR7L-R55-G5 | BM36: =IF(COUNTIFS('在庫使用計画 (ノート全体試算)'!C:C,マスタ_EOLリスト[[#This Row],[製品型番]])=0,"記載なし","") | BN36: =IF(COUNTIFS('在庫使用計画 (一般)'!C:C,マスタ_EOLリスト[[#This Row],[製品型番]])=0,"記載なし","") | BO36: =IF(COUNTIFS('在庫使用計画 (法人)'!C:C,マスタ_EOLリスト[[#This Row],[製品型番]])=0,"記載なし","") | BP36: =IF(COUNTIFS('在庫使用計画 (全体実績+予測）0701'!C:C,マスタ_EOLリスト[[#This Row],[製品型番]])=0,"記載なし","") | BQ36: =IF(COUNTIFS('在庫使用計画 (計画 予測)'!C:C,マスタ_EOLリスト[[#This Row],[製品型番]])=0,"記載なし","") | BR36: =IF(COUNTIFS(在庫確認!B:B,マスタ_EOLリスト[[#This Row],[製品型番]])=0,"記載なし","") | BS36: =COUNTIF(#REF!,マスタ_EOLリスト[[#This Row],[製品型番]]) -> #REF!
A37: RL7C-R55-5N | B37: 2発売中 | C37: 1GALLERIA-G | D37: RL7C-R55-5N | E37: 317461 | F37: 組CLE V350SNMQ(R1 GG 15.6FHD 14650HX 5050 180W L6) | G37: V35 | H37: CLE-V35-14650HX-5050-L6 | I37: 15 | K37: i7-14650HX | L37: 5050 | M37: 0 | N37: 0 | R37: 7-8月にID-2に切替 | AW37: TRUE | AX37: 在庫無し | BJ37: NPR7L-R55-G5 | BM37: =IF(COUNTIFS('在庫使用計画 (ノート全体試算)'!C:C,マスタ_EOLリスト[[#This Row],[製品型番]])=0,"記載なし","") | BN37: =IF(COUNTIFS('在庫使用計画 (一般)'!C:C,マスタ_EOLリスト[[#This Row],[製品型番]])=0,"記載なし","") | BO37: =IF(COUNTIFS('在庫使用計画 (法人)'!C:C,マスタ_EOLリスト[[#This Row],[製品型番]])=0,"記載なし","") | BP37: =IF(COUNTIFS('在庫使用計画 (全体実績+予測）0701'!C:C,マスタ_EOLリスト[[#This Row],[製品型番]])=0,"記載なし","") | BQ37: =IF(COUNTIFS('在庫使用計画 (計画 予測)'!C:C,マスタ_EOLリスト[[#This Row],[製品型番]])=0,"記載なし","") | BR37: =IF(COUNTIFS(在庫確認!B:B,マスタ_EOLリスト[[#This Row],[製品型番]])=0,"記載なし","") | BS37: =COUNTIF(#REF!,マスタ_EOLリスト[[#This Row],[製品型番]]) -> #REF!
A38: RL7C-R46-5N | B38: 4EOL(完全終息) | C38: 1GALLERIA-G | D38: RL7C-R46-5N | E38: 201898 | F38: 組UNW GM5PD0O(GG 15.6FHD 13620H 4060 230W L6) | G38: ID-O3 | H38: UNW-O3-13620H-4060-L6 | I38: 15 | K38: i7-13620H | L38: 4060 | M38: 0 | N38: 0 | P38: 45561 | Q38: 45839 | U38: XL7C-R46 の後継 | W38: 6728 | Z38: 222818 | AA38: 5060モデル 10月発売 | AB38: 212469,216515 | AC38: V56 AMD + 5060 / ARL-HX + 5060 / V35 14650HX 5050 | AL38: 45537 | AM38: 6 | AN38: 230W | AX38: 在庫無し | BA38: Galaxy Black | BB38: Black | BC38: Galaxy Black | BD38: Black | BM38: =IF(COUNTIFS('在庫使用計画 (ノート全体試算)'!C:C,マスタ_EOLリスト[[#This Row],[製品型番]])=0,"記載なし","") | BN38: =IF(COUNTIFS('在庫使用計画 (一般)'!C:C,マスタ_EOLリスト[[#This Row],[製品型番]])=0,"記載なし","") | BO38: =IF(COUNTIFS('在庫使用計画 (法人)'!C:C,マスタ_EOLリスト[[#This Row],[製品型番]])=0,"記載なし","") | BP38: =IF(COUNTIFS('在庫使用計画 (全体実績+予測）0701'!C:C,マスタ_EOLリスト[[#This Row],[製品型番]])=0,"記載なし","") | BQ38: =IF(COUNTIFS('在庫使用計画 (計画 予測)'!C:C,マスタ_EOLリスト[[#This Row],[製品型番]])=0,"記載なし","") -> 記載なし | BR38: =IF(COUNTIFS(在庫確認!B:B,マスタ_EOLリスト[[#This Row],[製品型番]])=0,"記載なし","") | BS38: =COUNTIF(#REF!,マスタ_EOLリスト[[#This Row],[製品型番]]) -> #REF!
A39: RL7C-R45-5N | B39: 2発売中 | C39: 1GALLERIA-G | D39: RL7C-R45-5N | E39: 201900 | F39: 組UNW GM5PD5E(GG 15.6FHD 13620H 4050 230W L6) | G39: ID-E | H39: UNW-E-13620H-4050-L6 | I39: 15 | K39: i7-13620H | L39: 4050 | M39: 1414 | N39: 1414 | P39: 45561 | U39: XL7C-R45 の後継 | W39: 12078 | AC39: V35 14650HX 5050/5060 | AL39: 45553 | AM39: 35 | AN39: 230W | AO39: 19.5/20 | AP39: 11.8/11.5 | AQ39: 5525+ | AR39: 199688 | AS39: C13-14 | AT39: 171358 | AW39: TRUE | AX39: 組UNW GM5PD5E(GG 15.6FHD 13620H 4050 230W | AY39: 115 | BA39: S17S 暮石灰 | BB39: S17S 暮石灰 | BC39: S17S 暮石灰 | BD39: S17S 暮石灰 | BJ39: NPC5L-R55-G5 | BM39: =IF(COUNTIFS('在庫使用計画 (ノート全体試算)'!C:C,マスタ_EOLリスト[[#This Row],[製品型番]])=0,"記載なし","") | BN39: =IF(COUNTIFS('在庫使用計画 (一般)'!C:C,マスタ_EOLリスト[[#This Row],[製品型番]])=0,"記載なし","") | BO39: =IF(COUNTIFS('在庫使用計画 (法人)'!C:C,マスタ_EOLリスト[[#This Row],[製品型番]])=0,"記載なし","") | BP39: =IF(COUNTIFS('在庫使用計画 (全体実績+予測）0701'!C:C,マスタ_EOLリスト[[#This Row],[製品型番]])=0,"記載なし","") | BQ39: =IF(COUNTIFS('在庫使用計画 (計画 予測)'!C:C,マスタ_EOLリスト[[#This Row],[製品型番]])=0,"記載なし","") | BR39: =IF(COUNTIFS(在庫確認!B:B,マスタ_EOLリスト[[#This Row],[製品型番]])=0,"記載なし","") | BS39: =COUNTIF(#REF!,マスタ_EOLリスト[[#This Row],[製品型番]]) -> #REF!
A40: RL7C-R35-5N | B40: 3EOL(在庫あり) | C40: 1GALLERIA-G | D40: RL7C-R35-5N | E40: 199024 | F40: 組UNW GM5PD3E(R1 GG 15.6FHD 13620H 3050 180W L6) | G40: ID-E | H40: UNW-E-13620H-3050-L6 | I40: 15 | K40: i7-13620H | L40: 3050 | M40: 2039 | N40: 2039 | Q40: 2026年 6月頃 | R40: Copilot key対応版 | W40: 19980 | AK40: 207649 | AL40: 45525 | AM40: 70 | AN40: 180W | AO40: 19.5/20 | AP40: 9.23/8 | AQ40: 5525+ | AR40: 199687 | AS40: C5-C6 | AT40: 171480 | AW40: TRUE | AX40: 組UNW GM5PD3E(R1 GG 15.6FHD 13620H 3050 1 | BJ40: x | BM40: =IF(COUNTIFS('在庫使用計画 (ノート全体試算)'!C:C,マスタ_EOLリスト[[#This Row],[製品型番]])=0,"記載なし","") | BN40: =IF(COUNTIFS('在庫使用計画 (一般)'!C:C,マスタ_EOLリスト[[#This Row],[製品型番]])=0,"記載なし","") | BO40: =IF(COUNTIFS('在庫使用計画 (法人)'!C:C,マスタ_EOLリスト[[#This Row],[製品型番]])=0,"記載なし","") | BP40: =IF(COUNTIFS('在庫使用計画 (全体実績+予測）0701'!C:C,マスタ_EOLリスト[[#This Row],[製品型番]])=0,"記載なし","") | BQ40: =IF(COUNTIFS('在庫使用計画 (計画 予測)'!C:C,マスタ_EOLリスト[[#This Row],[製品型番]])=0,"記載なし","") | BR40: =IF(COUNTIFS(在庫確認!B:B,マスタ_EOLリスト[[#This Row],[製品型番]])=0,"記載なし","") | BS40: =COUNTIF(#REF!,マスタ_EOLリスト[[#This Row],[製品型番]]) -> #REF!
A41: RL5C-R35N | B41: 4EOL(完全終息) | C41: 1GALLERIA-G | D41: RL5C-R35N | E41: 199025 | F41: 組TFH GM5AGEE(R1 15.6FHD 12450H 3050 150W L6) | G41: ID-E | H41: TFH-E-12450H-3050-L6 | I41: 15 | K41: i5-12450H | L41: 3050 | M41: 0 | N41: 0 | Q41: 2025年4-5月 | R41: Copilot key対応版 | Z41: 199024 | AA41: 組UNW GM5PD3E(R1 GG 15.6FHD 13620H 3050 180W L6) | AK41: 207658 | AL41: 45525 | AM41: 70 | AN41: 150W | AO41: 19 | AP41: 7.89 | AQ41: 5525+ | AX41: 在庫無し | BJ41: モールモデル製品準備？ | BM41: =IF(COUNTIFS('在庫使用計画 (ノート全体試算)'!C:C,マスタ_EOLリスト[[#This Row],[製品型番]])=0,"記載なし","") | BN41: =IF(COUNTIFS('在庫使用計画 (一般)'!C:C,マスタ_EOLリスト[[#This Row],[製品型番]])=0,"記載なし","") | BO41: =IF(COUNTIFS('在庫使用計画 (法人)'!C:C,マスタ_EOLリスト[[#This Row],[製品型番]])=0,"記載なし","") | BP41: =IF(COUNTIFS('在庫使用計画 (全体実績+予測）0701'!C:C,マスタ_EOLリスト[[#This Row],[製品型番]])=0,"記載なし","") | BQ41: =IF(COUNTIFS('在庫使用計画 (計画 予測)'!C:C,マスタ_EOLリスト[[#This Row],[製品型番]])=0,"記載なし","") | BR41: =IF(COUNTIFS(在庫確認!B:B,マスタ_EOLリスト[[#This Row],[製品型番]])=0,"記載なし","") | BS41: =COUNTIF(#REF!,マスタ_EOLリスト[[#This Row],[製品型番]]) -> #REF!
A42: RL5C-R35-5N | B42: 3EOL(在庫あり) | C42: 1GALLERIA-G | D42: RL5C-R35-5N | E42: 218711 | F42: 組TFH GM5PGEE(GG 15.6FHD 13420H 3050 150W L6) | G42: ID-E | H42: TFH-E-13420H-3050-L6 | I42: 15 | K42: i5-13420H | L42: 3050 | M42: 5 | N42: 5 | P42: 2025年10月頃 | Q42: 2026年2月頃 | R42: 通販モール専用モデル 500台のみ | V42: 500 | W42: 506 | Z42: 199024 | AA42: 組UNW GM5PD3E(R1 GG 15.6FHD 13620H 3050 180W L6) | AK42: 207658 | AL42: 45559 | AM42: 4 | AN42: 150W | AO42: 19 | AP42: 7.89 | AQ42: 5525+ | AW42: TRUE | AX42: 組TFH GM5PGEE(GG 15.6FHD 13420H 3050 150W | BJ42: x | BM42: =IF(COUNTIFS('在庫使用計画 (ノート全体試算)'!C:C,マスタ_EOLリスト[[#This Row],[製品型番]])=0,"記載なし","") | BN42: =IF(COUNTIFS('在庫使用計画 (一般)'!C:C,マスタ_EOLリスト[[#This Row],[製品型番]])=0,"記載なし","") | BO42: =IF(COUNTIFS('在庫使用計画 (法人)'!C:C,マスタ_EOLリスト[[#This Row],[製品型番]])=0,"記載なし","") | BP42: =IF(COUNTIFS('在庫使用計画 (全体実績+予測）0701'!C:C,マスタ_EOLリスト[[#This Row],[製品型番]])=0,"記載なし","") | BQ42: =IF(COUNTIFS('在庫使用計画 (計画 予測)'!C:C,マスタ_EOLリスト[[#This Row],[製品型番]])=0,"記載なし","") | BR42: =IF(COUNTIFS(在庫確認!B:B,マスタ_EOLリスト[[#This Row],[製品型番]])=0,"記載なし","") | BS42: =COUNTIF(#REF!,マスタ_EOLリスト[[#This Row],[製品型番]]) -> #REF!
A43: RL7C-R45-4 | B43: 4EOL(完全終息) | C43: 1GALLERIA-G | D43: RL7C-R45-4 | E43: 199319 | F43: 組CLE V545TNC(R1 GG 14QWXGA+ 155H 4050 180W L6) | G43: V54 | H43: CLE-V540-155H-4050-L6 | I43: 14 | K43: u7-155H | L43: 4050 | M43: 0 | N43: 0 | R43: Copilot key対応版,法人案件で 1000台追加 | W43: 1750 | Z43: 後継予定なし | AK43: 207651 | AL43: 45525 | AM43: 70 | AN43: 180W | AX43: 在庫無し | BA43: Galaxy Black | BB43: Black | BC43: Galaxy Black | BD43: Black | BJ43: NPC5L-R55-G5 | BM43: =IF(COUNTIFS('在庫使用計画 (ノート全体試算)'!C:C,マスタ_EOLリスト[[#This Row],[製品型番]])=0,"記載なし","") | BN43: =IF(COUNTIFS('在庫使用計画 (一般)'!C:C,マスタ_EOLリスト[[#This Row],[製品型番]])=0,"記載なし","") | BO43: =IF(COUNTIFS('在庫使用計画 (法人)'!C:C,マスタ_EOLリスト[[#This Row],[製品型番]])=0,"記載なし","") | BP43: =IF(COUNTIFS('在庫使用計画 (全体実績+予測）0701'!C:C,マスタ_EOLリスト[[#This Row],[製品型番]])=0,"記載なし","") | BQ43: =IF(COUNTIFS('在庫使用計画 (計画 予測)'!C:C,マスタ_EOLリスト[[#This Row],[製品型番]])=0,"記載なし","") | BR43: =IF(COUNTIFS(在庫確認!B:B,マスタ_EOLリスト[[#This Row],[製品型番]])=0,"記載なし","") | BS43: =COUNTIF(#REF!,マスタ_EOLリスト[[#This Row],[製品型番]]) -> #REF!
A44: RL7C-R45-4 | B44: 2発売中 | C44: 1GALLERIA-G | D44: RL7C-R45-4 | E44: 304067 | F44: 組CLE V545TNC(R2 GG 14QWXGA+ 155H 4050 180W L6) | G44: V54 | H44: CLE-V540-155H-4050-L6 | I44: 14 | K44: u7-155H | L44: 4050 | M44: 290 | N44: 290 | O44: 1/M | R44: 金沢大学案件。CLE LCD調達ミスにより4M変更。類似のV545KU-TDで使用のLCDを使用 | AW44: TRUE | AX44: 組CLE V545TNC(R2 GG 14QWXGA+ 155H 4050 18 | BJ44: NPC5L-R55-G5 | BM44: =IF(COUNTIFS('在庫使用計画 (ノート全体試算)'!C:C,マスタ_EOLリスト[[#This Row],[製品型番]])=0,"記載なし","") | BN44: =IF(COUNTIFS('在庫使用計画 (一般)'!C:C,マスタ_EOLリスト[[#This Row],[製品型番]])=0,"記載なし","") | BO44: =IF(COUNTIFS('在庫使用計画 (法人)'!C:C,マスタ_EOLリスト[[#This Row],[製品型番]])=0,"記載なし","") | BP44: =IF(COUNTIFS('在庫使用計画 (全体実績+予測）0701'!C:C,マスタ_EOLリスト[[#This Row],[製品型番]])=0,"記載なし","") | BQ44: =IF(COUNTIFS('在庫使用計画 (計画 予測)'!C:C,マスタ_EOLリスト[[#This Row],[製品型番]])=0,"記載なし","") | BR44: =IF(COUNTIFS(在庫確認!B:B,マスタ_EOLリスト[[#This Row],[製品型番]])=0,"記載なし","") | BS44: =COUNTIF(#REF!,マスタ_EOLリスト[[#This Row],[製品型番]]) -> #REF!
A45: RL7C-R45-4 | B45: 4EOL(完全終息) | C45: 1GALLERIA-G | D45: RL7C-R45-4 | E45: 193186 | F45: 組CLE V545TNC(14QWXGA+ 155H 4050 180W L6) | G45: V54 | H45: V540-155H-4050-gaming | K45: u7-155H | L45: 4050 | M45: 0 | N45: 0 | O45: 5/12 WK | P45: 45463 | Q45: 2024年5月頃 | U45: Copilot keyモデルにスライド | V45: 900 | W45: 706 | Z45: 後継予定なし | AK45: 194888 | AL45: 45435 | AM45: 450 | AN45: 180W | AX45: 在庫無し | BA45: S60 鐵灰 | BB45: S60 鐵灰 | BC45: S60 鐵灰 | BD45: S60 鐵灰 | BM45: =IF(COUNTIFS('在庫使用計画 (ノート全体試算)'!C:C,マスタ_EOLリスト[[#This Row],[製品型番]])=0,"記載なし","") | BN45: =IF(COUNTIFS('在庫使用計画 (一般)'!C:C,マスタ_EOLリスト[[#This Row],[製品型番]])=0,"記載なし","") | BO45: =IF(COUNTIFS('在庫使用計画 (法人)'!C:C,マスタ_EOLリスト[[#This Row],[製品型番]])=0,"記載なし","") | BP45: =IF(COUNTIFS('在庫使用計画 (全体実績+予測）0701'!C:C,マスタ_EOLリスト[[#This Row],[製品型番]])=0,"記載なし","") | BQ45: =IF(COUNTIFS('在庫使用計画 (計画 予測)'!C:C,マスタ_EOLリスト[[#This Row],[製品型番]])=0,"記載なし","") | BR45: =IF(COUNTIFS(在庫確認!B:B,マスタ_EOLリスト[[#This Row],[製品型番]])=0,"記載なし","") | BS45: =COUNTIF(#REF!,マスタ_EOLリスト[[#This Row],[製品型番]]) -> #REF!
A46: RL7C-R35N | B46: 4EOL(完全終息) | C46: 1GALLERIA-G | D46: RL7C-R35N | E46: 187688 | F46: 組TFH GM5AGEE(15.6FHD 12650H 3050 150W L6) | G46: ID-E | H46: TFH-E-12650H-3050-L6 | K46: i7-12650H | L46: 3050 | M46: 0 | N46: 0 | P46: 45267 | Q46: 2024年5月頃 | V46: 3600 | W46: 2160 | Z46: 193184 | AA46: 組UNW GM5PD3E(15.6FHD 13620H 3050 180W L6 | AC46: 2024年3月～4月 同ID 12650→13620 | AH46: ID変化なし | AL46: 45471 | AM46: 80 | AN46: 150W | AO46: 19 | AP46: 7.89 | AQ46: 5525+ | AX46: 在庫無し | BA46: S60 鐵灰 | BB46: S60 鐵灰 | BC46: S60 鐵灰 | BD46: S60 鐵灰 | BM46: =IF(COUNTIFS('在庫使用計画 (ノート全体試算)'!C:C,マスタ_EOLリスト[[#This Row],[製品型番]])=0,"記載なし","") | BN46: =IF(COUNTIFS('在庫使用計画 (一般)'!C:C,マスタ_EOLリスト[[#This Row],[製品型番]])=0,"記載なし","") -> 記載なし | BO46: =IF(COUNTIFS('在庫使用計画 (法人)'!C:C,マスタ_EOLリスト[[#This Row],[製品型番]])=0,"記載なし","") | BP46: =IF(COUNTIFS('在庫使用計画 (全体実績+予測）0701'!C:C,マスタ_EOLリスト[[#This Row],[製品型番]])=0,"記載なし","") | BQ46: =IF(COUNTIFS('在庫使用計画 (計画 予測)'!C:C,マスタ_EOLリスト[[#This Row],[製品型番]])=0,"記載なし","") -> 記載なし | BR46: =IF(COUNTIFS(在庫確認!B:B,マスタ_EOLリスト[[#This Row],[製品型番]])=0,"記載なし","") | BS46: =COUNTIF(#REF!,マスタ_EOLリスト[[#This Row],[製品型番]]) -> #REF!
A47: RL7C-R35-5N | B47: 4EOL(完全終息) | C47: 1GALLERIA-G | D47: RL7C-R35-5N | E47: 193184 | F47: 組UNW GM5PD3E(15.6FHD 13620H 3050 180W L6) | G47: ID-E | H47: ID-E-13620H-3050-gaming | K47: i7-13620H | L47: 3050 | M47: 0 | N47: 0 | O47: 3/31 WK | P47: 45428 | Q47: 2025年6月頃 | U47: Copilot keyモデルにスライド | V47: 3000 | W47: 3576 | Z47: 199024 | AA47: 組UNW GM5PD3E(R1 GG 15.6FHD 13620H 3050 180W L6) | AK47: 194885 | AL47: 45435 | AM47: 450 | AX47: 在庫無し | BA47: Light Gray | BB47: Black | BC47: Light Gray | BD47: Light Gray | BM47: =IF(COUNTIFS('在庫使用計画 (ノート全体試算)'!C:C,マスタ_EOLリスト[[#This Row],[製品型番]])=0,"記載なし","") | BN47: =IF(COUNTIFS('在庫使用計画 (一般)'!C:C,マスタ_EOLリスト[[#This Row],[製品型番]])=0,"記載なし","") | BO47: =IF(COUNTIFS('在庫使用計画 (法人)'!C:C,マスタ_EOLリスト[[#This Row],[製品型番]])=0,"記載なし","") | BP47: =IF(COUNTIFS('在庫使用計画 (全体実績+予測）0701'!C:C,マスタ_EOLリスト[[#This Row],[製品型番]])=0,"記載なし","") | BQ47: =IF(COUNTIFS('在庫使用計画 (計画 予測)'!C:C,マスタ_EOLリスト[[#This Row],[製品型番]])=0,"記載なし","") | BR47: =IF(COUNTIFS(在庫確認!B:B,マスタ_EOLリスト[[#This Row],[製品型番]])=0,"記載なし","") | BS47: =COUNTIF(#REF!,マスタ_EOLリスト[[#This Row],[製品型番]]) -> #REF!
A48: RL7C-R35-5N | B48: 4EOL(完全終息) | C48: 1GALLERIA-G | D48: RL7C-R35-5N | E48: 193184 | F48: 組UNW GM5PD3E(15.6FHD 13620H 3050 180W L6 | G48: ID-E | H48: ID-E-13620H-3050-gaming | K48: i7-13620H | L48: 3050 | M48: 0 | N48: 0 | W48: 3576 | AN48: 180W | AX48: 在庫無し | BA48: Light Gray | BB48: Black | BC48: Light Gray | BD48: Light Gray | BM48: =IF(COUNTIFS('在庫使用計画 (ノート全体試算)'!C:C,マスタ_EOLリスト[[#This Row],[製品型番]])=0,"記載なし","") | BN48: =IF(COUNTIFS('在庫使用計画 (一般)'!C:C,マスタ_EOLリスト[[#This Row],[製品型番]])=0,"記載なし","") | BO48: =IF(COUNTIFS('在庫使用計画 (法人)'!C:C,マスタ_EOLリスト[[#This Row],[製品型番]])=0,"記載なし","") | BP48: =IF(COUNTIFS('在庫使用計画 (全体実績+予測）0701'!C:C,マスタ_EOLリスト[[#This Row],[製品型番]])=0,"記載なし","") | BQ48: =IF(COUNTIFS('在庫使用計画 (計画 予測)'!C:C,マスタ_EOLリスト[[#This Row],[製品型番]])=0,"記載なし","") | BR48: =IF(COUNTIFS(在庫確認!B:B,マスタ_EOLリスト[[#This Row],[製品型番]])=0,"記載なし","") | BS48: =COUNTIF(#REF!,マスタ_EOLリスト[[#This Row],[製品型番]]) -> #REF!
A49: RL5R-G165 | B49: 4EOL(完全終息) | C49: 1GALLERIA-G | D49: RL5R-G165 | E49: 179164 | F49: 組TFH GM5RG1E(15FHD 6600H 1650 120W L9) | G49: ID-E | H49: TFH-E-6600H-1650-L9 | K49: R5-6600H | L49: 1650 | M49: 0 | N49: 0 | P49: 45056 | R49: 計画下方修正 | U49: 10/21 法人確保分のため対応不可 | V49: 16830 | W49: 6420 | X49: 672 | Z49: 187577 | AA49: 組TFH GM5AGEE(15.6FHD 12450H 3050 150W L6) | AI49: 199025 | AJ49: CPU,GPUともに上位に変更 | AN49: 120W | AX49: 在庫無し | BA49: Light Gray | BB49: Black | BC49: Light Gray | BD49: Light Gray | BM49: =IF(COUNTIFS('在庫使用計画 (ノート全体試算)'!C:C,マスタ_EOLリスト[[#This Row],[製品型番]])=0,"記載なし","") | BN49: =IF(COUNTIFS('在庫使用計画 (一般)'!C:C,マスタ_EOLリスト[[#This Row],[製品型番]])=0,"記載なし","") | BO49: =IF(COUNTIFS('在庫使用計画 (法人)'!C:C,マスタ_EOLリスト[[#This Row],[製品型番]])=0,"記載なし","") | BP49: =IF(COUNTIFS('在庫使用計画 (全体実績+予測）0701'!C:C,マスタ_EOLリスト[[#This Row],[製品型番]])=0,"記載なし","") | BQ49: =IF(COUNTIFS('在庫使用計画 (計画 予測)'!C:C,マスタ_EOLリスト[[#This Row],[製品型番]])=0,"記載なし","") -> 記載なし | BR49: =IF(COUNTIFS(在庫確認!B:B,マスタ_EOLリスト[[#This Row],[製品型番]])=0,"記載なし","") | BS49: =COUNTIF(#REF!,マスタ_EOLリスト[[#This Row],[製品型番]]) -> #REF!
A50: RL5C-R35N | B50: 4EOL(完全終息) | C50: 1GALLERIA-G | D50: RL5C-R35N | E50: 187577 | F50: 組TFH GM5AGEE(15.6FHD 12450H 3050 150W L6) | G50: ID-E | H50: TFH-E-12450H-3050-L6 | K50: i5-12450H | L50: 3050 | M50: 0 | N50: 0 | P50: 45267 | Q50: 在庫限り↓にスライド | U50: Copilot keyモデルにスライド | V50: 12800 | W50: 3720 | Z50: 199025 | AA50: 組TFH GM5AGEE(R1 15.6FHD 12450H 3050 150W L6) | AC50: 2024年3月～4月 同ID 12650→13620 | AH50: ID変化なし | AK50: 188473 | AL50: 45435 | AM50: 500 | AN50: 150W | AO50: 19 | AP50: 7.89 | AQ50: 5525+ | AX50: 在庫無し | BM50: =IF(COUNTIFS('在庫使用計画 (ノート全体試算)'!C:C,マスタ_EOLリスト[[#This Row],[製品型番]])=0,"記載なし","") | BN50: =IF(COUNTIFS('在庫使用計画 (一般)'!C:C,マスタ_EOLリスト[[#This Row],[製品型番]])=0,"記載なし","") | BO50: =IF(COUNTIFS('在庫使用計画 (法人)'!C:C,マスタ_EOLリスト[[#This Row],[製品型番]])=0,"記載なし","") | BP50: =IF(COUNTIFS('在庫使用計画 (全体実績+予測）0701'!C:C,マスタ_EOLリスト[[#This Row],[製品型番]])=0,"記載なし","") | BQ50: =IF(COUNTIFS('在庫使用計画 (計画 予測)'!C:C,マスタ_EOLリスト[[#This Row],[製品型番]])=0,"記載なし","") | BR50: =IF(COUNTIFS(在庫確認!B:B,マスタ_EOLリスト[[#This Row],[製品型番]])=0,"記載なし","") | BS50: =COUNTIF(#REF!,マスタ_EOLリスト[[#This Row],[製品型番]]) -> #REF!
A51: NPR7L-R55-G5 | B51: 1新規(発売前) | C51: 1GALLERIA-G | D51: NPR7L-R55-G5 | G51: ID-2 | H51: UNW-ID2 | I51: 15 | L51: 5050 | M51: 0 | N51: 0 | AX51: 在庫無し | BJ51: x | BM51: =IF(COUNTIFS('在庫使用計画 (ノート全体試算)'!C:C,マスタ_EOLリスト[[#This Row],[製品型番]])=0,"記載なし","") | BN51: =IF(COUNTIFS('在庫使用計画 (一般)'!C:C,マスタ_EOLリスト[[#This Row],[製品型番]])=0,"記載なし","") | BO51: =IF(COUNTIFS('在庫使用計画 (法人)'!C:C,マスタ_EOLリスト[[#This Row],[製品型番]])=0,"記載なし","") | BP51: =IF(COUNTIFS('在庫使用計画 (全体実績+予測）0701'!C:C,マスタ_EOLリスト[[#This Row],[製品型番]])=0,"記載なし","") | BQ51: =IF(COUNTIFS('在庫使用計画 (計画 予測)'!C:C,マスタ_EOLリスト[[#This Row],[製品型番]])=0,"記載なし","") | BR51: =IF(COUNTIFS(在庫確認!B:B,マスタ_EOLリスト[[#This Row],[製品型番]])=0,"記載なし","") -> 記載なし | BS51: =COUNTIF(#REF!,マスタ_EOLリスト[[#This Row],[製品型番]]) -> #REF!
A52: NPC7L-R57-G5 | B52: 1新規(発売前) | C52: 1GALLERIA-G | D52: NPC7L-R57-G5 | G52: ID-2 | H52: UNW-2-14650HX-5070-L6-DDR5-15.3 | I52: 15 | L52: 5070 | M52: 0 | N52: 0 | AX52: 在庫無し | BJ52: x | BM52: =IF(COUNTIFS('在庫使用計画 (ノート全体試算)'!C:C,マスタ_EOLリスト[[#This Row],[製品型番]])=0,"記載なし","") | BN52: =IF(COUNTIFS('在庫使用計画 (一般)'!C:C,マスタ_EOLリスト[[#This Row],[製品型番]])=0,"記載なし","") | BO52: =IF(COUNTIFS('在庫使用計画 (法人)'!C:C,マスタ_EOLリスト[[#This Row],[製品型番]])=0,"記載なし","") | BP52: =IF(COUNTIFS('在庫使用計画 (全体実績+予測）0701'!C:C,マスタ_EOLリスト[[#This Row],[製品型番]])=0,"記載なし","") | BQ52: =IF(COUNTIFS('在庫使用計画 (計画 予測)'!C:C,マスタ_EOLリスト[[#This Row],[製品型番]])=0,"記載なし","") | BR52: =IF(COUNTIFS(在庫確認!B:B,マスタ_EOLリスト[[#This Row],[製品型番]])=0,"記載なし","") -> 記載なし | BS52: =COUNTIF(#REF!,マスタ_EOLリスト[[#This Row],[製品型番]]) -> #REF!
A53: NPC7L-R56-G5 | B53: 1新規(発売前) | C53: 1GALLERIA-G | D53: NPC7L-R56-G5 | E53: 353328 | F53: 組UNW X5RP5562(GG 15.3WUXGA 14650HX 5060 210W L6) | G53: ID-2 | H53: UNW-2-14650HX-5060-L6-DDR5-15.3 | I53: 15 | L53: 5060 | M53: 0 | N53: 1355 | AW53: TRUE | AX53: 在庫無し | BJ53: x | BM53: =IF(COUNTIFS('在庫使用計画 (ノート全体試算)'!C:C,マスタ_EOLリスト[[#This Row],[製品型番]])=0,"記載なし","") | BN53: =IF(COUNTIFS('在庫使用計画 (一般)'!C:C,マスタ_EOLリスト[[#This Row],[製品型番]])=0,"記載なし","") | BO53: =IF(COUNTIFS('在庫使用計画 (法人)'!C:C,マスタ_EOLリスト[[#This Row],[製品型番]])=0,"記載なし","") | BP53: =IF(COUNTIFS('在庫使用計画 (全体実績+予測）0701'!C:C,マスタ_EOLリスト[[#This Row],[製品型番]])=0,"記載なし","") | BQ53: =IF(COUNTIFS('在庫使用計画 (計画 予測)'!C:C,マスタ_EOLリスト[[#This Row],[製品型番]])=0,"記載なし","") | BR53: =IF(COUNTIFS(在庫確認!B:B,マスタ_EOLリスト[[#This Row],[製品型番]])=0,"記載なし","") -> 記載なし | BS53: =COUNTIF(#REF!,マスタ_EOLリスト[[#This Row],[製品型番]]) -> #REF!
A54: NPC5L-R55-G5 | B54: 1新規(発売前) | C54: 1GALLERIA-G | D54: NPC5L-R55-G5 | E54: 353329 | F54: 組UNW M5RP555E(GG 15.6FHD 14450HX 5050 230W L6) | G54: ID-E | H54: UNW-E-14450HX-5050-L6-DDR5-15.6 | I54: 15 | L54: 5050 | M54: 0 | N54: 1805 | AW54: TRUE | AX54: 在庫無し | BJ54: x | BM54: =IF(COUNTIFS('在庫使用計画 (ノート全体試算)'!C:C,マスタ_EOLリスト[[#This Row],[製品型番]])=0,"記載なし","") | BN54: =IF(COUNTIFS('在庫使用計画 (一般)'!C:C,マスタ_EOLリスト[[#This Row],[製品型番]])=0,"記載なし","") | BO54: =IF(COUNTIFS('在庫使用計画 (法人)'!C:C,マスタ_EOLリスト[[#This Row],[製品型番]])=0,"記載なし","") | BP54: =IF(COUNTIFS('在庫使用計画 (全体実績+予測）0701'!C:C,マスタ_EOLリスト[[#This Row],[製品型番]])=0,"記載なし","") | BQ54: =IF(COUNTIFS('在庫使用計画 (計画 予測)'!C:C,マスタ_EOLリスト[[#This Row],[製品型番]])=0,"記載なし","") | BR54: =IF(COUNTIFS(在庫確認!B:B,マスタ_EOLリスト[[#This Row],[製品型番]])=0,"記載なし","") -> 記載なし | BS54: =COUNTIF(#REF!,マスタ_EOLリスト[[#This Row],[製品型番]]) -> #REF!
A55: RM7C-R45 | B55: 4EOL(完全終息) | C55: 1GALLERIA-G | D55: RM7C-R45 | E55: 185107 | F55: 組CLE NV45RNC-TD(14FHD 13700H 4050 180W L6) | G55: NV45 | H55: CLE-NV45-13700H-4050-L6 | K55: i7-13700H | L55: 4050 | M55: 0 | N55: 0 | P55: 45246 | Q55: 2024年5月頃 | W55: 900 | Z55: なし | AB55: なし | AH55: 後継IDは変更 →V54 | AL55: 45471 | AM55: 80 | AX55: 在庫無し | BM55: =IF(COUNTIFS('在庫使用計画 (ノート全体試算)'!C:C,マスタ_EOLリスト[[#This Row],[製品型番]])=0,"記載なし","") | BN55: =IF(COUNTIFS('在庫使用計画 (一般)'!C:C,マスタ_EOLリスト[[#This Row],[製品型番]])=0,"記載なし","") -> 記載なし | BO55: =IF(COUNTIFS('在庫使用計画 (法人)'!C:C,マスタ_EOLリスト[[#This Row],[製品型番]])=0,"記載なし","") | BP55: =IF(COUNTIFS('在庫使用計画 (全体実績+予測）0701'!C:C,マスタ_EOLリスト[[#This Row],[製品型番]])=0,"記載なし","") | BQ55: =IF(COUNTIFS('在庫使用計画 (計画 予測)'!C:C,マスタ_EOLリスト[[#This Row],[製品型番]])=0,"記載なし","") -> 記載なし | BR55: =IF(COUNTIFS(在庫確認!B:B,マスタ_EOLリスト[[#This Row],[製品型番]])=0,"記載なし","") -> 記載なし | BS55: =COUNTIF(#REF!,マスタ_EOLリスト[[#This Row],[製品型番]]) -> #REF!
A56: UL9C-R49-C6 | B56: 4EOL(完全終息) | C56: 2GALLERIA-C | D56: UL9C-R49-C6 | E56: 199018 | F56: 組UNW GM6IX9B(R1 16 3K 14900HX 4090 280W L6) | G56: ID-B | H56: ID-B 14900HX-4090-creator-L6 | I56: 16 | K56: i9-14900HX | L56: 4090 | M56: 0 | N56: 0 | R56: Copilot key対応版 | Z56: 212347 | AC56: 3月 18”モデルが性能後継 | AK56: 207655 | AL56: 45525 | AM56: 70 | AN56: 280W | AX56: 在庫無し | BA56: Ink Stone Black | BB56: Ink Stone Black | BC56: Ink Stone Black | BD56: Ink Stone Black | BM56: =IF(COUNTIFS('在庫使用計画 (ノート全体試算)'!C:C,マスタ_EOLリスト[[#This Row],[製品型番]])=0,"記載なし","") | BN56: =IF(COUNTIFS('在庫使用計画 (一般)'!C:C,マスタ_EOLリスト[[#This Row],[製品型番]])=0,"記載なし","") -> 記載なし | BO56: =IF(COUNTIFS('在庫使用計画 (法人)'!C:C,マスタ_EOLリスト[[#This Row],[製品型番]])=0,"記載なし","") | BP56: =IF(COUNTIFS('在庫使用計画 (全体実績+予測）0701'!C:C,マスタ_EOLリスト[[#This Row],[製品型番]])=0,"記載なし","") | BQ56: =IF(COUNTIFS('在庫使用計画 (計画 予測)'!C:C,マスタ_EOLリスト[[#This Row],[製品型番]])=0,"記載なし","") -> 記載なし | BR56: =IF(COUNTIFS(在庫確認!B:B,マスタ_EOLリスト[[#This Row],[製品型番]])=0,"記載なし","") | BS56: =COUNTIF(#REF!,マスタ_EOLリスト[[#This Row],[製品型番]]) -> #REF!
A57: UL9C-R49-C6 | B57: 4EOL(完全終息) | C57: 2GALLERIA-C | D57: UL9C-R49-C6 | E57: 193190 | F57: 組UNW GM6IX9B(16 3K 14900HX 4090 280W L6) | G57: ID-B | H57: ID-B 14900HX-4090-creator-L6 | K57: i9-14900HX | L57: 4090 | M57: 0 | N57: 0 | P57: 45428 | Q57: 2024年5月頃 | U57: Copilot keyモデルにスライド | V57: 150 | W57: 146 | AK57: 194884 | AL57: 45519 | AM57: 10 | AN57: 280W | AX57: 在庫無し | BA57: Ink Stone Black | BB57: Ink Stone Black | BC57: Ink Stone Black | BD57: Ink Stone Black | BM57: =IF(COUNTIFS('在庫使用計画 (ノート全体試算)'!C:C,マスタ_EOLリスト[[#This Row],[製品型番]])=0,"記載なし","") | BN57: =IF(COUNTIFS('在庫使用計画 (一般)'!C:C,マスタ_EOLリスト[[#This Row],[製品型番]])=0,"記載なし","") -> 記載なし | BO57: =IF(COUNTIFS('在庫使用計画 (法人)'!C:C,マスタ_EOLリスト[[#This Row],[製品型番]])=0,"記載なし","") | BP57: =IF(COUNTIFS('在庫使用計画 (全体実績+予測）0701'!C:C,マスタ_EOLリスト[[#This Row],[製品型番]])=0,"記載なし","") | BQ57: =IF(COUNTIFS('在庫使用計画 (計画 予測)'!C:C,マスタ_EOLリスト[[#This Row],[製品型番]])=0,"記載なし","") -> 記載なし | BR57: =IF(COUNTIFS(在庫確認!B:B,マスタ_EOLリスト[[#This Row],[製品型番]])=0,"記載なし","") | BS57: =COUNTIF(#REF!,マスタ_EOLリスト[[#This Row],[製品型番]]) -> #REF!
A58: ZL9C-R57-C7 | B58: 2発売中 | C58: 2GALLERIA-C | D58: ZL9C-R57-C7 | E58: 216518 | F58: 組CLE V370SNPQ(GC 17.3QHD 14900HX 5070 180W L6) | G58: V37 | H58: CLE-V37-14900HX-5070-L6 Creator | I58: 17 | K58: i9-14900HX | L58: 5070 | M58: 38 | N58: 38 | O58: 2025年4月末 | P58: 45832 | W58: 926 | AN58: 180W | AU58: 65W-100W | AW58: TRUE | AX58: 組CLE V370SNPQ(GC 17.3QHD 14900HX 5070 18 | AY58: 115 | BA58: S10S 鐵灰 | BB58: S60 鐵灰 | BC58: S60 鐵灰 | BD58: S60 鐵灰 | BJ58: x | BM58: =IF(COUNTIFS('在庫使用計画 (ノート全体試算)'!C:C,マスタ_EOLリスト[[#This Row],[製品型番]])=0,"記載なし","") | BN58: =IF(COUNTIFS('在庫使用計画 (一般)'!C:C,マスタ_EOLリスト[[#This Row],[製品型番]])=0,"記載なし","") | BO58: =IF(COUNTIFS('在庫使用計画 (法人)'!C:C,マスタ_EOLリスト[[#This Row],[製品型番]])=0,"記載なし","") | BP58: =IF(COUNTIFS('在庫使用計画 (全体実績+予測）0701'!C:C,マスタ_EOLリスト[[#This Row],[製品型番]])=0,"記載なし","") | BQ58: =IF(COUNTIFS('在庫使用計画 (計画 予測)'!C:C,マスタ_EOLリスト[[#This Row],[製品型番]])=0,"記載なし","") | BR58: =IF(COUNTIFS(在庫確認!B:B,マスタ_EOLリスト[[#This Row],[製品型番]])=0,"記載なし","") | BS58: =COUNTIF(#REF!,マスタ_EOLリスト[[#This Row],[製品型番]]) -> #REF!
A59: ZL9C-R57-C7 | B59: 2発売中 | C59: 2GALLERIA-C | D59: ZL9C-R57-C7 | E59: 362644 | F59: 組CLE V370SNPQ(R1 GC 17.3QHD 14900HX 5070 180W L6) | G59: V37 | H59: CLE-V37-14900HX-5070-L6 Creator | I59: 17 | K59: i9-14900HX | L59: 5070 | M59: 0 | N59: 90 | AW59: TRUE | AX59: 在庫無し | BJ59: x | BM59: =IF(COUNTIFS('在庫使用計画 (ノート全体試算)'!C:C,マスタ_EOLリスト[[#This Row],[製品型番]])=0,"記載なし","") | BN59: =IF(COUNTIFS('在庫使用計画 (一般)'!C:C,マスタ_EOLリスト[[#This Row],[製品型番]])=0,"記載なし","") | BO59: =IF(COUNTIFS('在庫使用計画 (法人)'!C:C,マスタ_EOLリスト[[#This Row],[製品型番]])=0,"記載なし","") | BP59: =IF(COUNTIFS('在庫使用計画 (全体実績+予測）0701'!C:C,マスタ_EOLリスト[[#This Row],[製品型番]])=0,"記載なし","") | BQ59: =IF(COUNTIFS('在庫使用計画 (計画 予測)'!C:C,マスタ_EOLリスト[[#This Row],[製品型番]])=0,"記載なし","") | BR59: =IF(COUNTIFS(在庫確認!B:B,マスタ_EOLリスト[[#This Row],[製品型番]])=0,"記載なし","") | BS59: =COUNTIF(#REF!,マスタ_EOLリスト[[#This Row],[製品型番]]) -> #REF!
A60: ZL9C-R47-C7 | B60: 4EOL(完全終息) | C60: 2GALLERIA-C | D60: ZL9C-R47-C7 | E60: 193188 | F60: 組CLE PD71SNE-D(17.3UHD 14900HX 4070 280W L6) | G60: PD71 | H60: PD71-14900HX-4070-creator | K60: i9-14900HX | L60: 4070 | M60: 0 | N60: 0 | O60: 3/24 WK | P60: 45428 | Q60: 2024年5月頃 | V60: 280 | W60: 386 | Z60: 216518 | AA60: ZL9C-R57-C7 | AL60: 45519 | AM60: 10 | AN60: 280W | AQ60: 特殊 | AX60: 在庫無し | BA60: Ink Stone Black | BB60: Ink Stone Black | BC60: Ink Stone Black | BD60: Ink Stone Black | BM60: =IF(COUNTIFS('在庫使用計画 (ノート全体試算)'!C:C,マスタ_EOLリスト[[#This Row],[製品型番]])=0,"記載なし","") | BN60: =IF(COUNTIFS('在庫使用計画 (一般)'!C:C,マスタ_EOLリスト[[#This Row],[製品型番]])=0,"記載なし","") -> 記載なし | BO60: =IF(COUNTIFS('在庫使用計画 (法人)'!C:C,マスタ_EOLリスト[[#This Row],[製品型番]])=0,"記載なし","") | BP60: =IF(COUNTIFS('在庫使用計画 (全体実績+予測）0701'!C:C,マスタ_EOLリスト[[#This Row],[製品型番]])=0,"記載なし","") | BQ60: =IF(COUNTIFS('在庫使用計画 (計画 予測)'!C:C,マスタ_EOLリスト[[#This Row],[製品型番]])=0,"記載なし","") -> 記載なし | BR60: =IF(COUNTIFS(在庫確認!B:B,マスタ_EOLリスト[[#This Row],[製品型番]])=0,"記載なし","") | BS60: =COUNTIF(#REF!,マスタ_EOLリスト[[#This Row],[製品型番]]) -> #REF!
A61: XL7C-R56-C6A | B61: 2発売中 | C61: 2GALLERIA-C | D61: XL7C-R56-C6A | E61: 220827 | F61: 組MSH 15F5(GC 16WQXGA 255H 5060 240W L6) | G61: 15F5 | H61: MSH-15F5-255H-5060-L6 Creator | I61: 16 | K61: u7-255HX | L61: 5060 | M61: 20 | N61: 20 | P61: 2025年10月頃 | W61: 1000 | AW61: TRUE | AX61: 組MSH 15F5(GC 16WQXGA 255H 5060 240W L6) | AY61: 105 | BA61: S17S 暮石灰 | BB61: S17S 暮石灰 | BC61: S17S 暮石灰 | BD61: S17S 暮石灰 | BJ61: x | BM61: =IF(COUNTIFS('在庫使用計画 (ノート全体試算)'!C:C,マスタ_EOLリスト[[#This Row],[製品型番]])=0,"記載なし","") | BN61: =IF(COUNTIFS('在庫使用計画 (一般)'!C:C,マスタ_EOLリスト[[#This Row],[製品型番]])=0,"記載なし","") | BO61: =IF(COUNTIFS('在庫使用計画 (法人)'!C:C,マスタ_EOLリスト[[#This Row],[製品型番]])=0,"記載なし","") | BP61: =IF(COUNTIFS('在庫使用計画 (全体実績+予測）0701'!C:C,マスタ_EOLリスト[[#This Row],[製品型番]])=0,"記載なし","") | BQ61: =IF(COUNTIFS('在庫使用計画 (計画 予測)'!C:C,マスタ_EOLリスト[[#This Row],[製品型番]])=0,"記載なし","") | BR61: =IF(COUNTIFS(在庫確認!B:B,マスタ_EOLリスト[[#This Row],[製品型番]])=0,"記載なし","") | BS61: =COUNTIF(#REF!,マスタ_EOLリスト[[#This Row],[製品型番]]) -> #REF!
A62: XL7C-R46H-C6 | B62: 4EOL(完全終息) | C62: 2GALLERIA-C | D62: XL7C-R46H-C6 | E62: 189152 | F62: 組UNW PH6PG02(GC 16WQXGA 13700H 4060 150W L6) | G62: 6H2 | H62: UNW-6H2-13700H-4060-L6-WQXGA | K62: i7-13700H | L62: 4060 | M62: 0 | N62: 0 | P62: 45449 | V62: 400 | W62: 400 | AL62: 45478 | AM62: 150 | AN62: 150W | AO62: 19 | AP62: 7.89 | AQ62: 5525+ | AX62: 在庫無し | BA62: Ink Stone Black | BB62: Ink Stone Black | BC62: Ink Stone Black | BD62: Ink Stone Black | BM62: =IF(COUNTIFS('在庫使用計画 (ノート全体試算)'!C:C,マスタ_EOLリスト[[#This Row],[製品型番]])=0,"記載なし","") | BN62: =IF(COUNTIFS('在庫使用計画 (一般)'!C:C,マスタ_EOLリスト[[#This Row],[製品型番]])=0,"記載なし","") -> 記載なし | BO62: =IF(COUNTIFS('在庫使用計画 (法人)'!C:C,マスタ_EOLリスト[[#This Row],[製品型番]])=0,"記載なし","") | BP62: =IF(COUNTIFS('在庫使用計画 (全体実績+予測）0701'!C:C,マスタ_EOLリスト[[#This Row],[製品型番]])=0,"記載なし","") | BQ62: =IF(COUNTIFS('在庫使用計画 (計画 予測)'!C:C,マスタ_EOLリスト[[#This Row],[製品型番]])=0,"記載なし","") -> 記載なし | BR62: =IF(COUNTIFS(在庫確認!B:B,マスタ_EOLリスト[[#This Row],[製品型番]])=0,"記載なし","") | BS62: =COUNTIF(#REF!,マスタ_EOLリスト[[#This Row],[製品型番]]) -> #REF!
A63: NDR9L-R56-C6 | B63: 2発売中 | C63: 2GALLERIA-C | D63: NDR9L-R56-C6 | E63: 295634 | F63: 組CLE V561GNN-TD(GC 16WQUXGA HX470 5060 180WL6TPM) | G63: V56 | H63: CLE-V56-AI9-470-5060-L6 Creator | I63: 16 | J63: 必須 | K63: R AI9 HX470 | L63: 5060 | M63: 348 | N63: 348 | P63: 46044 | R63: 1/13受注開始、納期2w | W63: 200 | AW63: TRUE | AX63: 組CLE V561GNN-TD(GC 16WQUXGA HX470 5060 1 | AY63: 115 | BA63: Ink Stone Black | BB63: Ink Stone Black | BC63: Ink Stone Black | BD63: Ink Stone Black | BJ63: x | BM63: =IF(COUNTIFS('在庫使用計画 (ノート全体試算)'!C:C,マスタ_EOLリスト[[#This Row],[製品型番]])=0,"記載なし","") | BN63: =IF(COUNTIFS('在庫使用計画 (一般)'!C:C,マスタ_EOLリスト[[#This Row],[製品型番]])=0,"記載なし","") | BO63: =IF(COUNTIFS('在庫使用計画 (法人)'!C:C,マスタ_EOLリスト[[#This Row],[製品型番]])=0,"記載なし","") | BP63: =IF(COUNTIFS('在庫使用計画 (全体実績+予測）0701'!C:C,マスタ_EOLリスト[[#This Row],[製品型番]])=0,"記載なし","") | BQ63: =IF(COUNTIFS('在庫使用計画 (計画 予測)'!C:C,マスタ_EOLリスト[[#This Row],[製品型番]])=0,"記載なし","") | BR63: =IF(COUNTIFS(在庫確認!B:B,マスタ_EOLリスト[[#This Row],[製品型番]])=0,"記載なし","") | BS63: =COUNTIF(#REF!,マスタ_EOLリスト[[#This Row],[製品型番]]) -> #REF!
A64: #N/A | B64: 1新規(発売前) | C64: 2GALLERIA-C | D64: NDC7L-R57Z-C6 | H64: BYD- | I64: 16 | M64: 0 | N64: 0 | AX64: 在庫無し | BJ64: x | BM64: =IF(COUNTIFS('在庫使用計画 (ノート全体試算)'!C:C,マスタ_EOLリスト[[#This Row],[製品型番]])=0,"記載なし","") -> 記載なし | BN64: =IF(COUNTIFS('在庫使用計画 (一般)'!C:C,マスタ_EOLリスト[[#This Row],[製品型番]])=0,"記載なし","") -> 記載なし | BO64: =IF(COUNTIFS('在庫使用計画 (法人)'!C:C,マスタ_EOLリスト[[#This Row],[製品型番]])=0,"記載なし","") -> 記載なし | BP64: =IF(COUNTIFS('在庫使用計画 (全体実績+予測）0701'!C:C,マスタ_EOLリスト[[#This Row],[製品型番]])=0,"記載なし","") -> 記載なし | BQ64: =IF(COUNTIFS('在庫使用計画 (計画 予測)'!C:C,マスタ_EOLリスト[[#This Row],[製品型番]])=0,"記載なし","") | BR64: =IF(COUNTIFS(在庫確認!B:B,マスタ_EOLリスト[[#This Row],[製品型番]])=0,"記載なし","") -> 記載なし | BS64: =COUNTIF(#REF!,マスタ_EOLリスト[[#This Row],[製品型番]]) -> #REF!
A65: NDR9L-IG-C4 | B65: 2発売中 | C65: 2GALLERIA-C | D65: NDR9L-IG-C4 | E65: 295632 | F65: 組CLE V545GU-TD(GC 14QWXGA+ HX470 UMA 90WL6TPM) | G65: V54 | H65: CLE-V54-AI9-470-UMA-L6 Creator | I65: 14 | J65: 必須 | K65: R AI9 HX470 | L65: UMA | M65: 420 | N65: 420 | P65: 46044 | R65: 1/13受注開始、納期2w | W65: 250 | AN65: 90W | AO65: 19 | AQ65: 5517+ | AW65: TRUE | AX65: 組CLE V545GU-TD(GC 14QWXGA+ HX470 UMA 90W | BA65: Titanium Grey | BB65: Black | BC65: Titanium Grey | BD65: Titanium Grey | BJ65: x | BM65: =IF(COUNTIFS('在庫使用計画 (ノート全体試算)'!C:C,マスタ_EOLリスト[[#This Row],[製品型番]])=0,"記載なし","") | BN65: =IF(COUNTIFS('在庫使用計画 (一般)'!C:C,マスタ_EOLリスト[[#This Row],[製品型番]])=0,"記載なし","") | BO65: =IF(COUNTIFS('在庫使用計画 (法人)'!C:C,マスタ_EOLリスト[[#This Row],[製品型番]])=0,"記載なし","") | BP65: =IF(COUNTIFS('在庫使用計画 (全体実績+予測）0701'!C:C,マスタ_EOLリスト[[#This Row],[製品型番]])=0,"記載なし","") | BQ65: =IF(COUNTIFS('在庫使用計画 (計画 予測)'!C:C,マスタ_EOLリスト[[#This Row],[製品型番]])=0,"記載なし","") | BR65: =IF(COUNTIFS(在庫確認!B:B,マスタ_EOLリスト[[#This Row],[製品型番]])=0,"記載なし","") -> 記載なし | BS65: =COUNTIF(#REF!,マスタ_EOLリスト[[#This Row],[製品型番]]) -> #REF!
A66: NDR9L-IG-C4 | B66: 2発売中 | C66: 2GALLERIA-C | D66: NDR9L-IG-C4 | E66: 367381 | F66: 組CLE V545GU-TD(R1GC 14QWXGA+ HX470 UMA 90W L6) | G66: V54 | H66: CLE-V54-AI9-470-UMA-L6 Creator | I66: 14 | J66: 必須 | K66: R AI9 HX470 | L66: UMA | M66: 0 | N66: 0 | P66: 46044 | R66: 1/13受注開始、納期2w | W66: 0 | AN66: 90W | AO66: 19 | AQ66: 5517+ | AW66: TRUE | AX66: 在庫無し | BA66: Titanium Grey | BB66: Black | BC66: Titanium Grey | BD66: Titanium Grey | BJ66: x | BM66: =IF(COUNTIFS('在庫使用計画 (ノート全体試算)'!C:C,マスタ_EOLリスト[[#This Row],[製品型番]])=0,"記載なし","") | BN66: =IF(COUNTIFS('在庫使用計画 (一般)'!C:C,マスタ_EOLリスト[[#This Row],[製品型番]])=0,"記載なし","") | BO66: =IF(COUNTIFS('在庫使用計画 (法人)'!C:C,マスタ_EOLリスト[[#This Row],[製品型番]])=0,"記載なし","") | BP66: =IF(COUNTIFS('在庫使用計画 (全体実績+予測）0701'!C:C,マスタ_EOLリスト[[#This Row],[製品型番]])=0,"記載なし","") | BQ66: =IF(COUNTIFS('在庫使用計画 (計画 予測)'!C:C,マスタ_EOLリスト[[#This Row],[製品型番]])=0,"記載なし","") | BR66: =IF(COUNTIFS(在庫確認!B:B,マスタ_EOLリスト[[#This Row],[製品型番]])=0,"記載なし","") -> 記載なし | BS66: =COUNTIF(#REF!,マスタ_EOLリスト[[#This Row],[製品型番]]) -> #REF!
A67: RL7C-R56-C5N | B67: 2発売中 | C67: 2GALLERIA-C | D67: RL7C-R56-C5N | E67: 216521 | F67: 組CLE V350SNNQ(GC 15.6QHD 14650HX 5060 180W L6) | G67: V35 | H67: CLE-V35-14650HX-5060-L6 Creator | I67: 15 | K67: i7-14650HX | L67: 5060 | M67: 536 | N67: 536 | O67: 2025年4月末 | P67: 45832 | W67: 2552 | AN67: 180W | AU67: 65W-100W | AW67: TRUE | AX67: 組CLE V350SNNQ(GC 15.6QHD 14650HX 5060 18 | AY67: 115 | BA67: S17S 暮石灰 | BB67: S17S 暮石灰 | BC67: S17S 暮石灰 | BD67: S17S 暮石灰 | BJ67: NSC7L-R56-C6 | BM67: =IF(COUNTIFS('在庫使用計画 (ノート全体試算)'!C:C,マスタ_EOLリスト[[#This Row],[製品型番]])=0,"記載なし","") | BN67: =IF(COUNTIFS('在庫使用計画 (一般)'!C:C,マスタ_EOLリスト[[#This Row],[製品型番]])=0,"記載なし","") | BO67: =IF(COUNTIFS('在庫使用計画 (法人)'!C:C,マスタ_EOLリスト[[#This Row],[製品型番]])=0,"記載なし","") | BP67: =IF(COUNTIFS('在庫使用計画 (全体実績+予測）0701'!C:C,マスタ_EOLリスト[[#This Row],[製品型番]])=0,"記載なし","") | BQ67: =IF(COUNTIFS('在庫使用計画 (計画 予測)'!C:C,マスタ_EOLリスト[[#This Row],[製品型番]])=0,"記載なし","") | BR67: =IF(COUNTIFS(在庫確認!B:B,マスタ_EOLリスト[[#This Row],[製品型番]])=0,"記載なし","") | BS67: =COUNTIF(#REF!,マスタ_EOLリスト[[#This Row],[製品型番]]) -> #REF!
A68: RL7C-R55-C5N | B68: 2発売中 | C68: 2GALLERIA-C | D68: RL7C-R55-C5N | E68: 216524 | F68: 組CLE V350SNMQ(GC 15.6QHD 14650HX 5050 180W L6) | G68: V35 | H68: CLE-V35-14650HX-5050-L6 Creator | I68: 15 | K68: i7-14650HX | L68: 5050 | M68: 42 | N68: 42 | O68: 2025年5月末 | P68: 45832 | W68: 1540 | AN68: 180W | AU68: 65W-100W | AW68: TRUE | AX68: 組CLE V350SNMQ(GC 15.6QHD 14650HX 5050 18 | AY68: 115 | BA68: S10S 鐵灰 | BB68: S60 鐵灰 | BC68: S60 鐵灰 | BD68: S60 鐵灰 | BJ68: NSC7L-R55-C6 | BM68: =IF(COUNTIFS('在庫使用計画 (ノート全体試算)'!C:C,マスタ_EOLリスト[[#This Row],[製品型番]])=0,"記載なし","") | BN68: =IF(COUNTIFS('在庫使用計画 (一般)'!C:C,マスタ_EOLリスト[[#This Row],[製品型番]])=0,"記載なし","") | BO68: =IF(COUNTIFS('在庫使用計画 (法人)'!C:C,マスタ_EOLリスト[[#This Row],[製品型番]])=0,"記載なし","") | BP68: =IF(COUNTIFS('在庫使用計画 (全体実績+予測）0701'!C:C,マスタ_EOLリスト[[#This Row],[製品型番]])=0,"記載なし","") | BQ68: =IF(COUNTIFS('在庫使用計画 (計画 予測)'!C:C,マスタ_EOLリスト[[#This Row],[製品型番]])=0,"記載なし","") | BR68: =IF(COUNTIFS(在庫確認!B:B,マスタ_EOLリスト[[#This Row],[製品型番]])=0,"記載なし","") | BS68: =COUNTIF(#REF!,マスタ_EOLリスト[[#This Row],[製品型番]]) -> #REF!
A69: #N/A | B69: 4EOL(完全終息) | C69: 2GALLERIA-C | D69: RL7C-R46-C5N | E69: 199021 | F69: 組UNW GM5PD0O(R1 GC 15.6QHD 13620H 4060 230W L6) | G69: ID-O3 | H69: UNW-O3-13620H-4060-L6 Creator | I69: 15 | K69: i7-13620H | L69: 4060 | M69: 0 | N69: 0 | Q69: 2025年7-8月 | R69: Copilot key対応版 | Z69: 216521 | AA69: 組CLE V350SNNQ(GC 15.6QHD 14650HX 5060 180W L6) | AK69: 207648 | AL69: 45525 | AM69: 70 | AN69: 230W | AX69: 在庫無し | BM69: =IF(COUNTIFS('在庫使用計画 (ノート全体試算)'!C:C,マスタ_EOLリスト[[#This Row],[製品型番]])=0,"記載なし","") -> 記載なし | BN69: =IF(COUNTIFS('在庫使用計画 (一般)'!C:C,マスタ_EOLリスト[[#This Row],[製品型番]])=0,"記載なし","") -> 記載なし | BO69: =IF(COUNTIFS('在庫使用計画 (法人)'!C:C,マスタ_EOLリスト[[#This Row],[製品型番]])=0,"記載なし","") | BP69: =IF(COUNTIFS('在庫使用計画 (全体実績+予測）0701'!C:C,マスタ_EOLリスト[[#This Row],[製品型番]])=0,"記載なし","") -> 記載なし | BQ69: =IF(COUNTIFS('在庫使用計画 (計画 予測)'!C:C,マスタ_EOLリスト[[#This Row],[製品型番]])=0,"記載なし","") -> 記載なし | BR69: =IF(COUNTIFS(在庫確認!B:B,マスタ_EOLリスト[[#This Row],[製品型番]])=0,"記載なし","") | BS69: =COUNTIF(#REF!,マスタ_EOLリスト[[#This Row],[製品型番]]) -> #REF!
A70: RL7C-R45-C5N | B70: 3EOL(在庫あり) | C70: 2GALLERIA-C | D70: RL7C-R45-C5N | E70: 199022 | F70: 組UNW GM5PD5E(R1 GC 15.6QHD 13620H 4050 230W L6) | G70: ID-E | H70: UNW-E-13620H-4050-L6 Creator | I70: 15 | K70: i7-13620H | L70: 4050 | M70: 555 | N70: 555 | Q70: 46054 | R70: Copilot key対応版 | W70: 3390 | Z70: 216524 | AA70: 組CLE V350SNMQ(GC 15.6QHD 14650HX 5050 180W L6) | AK70: 207656 | AL70: 45553 | AM70: 35 | AN70: 230W | AO70: 19.5/20 | AP70: 11.8/11.5 | AQ70: 5525+ | AR70: 199688 | AS70: C13-14 | AT70: 171358 | AW70: TRUE | AX70: 組UNW GM5PD5E(R1 GC 15.6QHD 13620H 4050 2 | AY70: 1.15 | BJ70: CLE NP55/UNW ID-E(RTX 3050 4G)? | BM70: =IF(COUNTIFS('在庫使用計画 (ノート全体試算)'!C:C,マスタ_EOLリスト[[#This Row],[製品型番]])=0,"記載なし","") | BN70: =IF(COUNTIFS('在庫使用計画 (一般)'!C:C,マスタ_EOLリスト[[#This Row],[製品型番]])=0,"記載なし","") | BO70: =IF(COUNTIFS('在庫使用計画 (法人)'!C:C,マスタ_EOLリスト[[#This Row],[製品型番]])=0,"記載なし","") | BP70: =IF(COUNTIFS('在庫使用計画 (全体実績+予測）0701'!C:C,マスタ_EOLリスト[[#This Row],[製品型番]])=0,"記載なし","") | BQ70: =IF(COUNTIFS('在庫使用計画 (計画 予測)'!C:C,マスタ_EOLリスト[[#This Row],[製品型番]])=0,"記載なし","") | BR70: =IF(COUNTIFS(在庫確認!B:B,マスタ_EOLリスト[[#This Row],[製品型番]])=0,"記載なし","") | BS70: =COUNTIF(#REF!,マスタ_EOLリスト[[#This Row],[製品型番]]) -> #REF!
A71: RL7C-R35-C5N | B71: 3EOL(在庫あり) | C71: 2GALLERIA-C | D71: RL7C-R35-C5N | E71: 199023 | F71: 組UNW GM5PD3E(R1 GC 15.6QHD 13620H 3050 180W L6) | G71: ID-E | H71: UNW-E-13620H-3050-L6 Creator | I71: 15 | K71: i7-13620H | L71: 3050 | M71: 11 | N71: 11 | Q71: 46023 | R71: Copilot key対応版 | W71: 4880 | AK71: 207657 | AL71: 45483 | AM71: 125 | AN71: 180W | AW71: TRUE | AX71: 組UNW GM5PD3E(R1 GC 15.6QHD 13620H 3050 1 | BJ71: CLE NP55/UNW ID-E(RTX 3050 4G)? | BM71: =IF(COUNTIFS('在庫使用計画 (ノート全体試算)'!C:C,マスタ_EOLリスト[[#This Row],[製品型番]])=0,"記載なし","") | BN71: =IF(COUNTIFS('在庫使用計画 (一般)'!C:C,マスタ_EOLリスト[[#This Row],[製品型番]])=0,"記載なし","") | BO71: =IF(COUNTIFS('在庫使用計画 (法人)'!C:C,マスタ_EOLリスト[[#This Row],[製品型番]])=0,"記載なし","") | BP71: =IF(COUNTIFS('在庫使用計画 (全体実績+予測）0701'!C:C,マスタ_EOLリスト[[#This Row],[製品型番]])=0,"記載なし","") | BQ71: =IF(COUNTIFS('在庫使用計画 (計画 予測)'!C:C,マスタ_EOLリスト[[#This Row],[製品型番]])=0,"記載なし","") | BR71: =IF(COUNTIFS(在庫確認!B:B,マスタ_EOLリスト[[#This Row],[製品型番]])=0,"記載なし","") | BS71: =COUNTIF(#REF!,マスタ_EOLリスト[[#This Row],[製品型番]]) -> #REF!
A72: #N/A | B72: 4EOL(完全終息) | C72: 2GALLERIA-C | D72: RL7C-R46-C5N | E72: 193192 | F72: 組UNW GM5PD0O(15.6QHD 13620H 4060 230W L6) | G72: ID-O3 | H72: ID-O3-13620H-4060-creator | K72: i7-13620H | L72: 4060 | M72: 0 | N72: 0 | O72: 3/31 WK | P72: 45428 | U72: Copilot keyモデルにスライド | V72: 4200 | W72: 1936 | AK72: 194890 | AL72: 45481 | AM72: 35 | AN72: 230W | AX72: 在庫無し | BA72: Ink Stone Black | BB72: Ink Stone Black | BC72: Ink Stone Black | BD72: Ink Stone Black | BM72: =IF(COUNTIFS('在庫使用計画 (ノート全体試算)'!C:C,マスタ_EOLリスト[[#This Row],[製品型番]])=0,"記載なし","") -> 記載なし | BN72: =IF(COUNTIFS('在庫使用計画 (一般)'!C:C,マスタ_EOLリスト[[#This Row],[製品型番]])=0,"記載なし","") -> 記載なし | BO72: =IF(COUNTIFS('在庫使用計画 (法人)'!C:C,マスタ_EOLリスト[[#This Row],[製品型番]])=0,"記載なし","") | BP72: =IF(COUNTIFS('在庫使用計画 (全体実績+予測）0701'!C:C,マスタ_EOLリスト[[#This Row],[製品型番]])=0,"記載なし","") -> 記載なし | BQ72: =IF(COUNTIFS('在庫使用計画 (計画 予測)'!C:C,マスタ_EOLリスト[[#This Row],[製品型番]])=0,"記載なし","") -> 記載なし | BR72: =IF(COUNTIFS(在庫確認!B:B,マスタ_EOLリスト[[#This Row],[製品型番]])=0,"記載なし","") | BS72: =COUNTIF(#REF!,マスタ_EOLリスト[[#This Row],[製品型番]]) -> #REF!
A73: RL7C-R45-C5N | B73: 4EOL(完全終息) | C73: 2GALLERIA-C | D73: RL7C-R45-C5N | E73: 193194 | F73: 組UNW GM5PD5E(15.6QHD 13620H 4050 230W L6) | G73: ID-E | H73: ID-E-13620H-4050-creator | K73: i7-13620H | L73: 4050 | M73: 0 | N73: 0 | O73: 3/31 WK | P73: 45428 | U73: Copilot keyモデルにスライド | V73: 3500 | W73: 1276 | Z73: 199022 | AK73: 194892 | AL73: 45457 | AM73: 110 | AN73: 230W | AX73: 在庫無し | BM73: =IF(COUNTIFS('在庫使用計画 (ノート全体試算)'!C:C,マスタ_EOLリスト[[#This Row],[製品型番]])=0,"記載なし","") | BN73: =IF(COUNTIFS('在庫使用計画 (一般)'!C:C,マスタ_EOLリスト[[#This Row],[製品型番]])=0,"記載なし","") | BO73: =IF(COUNTIFS('在庫使用計画 (法人)'!C:C,マスタ_EOLリスト[[#This Row],[製品型番]])=0,"記載なし","") | BP73: =IF(COUNTIFS('在庫使用計画 (全体実績+予測）0701'!C:C,マスタ_EOLリスト[[#This Row],[製品型番]])=0,"記載なし","") | BQ73: =IF(COUNTIFS('在庫使用計画 (計画 予測)'!C:C,マスタ_EOLリスト[[#This Row],[製品型番]])=0,"記載なし","") | BR73: =IF(COUNTIFS(在庫確認!B:B,マスタ_EOLリスト[[#This Row],[製品型番]])=0,"記載なし","") | BS73: =COUNTIF(#REF!,マスタ_EOLリスト[[#This Row],[製品型番]]) -> #REF!
A74: RL7C-R35-C5N | B74: 4EOL(完全終息) | C74: 2GALLERIA-C | D74: RL7C-R35-C5N | E74: 193196 | F74: 組UNW GM5PD3E(15.6QHD 13620H 3050 180W L6) | G74: ID-E | H74: ID-E-13620H-3050-creator | K74: i7-13620H | L74: 3050 | M74: 0 | N74: 0 | O74: 3/31 WK | P74: 45428 | U74: Copilot keyモデルにスライド | V74: 2940 | W74: 1586 | AK74: 194886 | AL74: 45481 | AM74: 150 | AN74: 180W | AX74: 在庫無し | BM74: =IF(COUNTIFS('在庫使用計画 (ノート全体試算)'!C:C,マスタ_EOLリスト[[#This Row],[製品型番]])=0,"記載なし","") | BN74: =IF(COUNTIFS('在庫使用計画 (一般)'!C:C,マスタ_EOLリスト[[#This Row],[製品型番]])=0,"記載なし","") | BO74: =IF(COUNTIFS('在庫使用計画 (法人)'!C:C,マスタ_EOLリスト[[#This Row],[製品型番]])=0,"記載なし","") | BP74: =IF(COUNTIFS('在庫使用計画 (全体実績+予測）0701'!C:C,マスタ_EOLリスト[[#This Row],[製品型番]])=0,"記載なし","") | BQ74: =IF(COUNTIFS('在庫使用計画 (計画 予測)'!C:C,マスタ_EOLリスト[[#This Row],[製品型番]])=0,"記載なし","") | BR74: =IF(COUNTIFS(在庫確認!B:B,マスタ_EOLリスト[[#This Row],[製品型番]])=0,"記載なし","") | BS74: =COUNTIF(#REF!,マスタ_EOLリスト[[#This Row],[製品型番]]) -> #REF!
A75: NSC7L-R56-C6 | B75: 1新規(発売前) | C75: 2GALLERIA-C | D75: NSC7L-R56-C6 | E75: 303437 | F75: 組QNT NLT(GC 16WQGXA 240H 5060 230W L6) | G75: NLT | H75: QNT-NLT-240H-5060-L6-GC | I75: 16 | M75: 0 | N75: 1100 | O75: 4/12wk | AW75: TRUE | AX75: 在庫無し | BA75: Light Gray | BB75: Black | BC75: Light Gray | BD75: Light Gray | BJ75: x | BM75: =IF(COUNTIFS('在庫使用計画 (ノート全体試算)'!C:C,マスタ_EOLリスト[[#This Row],[製品型番]])=0,"記載なし","") | BN75: =IF(COUNTIFS('在庫使用計画 (一般)'!C:C,マスタ_EOLリスト[[#This Row],[製品型番]])=0,"記載なし","") | BO75: =IF(COUNTIFS('在庫使用計画 (法人)'!C:C,マスタ_EOLリスト[[#This Row],[製品型番]])=0,"記載なし","") | BP75: =IF(COUNTIFS('在庫使用計画 (全体実績+予測）0701'!C:C,マスタ_EOLリスト[[#This Row],[製品型番]])=0,"記載なし","") | BQ75: =IF(COUNTIFS('在庫使用計画 (計画 予測)'!C:C,マスタ_EOLリスト[[#This Row],[製品型番]])=0,"記載なし","") | BR75: =IF(COUNTIFS(在庫確認!B:B,マスタ_EOLリスト[[#This Row],[製品型番]])=0,"記載なし","") -> 記載なし | BS75: =COUNTIF(#REF!,マスタ_EOLリスト[[#This Row],[製品型番]]) -> #REF!
A76: NSC7L-R55-C6 | B76: 1新規(発売前) | C76: 2GALLERIA-C | D76: NSC7L-R55-C6 | E76: 303438 | F76: 組QNT NLT(GC 16WQGXA 240H 5050 230W L6) | G76: NLT | H76: QNT-NLT-240H-5050-L6-GC | I76: 16 | M76: 0 | N76: 730 | O76: 4/12wk | AW76: TRUE | AX76: 在庫無し | BA76: Light Gray | BB76: Black | BC76: Light Gray | BD76: Light Gray | BJ76: x | BM76: =IF(COUNTIFS('在庫使用計画 (ノート全体試算)'!C:C,マスタ_EOLリスト[[#This Row],[製品型番]])=0,"記載なし","") | BN76: =IF(COUNTIFS('在庫使用計画 (一般)'!C:C,マスタ_EOLリスト[[#This Row],[製品型番]])=0,"記載なし","") | BO76: =IF(COUNTIFS('在庫使用計画 (法人)'!C:C,マスタ_EOLリスト[[#This Row],[製品型番]])=0,"記載なし","") | BP76: =IF(COUNTIFS('在庫使用計画 (全体実績+予測）0701'!C:C,マスタ_EOLリスト[[#This Row],[製品型番]])=0,"記載なし","") | BQ76: =IF(COUNTIFS('在庫使用計画 (計画 予測)'!C:C,マスタ_EOLリスト[[#This Row],[製品型番]])=0,"記載なし","") | BR76: =IF(COUNTIFS(在庫確認!B:B,マスタ_EOLリスト[[#This Row],[製品型番]])=0,"記載なし","") -> 記載なし | BS76: =COUNTIF(#REF!,マスタ_EOLリスト[[#This Row],[製品型番]]) -> #REF!
A77: NSC5L-IG-C4 (32GB) | B77: 1新規(発売前) | C77: 2GALLERIA-C | D77: NSC5L-IG-C4 (32GB) | E77: 302060 | F77: 組WZN A14JG(GC 14WUXGA 125U UMA 32G 65W L7) | G77: A14JG | H77: WZN-A14JG-125U-UMA-32G-L7-GC | I77: 16 | M77: 0 | N77: 505 | O77: 46257 | AW77: TRUE | AX77: 在庫無し | BA77: S10S 鐵灰 | BB77: S60 鐵灰 | BC77: S60 鐵灰 | BD77: S60 鐵灰 | BJ77: x | BM77: =IF(COUNTIFS('在庫使用計画 (ノート全体試算)'!C:C,マスタ_EOLリスト[[#This Row],[製品型番]])=0,"記載なし","") | BN77: =IF(COUNTIFS('在庫使用計画 (一般)'!C:C,マスタ_EOLリスト[[#This Row],[製品型番]])=0,"記載なし","") | BO77: =IF(COUNTIFS('在庫使用計画 (法人)'!C:C,マスタ_EOLリスト[[#This Row],[製品型番]])=0,"記載なし","") | BP77: =IF(COUNTIFS('在庫使用計画 (全体実績+予測）0701'!C:C,マスタ_EOLリスト[[#This Row],[製品型番]])=0,"記載なし","") | BQ77: =IF(COUNTIFS('在庫使用計画 (計画 予測)'!C:C,マスタ_EOLリスト[[#This Row],[製品型番]])=0,"記載なし","") | BR77: =IF(COUNTIFS(在庫確認!B:B,マスタ_EOLリスト[[#This Row],[製品型番]])=0,"記載なし","") -> 記載なし | BS77: =COUNTIF(#REF!,マスタ_EOLリスト[[#This Row],[製品型番]]) -> #REF!
A78: NSC5L-IG-C4 (16GB) | B78: 1新規(発売前) | C78: 2GALLERIA-C | D78: NSC5L-IG-C4 (16GB) | E78: 302059 | F78: 組WZN A14JG(GC 14WUXGA 125U UMA 16G 65W L7) | G78: A14JG | H78: WZN-A14JG-125U-UMA-16G-L7-GC | I78: 16 | M78: 0 | N78: 555 | O78: 46257 | AW78: TRUE | AX78: 在庫無し | BA78: S10S 鐵灰 | BB78: S60 鐵灰 | BC78: S60 鐵灰 | BD78: S60 鐵灰 | BJ78: x | BM78: =IF(COUNTIFS('在庫使用計画 (ノート全体試算)'!C:C,マスタ_EOLリスト[[#This Row],[製品型番]])=0,"記載なし","") | BN78: =IF(COUNTIFS('在庫使用計画 (一般)'!C:C,マスタ_EOLリスト[[#This Row],[製品型番]])=0,"記載なし","") | BO78: =IF(COUNTIFS('在庫使用計画 (法人)'!C:C,マスタ_EOLリスト[[#This Row],[製品型番]])=0,"記載なし","") | BP78: =IF(COUNTIFS('在庫使用計画 (全体実績+予測）0701'!C:C,マスタ_EOLリスト[[#This Row],[製品型番]])=0,"記載なし","") | BQ78: =IF(COUNTIFS('在庫使用計画 (計画 予測)'!C:C,マスタ_EOLリスト[[#This Row],[製品型番]])=0,"記載なし","") | BR78: =IF(COUNTIFS(在庫確認!B:B,マスタ_EOLリスト[[#This Row],[製品型番]])=0,"記載なし","") -> 記載なし | BS78: =COUNTIF(#REF!,マスタ_EOLリスト[[#This Row],[製品型番]]) -> #REF!
A79: DL9R-IG-C4A | B79: 4EOL(完全終息) | C79: 2GALLERIA-C | D79: DL9R-IG-C4A | E79: 208299 | F79: 組CLE V545KU-TD(GC 14QWXGA+ HX370 UMA 90W L6) | G79: V54 | H79: CLE-V54-HX370-UMA-L6 Creator | I79: 14 | J79: 必須 | K79: R AI9 370HX | L79: UMA | M79: 0 | N79: 0 | P79: 45708 | W79: 1000 | Z79: 216787 | AN79: 90W | AO79: 19 | AQ79: 5517+ | AX79: 在庫無し | AY79: - | BM79: =IF(COUNTIFS('在庫使用計画 (ノート全体試算)'!C:C,マスタ_EOLリスト[[#This Row],[製品型番]])=0,"記載なし","") | BN79: =IF(COUNTIFS('在庫使用計画 (一般)'!C:C,マスタ_EOLリスト[[#This Row],[製品型番]])=0,"記載なし","") | BO79: =IF(COUNTIFS('在庫使用計画 (法人)'!C:C,マスタ_EOLリスト[[#This Row],[製品型番]])=0,"記載なし","") | BP79: =IF(COUNTIFS('在庫使用計画 (全体実績+予測）0701'!C:C,マスタ_EOLリスト[[#This Row],[製品型番]])=0,"記載なし","") | BQ79: =IF(COUNTIFS('在庫使用計画 (計画 予測)'!C:C,マスタ_EOLリスト[[#This Row],[製品型番]])=0,"記載なし","") | BR79: =IF(COUNTIFS(在庫確認!B:B,マスタ_EOLリスト[[#This Row],[製品型番]])=0,"記載なし","") | BS79: =COUNTIF(#REF!,マスタ_EOLリスト[[#This Row],[製品型番]]) -> #REF!
A80: DL9R-IG-C4A | B80: 3EOL(在庫あり) | C80: 2GALLERIA-C | D80: DL9R-IG-C4A | E80: 216787 | F80: 組CLE V545KU-TD(R1 GC 14QWXGA+ HX370 UMA 90W L6) | G80: V54 | H80: CLE-V54-HX370-UMA-L6 Creator | I80: 14 | J80: 必須 | K80: R AI9 370HX | L80: UMA | M80: 26 | N80: 26 | P80: 45708 | Q80: 2026年3月頃 | R80: →後継はCPU切替 | W80: 1940 | AB80: 295632 | AC80: V54 HX470 | AN80: 90W | AO80: 19 | AQ80: 5517+ | AW80: TRUE | AX80: 組CLE V545KU-TD(R1 GC 14QWXGA+ HX370 UMA | AY80: - | BA80: S60 鐵灰 | BB80: S60 鐵灰 | BC80: S60 鐵灰 | BD80: S60 鐵灰 | BJ80: x | BM80: =IF(COUNTIFS('在庫使用計画 (ノート全体試算)'!C:C,マスタ_EOLリスト[[#This Row],[製品型番]])=0,"記載なし","") | BN80: =IF(COUNTIFS('在庫使用計画 (一般)'!C:C,マスタ_EOLリスト[[#This Row],[製品型番]])=0,"記載なし","") | BO80: =IF(COUNTIFS('在庫使用計画 (法人)'!C:C,マスタ_EOLリスト[[#This Row],[製品型番]])=0,"記載なし","") | BP80: =IF(COUNTIFS('在庫使用計画 (全体実績+予測）0701'!C:C,マスタ_EOLリスト[[#This Row],[製品型番]])=0,"記載なし","") | BQ80: =IF(COUNTIFS('在庫使用計画 (計画 予測)'!C:C,マスタ_EOLリスト[[#This Row],[製品型番]])=0,"記載なし","") | BR80: =IF(COUNTIFS(在庫確認!B:B,マスタ_EOLリスト[[#This Row],[製品型番]])=0,"記載なし","") | BS80: =COUNTIF(#REF!,マスタ_EOLリスト[[#This Row],[製品型番]]) -> #REF!
A81: DL7C-IG-C4 | B81: 4EOL(完全終息) | C81: 2GALLERIA-C | D81: DL7C-IG-C4 | E81: 193198 | F81: 組CLE V545TU(GC 14QWXGA+ 155H UMA 90W L6) | G81: V54 | H81: CLE-V540-155H-UMA-L6 Creator | I81: 14 | K81: u7-155H | L81: UMA | M81: 0 | N81: 0 | O81: 5/12 WK | P81: 45463 | Q81: 2024年5月頃 | R81: 法人で追加の話あり | U81: Copilot keyモデルにスライド | V81: 3136 | W81: 1326 | AB81: 216787 | AK81: 194893 | AL81: 45439 | AM81: 6 | AN81: 90W | AX81: 在庫無し | AY81: - | BM81: =IF(COUNTIFS('在庫使用計画 (ノート全体試算)'!C:C,マスタ_EOLリスト[[#This Row],[製品型番]])=0,"記載なし","") | BN81: =IF(COUNTIFS('在庫使用計画 (一般)'!C:C,マスタ_EOLリスト[[#This Row],[製品型番]])=0,"記載なし","") | BO81: =IF(COUNTIFS('在庫使用計画 (法人)'!C:C,マスタ_EOLリスト[[#This Row],[製品型番]])=0,"記載なし","") | BP81: =IF(COUNTIFS('在庫使用計画 (全体実績+予測）0701'!C:C,マスタ_EOLリスト[[#This Row],[製品型番]])=0,"記載なし","") -> 記載なし | BQ81: =IF(COUNTIFS('在庫使用計画 (計画 予測)'!C:C,マスタ_EOLリスト[[#This Row],[製品型番]])=0,"記載なし","") -> 記載なし | BR81: =IF(COUNTIFS(在庫確認!B:B,マスタ_EOLリスト[[#This Row],[製品型番]])=0,"記載なし","") | BS81: =COUNTIF(#REF!,マスタ_EOLリスト[[#This Row],[製品型番]]) -> #REF!
A82: DL7C-IG-C6 | B82: 4EOL(完全終息) | C82: 2GALLERIA-C | D82: DL7C-IG-C6 | E82: 193210 | F82: 組CLE V560TU-TD(16QHD+ 144Hz 155H UMA 90W L6) | G82: V56 | H82: V560-155H-UMA-Creator | K82: u7-155H | L82: UMA | M82: 0 | N82: 0 | O82: 4/1 WK | P82: 45463 | Q82: 2024年5月頃 | U82: Copilot keyモデルにスライド | V82: 450 | W82: 637 | AK82: 194897 | AL82: 45483 | AM82: 125 | AN82: 90W | AX82: 在庫無し | BM82: =IF(COUNTIFS('在庫使用計画 (ノート全体試算)'!C:C,マスタ_EOLリスト[[#This Row],[製品型番]])=0,"記載なし","") | BN82: =IF(COUNTIFS('在庫使用計画 (一般)'!C:C,マスタ_EOLリスト[[#This Row],[製品型番]])=0,"記載なし","") -> 記載なし | BO82: =IF(COUNTIFS('在庫使用計画 (法人)'!C:C,マスタ_EOLリスト[[#This Row],[製品型番]])=0,"記載なし","") | BP82: =IF(COUNTIFS('在庫使用計画 (全体実績+予測）0701'!C:C,マスタ_EOLリスト[[#This Row],[製品型番]])=0,"記載なし","") | BQ82: =IF(COUNTIFS('在庫使用計画 (計画 予測)'!C:C,マスタ_EOLリスト[[#This Row],[製品型番]])=0,"記載なし","") -> 記載なし | BR82: =IF(COUNTIFS(在庫確認!B:B,マスタ_EOLリスト[[#This Row],[製品型番]])=0,"記載なし","") | BS82: =COUNTIF(#REF!,マスタ_EOLリスト[[#This Row],[製品型番]]) -> #REF!
A83: DL7C-IG-C6 | B83: 4EOL(完全終息) | C83: 2GALLERIA-C | D83: DL7C-IG-C6 | E83: 199320 | F83: 組CLE V561TU-TD(R1 GC 16QHD+ 144Hz 155H UMA 90W L6) | G83: V56 | H83: V560-155H-UMA-Creator | K83: u7-155H | L83: UMA | M83: 0 | N83: 0 | Q83: 2025年4-5月 | R83: Copilot key対応版 | W83: 0 | Z83: なし | AC83: DX-L7LA / XL7C-R45-6が近いライン | AI83: 199320 | AK83: 207662 | AL83: 45483 | AM83: 125 | AN83: 90W | AX83: 在庫無し | BM83: =IF(COUNTIFS('在庫使用計画 (ノート全体試算)'!C:C,マスタ_EOLリスト[[#This Row],[製品型番]])=0,"記載なし","") | BN83: =IF(COUNTIFS('在庫使用計画 (一般)'!C:C,マスタ_EOLリスト[[#This Row],[製品型番]])=0,"記載なし","") -> 記載なし | BO83: =IF(COUNTIFS('在庫使用計画 (法人)'!C:C,マスタ_EOLリスト[[#This Row],[製品型番]])=0,"記載なし","") | BP83: =IF(COUNTIFS('在庫使用計画 (全体実績+予測）0701'!C:C,マスタ_EOLリスト[[#This Row],[製品型番]])=0,"記載なし","") | BQ83: =IF(COUNTIFS('在庫使用計画 (計画 予測)'!C:C,マスタ_EOLリスト[[#This Row],[製品型番]])=0,"記載なし","") -> 記載なし | BR83: =IF(COUNTIFS(在庫確認!B:B,マスタ_EOLリスト[[#This Row],[製品型番]])=0,"記載なし","") | BS83: =COUNTIF(#REF!,マスタ_EOLリスト[[#This Row],[製品型番]]) -> #REF!
A84: DL7C-IG-C4 | B84: 4EOL(完全終息) | C84: 2GALLERIA-C | D84: DL7C-IG-C4 | E84: 199322 | F84: 組CLE V545TU(R1 GC 14QWXGA+ 155H UMA 90W L6) | G84: V54 | H84: V540-155H-UMA-creator | K84: u7-155H | L84: UMA | M84: 0 | N84: 0 | R84: Copilot key対応版 | W84: 320 | AB84: 216787 | AK84: 207652 | AL84: 45483 | AM84: 125 | AN84: 90W | AX84: 在庫無し | BM84: =IF(COUNTIFS('在庫使用計画 (ノート全体試算)'!C:C,マスタ_EOLリスト[[#This Row],[製品型番]])=0,"記載なし","") | BN84: =IF(COUNTIFS('在庫使用計画 (一般)'!C:C,マスタ_EOLリスト[[#This Row],[製品型番]])=0,"記載なし","") | BO84: =IF(COUNTIFS('在庫使用計画 (法人)'!C:C,マスタ_EOLリスト[[#This Row],[製品型番]])=0,"記載なし","") | BP84: =IF(COUNTIFS('在庫使用計画 (全体実績+予測）0701'!C:C,マスタ_EOLリスト[[#This Row],[製品型番]])=0,"記載なし","") -> 記載なし | BQ84: =IF(COUNTIFS('在庫使用計画 (計画 予測)'!C:C,マスタ_EOLリスト[[#This Row],[製品型番]])=0,"記載なし","") -> 記載なし | BR84: =IF(COUNTIFS(在庫確認!B:B,マスタ_EOLリスト[[#This Row],[製品型番]])=0,"記載なし","") | BS84: =COUNTIF(#REF!,マスタ_EOLリスト[[#This Row],[製品型番]]) -> #REF!
A85: DL7C-IG-C4 | B85: 4EOL(完全終息) | C85: 2GALLERIA-C | D85: DL7C-IG-C4 | E85: 208425 | F85: 組CLE V545TU(R2 GC 14QWXGA+ 155H UMA 90W L6) | G85: V54 | H85: V540-155H-UMA-creator | K85: u7-155H | L85: UMA | M85: 0 | N85: 0 | W85: 80 | AB85: 216787 | AN85: 90W | AX85: 在庫無し | BM85: =IF(COUNTIFS('在庫使用計画 (ノート全体試算)'!C:C,マスタ_EOLリスト[[#This Row],[製品型番]])=0,"記載なし","") | BN85: =IF(COUNTIFS('在庫使用計画 (一般)'!C:C,マスタ_EOLリスト[[#This Row],[製品型番]])=0,"記載なし","") | BO85: =IF(COUNTIFS('在庫使用計画 (法人)'!C:C,マスタ_EOLリスト[[#This Row],[製品型番]])=0,"記載なし","") | BP85: =IF(COUNTIFS('在庫使用計画 (全体実績+予測）0701'!C:C,マスタ_EOLリスト[[#This Row],[製品型番]])=0,"記載なし","") -> 記載なし | BQ85: =IF(COUNTIFS('在庫使用計画 (計画 予測)'!C:C,マスタ_EOLリスト[[#This Row],[製品型番]])=0,"記載なし","") -> 記載なし | BR85: =IF(COUNTIFS(在庫確認!B:B,マスタ_EOLリスト[[#This Row],[製品型番]])=0,"記載なし","") | BS85: =COUNTIF(#REF!,マスタ_EOLリスト[[#This Row],[製品型番]]) -> #REF!
A86: #N/A | B86: 5開発中止 | C86: 2GALLERIA-C | D86: MDR9N-IG-CW | E86: 320747 | F86: 組CLE R101GU(GC MiniPC AI9-HX470 L6 65W WH) | G86: R101GU | H86: CLE-MiniPC-AI9-HX470-白-GC | I86: 0 | M86: 0 | N86: 0 | R86: 販売予定 2026/5月~11月：600台 | AW86: TRUE | AX86: 在庫無し | BM86: =IF(COUNTIFS('在庫使用計画 (ノート全体試算)'!C:C,マスタ_EOLリスト[[#This Row],[製品型番]])=0,"記載なし","") -> 記載なし | BN86: =IF(COUNTIFS('在庫使用計画 (一般)'!C:C,マスタ_EOLリスト[[#This Row],[製品型番]])=0,"記載なし","") -> 記載なし | BO86: =IF(COUNTIFS('在庫使用計画 (法人)'!C:C,マスタ_EOLリスト[[#This Row],[製品型番]])=0,"記載なし","") -> 記載なし | BP86: =IF(COUNTIFS('在庫使用計画 (全体実績+予測）0701'!C:C,マスタ_EOLリスト[[#This Row],[製品型番]])=0,"記載なし","") -> 記載なし | BQ86: =IF(COUNTIFS('在庫使用計画 (計画 予測)'!C:C,マスタ_EOLリスト[[#This Row],[製品型番]])=0,"記載なし","") -> 記載なし | BR86: =IF(COUNTIFS(在庫確認!B:B,マスタ_EOLリスト[[#This Row],[製品型番]])=0,"記載なし","") -> 記載なし | BS86: =COUNTIF(#REF!,マスタ_EOLリスト[[#This Row],[製品型番]]) -> #REF!
A87: #N/A | B87: 5開発中止 | C87: 2GALLERIA-C | D87: MDR9N-IG-CB | E87: 320748 | F87: 組CLE R100GU(GC MiniPC AI9-HX470 L6 65W BK) | G87: R100GU | H87: CLE-MiniPC-AI9-HX470-黒-GC | I87: 0 | M87: 0 | N87: 0 | R87: 販売予定 2026/5月~11月：600台 | AW87: TRUE | AX87: 在庫無し | BM87: =IF(COUNTIFS('在庫使用計画 (ノート全体試算)'!C:C,マスタ_EOLリスト[[#This Row],[製品型番]])=0,"記載なし","") -> 記載なし | BN87: =IF(COUNTIFS('在庫使用計画 (一般)'!C:C,マスタ_EOLリスト[[#This Row],[製品型番]])=0,"記載なし","") -> 記載なし | BO87: =IF(COUNTIFS('在庫使用計画 (法人)'!C:C,マスタ_EOLリスト[[#This Row],[製品型番]])=0,"記載なし","") -> 記載なし | BP87: =IF(COUNTIFS('在庫使用計画 (全体実績+予測）0701'!C:C,マスタ_EOLリスト[[#This Row],[製品型番]])=0,"記載なし","") -> 記載なし | BQ87: =IF(COUNTIFS('在庫使用計画 (計画 予測)'!C:C,マスタ_EOLリスト[[#This Row],[製品型番]])=0,"記載なし","") -> 記載なし | BR87: =IF(COUNTIFS(在庫確認!B:B,マスタ_EOLリスト[[#This Row],[製品型番]])=0,"記載なし","") -> 記載なし | BS87: =COUNTIF(#REF!,マスタ_EOLリスト[[#This Row],[製品型番]]) -> #REF!
A88: #N/A | B88: 5開発中止 | C88: 2GALLERIA-C | D88: MSR7N-IG-CW | E88: 320750 | F88: 組CLE R101GU(GC MiniPC AI7-450 L6 65W WH) | G88: R101GU | H88: CLE-MiniPC-AI7-450-白-GC | I88: 0 | M88: 0 | N88: 0 | R88: 販売予定 2026/5月~11月：600台 | AW88: TRUE | AX88: 在庫無し | BM88: =IF(COUNTIFS('在庫使用計画 (ノート全体試算)'!C:C,マスタ_EOLリスト[[#This Row],[製品型番]])=0,"記載なし","") -> 記載なし | BN88: =IF(COUNTIFS('在庫使用計画 (一般)'!C:C,マスタ_EOLリスト[[#This Row],[製品型番]])=0,"記載なし","") -> 記載なし | BO88: =IF(COUNTIFS('在庫使用計画 (法人)'!C:C,マスタ_EOLリスト[[#This Row],[製品型番]])=0,"記載なし","") -> 記載なし | BP88: =IF(COUNTIFS('在庫使用計画 (全体実績+予測）0701'!C:C,マスタ_EOLリスト[[#This Row],[製品型番]])=0,"記載なし","") -> 記載なし | BQ88: =IF(COUNTIFS('在庫使用計画 (計画 予測)'!C:C,マスタ_EOLリスト[[#This Row],[製品型番]])=0,"記載なし","") -> 記載なし | BR88: =IF(COUNTIFS(在庫確認!B:B,マスタ_EOLリスト[[#This Row],[製品型番]])=0,"記載なし","") -> 記載なし | BS88: =COUNTIF(#REF!,マスタ_EOLリスト[[#This Row],[製品型番]]) -> #REF!
A89: #N/A | B89: 5開発中止 | C89: 2GALLERIA-C | D89: MSR7N-IG-CB | E89: 320751 | F89: 組CLE R100GU(GC MiniPC AI7-450 L6 65W BK) | G89: R100GU | H89: CLE-MiniPC-AI7-450-黒-GC | I89: 0 | M89: 0 | N89: 0 | R89: 販売予定 2026/5月~11月：600台 | AW89: TRUE | AX89: 在庫無し | BM89: =IF(COUNTIFS('在庫使用計画 (ノート全体試算)'!C:C,マスタ_EOLリスト[[#This Row],[製品型番]])=0,"記載なし","") -> 記載なし | BN89: =IF(COUNTIFS('在庫使用計画 (一般)'!C:C,マスタ_EOLリスト[[#This Row],[製品型番]])=0,"記載なし","") -> 記載なし | BO89: =IF(COUNTIFS('在庫使用計画 (法人)'!C:C,マスタ_EOLリスト[[#This Row],[製品型番]])=0,"記載なし","") -> 記載なし | BP89: =IF(COUNTIFS('在庫使用計画 (全体実績+予測）0701'!C:C,マスタ_EOLリスト[[#This Row],[製品型番]])=0,"記載なし","") -> 記載なし | BQ89: =IF(COUNTIFS('在庫使用計画 (計画 予測)'!C:C,マスタ_EOLリスト[[#This Row],[製品型番]])=0,"記載なし","") -> 記載なし | BR89: =IF(COUNTIFS(在庫確認!B:B,マスタ_EOLリスト[[#This Row],[製品型番]])=0,"記載なし","") -> 記載なし | BS89: =COUNTIF(#REF!,マスタ_EOLリスト[[#This Row],[製品型番]]) -> #REF!
A90: #N/A | B90: 5開発中止 | C90: 2GALLERIA-C | D90: MCR7N-IG-CW | E90: 320752 | F90: 組CLE R101EU(GC MiniPC R7-255 L6 65W WH) | G90: R101EU | H90: CLE-MiniPC-R7-255-白-GC | I90: 0 | M90: 0 | N90: 0 | R90: 販売予定 2026/5月~11月：600台 | AW90: TRUE | AX90: 在庫無し | BM90: =IF(COUNTIFS('在庫使用計画 (ノート全体試算)'!C:C,マスタ_EOLリスト[[#This Row],[製品型番]])=0,"記載なし","") -> 記載なし | BN90: =IF(COUNTIFS('在庫使用計画 (一般)'!C:C,マスタ_EOLリスト[[#This Row],[製品型番]])=0,"記載なし","") -> 記載なし | BO90: =IF(COUNTIFS('在庫使用計画 (法人)'!C:C,マスタ_EOLリスト[[#This Row],[製品型番]])=0,"記載なし","") -> 記載なし | BP90: =IF(COUNTIFS('在庫使用計画 (全体実績+予測）0701'!C:C,マスタ_EOLリスト[[#This Row],[製品型番]])=0,"記載なし","") -> 記載なし | BQ90: =IF(COUNTIFS('在庫使用計画 (計画 予測)'!C:C,マスタ_EOLリスト[[#This Row],[製品型番]])=0,"記載なし","") -> 記載なし | BR90: =IF(COUNTIFS(在庫確認!B:B,マスタ_EOLリスト[[#This Row],[製品型番]])=0,"記載なし","") -> 記載なし | BS90: =COUNTIF(#REF!,マスタ_EOLリスト[[#This Row],[製品型番]]) -> #REF!
A91: #N/A | B91: 5開発中止 | C91: 2GALLERIA-C | D91: MCR7N-IG-CB | E91: 320753 | F91: 組CLE R100EU(GC MiniPC R7-255 L6 65W BK) | G91: R100EU | H91: CLE-MiniPC-R7-255-黒-GC | I91: 0 | M91: 0 | N91: 0 | R91: 販売予定 2026/5月~11月：600台 | AW91: TRUE | AX91: 在庫無し | BM91: =IF(COUNTIFS('在庫使用計画 (ノート全体試算)'!C:C,マスタ_EOLリスト[[#This Row],[製品型番]])=0,"記載なし","") -> 記載なし | BN91: =IF(COUNTIFS('在庫使用計画 (一般)'!C:C,マスタ_EOLリスト[[#This Row],[製品型番]])=0,"記載なし","") -> 記載なし | BO91: =IF(COUNTIFS('在庫使用計画 (法人)'!C:C,マスタ_EOLリスト[[#This Row],[製品型番]])=0,"記載なし","") -> 記載なし | BP91: =IF(COUNTIFS('在庫使用計画 (全体実績+予測）0701'!C:C,マスタ_EOLリスト[[#This Row],[製品型番]])=0,"記載なし","") -> 記載なし | BQ91: =IF(COUNTIFS('在庫使用計画 (計画 予測)'!C:C,マスタ_EOLリスト[[#This Row],[製品型番]])=0,"記載なし","") -> 記載なし | BR91: =IF(COUNTIFS(在庫確認!B:B,マスタ_EOLリスト[[#This Row],[製品型番]])=0,"記載なし","") -> 記載なし | BS91: =COUNTIF(#REF!,マスタ_EOLリスト[[#This Row],[製品型番]]) -> #REF!
A92: R5-RL5 | B92: 4EOL(完全終息) | C92: 2GALLERIA-C | D92: R5-RL5 | E92: 189169 | F92: 組TFH GM5PG5O(15.6QHD 13700H 4050 230W L6 | G92: ID-O3 | H92: TFH-O3-13700H-4050-L6 raytrek | K92: i7-13700H | L92: 4050 | M92: 0 | N92: 0 | W92: 1000 | AL92: 45457 | AM92: 450 | AX92: 在庫無し | BM92: =IF(COUNTIFS('在庫使用計画 (ノート全体試算)'!C:C,マスタ_EOLリスト[[#This Row],[製品型番]])=0,"記載なし","") | BN92: =IF(COUNTIFS('在庫使用計画 (一般)'!C:C,マスタ_EOLリスト[[#This Row],[製品型番]])=0,"記載なし","") | BO92: =IF(COUNTIFS('在庫使用計画 (法人)'!C:C,マスタ_EOLリスト[[#This Row],[製品型番]])=0,"記載なし","") | BP92: =IF(COUNTIFS('在庫使用計画 (全体実績+予測）0701'!C:C,マスタ_EOLリスト[[#This Row],[製品型番]])=0,"記載なし","") | BQ92: =IF(COUNTIFS('在庫使用計画 (計画 予測)'!C:C,マスタ_EOLリスト[[#This Row],[製品型番]])=0,"記載なし","") -> 記載なし | BR92: =IF(COUNTIFS(在庫確認!B:B,マスタ_EOLリスト[[#This Row],[製品型番]])=0,"記載なし","") | BS92: =COUNTIF(#REF!,マスタ_EOLリスト[[#This Row],[製品型番]]) -> #REF!
A93: A4-R | B93: 4EOL(完全終息) | C93: 2GALLERIA-C | D93: A4-R | E93: 189170 | F93: 組UNW PH4PRX2(14WUXGA 13700H UMA 90W L6) | G93: 4H2 | H93: UNW-4H2-13700H-UMA-L6 raytrek | K93: i7-13700H | M93: 0 | N93: 0 | W93: 640 | AL93: 45435 | AM93: 620 | AX93: 在庫無し | BM93: =IF(COUNTIFS('在庫使用計画 (ノート全体試算)'!C:C,マスタ_EOLリスト[[#This Row],[製品型番]])=0,"記載なし","") | BN93: =IF(COUNTIFS('在庫使用計画 (一般)'!C:C,マスタ_EOLリスト[[#This Row],[製品型番]])=0,"記載なし","") | BO93: =IF(COUNTIFS('在庫使用計画 (法人)'!C:C,マスタ_EOLリスト[[#This Row],[製品型番]])=0,"記載なし","") | BP93: =IF(COUNTIFS('在庫使用計画 (全体実績+予測）0701'!C:C,マスタ_EOLリスト[[#This Row],[製品型番]])=0,"記載なし","") | BQ93: =IF(COUNTIFS('在庫使用計画 (計画 予測)'!C:C,マスタ_EOLリスト[[#This Row],[製品型番]])=0,"記載なし","") -> 記載なし | BR93: =IF(COUNTIFS(在庫確認!B:B,マスタ_EOLリスト[[#This Row],[製品型番]])=0,"記載なし","") | BS93: =COUNTIF(#REF!,マスタ_EOLリスト[[#This Row],[製品型番]]) -> #REF!
A94: #N/A | B94: 4EOL(完全終息) | C94: 3THIRDWAVE | D94: DX-M7L | E94: 199321 | F94: 組CLE L261TU-TD(R1 Thirdwave16FHD155U UMA65WL6 210 | G94: L26 | H94: CLE-L260-155U-UMA-L6 Thirdwave | I94: 16 | K94: u7-155U | L94: UMA | M94: 0 | N94: 0 | Q94: 在庫限り | R94: 在庫限り | W94: 485 | AB94: 203728 | AC94: 組CLE L261LU-TD(Thirdwave 16FHD+ 258V UMA 32G 65W | AK94: 194894 | AL94: 45525 | AM94: 70 | AN94: 65W | AO94: 20 | AQ94: Type-c | AU94: 65W | AV94: 65W以上 | AX94: 在庫無し | BM94: =IF(COUNTIFS('在庫使用計画 (ノート全体試算)'!C:C,マスタ_EOLリスト[[#This Row],[製品型番]])=0,"記載なし","") -> 記載なし | BN94: =IF(COUNTIFS('在庫使用計画 (一般)'!C:C,マスタ_EOLリスト[[#This Row],[製品型番]])=0,"記載なし","") -> 記載なし | BO94: =IF(COUNTIFS('在庫使用計画 (法人)'!C:C,マスタ_EOLリスト[[#This Row],[製品型番]])=0,"記載なし","") -> 記載なし | BP94: =IF(COUNTIFS('在庫使用計画 (全体実績+予測）0701'!C:C,マスタ_EOLリスト[[#This Row],[製品型番]])=0,"記載なし","") | BQ94: =IF(COUNTIFS('在庫使用計画 (計画 予測)'!C:C,マスタ_EOLリスト[[#This Row],[製品型番]])=0,"記載なし","") -> 記載なし | BR94: =IF(COUNTIFS(在庫確認!B:B,マスタ_EOLリスト[[#This Row],[製品型番]])=0,"記載なし","") | BS94: =COUNTIF(#REF!,マスタ_EOLリスト[[#This Row],[製品型番]]) -> #REF!
A95: #N/A | B95: 4EOL(完全終息) | C95: 3THIRDWAVE | D95: DX-M7L | E95: 202294 | F95: 組CLE L261TU-TD(R2 Thirdwave16FHD155U UMA65WL6 210 | G95: L26 | H95: CLE-L260-155U-UMA-L6 Thirdwave | I95: 16 | K95: u7-155U | L95: UMA | M95: 0 | N95: 0 | Q95: 在庫限り | R95: Copilot key対応版 | W95: 350 | AB95: 203728 | AC95: 組CLE L261LU-TD(Thirdwave 16FHD+ 258V UMA 32G 65W | AK95: 207650 | AL95: 45553 | AM95: 35 | AN95: 65W | AO95: 20 | AQ95: Type-c | AU95: 65W | AV95: 65W以上 | AX95: 在庫無し | BJ95: DX-16PN7A | BM95: =IF(COUNTIFS('在庫使用計画 (ノート全体試算)'!C:C,マスタ_EOLリスト[[#This Row],[製品型番]])=0,"記載なし","") -> 記載なし | BN95: =IF(COUNTIFS('在庫使用計画 (一般)'!C:C,マスタ_EOLリスト[[#This Row],[製品型番]])=0,"記載なし","") -> 記載なし | BO95: =IF(COUNTIFS('在庫使用計画 (法人)'!C:C,マスタ_EOLリスト[[#This Row],[製品型番]])=0,"記載なし","") -> 記載なし | BP95: =IF(COUNTIFS('在庫使用計画 (全体実績+予測）0701'!C:C,マスタ_EOLリスト[[#This Row],[製品型番]])=0,"記載なし","") | BQ95: =IF(COUNTIFS('在庫使用計画 (計画 予測)'!C:C,マスタ_EOLリスト[[#This Row],[製品型番]])=0,"記載なし","") -> 記載なし | BR95: =IF(COUNTIFS(在庫確認!B:B,マスタ_EOLリスト[[#This Row],[製品型番]])=0,"記載なし","") | BS95: =COUNTIF(#REF!,マスタ_EOLリスト[[#This Row],[製品型番]]) -> #REF!
A96: #N/A | B96: 4EOL(完全終息) | C96: 3THIRDWAVE | D96: DX-L7LA | E96: 203728 | F96: 組CLE L261LU-TD(Thirdwave 16FHD+ 258V UMA 32G 65W | G96: L26 | H96: CLE-L26-258V-UMA-32G-L7 Thirdwave | I96: 16 | J96: 必須 | K96: u7-258V | L96: UMA | M96: 0 | N96: 0 | P96: 45565 | Q96: 2026年3-5月頃 | R96: Copilot +PC | W96: 395 | AL96: 45553 | AM96: 35 | AN96: 65W | AO96: 20 | AQ96: Type-c | AU96: 65W | AV96: 65W以上 | AX96: 在庫無し | BM96: =IF(COUNTIFS('在庫使用計画 (ノート全体試算)'!C:C,マスタ_EOLリスト[[#This Row],[製品型番]])=0,"記載なし","") -> 記載なし | BN96: =IF(COUNTIFS('在庫使用計画 (一般)'!C:C,マスタ_EOLリスト[[#This Row],[製品型番]])=0,"記載なし","") -> 記載なし | BO96: =IF(COUNTIFS('在庫使用計画 (法人)'!C:C,マスタ_EOLリスト[[#This Row],[製品型番]])=0,"記載なし","") -> 記載なし | BP96: =IF(COUNTIFS('在庫使用計画 (全体実績+予測）0701'!C:C,マスタ_EOLリスト[[#This Row],[製品型番]])=0,"記載なし","") | BQ96: =IF(COUNTIFS('在庫使用計画 (計画 予測)'!C:C,マスタ_EOLリスト[[#This Row],[製品型番]])=0,"記載なし","") -> 記載なし | BR96: =IF(COUNTIFS(在庫確認!B:B,マスタ_EOLリスト[[#This Row],[製品型番]])=0,"記載なし","") | BS96: =COUNTIF(#REF!,マスタ_EOLリスト[[#This Row],[製品型番]]) -> #REF!
A97: #N/A | B97: 4EOL(完全終息) | C97: 3THIRDWAVE | D97: DX-L7LA | E97: 215699 | F97: 組CLE L261LU-TD(R1 Thirdwave16FHD+258V UMA32G65WL7 | G97: L26 | H97: CLE-L26-258V-UMA-32G-L7 Thirdwave | I97: 16 | J97: 必須 | K97: u7-258V | L97: UMA | M97: 0 | N97: 0 | Q97: 2026年3-5月頃 | R97: 4M LCD変更 | W97: 150 | AN97: 65W | AO97: 20 | AQ97: Type-c | AU97: 65W | AV97: 65W以上 | AX97: 在庫無し | BJ97: DX-16PN7A | BM97: =IF(COUNTIFS('在庫使用計画 (ノート全体試算)'!C:C,マスタ_EOLリスト[[#This Row],[製品型番]])=0,"記載なし","") -> 記載なし | BN97: =IF(COUNTIFS('在庫使用計画 (一般)'!C:C,マスタ_EOLリスト[[#This Row],[製品型番]])=0,"記載なし","") -> 記載なし | BO97: =IF(COUNTIFS('在庫使用計画 (法人)'!C:C,マスタ_EOLリスト[[#This Row],[製品型番]])=0,"記載なし","") -> 記載なし | BP97: =IF(COUNTIFS('在庫使用計画 (全体実績+予測）0701'!C:C,マスタ_EOLリスト[[#This Row],[製品型番]])=0,"記載なし","") | BQ97: =IF(COUNTIFS('在庫使用計画 (計画 予測)'!C:C,マスタ_EOLリスト[[#This Row],[製品型番]])=0,"記載なし","") -> 記載なし | BR97: =IF(COUNTIFS(在庫確認!B:B,マスタ_EOLリスト[[#This Row],[製品型番]])=0,"記載なし","") | BS97: =COUNTIF(#REF!,マスタ_EOLリスト[[#This Row],[製品型番]]) -> #REF!
A98: #N/A | B98: 4EOL(完全終息) | C98: 3THIRDWAVE | D98: DX-L7LA | E98: 223060 | F98: 組CLE L261LU-TD(R2 TW16FHD+258V UMA32G 65W L7 TPM) | G98: L26 | H98: CLE-L26-258V-UMA-32G-L7 Thirdwave | I98: 16 | M98: 0 | N98: 0 | AX98: 在庫無し | BJ98: DX-16PN7A | BM98: =IF(COUNTIFS('在庫使用計画 (ノート全体試算)'!C:C,マスタ_EOLリスト[[#This Row],[製品型番]])=0,"記載なし","") -> 記載なし | BN98: =IF(COUNTIFS('在庫使用計画 (一般)'!C:C,マスタ_EOLリスト[[#This Row],[製品型番]])=0,"記載なし","") -> 記載なし | BO98: =IF(COUNTIFS('在庫使用計画 (法人)'!C:C,マスタ_EOLリスト[[#This Row],[製品型番]])=0,"記載なし","") -> 記載なし | BP98: =IF(COUNTIFS('在庫使用計画 (全体実績+予測）0701'!C:C,マスタ_EOLリスト[[#This Row],[製品型番]])=0,"記載なし","") | BQ98: =IF(COUNTIFS('在庫使用計画 (計画 予測)'!C:C,マスタ_EOLリスト[[#This Row],[製品型番]])=0,"記載なし","") -> 記載なし | BR98: =IF(COUNTIFS(在庫確認!B:B,マスタ_EOLリスト[[#This Row],[製品型番]])=0,"記載なし","") | BS98: =COUNTIF(#REF!,マスタ_EOLリスト[[#This Row],[製品型番]]) -> #REF!
A99: DX-16PN7A | B99: 2発売中 | C99: 3THIRDWAVE | D99: DX-16PN7A | E99: 295636 | F99: 組CLE L261JU(TW 16FHD+ 355 UMA 32GB65WL7TPM) | G99: L26 | H99: CLE-L26-U7-355-UMA-32G-L7 Thirdwave | I99: 16 | J99: 必須 | K99: u7-355 | M99: 168 | N99: 168 | P99: 46049 | Q99: 2027年1-3月 | R99: 1/7受注開始、納期4w | AW99: TRUE | AX99: 組CLE L261JU(TW 16FHD+ 355 UMA 32GB65WL7T | BA99: Titanium Grey | BB99: Black | BC99: Titanium Grey | BD99: Titanium Grey | BJ99: x | BM99: =IF(COUNTIFS('在庫使用計画 (ノート全体試算)'!C:C,マスタ_EOLリスト[[#This Row],[製品型番]])=0,"記載なし","") | BN99: =IF(COUNTIFS('在庫使用計画 (一般)'!C:C,マスタ_EOLリスト[[#This Row],[製品型番]])=0,"記載なし","") | BO99: =IF(COUNTIFS('在庫使用計画 (法人)'!C:C,マスタ_EOLリスト[[#This Row],[製品型番]])=0,"記載なし","") | BP99: =IF(COUNTIFS('在庫使用計画 (全体実績+予測）0701'!C:C,マスタ_EOLリスト[[#This Row],[製品型番]])=0,"記載なし","") | BQ99: =IF(COUNTIFS('在庫使用計画 (計画 予測)'!C:C,マスタ_EOLリスト[[#This Row],[製品型番]])=0,"記載なし","") | BR99: =IF(COUNTIFS(在庫確認!B:B,マスタ_EOLリスト[[#This Row],[製品型番]])=0,"記載なし","") -> 記載なし | BS99: =COUNTIF(#REF!,マスタ_EOLリスト[[#This Row],[製品型番]]) -> #REF!
A100: DX-16PN7A | B100: 2発売中 | C100: 3THIRDWAVE | D100: DX-16PN7A | E100: 367378 | F100: 組CLE L261JU(R1TW 16FHD+ 355 UMA 32GB65WL7TPM) | G100: L26 | H100: CLE-L26-U7-355-UMA-32G-L7 Thirdwave | I100: 16 | J100: 必須 | K100: u7-355 | M100: 0 | N100: 0 | P100: 46049 | Q100: 2027年1-3月 | R100: 1/7受注開始、納期4w | AW100: TRUE | AX100: 在庫無し | BA100: Titanium Grey | BB100: Black | BC100: Titanium Grey | BD100: Titanium Grey | BJ100: x | BM100: =IF(COUNTIFS('在庫使用計画 (ノート全体試算)'!C:C,マスタ_EOLリスト[[#This Row],[製品型番]])=0,"記載なし","") | BN100: =IF(COUNTIFS('在庫使用計画 (一般)'!C:C,マスタ_EOLリスト[[#This Row],[製品型番]])=0,"記載なし","") | BO100: =IF(COUNTIFS('在庫使用計画 (法人)'!C:C,マスタ_EOLリスト[[#This Row],[製品型番]])=0,"記載なし","") | BP100: =IF(COUNTIFS('在庫使用計画 (全体実績+予測）0701'!C:C,マスタ_EOLリスト[[#This Row],[製品型番]])=0,"記載なし","") | BQ100: =IF(COUNTIFS('在庫使用計画 (計画 予測)'!C:C,マスタ_EOLリスト[[#This Row],[製品型番]])=0,"記載なし","") | BR100: =IF(COUNTIFS(在庫確認!B:B,マスタ_EOLリスト[[#This Row],[製品型番]])=0,"記載なし","") -> 記載なし | BS100: =COUNTIF(#REF!,マスタ_EOLリスト[[#This Row],[製品型番]]) -> #REF!
...

Sheet 基準データ
B2: 事業年度 | C2: 43 | D2: 期 | G2: 検索フォルダ名 | H2: ファイル名 | I2: 更新日時 | N2: 期 | O2: 40 | P2: 41 | Q2: 42 | R2: 43
B3: 期間 | C3: =DATE($C$2+1982,8,1) -> 45870 | D3: ～ | E3: =DATE($C$2+1983,7,31) -> 46234 | G3: 43上期 | H3: 【日次】ノート集計【2026年7月】_0702.xlsx | I3: 46206.535 | N3: 販売台数 | O3: 36293 | P3: 41075 | Q3: 41710 | R3: 21838
N4: SKU | O4: 44 | P4: 64 | Q4: 59 | R4: 37
B5: 基準日(最新出荷日) | C5: {=INT(実績ファイル更新日時[更新日時])-1} -> 46205 | E5: =TODAY() -> 46209 | N5: 台/SKU | O5: =O3/O4 -> 824.84091 | P5: =P3/P4 -> 641.79688 | Q5: =Q3/Q4 -> 706.94915 | R5: =R3/R4 -> 590.21622
B6: 月初日 | C6: =EOMONTH($C$5,-1)+1 -> 46204
B7: 月末日 | C7: =EOMONTH($C$5,0) -> 46234 | N7: 台数予算 | Q7: 30000
B8: 当月残日数 | C8: =C7-C5 -> 29 | N8: 必要SKU（800台/SKUとした場合） | Q8: =Q7/800 -> 37.5
B9: 残月割合 | C9: =($C$7-$C$5)/DAY($C$7) -> 0.93548387

Sheet このファイルについて
A2: ■ファイルの目的
B3: 製品の在庫過不足を確認し、購買の追加発注判断をかけるために、各販売計画を集計します。
B4: また、その妥当性（無理のある計画ではないか？）の判断も行います。
A7: ■概要
B8: 法人、一般の製品担当が販売計画を作成、合わせて全体としての計画数を集計します。
B9: 実績・予測値から妥当性を判断し、問題がある（予測と計画の差異が大きい）場合は各担当に確認します。
B10: ➡施策予定があり販売計画が上がる、競合や市場動向から計画が落ち込むなど、乖離が納得できるものならOK
B11: 妥当性判断ができたら集計したファイルを購買の『NoteONE計画』に反映します。
B12: ➡購買はこれを元に在庫手配、追加発注を行います。
B13: \\172.25.20.11\サードウェーブグループ\41上期\サードウェーブ\購買本部\【通常業務】\ONE
A18: ■大まかな流れ
B19: 在庫使用計画（一般）、在庫使用計画（法人）で更新された数値の合計が、在庫使用計画（ノート全体試算）に反映。
B20: 反映されたファイルについて、最新使用計画（mmdd更新）※mmddは日付でコピーを作成、それをもとにONE計画を更新。
B21: 日次集計ファイルは、最新使用計画（mmdd更新）の最新の日付を確認し、新しくなっていれば集計ファイルに反映。
B22: その際に、法人 一般もあわせて更新する。
B24: 企画： | C24: 『在庫使用計画（一般）』を更新。
B25: 法人： | C25: 『在庫使用計画（法人）』を更新。
B26: ノート担当： | C26: 週一回、ファイル更新を確認し、NoteONE計画のファイルを更新します。（月～火の午前中）
C27: 『在庫使用計画（全体）』をコピー、名称を『在庫使用計画（mmdd）』（mmddは更新日）に変更。
C28: 在庫使用計画 (計画 予測)のシートを確認し、計画を検証。（実績との乖離や在庫数が適正か確認）
C29: ↑の更新ファイルをもとに、購買がOne計画を更新
C30: 市村さんに連絡し、ノート日次集計のファイルに反映してもらう。
B32: 責任範囲 | Q32: tips
B33: 企画： | C33: 『在庫使用計画（一般）』のシート | Q33: ・Power Query更新時に「外部データのフォーマットが不正」といったエラーが出ることがあるが、
B34: 法人： | C34: 『在庫使用計画（法人）』のシート | Q34: Power Queryのプロセスが残留してしまっていることが原因の場合がある。
B35: ノート担当： | C35: 更新連絡を受けた後の購買への変更依頼（ONEファイルへの反映） | Q35: この場合、Microsoft.Mashup.Container.Loader.exeをタスクマネージャーから落とすことで改善
C36: 販売計画の妥当性確認、異常と見える場合は要素（施策対応、状況など）を確認。
C37: 必要に応じて、各担当者に計画再修正を行ってもらう。
A40: ■ファイルの構成
B41: 【在庫使用計画（全体実績+予測）】：先月までは実績、当月は着地予測を入力、次月以降は過去の係数（ブランドごとの前月比係数）をもとに予測値を試算
C42: 前月までは実績、当月は着地予測、次月以降は「当月予測x係数」による予測
B43: 【在庫使用計画 (ノート全体試算)】：TWとして全体の販売計画数を表示、このファイルをもとに日付ファイルを作成し、NoteONE計画のファイルに反映する
C44: 在庫使用計画 (一般)：製品担当者が一般分（通販・店舗）の販売計画を入力
C45: 在庫使用計画 (法人)：法人担当者が法人（法人営業分）の販売計画を入力
B46: 【在庫確認】：起点時（基本的には月初時点）の在庫と注残を確認。この先4か月、つまりこれから発注するものが入荷するまで販売計画を満たす在庫があるかどうか
C47: SAP貼り付け(901) ※()内は更新日付：SAPデータを貼り付け
C48: Onenote貼り付け(901) ※()内は更新日付：ONEデータを貼り付け
B50: 43期 | C50: 今期の予算と実績
B51: 在庫使用計画（mmdd）：最新の販売計画（過去計画の履歴）
A54: ■週次の作業ながれ
B55: 毎週 月曜日 | C55: SAP貼り付け(mmdd)シートの更新 | I55: Power Query
C56: 「Onenote貼り付け(mmdd)」シート更新 | I56: Power Query
C57: 「マスタ」シート更新 | I57: Power Query
C58: 【在庫使用計画（計画 予測）】のシートを確認。
C59: 「在庫使用計画(mmdd)」シートのバックアップと「4ヶ月計」シートの推移を追加更新 | N59: バックアップ&差分検出VBAを作成し、置換済
C60: 「(全体実績+予測）の元データ」シートを「在庫使用計画 (全体実績+予測）」シートに貼り付け→数値貼り付け
C61: ↑在庫管理業務ファイルを開かなくても全員が見れるようにするため
B62: 発注するものの確認 | C62: ・計画（白のライン）で赤文字（4か月計画に対し、在庫の不足が発生）が出てないか確認。
C63: 合わせて実績（緑のライン）で赤文字（4か月計画に対し、在庫の不足が発生）が出てないか確認。 | T63: 以下 Note ONE計画 更新方法のシートに記載
C64: ・赤文字が出ている部分に対し、詳細を確認、例）法人の案件が入っている など。計画と実績が乖離している場合は要注意。
C65: この場合、まずは状況の把握。（例1 販売直後で乖離が出ている。例2 直近納品までのつなぎとして、販売抑制をかけた）など | T65: ■更新方法（企画側）
C66: 状況把握したうえで妥当と判断できればそのままでOK。 | S66: 1 | T66: 販売計画のシートで最新版をコピー。更新日の日付でシートを作成。
C67: 計画・実績予測の乖離に説明ができない場合、各担当者に確認。 | S67: 2 | T67: 1.で作ったシートを計算式→数字に変換。（Ctrl + A,Ctrl +Cで全体コピーして、数字で貼り付けを選択）
C68: ・説明可能な状況になったら、【在庫使用計画 (ノート全体試算)】のシートをコピーし、名称を在庫使用計画 (mmdd)に変更。 ※mmddは当日の日付 | T68: （目的はデータを軽くすることと、このシートに張り付けるときにリンクが残らないようにすること）
C69: 新しく作った【在庫使用計画 (mmdd)】のシートをCtrl+A で全選択、オールコピーしたうえで同じ場所に数字として貼り付け | S69: 3 | T69: 2.で作ったデータをそのままコピーして、販売計画のシートに貼り付け。
C70: ・ファイルが出来たら、↓「NoteONE計画.xlsm」ファイルを開き、「販売計画_最新(mmdd)」シートに上記シート内容をコピー | T70: 2.と同じく Ctrl + A,Ctrl +Cでコピーして数字で貼り付け
C71: ONE ファイル | T71: シート名を販売計画_24xxxx ←更新日に変更
C72: ※詳細はNoteONE計画の 更新方法のシート手順参照。手動保存を忘れがちなので注意 | S72: 4 | T72: 部品予測のシートを確認
C73: ・「ONE_08_NotePC_社外秘」ファイル「販売計画」シートの直近の入荷予定機種を中心に、変更が反映されているか確認（3期種以上） | T73: 販売計画が反映されているか、エラーが出ていないか確認。
C75: ・市村さんに連絡（Team「デマンド計画 ノート（ONE）計画 更新連絡」） | T75: 部品予測のシートに、新規発注製品がある場合
C76: ノート販売（ONE）計画 更新連絡 | T76: E列に販売型番を登録
C77: ↑ここにて更新を連絡 to 購買 cc 市村さん 企画関係者
A80: ■月次の作業ながれ①
B81: 月末 | C81: 「x月分ノート報告(企画・法人)」会議時に使用するデータを作成するため、前述会議開催の週頭に行う
C82: 理想としては、数日前には各担当に乖離機種について修正依頼を行い、会議時に回答を得る形
C83: x月分宿題（修正依頼） ノートPC相談室のteams
C84: 【在庫使用計画（計画 予測）】のシートを確認。
C85: ファイルの目的は、在庫-計画-販売を適正化し、在庫過不足なく動かすこと
C86: にあるので、それぞれの乖離について振り返りと先の対応を確認する必要がある。
C87: ※基本的に各担当者は週次更新することになっているが、見切れていない部分を指摘する必要がある。
B89: 作業目的 | C89: ① 各担当者に来月以降の適正な計画値を入力してもらうこと （無理な計画やそれによる混乱を事前に防ぐ）
C90: 同時に、在庫過剰についてもアラートを出し、売り切りまでの施策準備をしてもらう。
C91: ② 購買に対し、修正した計画で発注手配をしてもらう。
C92: （基本的に週次の更新と同じ）
B94: 実作業 | C94: 各種チェックをするためにステータスを更新にする必要があります。
C95: 在庫状況 / 注残状況 / 販売状況(当月着地見込み)
C96: MTG直前の月曜時点での状況に合わせる（週次更新と合わせて対応できるため）
C97: 1.【在庫状況の更新】 SAP貼り付けを最新のデータ（月曜時点）に更新
C98: 2.【注残状況の更新】 Onenote貼り付けを最新のデータ（月曜時点）に更新
C99: ※1. 2.は週次更新と同じファイルをはりつければOK
C100: 3.【販売状況の更新】 在庫使用計画（全体実績+予測）のシート、各モデル当月の販売見込みについて、週次ファイルの着地見込み数を入力
C101: 4.【4か月計画の確認】 在庫使用計画 (計画 予測) 4か月計画の項目を翌月以降の4カ月合計に変更
C102: ※20日時点など、月末までに日数がある場合は当月分の補正を追加する
C103: 20日なら +当月計画 * 0.5、25日なら +当月計画*0.25 など（概算見込みでOK）
C104: ↑ここまでが事前準備
C106: 在庫使用計画 (計画 予測) のシートを確認
C107: ・計画と実績の乖離が大きいものをアラート。計画変更をかけるか、施策対応をいれるか担当者に回答を求める
... C115: 翌週明けの購買とのMTGで、受け取った回答を購買に共有
A119: ■月次の作業ながれ②
B120: 月初 | C120: 「在庫使用計画 (全体実績+予測）」シートの更新 | P120: 45870 | Q120: 45901 | R120: 45931 | S120: 45962
C121: 前月を着地予測から結果に書き換えし、当月を着地予測に変更 | N121: RL7C-R45-5N | P121: 764 | Q121: 617 | R121: 558.18883 | S121: 585.80828
P122: ↑前月結果
Q123: ↑当月は着地予測
R124: ↑翌月以降は当月着地予測×前月比
A127: ■新規モデル追加時対応
B128: 1 | C128: 在庫使用計画 (一般)、在庫使用計画 (法人)、在庫使用計画 (全体実績+予測）、在庫使用計画 (4ヶ月）、在庫使用計画 (ノート全体試算)、在庫使用計画 (計画 予測)、在庫確認の7シートに列追加。
B129: 2 | C129: 数式の確認とコピー作業時の過去実績等不要データが残っていないか確認。
B130: 3 | C130: モデル追加した旨、各ラインナップ担当に連絡し、計画の記入を依頼。チーム「ノート相談室」にてスレッドを立てる。
B131: 4 | C131: 購買にONEの更新を依頼。＠まいけるさん（行追加と参照の設定を依頼。）
B132: 5 | C132: 1 の各シートにスペック等を記載。ソースは企画書（Teamsで検索）
...

Sheet 在庫使用計画 (4ヶ月計)
B1: GALLERIA | C1: model名 | D1: 品目 | E1: CPU | F1: GPU | G1: メモリ | H1: 在庫+注残 | I1: 次回入荷日 | J1: 次回入荷数量 | K1: 922 | L1: 929 | M1: 1003 | N1: 1006 | O1: 1014 | P1: 1016 | Q1: 1020 | R1: 1027 | S1: 1028 | T1: 1105 | U1: 1110 | V1: 1111 | W1: 1112 | X1: 1117 | Y1: 1118 | Z1: 1120 | AA1: 1125 | AB1: 1128 | AC1: 1202 | AD1: 1205 | AE1: 1211 | AF1: 1215 | AG1: 1219 | AH1: 1224 | AI1: 0105 | AJ1: 0115 | AK1: 0119 | AL1: 0120 | AM1: 0121 | AN1: 0128 | AO1: 0129 | AP1: 0202 | AQ1: 0209 | AR1: 0210 | AS1: 0213 | AT1: 0216 | AU1: 0218
A2: 18"-G | B2: {=IF(C2:C27="","",_xlfn.XLOOKUP(C2:C27,マスタ_EOLリスト[製品型番],マスタ_EOLリスト[綽名]))} -> CLE-X58-275HX-5090-L6 | C2: UL9C-R59-8A | D2: {=IF($C2:$C27<>"", _xlfn.MAXIFS(#REF!,マスタ_EOLリスト[製品型番],$C2:$C27), "")} -> #REF! | E2: ARL i9-275HX | F2: 5090 | G2: DDR5 | H2: {=IF($C2:$C27<>"", _xlfn.XLOOKUP($C2:$C27, '在庫使用計画 (ノート全体試算)'!C:C, '在庫使用計画 (ノート全体試算)'!G:G),"")} -> 66 | I2: {=IF(_xlfn.ANCHORARRAY(D2)<>"", _xlfn.XLOOKUP(_xlfn.ANCHORARRAY(D2),購買計画one_note_貼り付け[コード],購買計画one_note_貼り付け[納品日],""), "")} -> #REF! | J2: {=IF(_xlfn.ANCHORARRAY(D2)<>"", _xlfn.XLOOKUP(_xlfn.ANCHORARRAY(D2),購買計画one_note_貼り付け[コード],購買計画one_note_貼り付け[数量],""), "")} -> #REF! | K2: 157.70079 | L2: 186.6368 | M2: 186.6368 | N2: 186.6368 | O2: 165.6368 | P2: 165.6368 | Q2: 165.6368 | R2: 165.6368 | S2: 165.6368 | T2: 190 | U2: 190 | V2: 190 | W2: 190 | X2: 190 | Y2: 190 | Z2: 190 | AA2: 190 | AB2: 227 | AC2: 227 | AD2: 227 | AE2: 181.77703 | AF2: 181.77703 | AG2: 164.09835 | AH2: 164.09835 | AI2: 143.10704 | AJ2: 143.10704 | AK2: 159.41505 | AL2: 160.41505 | AM2: 160.41505 | AN2: 160.41505 | AO2: 160.41505 | AP2: 141.94174 | AQ2: 144.94174 | AR2: 144.94174 | AS2: 144.94174 | AT2: 144.94174 | AU2: 176.94174 | AV2: {=IFERROR(_xlfn.XLOOKUP($C2, INDIRECT("'在庫使用計画 ("&AV$1&")'!D:D"), INDIRECT("'在庫使用計画 ("&AV$1&")'!I:I") ),"")} | AW2: {=IFERROR(_xlfn.XLOOKUP($C2, INDIRECT("'在庫使用計画 ("&AW$1&")'!D:D"), INDIRECT("'在庫使用計画 ("&AW$1&")'!I:I") ),"")} | AX2: {=IFERROR(_xlfn.XLOOKUP($C2, INDIRECT("'在庫使用計画 ("&AX$1&")'!D:D"), INDIRECT("'在庫使用計画 ("&AX$1&")'!I:I") ),"")}
B3: CLE-X58-290HXP-5090-L6-GG | C3: NMC9L-R59-G8 | D3: #REF! | H3: 137 | I3: #REF! | J3: #REF! | AQ3: 26.921683
B4: #N/A | C4: NMC9L-R58-G6 | D4: #REF! | H4: #N/A | I4: #REF! | J4: #REF! | AQ4: 0
AV5: {=IFERROR(_xlfn.XLOOKUP($C5, INDIRECT("'在庫使用計画 ("&AV$1&")'!D:D"), INDIRECT("'在庫使用計画 ("&AV$1&")'!I:I") ),"")} | AW5: {=IFERROR(_xlfn.XLOOKUP($C5, INDIRECT("'在庫使用計画 ("&AW$1&")'!D:D"), INDIRECT("'在庫使用計画 ("&AW$1&")'!I:I") ),"")} | AX5: {=IFERROR(_xlfn.XLOOKUP($C5, INDIRECT("'在庫使用計画 ("&AX$1&")'!D:D"), INDIRECT("'在庫使用計画 ("&AX$1&")'!I:I") ),"")}
A6: 16”-G | B6: UNW-K-9955HX-5070Ti-L6 | C6: ZL9R-R57T-6 | D6: #REF! | E6: FRR 9955HX | F6: 5070Ti | G6: DDR5 | H6: 11 | I6: #REF! | J6: #REF! | K6: 581.02728 | L6: 550.40934 | M6: 508.89653 | N6: 508.89653 | O6: 508.89653 | P6: 508.89653 | Q6: 508.89653 | R6: 508.89653 | S6: 508.89653 | T6: 497.94982 | U6: 497.94982 | V6: 497.94982 | W6: 497.94982 | X6: 497.94982 | Y6: 497.94982 | Z6: 545.94982 | AA6: 545.94982 | AB6: 602.33455 | AC6: 602.33455 | AD6: 602.33455 | AE6: 273.49833 | AF6: 273.49833 | AG6: 281.34424 | AH6: 281.34424 | AI6: 289.37465 | AJ6: 289.37465 | AK6: 324.75962 | AL6: 324.75962 | AM6: 324.75962 | AN6: 324.75962 | AO6: 324.75962 | AP6: 296.82522 | AQ6: 311.82522 | AR6: 311.82522 | AS6: 311.82522 | AT6: 311.82522 | AU6: 311.82522 | AV6: {=IFERROR(_xlfn.XLOOKUP($C6, INDIRECT("'在庫使用計画 ("&AV$1&")'!D:D"), INDIRECT("'在庫使用計画 ("&AV$1&")'!I:I") ),"")} | AW6: {=IFERROR(_xlfn.XLOOKUP($C6, INDIRECT("'在庫使用計画 ("&AW$1&")'!D:D"), INDIRECT("'在庫使用計画 ("&AW$1&")'!I:I") ),"")} | AX6: {=IFERROR(_xlfn.XLOOKUP($C6, INDIRECT("'在庫使用計画 ("&AX$1&")'!D:D"), INDIRECT("'在庫使用計画 ("&AX$1&")'!I:I") ),"")}
B7: #N/A | C7: NDR9L-R57T-G6Z | D7: #REF! | E7: ARL-HX U9-275HX | F7: 5070Ti | G7: DDR5 | H7: #N/A | I7: #REF! | J7: #REF! | K7: 499.77757 | L7: 488.11959 | M7: 302.68606 | N7: 302.68606 | O7: 305.68606 | P7: 305.68606 | Q7: 305.68606 | R7: 305.68606 | S7: 305.68606 | T7: 297.44417 | U7: 297.44417 | V7: 297.44417 | W7: 297.44417 | X7: 297.44417 | Y7: 297.44417 | Z7: 297.44417 | AA7: 297.44417 | AB7: 329.62264 | AC7: 329.62264 | AD7: 329.62264 | AE7: 499.99666 | AF7: 499.99666 | AG7: 496.6393 | AH7: 496.6393 | AI7: 511.69578 | AJ7: 511.69578 | AK7: 459.64838 | AL7: 459.64838 | AM7: 459.64838 | AN7: 459.64838 | AO7: 459.64838 | AP7: 433.11925 | AQ7: 0 | AR7: 0 | AS7: 0 | AT7: 0 | AV7: {=IFERROR(_xlfn.XLOOKUP($C7, INDIRECT("'在庫使用計画 ("&AV$1&")'!D:D"), INDIRECT("'在庫使用計画 ("&AV$1&")'!I:I") ),"")} | AW7: {=IFERROR(_xlfn.XLOOKUP($C7, INDIRECT("'在庫使用計画 ("&AW$1&")'!D:D"), INDIRECT("'在庫使用計画 ("&AW$1&")'!I:I") ),"")} | AX7: {=IFERROR(_xlfn.XLOOKUP($C7, INDIRECT("'在庫使用計画 ("&AX$1&")'!D:D"), INDIRECT("'在庫使用計画 ("&AX$1&")'!I:I") ),"")}
B8: UNW-K-275HX-5070Ti-L6 | C8: ZL9C-R57T-6A | D8: #REF! | E8: ARL-HX U9-275HX | F8: 5070Ti | G8: DDR5 | H8: 553 | I8: #REF! | J8: #REF! | K8: 499.77757 | L8: 488.11959 | M8: 302.68606 | N8: 302.68606 | O8: 305.68606 | P8: 305.68606 | Q8: 305.68606 | R8: 305.68606 | S8: 305.68606 | T8: 297.44417 | U8: 297.44417 | V8: 297.44417 | W8: 297.44417 | X8: 297.44417 | Y8: 297.44417 | Z8: 297.44417 | AA8: 297.44417 | AB8: 329.62264 | AC8: 329.62264 | AD8: 329.62264 | AE8: 499.99666 | AF8: 499.99666 | AG8: 496.6393 | AH8: 496.6393 | AI8: 511.69578 | AJ8: 511.69578 | AK8: 459.64838 | AL8: 459.64838 | AM8: 459.64838 | AN8: 459.64838 | AO8: 459.64838 | AP8: 433.11925 | AQ8: 455.11925 | AR8: 467.11925 | AS8: 467.11925 | AT8: 467.11925 | AU8: 467.11925 | AV8: {=IFERROR(_xlfn.XLOOKUP($C8, INDIRECT("'在庫使用計画 ("&AV$1&")'!D:D"), INDIRECT("'在庫使用計画 ("&AV$1&")'!I:I") ),"")} | AW8: {=IFERROR(_xlfn.XLOOKUP($C8, INDIRECT("'在庫使用計画 ("&AW$1&")'!D:D"), INDIRECT("'在庫使用計画 ("&AW$1&")'!I:I") ),"")} | AX8: {=IFERROR(_xlfn.XLOOKUP($C8, INDIRECT("'在庫使用計画 ("&AX$1&")'!D:D"), INDIRECT("'在庫使用計画 ("&AX$1&")'!I:I") ),"")}
B9: UNW-K-290HXP-5070Ti-L6 | C9: NDC9L-R57T-G6 | D9: #REF! | E9: ARL-HX U7-255HX | F9: 5070 | G9: DDR5 | H9: #N/A | I9: #REF! | J9: #REF! | K9: 433.93619 | L9: 431.12627 | M9: 328.10521 | N9: 328.10521 | O9: 361.10521 | P9: 361.10521 | Q9: 361.10521 | R9: 361.10521 | S9: 361.10521 | T9: 440.89273 | U9: 424.30866 | V9: 424.30866 | W9: 424.30866 | X9: 424.30866 | Y9: 424.30866 | Z9: 424.30866 | AA9: 424.30866 | AB9: 583.01245 | AC9: 583.01245 | AD9: 583.01245 | AE9: 358.27536 | AF9: 358.27536 | AG9: 386.54095 | AH9: 386.54095 | AI9: 379.58873 | AJ9: 379.58873 | AK9: 416.59963 | AL9: 416.59963 | AM9: 416.59963 | AN9: 416.59963 | AO9: 416.59963 | AP9: 384.17888 | AQ9: 0 | AR9: 0 | AS9: 0 | AT9: 0 | AU9: 0 | AV9: {=IFERROR(_xlfn.XLOOKUP($C9, INDIRECT("'在庫使用計画 ("&AV$1&")'!D:D"), INDIRECT("'在庫使用計画 ("&AV$1&")'!I:I") ),"")} | AW9: {=IFERROR(_xlfn.XLOOKUP($C9, INDIRECT("'在庫使用計画 ("&AW$1&")'!D:D"), INDIRECT("'在庫使用計画 ("&AW$1&")'!I:I") ),"")} | AX9: {=IFERROR(_xlfn.XLOOKUP($C9, INDIRECT("'在庫使用計画 ("&AX$1&")'!D:D"), INDIRECT("'在庫使用計画 ("&AX$1&")'!I:I") ),"")}
B10: UNW-K-255HX-5070-L6 | C10: ZL7C-R57-6A | D10: #REF! | E10: ARL-HX U7-255HX | F10: 5070 | G10: DDR5 | H10: 268 | I10: #REF! | J10: #REF! | K10: 433.93619 | L10: 431.12627 | M10: 328.10521 | N10: 328.10521 | O10: 361.10521 | P10: 361.10521 | Q10: 361.10521 | R10: 361.10521 | S10: 361.10521 | T10: 440.89273 | U10: 424.30866 | V10: 424.30866 | W10: 424.30866 | X10: 424.30866 | Y10: 424.30866 | Z10: 424.30866 | AA10: 424.30866 | AB10: 583.01245 | AC10: 583.01245 | AD10: 583.01245 | AE10: 358.27536 | AF10: 358.27536 | AG10: 386.54095 | AH10: 386.54095 | AI10: 379.58873 | AJ10: 379.58873 | AK10: 416.59963 | AL10: 416.59963 | AM10: 416.59963 | AN10: 416.59963 | AO10: 416.59963 | AP10: 384.17888 | AQ10: 371.17888 | AR10: 319.17343 | AS10: 319.17343 | AT10: 319.17343 | AU10: 319.17343 | AV10: {=IFERROR(_xlfn.XLOOKUP($C10, INDIRECT("'在庫使用計画 ("&AV$1&")'!D:D"), INDIRECT("'在庫使用計画 ("&AV$1&")'!I:I") ),"")} | AW10: {=IFERROR(_xlfn.XLOOKUP($C10, INDIRECT("'在庫使用計画 ("&AW$1&")'!D:D"), INDIRECT("'在庫使用計画 ("&AW$1&")'!I:I") ),"")} | AX10: {=IFERROR(_xlfn.XLOOKUP($C10, INDIRECT("'在庫使用計画 ("&AX$1&")'!D:D"), INDIRECT("'在庫使用計画 ("&AX$1&")'!I:I") ),"")}
B11: UNW-K-270HXP-5070-L6 | C11: NDC7L-R57-G6 | D11: #REF! | E11: Ryzen AI 7-350 | F11: 5060 | G11: DDR5 | H11: #N/A | I11: #REF! | J11: #REF! | K11: 317.37121 | L11: 325.36413 | M11: 411.95151 | N11: 411.95151 | O11: 411.95151 | P11: 411.95151 | Q11: 411.95151 | R11: 411.95151 | S11: 411.95151 | T11: 451.95151 | U11: 451.95151 | V11: 451.95151 | W11: 451.95151 | X11: 451.95151 | Y11: 451.95151 | Z11: 451.95151 | AA11: 451.95151 | AB11: 443.39759 | AC11: 443.39759 | AD11: 443.39759 | AE11: 384.66221 | AF11: 384.66221 | AG11: 297.6393 | AH11: 297.6393 | AI11: 279.69578 | AJ11: 279.69578 | AK11: 246.24243 | AL11: 276.24243 | AM11: 276.24243 | AN11: 276.24243 | AO11: 276.24243 | AP11: 262.23714 | AQ11: 0 | AR11: 0 | AS11: 0 | AT11: 0 | AU11: 0 | AV11: {=IFERROR(_xlfn.XLOOKUP($C11, INDIRECT("'在庫使用計画 ("&AV$1&")'!D:D"), INDIRECT("'在庫使用計画 ("&AV$1&")'!I:I") ),"")} | AW11: {=IFERROR(_xlfn.XLOOKUP($C11, INDIRECT("'在庫使用計画 ("&AW$1&")'!D:D"), INDIRECT("'在庫使用計画 ("&AW$1&")'!I:I") ),"")} | AX11: {=IFERROR(_xlfn.XLOOKUP($C11, INDIRECT("'在庫使用計画 ("&AX$1&")'!D:D"), INDIRECT("'在庫使用計画 ("&AX$1&")'!I:I") ),"")}
B12: CLE-V56-350-5060-L6 | C12: XL7R-R56-6A | D12: #REF! | E12: Ryzen AI 7-350 | F12: 5060 | G12: DDR5 | H12: 0 | I12: #REF! | J12: #REF! | K12: 317.37121 | L12: 325.36413 | M12: 411.95151 | N12: 411.95151 | O12: 411.95151 | P12: 411.95151 | Q12: 411.95151 | R12: 411.95151 | S12: 411.95151 | T12: 451.95151 | U12: 451.95151 | V12: 451.95151 | W12: 451.95151 | X12: 451.95151 | Y12: 451.95151 | Z12: 451.95151 | AA12: 451.95151 | AB12: 443.39759 | AC12: 443.39759 | AD12: 443.39759 | AE12: 384.66221 | AF12: 384.66221 | AG12: 297.6393 | AH12: 297.6393 | AI12: 279.69578 | AJ12: 279.69578 | AK12: 246.24243 | AL12: 276.24243 | AM12: 276.24243 | AN12: 276.24243 | AO12: 276.24243 | AP12: 262.23714 | AQ12: 254.23714 | AR12: 254.23714 | AS12: 254.23714 | AT12: 254.23714 | AU12: 254.23714 | AV12: {=IFERROR(_xlfn.XLOOKUP($C12, INDIRECT("'在庫使用計画 ("&AV$1&")'!D:D"), INDIRECT("'在庫使用計画 ("&AV$1&")'!I:I") ),"")} | AW12: {=IFERROR(_xlfn.XLOOKUP($C12, INDIRECT("'在庫使用計画 ("&AW$1&")'!D:D"), INDIRECT("'在庫使用計画 ("&AW$1&")'!I:I") ),"")} | AX12: {=IFERROR(_xlfn.XLOOKUP($C12, INDIRECT("'在庫使用計画 ("&AX$1&")'!D:D"), INDIRECT("'在庫使用計画 ("&AX$1&")'!I:I") ),"")}
B13: UNW-U-255HX-5060-L6 | C13: XL7C-R56-6A | D13: #REF! | E13: ARL-HX U7-255HX | F13: 5060 | G13: DDR5 | H13: 5 | I13: #REF! | J13: #REF! | K13: 587.65526 | L13: 619.74084 | M13: 187.94817 | N13: 187.94817 | O13: 185.94817 | P13: 185.94817 | Q13: 185.94817 | R13: 185.94817 | S13: 185.94817 | T13: 284.75548 | U13: 284.75548 | V13: 284.75548 | W13: 284.75548 | X13: 284.75548 | Y13: 284.75548 | Z13: 284.75548 | AA13: 284.75548 | AB13: 423.82859 | AC13: 423.82859 | AD13: 448.82859 | AE13: 332.44696 | AF13: 332.44696 | AG13: 318.3989 | AH13: 318.3989 | AI13: 332.07136 | AJ13: 332.07136 | AK13: 351.20739 | AL13: 351.20739 | AM13: 351.20739 | AN13: 351.20739 | AO13: 351.20739 | AP13: 346.23578 | AQ13: 350.23578 | AR13: 233.23578 | AS13: 233.23578 | AT13: 233.23578 | AU13: 233.23578 | AV13: {=IFERROR(_xlfn.XLOOKUP($C13, INDIRECT("'在庫使用計画 ("&AV$1&")'!D:D"), INDIRECT("'在庫使用計画 ("&AV$1&")'!I:I") ),"")} | AW13: {=IFERROR(_xlfn.XLOOKUP($C13, INDIRECT("'在庫使用計画 ("&AW$1&")'!D:D"), INDIRECT("'在庫使用計画 ("&AW$1&")'!I:I") ),"")} | AX13: {=IFERROR(_xlfn.XLOOKUP($C13, INDIRECT("'在庫使用計画 ("&AX$1&")'!D:D"), INDIRECT("'在庫使用計画 ("&AX$1&")'!I:I") ),"")}
AV14: {=IFERROR(_xlfn.XLOOKUP($C14, INDIRECT("'在庫使用計画 ("&AV$1&")'!D:D"), INDIRECT("'在庫使用計画 ("&AV$1&")'!I:I") ),"")} | AW14: {=IFERROR(_xlfn.XLOOKUP($C14, INDIRECT("'在庫使用計画 ("&AW$1&")'!D:D"), INDIRECT("'在庫使用計画 ("&AW$1&")'!I:I") ),"")} | AX14: {=IFERROR(_xlfn.XLOOKUP($C14, INDIRECT("'在庫使用計画 ("&AX$1&")'!D:D"), INDIRECT("'在庫使用計画 ("&AX$1&")'!I:I") ),"")}
A15: 15"-G | B15: UNW-2-14650HX-5070-L6-DDR5-15.3 | C15: NPC7L-R57-G5 | D15: #REF! | E15: RPL i7-14650HX | F15: 5060 | G15: DDR5 | H15: 0 | I15: #REF! | J15: #REF! | K15: 1605.1239 | L15: 2223.3461 | M15: 2223.3461 | N15: 2223.3461 | O15: 2178.3461 | P15: 2178.3461 | Q15: 2178.3461 | R15: 2178.3461 | S15: 2178.3461 | T15: 1619.5342 | U15: 1619.5342 | V15: 1619.5342 | W15: 1619.5342 | X15: 1619.5342 | Y15: 1619.5342 | Z15: 1844.5342 | AA15: 1844.5342 | AB15: 2046.9289 | AC15: 2046.9289 | AD15: 2046.9289 | AE15: 1183.767 | AF15: 1183.767 | AG15: 1587.7976 | AH15: 1587.7976 | AI15: 1574.4075 | AJ15: 1574.4075 | AK15: 1772.2819 | AL15: 1772.2819 | AM15: 1772.2819 | AN15: 1772.2819 | AO15: 1772.2819 | AP15: 1702.7196 | AQ15: 0 | AR15: 0 | AS15: 0 | AT15: 0 | AU15: 0 | AV15: {=IFERROR(_xlfn.XLOOKUP($C15, INDIRECT("'在庫使用計画 ("&AV$1&")'!D:D"), INDIRECT("'在庫使用計画 ("&AV$1&")'!I:I") ),"")} | AW15: {=IFERROR(_xlfn.XLOOKUP($C15, INDIRECT("'在庫使用計画 ("&AW$1&")'!D:D"), INDIRECT("'在庫使用計画 ("&AW$1&")'!I:I") ),"")} | AX15: {=IFERROR(_xlfn.XLOOKUP($C15, INDIRECT("'在庫使用計画 ("&AX$1&")'!D:D"), INDIRECT("'在庫使用計画 ("&AX$1&")'!I:I") ),"")}
B16: CLE-V35-14650HX-5060-L6 | C16: RL7C-R56-5N | D16: #REF! | E16: RPL i7-14650HX | F16: 5060 | G16: DDR5 | H16: 152 | I16: #REF! | J16: #REF! | K16: 1605.1239 | L16: 2223.3461 | M16: 2223.3461 | N16: 2223.3461 | O16: 2178.3461 | P16: 2178.3461 | Q16: 2178.3461 | R16: 2178.3461 | S16: 2178.3461 | T16: 1619.5342 | U16: 1619.5342 | V16: 1619.5342 | W16: 1619.5342 | X16: 1619.5342 | Y16: 1619.5342 | Z16: 1844.5342 | AA16: 1844.5342 | AB16: 2046.9289 | AC16: 2046.9289 | AD16: 2046.9289 | AE16: 1183.767 | AF16: 1183.767 | AG16: 1587.7976 | AH16: 1587.7976 | AI16: 1574.4075 | AJ16: 1574.4075 | AK16: 1772.2819 | AL16: 1772.2819 | AM16: 1772.2819 | AN16: 1772.2819 | AO16: 1772.2819 | AP16: 1702.7196 | AQ16: 1577.7196 | AR16: 1587.7196 | AS16: 1587.7196 | AT16: 1587.7196 | AU16: 1587.7196 | AV16: {=IFERROR(_xlfn.XLOOKUP($C16, INDIRECT("'在庫使用計画 ("&AV$1&")'!D:D"), INDIRECT("'在庫使用計画 ("&AV$1&")'!I:I") ),"")} | AW16: {=IFERROR(_xlfn.XLOOKUP($C16, INDIRECT("'在庫使用計画 ("&AW$1&")'!D:D"), INDIRECT("'在庫使用計画 ("&AW$1&")'!I:I") ),"")} | AX16: {=IFERROR(_xlfn.XLOOKUP($C16, INDIRECT("'在庫使用計画 ("&AX$1&")'!D:D"), INDIRECT("'在庫使用計画 ("&AX$1&")'!I:I") ),"")}
B17: UNW-2-14650HX-5060-L6-DDR5-15.3 | C17: NPC7L-R56-G5 | D17: #REF! | E17: RPL i7-14650HX | F17: 5050 | G17: DDR5 | H17: 1355 | I17: #REF! | J17: #REF! | K17: 1404.4849 | L17: 1416.4565 | M17: 1275.741 | N17: 1275.741 | O17: 1140.741 | P17: 1140.741 | Q17: 1140.741 | R17: 1140.741 | S17: 1140.741 | T17: 1844.0278 | U17: 1964.0278 | V17: 1633.5893 | W17: 1633.5893 | X17: 1633.5893 | Y17: 1633.5893 | Z17: 1633.5893 | AA17: 1633.5893 | AB17: 1698.2277 | AC17: 1698.2277 | AD17: 1698.2277 | AE17: 1479.4259 | AF17: 1479.4259 | AG17: 1545.4369 | AH17: 1545.4369 | AI17: 1469.1033 | AJ17: 1469.1033 | AK17: 1106.6928 | AL17: 1106.6928 | AM17: 1106.6928 | AN17: 1106.6928 | AO17: 1106.6928 | AP17: 959.94993 | AQ17: 0 | AR17: 0 | AS17: 0 | AT17: 0 | AU17: 0 | AV17: {=IFERROR(_xlfn.XLOOKUP($C17, INDIRECT("'在庫使用計画 ("&AV$1&")'!D:D"), INDIRECT("'在庫使用計画 ("&AV$1&")'!I:I") ),"")} | AW17: {=IFERROR(_xlfn.XLOOKUP($C17, INDIRECT("'在庫使用計画 ("&AW$1&")'!D:D"), INDIRECT("'在庫使用計画 ("&AW$1&")'!I:I") ),"")} | AX17: {=IFERROR(_xlfn.XLOOKUP($C17, INDIRECT("'在庫使用計画 ("&AX$1&")'!D:D"), INDIRECT("'在庫使用計画 ("&AX$1&")'!I:I") ),"")}
B18: CLE-V35-14650HX-5050-L6 | C18: RL7C-R55-5N | D18: #REF! | E18: RPL i7-14650HX | F18: 5050 | G18: DDR5 | H18: 702 | I18: #REF! | J18: #REF! | K18: 1404.4849 | L18: 1416.4565 | M18: 1275.741 | N18: 1275.741 | O18: 1140.741 | P18: 1140.741 | Q18: 1140.741 | R18: 1140.741 | S18: 1140.741 | T18: 1844.0278 | U18: 1964.0278 | V18: 1633.5893 | W18: 1633.5893 | X18: 1633.5893 | Y18: 1633.5893 | Z18: 1633.5893 | AA18: 1633.5893 | AB18: 1698.2277 | AC18: 1698.2277 | AD18: 1698.2277 | AE18: 1479.4259 | AF18: 1479.4259 | AG18: 1545.4369 | AH18: 1545.4369 | AI18: 1469.1033 | AJ18: 1469.1033 | AK18: 1106.6928 | AL18: 1106.6928 | AM18: 1106.6928 | AN18: 1106.6928 | AO18: 1106.6928 | AP18: 959.94993 | AQ18: 969.94993 | AR18: 1025.8671 | AS18: 1025.8671 | AT18: 1025.8671 | AU18: 1025.8671 | AV18: {=IFERROR(_xlfn.XLOOKUP($C18, INDIRECT("'在庫使用計画 ("&AV$1&")'!D:D"), INDIRECT("'在庫使用計画 ("&AV$1&")'!I:I") ),"")} | AW18: {=IFERROR(_xlfn.XLOOKUP($C18, INDIRECT("'在庫使用計画 ("&AW$1&")'!D:D"), INDIRECT("'在庫使用計画 ("&AW$1&")'!I:I") ),"")} | AX18: {=IFERROR(_xlfn.XLOOKUP($C18, INDIRECT("'在庫使用計画 ("&AX$1&")'!D:D"), INDIRECT("'在庫使用計画 ("&AX$1&")'!I:I") ),"")}
B19: UNW-E-14450HX-5050-L6-DDR5-15.6 | C19: NPC5L-R55-G5 | D19: #REF! | E19: RPL i7-13620H | F19: 4050 | G19: DDR5 | H19: 1805 | I19: #REF! | J19: #REF! | K19: 3367.7493 | L19: 3401.1799 | M19: 3401.1799 | N19: 3401.1799 | O19: 3346.1799 | P19: 3346.1799 | Q19: 3346.1799 | R19: 3436.1799 | S19: 3436.1799 | T19: 4371.2302 | U19: 4551.2302 | V19: 4371 | W19: 4371 | X19: 4371 | Y19: 4371 | Z19: 1987.6981 | AA19: 1987.6981 | AB19: 2407.0577 | AC19: 2407.0577 | AD19: 2407.0577 | AE19: 2407.0577 | AF19: 2407.0577 | AG19: 2436.8193 | AH19: 2436.8193 | AI19: 2394.2451 | AJ19: 2394.2451 | AK19: 2864.8426 | AL19: 2864.8426 | AM19: 2864.8426 | AN19: 2864.8426 | AO19: 2864.8426 | AP19: 2854.7292 | AQ19: 0 | AR19: 0 | AS19: 0 | AT19: 0 | AU19: 0 | AV19: {=IFERROR(_xlfn.XLOOKUP($C19, INDIRECT("'在庫使用計画 ("&AV$1&")'!D:D"), INDIRECT("'在庫使用計画 ("&AV$1&")'!I:I") ),"")} | AW19: {=IFERROR(_xlfn.XLOOKUP($C19, INDIRECT("'在庫使用計画 ("&AW$1&")'!D:D"), INDIRECT("'在庫使用計画 ("&AW$1&")'!I:I") ),"")} | AX19: {=IFERROR(_xlfn.XLOOKUP($C19, INDIRECT("'在庫使用計画 ("&AX$1&")'!D:D"), INDIRECT("'在庫使用計画 ("&AX$1&")'!I:I") ),"")}
B20: UNW-E-13620H-4050-L6 | C20: RL7C-R45-5N | D20: #REF! | E20: RPL i7-13620H | F20: 4050 | G20: DDR5 | H20: 1414 | I20: #REF! | J20: #REF! | K20: 3367.7493 | L20: 3401.1799 | M20: 3401.1799 | N20: 3401.1799 | O20: 3346.1799 | P20: 3346.1799 | Q20: 3346.1799 | R20: 3436.1799 | S20: 3436.1799 | T20: 4371.2302 | U20: 4551.2302 | V20: 4371 | W20: 4371 | X20: 4371 | Y20: 4371 | Z20: 1987.6981 | AA20: 1987.6981 | AB20: 2407.0577 | AC20: 2407.0577 | AD20: 2407.0577 | AE20: 2407.0577 | AF20: 2407.0577 | AG20: 2436.8193 | AH20: 2436.8193 | AI20: 2394.2451 | AJ20: 2394.2451 | AK20: 2864.8426 | AL20: 2864.8426 | AM20: 2864.8426 | AN20: 2864.8426 | AO20: 2864.8426 | AP20: 2854.7292 | AQ20: 2533.7292 | AR20: 2556.7292 | AS20: 2556.7292 | AT20: 2556.7292 | AU20: 2556.7292 | AV20: {=IFERROR(_xlfn.XLOOKUP($C20, INDIRECT("'在庫使用計画 ("&AV$1&")'!D:D"), INDIRECT("'在庫使用計画 ("&AV$1&")'!I:I") ),"")} | AW20: {=IFERROR(_xlfn.XLOOKUP($C20, INDIRECT("'在庫使用計画 ("&AW$1&")'!D:D"), INDIRECT("'在庫使用計画 ("&AW$1&")'!I:I") ),"")} | AX20: {=IFERROR(_xlfn.XLOOKUP($C20, INDIRECT("'在庫使用計画 ("&AX$1&")'!D:D"), INDIRECT("'在庫使用計画 ("&AX$1&")'!I:I") ),"")}
B21: UNW-E-13620H-3050-L6 | C21: RL7C-R35-5N | D21: #REF! | E21: RPL i7-13620H | F21: 3050 | G21: DDR5 | H21: 2039 | I21: #REF! | J21: #REF! | K21: 5255.8117 | L21: 5324.3603 | M21: 5324.3603 | N21: 5324.3603 | O21: 5304.3603 | P21: 5304.3603 | Q21: 5304.3603 | R21: 5304.3603 | S21: 5304.3603 | T21: 5367.7355 | U21: 5762.1098 | V21: 5582 | W21: 5582 | X21: 5582 | Y21: 5582 | Z21: 4728.1803 | AA21: 4728.1803 | AB21: 5096.53 | AC21: 5096.53 | AD21: 5096.53 | AE21: 5096.53 | AF21: 5096.53 | AG21: 4210.5568 | AH21: 4210.5568 | AI21: 4140.3127 | AJ21: 4140.3127 | AK21: 3662.516 | AL21: 3662.516 | AM21: 3662.516 | AN21: 3662.516 | AO21: 3662.516 | AP21: 3299.9067 | AQ21: 3119.9067 | AR21: 2947.234 | AS21: 2947.234 | AT21: 2947.234 | AU21: 2947.234 | AV21: {=IFERROR(_xlfn.XLOOKUP($C21, INDIRECT("'在庫使用計画 ("&AV$1&")'!D:D"), INDIRECT("'在庫使用計画 ("&AV$1&")'!I:I") ),"")} | AW21: {=IFERROR(_xlfn.XLOOKUP($C21, INDIRECT("'在庫使用計画 ("&AW$1&")'!D:D"), INDIRECT("'在庫使用計画 ("&AW$1&")'!I:I") ),"")} | AX21: {=IFERROR(_xlfn.XLOOKUP($C21, INDIRECT("'在庫使用計画 ("&AX$1&")'!D:D"), INDIRECT("'在庫使用計画 ("&AX$1&")'!I:I") ),"")}
B22: TFH-E-13420H-3050-L6 | C22: RL5C-R35-5N | D22: #REF! | E22: RPL i7-13420H | F22: 3050 | H22: 5 | I22: #REF! | J22: #REF! | K22: 333.30897 | L22: 378.30897 | M22: 378.30897 | N22: 378.30897 | O22: 378.30897 | P22: 378.30897 | Q22: 378.30897 | R22: 378.30897 | S22: 378.30897 | T22: 330 | U22: 330 | V22: 330 | W22: 330 | X22: 330 | Y22: 330 | Z22: 330 | AA22: 330 | AB22: 235 | AC22: 235 | AD22: 235 | AE22: 235 | AF22: 235 | AG22: 235 | AH22: 235 | AI22: 260 | AJ22: 260 | AK22: 260 | AL22: 260 | AM22: 260 | AN22: 260 | AO22: 260 | AP22: 190 | AQ22: 207 | AR22: 425.27949 | AS22: 425.27949 | AT22: 425.27949 | AU22: 425.27949 | AV22: {=IFERROR(_xlfn.XLOOKUP($C22, INDIRECT("'在庫使用計画 ("&AV$1&")'!D:D"), INDIRECT("'在庫使用計画 ("&AV$1&")'!I:I") ),"")} | AW22: {=IFERROR(_xlfn.XLOOKUP($C22, INDIRECT("'在庫使用計画 ("&AW$1&")'!D:D"), INDIRECT("'在庫使用計画 ("&AW$1&")'!I:I") ),"")} | AX22: {=IFERROR(_xlfn.XLOOKUP($C22, INDIRECT("'在庫使用計画 ("&AX$1&")'!D:D"), INDIRECT("'在庫使用計画 ("&AX$1&")'!I:I") ),"")}
B23: TFH-E-12450H-3050-L6 | C23: RL5C-R35N | D23: #REF! | E23: ADL-i5-12450H | F23: 3050 | G23: DDR4 | H23: 0 | I23: #REF! | J23: #REF! | L23: 45 | M23: 45 | N23: 45 | O23: 45 | P23: 45 | Q23: 45 | R23: 45 | S23: 45 | T23: 30 | U23: 30 | V23: 30 | W23: 30 | X23: 30 | Y23: 30 | Z23: 30 | AA23: 30 | AB23: 15 | AC23: 15 | AD23: 15 | AE23: 15 | AF23: 15 | AG23: 15 | AH23: 15 | AI23: 0 | AJ23: 0 | AK23: 0 | AL23: 0 | AM23: 0 | AN23: 0 | AO23: 0 | AP23: 0 | AQ23: 0 | AR23: 0 | AS23: 0 | AT23: 0 | AU23: 0 | AV23: {=IFERROR(_xlfn.XLOOKUP($C23, INDIRECT("'在庫使用計画 ("&AV$1&")'!D:D"), INDIRECT("'在庫使用計画 ("&AV$1&")'!I:I") ),"")} | AW23: {=IFERROR(_xlfn.XLOOKUP($C23, INDIRECT("'在庫使用計画 ("&AW$1&")'!D:D"), INDIRECT("'在庫使用計画 ("&AW$1&")'!I:I") ),"")} | AX23: {=IFERROR(_xlfn.XLOOKUP($C23, INDIRECT("'在庫使用計画 ("&AX$1&")'!D:D"), INDIRECT("'在庫使用計画 ("&AX$1&")'!I:I") ),"")}
AV24: {=IFERROR(_xlfn.XLOOKUP($C24, INDIRECT("'在庫使用計画 ("&AV$1&")'!D:D"), INDIRECT("'在庫使用計画 ("&AV$1&")'!I:I") ),"")} | AW24: {=IFERROR(_xlfn.XLOOKUP($C24, INDIRECT("'在庫使用計画 ("&AW$1&")'!D:D"), INDIRECT("'在庫使用計画 ("&AW$1&")'!I:I") ),"")} | AX24: {=IFERROR(_xlfn.XLOOKUP($C24, INDIRECT("'在庫使用計画 ("&AX$1&")'!D:D"), INDIRECT("'在庫使用計画 ("&AX$1&")'!I:I") ),"")}
A25: 14"-G | B25: CLE-V540-155H-4050-L6 | C25: RL7C-R45-4 | D25: #REF! | E25: MTL-UL7-155H | F25: 4050 | G25: DDR5 | H25: 290 | I25: #REF! | J25: #REF! | R25: 0 | S25: 0 | T25: 600 | U25: 600 | V25: 600 | W25: 600 | X25: 600 | Y25: 600 | Z25: 600 | AA25: 600 | AB25: 1000 | AC25: 1000 | AD25: 1000 | AE25: 1000 | AF25: 1000 | AG25: 1000 | AH25: 1000 | AI25: 1000 | AJ25: 1000 | AK25: 1000 | AL25: 1000 | AM25: 1000 | AN25: 840 | AO25: 840 | AP25: 880 | AQ25: 880 | AR25: 880 | AS25: 880 | AT25: 880 | AU25: 880 | AV25: {=IFERROR(_xlfn.XLOOKUP($C25, INDIRECT("'在庫使用計画 ("&AV$1&")'!D:D"), INDIRECT("'在庫使用計画 ("&AV$1&")'!I:I") ),"")} | AW25: {=IFERROR(_xlfn.XLOOKUP($C25, INDIRECT("'在庫使用計画 ("&AW$1&")'!D:D"), INDIRECT("'在庫使用計画 ("&AW$1&")'!I:I") ),"")} | AX25: {=IFERROR(_xlfn.XLOOKUP($C25, INDIRECT("'在庫使用計画 ("&AX$1&")'!D:D"), INDIRECT("'在庫使用計画 ("&AX$1&")'!I:I") ),"")}
AV27: {=IFERROR(_xlfn.XLOOKUP($C27, INDIRECT("'在庫使用計画 ("&AV$1&")'!D:D"), INDIRECT("'在庫使用計画 ("&AV$1&")'!I:I") ),"")} | AW27: {=IFERROR(_xlfn.XLOOKUP($C27, INDIRECT("'在庫使用計画 ("&AW$1&")'!D:D"), INDIRECT("'在庫使用計画 ("&AW$1&")'!I:I") ),"")} | AX27: {=IFERROR(_xlfn.XLOOKUP($C27, INDIRECT("'在庫使用計画 ("&AX$1&")'!D:D"), INDIRECT("'在庫使用計画 ("&AX$1&")'!I:I") ),"")}
B28: GALLERIA Gaming 合計 | C28: Gaming 計画合計 | K28: 14543.947 | L28: 15390.049 | M28: 14574.161 | N28: 14574.161 | O28: 14332.161 | P28: 14332.161 | Q28: 14332.161 | R28: 14422.161 | S28: 14422.161 | T28: 16325.521 | U28: 17003.312 | V28: 16312.533 | W28: 16312.533 | X28: 16312.533 | Y28: 16312.533 | Z28: 13348.411 | AA28: 13348.411 | AB28: 15107.94 | AC28: 15107.94 | AD28: 15132.94 | AE28: 13447.437 | AF28: 13447.437 | AG28: 12975.272 | AH28: 12975.272 | AI28: 12773.602 | AJ28: 12773.602 | AK28: 12624.206 | AL28: 12655.206 | AM28: 12655.206 | AN28: 12495.206 | AO28: 12495.206 | AP28: 11751.843 | AQ28: 11202.765 | AR28: 11153.362 | AS28: 11153.362 | AT28: 11153.362 | AU28: 11185.362 | AV28: =_xlfn.AGGREGATE(9,0,AV2:AV27) -> 0 | AW28: =_xlfn.AGGREGATE(9,0,AW2:AW27) -> 0 | AX28: =_xlfn.AGGREGATE(9,0,AX2:AX27) -> 0
B29: GALLERIA Gaming 予算 | AD29: 0 | AE29: 0 | AF29: 0 | AG29: 0 | AH29: 0 | AI29: 0 | AJ29: 0 | AK29: 0 | AL29: 0 | AM29: 0 | AN29: 0 | AO29: 0 | AP29: 0 | AQ29: 0 | AR29: 0 | AS29: 0 | AT29: 0 | AU29: 0 | AV29: {=IFERROR(_xlfn.XLOOKUP($C29, INDIRECT("'在庫使用計画 ("&AV$1&")'!C:C"), INDIRECT("'在庫使用計画 ("&AV$1&")'!H:H") ),"")} | AW29: {=IFERROR(_xlfn.XLOOKUP($C29, INDIRECT("'在庫使用計画 ("&AW$1&")'!C:C"), INDIRECT("'在庫使用計画 ("&AW$1&")'!H:H") ),"")} | AX29: {=IFERROR(_xlfn.XLOOKUP($C29, INDIRECT("'在庫使用計画 ("&AX$1&")'!C:C"), INDIRECT("'在庫使用計画 ("&AX$1&")'!H:H") ),"")}
B30: {=IF(C30:C56="","",_xlfn.XLOOKUP(C30:C56,マスタ_EOLリスト[製品型番],マスタ_EOLリスト[綽名]))} | D30: {=IF($C30:$C56<>"", _xlfn.MAXIFS(#REF!,マスタ_EOLリスト[製品型番],$C30:$C56), "")} | H30: {=IF(C30:C56<>"", _xlfn.XLOOKUP($C30:$C56, '在庫使用計画 (ノート全体試算)'!C:C, '在庫使用計画 (ノート全体試算)'!G:G),"")} | I30: {=IF(_xlfn.ANCHORARRAY(D30)<>"", _xlfn.XLOOKUP(_xlfn.ANCHORARRAY(D30),購買計画one_note_貼り付け[コード],購買計画one_note_貼り付け[納品日],""), "")} | J30: {=IF(_xlfn.ANCHORARRAY(D30)<>"", _xlfn.XLOOKUP(_xlfn.ANCHORARRAY(D30),購買計画one_note_貼り付け[コード],購買計画one_note_貼り付け[数量],""), "")} | AV30: {=IFERROR(_xlfn.XLOOKUP($C30, INDIRECT("'在庫使用計画 ("&AV$1&")'!D:D"), INDIRECT("'在庫使用計画 ("&AV$1&")'!I:I") ),"")} | AW30: {=IFERROR(_xlfn.XLOOKUP($C30, INDIRECT("'在庫使用計画 ("&AW$1&")'!D:D"), INDIRECT("'在庫使用計画 ("&AW$1&")'!I:I") ),"")} | AX30: {=IFERROR(_xlfn.XLOOKUP($C30, INDIRECT("'在庫使用計画 ("&AX$1&")'!D:D"), INDIRECT("'在庫使用計画 ("&AX$1&")'!I:I") ),"")}
A31: 17"-C | B31: #N/A | C31: NUC9L-R58-C6 | D31: #REF! | E31: RPL-HX R i9-14900HX | F31: 5070 | G31: DDR5 | H31: #N/A | I31: #REF! | J31: #REF! | K31: 392.35205 | L31: 415.35205 | M31: 415.35205 | N31: 415.35205 | O31: 415.35205 | P31: 415.35205 | Q31: 415.35205 | R31: 415.35205 | S31: 415.35205 | T31: 448 | U31: 448 | V31: 448 | W31: 448 | X31: 448 | Y31: 448 | Z31: 264.97417 | AA31: 264.97417 | AB31: 279.63592 | AC31: 279.63592 | AD31: 279.63592 | AE31: 279.63592 | AF31: 279.63592 | AG31: 210.72557 | AH31: 210.72557 | AI31: 190.57497 | AJ31: 190.57497 | AK31: 209.12346 | AL31: 209.12346 | AM31: 209.12346 | AN31: 209.12346 | AO31: 209.12346 | AP31: 189.13803 | AQ31: 0 | AR31: 0 | AS31: 0 | AT31: 0 | AU31: 35 | AV31: {=IFERROR(_xlfn.XLOOKUP($C31, INDIRECT("'在庫使用計画 ("&AV$1&")'!D:D"), INDIRECT("'在庫使用計画 ("&AV$1&")'!I:I") ),"")} | AW31: {=IFERROR(_xlfn.XLOOKUP($C31, INDIRECT("'在庫使用計画 ("&AW$1&")'!D:D"), INDIRECT("'在庫使用計画 ("&AW$1&")'!I:I") ),"")} | AX31: {=IFERROR(_xlfn.XLOOKUP($C31, INDIRECT("'在庫使用計画 ("&AX$1&")'!D:D"), INDIRECT("'在庫使用計画 ("&AX$1&")'!I:I") ),"")}
AV32: {=IFERROR(_xlfn.XLOOKUP($C32, INDIRECT("'在庫使用計画 ("&AV$1&")'!D:D"), INDIRECT("'在庫使用計画 ("&AV$1&")'!I:I") ),"")} | AW32: {=IFERROR(_xlfn.XLOOKUP($C32, INDIRECT("'在庫使用計画 ("&AW$1&")'!D:D"), INDIRECT("'在庫使用計画 ("&AW$1&")'!I:I") ),"")} | AX32: {=IFERROR(_xlfn.XLOOKUP($C32, INDIRECT("'在庫使用計画 ("&AX$1&")'!D:D"), INDIRECT("'在庫使用計画 ("&AX$1&")'!I:I") ),"")}
A33: 17"-C | B33: CLE-V37-14900HX-5070-L6 Creator | C33: ZL9C-R57-C7 | D33: #REF! | E33: RPL-HX R i9-14900HX | F33: 5070 | G33: DDR5 | H33: 128 | I33: #REF! | J33: #REF! | K33: 392.35205 | L33: 415.35205 | M33: 415.35205 | N33: 415.35205 | O33: 415.35205 | P33: 415.35205 | Q33: 415.35205 | R33: 415.35205 | S33: 415.35205 | T33: 448 | U33: 448 | V33: 448 | W33: 448 | X33: 448 | Y33: 448 | Z33: 264.97417 | AA33: 264.97417 | AB33: 279.63592 | AC33: 279.63592 | AD33: 279.63592 | AE33: 279.63592 | AF33: 279.63592 | AG33: 210.72557 | AH33: 210.72557 | AI33: 190.57497 | AJ33: 190.57497 | AK33: 209.12346 | AL33: 209.12346 | AM33: 209.12346 | AN33: 209.12346 | AO33: 209.12346 | AP33: 189.13803 | AQ33: 205.13803 | AR33: 212.13803 | AS33: 212.13803 | AT33: 212.13803 | AU33: 212.13803 | AV33: {=IFERROR(_xlfn.XLOOKUP($C33, INDIRECT("'在庫使用計画 ("&AV$1&")'!D:D"), INDIRECT("'在庫使用計画 ("&AV$1&")'!I:I") ),"")} | AW33: {=IFERROR(_xlfn.XLOOKUP($C33, INDIRECT("'在庫使用計画 ("&AW$1&")'!D:D"), INDIRECT("'在庫使用計画 ("&AW$1&")'!I:I") ),"")} | AX33: {=IFERROR(_xlfn.XLOOKUP($C33, INDIRECT("'在庫使用計画 ("&AX$1&")'!D:D"), INDIRECT("'在庫使用計画 ("&AX$1&")'!I:I") ),"")}
B34: #N/A | C34: NDC7L-R57-C6 | D34: #REF! | H34: 0 | I34: #REF! | J34: #REF! | AQ34: 0 | AR34: 0 | AS34: 0 | AT34: 0 | AU34: 0 | AV34: {=IFERROR(_xlfn.XLOOKUP($C34, INDIRECT("'在庫使用計画 ("&AV$1&")'!D:D"), INDIRECT("'在庫使用計画 ("&AV$1&")'!I:I") ),"")} | AW34: {=IFERROR(_xlfn.XLOOKUP($C34, INDIRECT("'在庫使用計画 ("&AW$1&")'!D:D"), INDIRECT("'在庫使用計画 ("&AW$1&")'!I:I") ),"")} | AX34: {=IFERROR(_xlfn.XLOOKUP($C34, INDIRECT("'在庫使用計画 ("&AX$1&")'!D:D"), INDIRECT("'在庫使用計画 ("&AX$1&")'!I:I") ),"")}
A35: 16”-C | B35: MSH-15F5-255H-5060-L6 Creator | C35: XL7C-R56-C6A | D35: #REF! | E35: ARL-H U7-255H | F35: 5060 | G35: DDR5 | H35: 20 | I35: #REF! | J35: #REF! | K35: 445 | L35: 540 | M35: 540 | N35: 540 | O35: 540 | P35: 540 | Q35: 540 | R35: 540 | S35: 540 | T35: 530 | U35: 530 | V35: 530 | W35: 530 | X35: 530 | Y35: 530 | Z35: 530 | AA35: 530 | AB35: 550 | AC35: 550 | AD35: 550 | AE35: 87.888517 | AF35: 87.888517 | AG35: 93.667359 | AH35: 93.667359 | AI35: 74.49827 | AJ35: 74.49827 | AK35: 112.33101 | AL35: 125.33101 | AM35: 125.33101 | AN35: 125.33101 | AO35: 125.33101 | AP35: 124.56901 | AQ35: 123.56901 | AR35: 191.81797 | AS35: 191.81797 | AT35: 191.81797 | AU35: 191.81797 | AV35: {=IFERROR(_xlfn.XLOOKUP($C35, INDIRECT("'在庫使用計画 ("&AV$1&")'!D:D"), INDIRECT("'在庫使用計画 ("&AV$1&")'!I:I") ),"")} | AW35: {=IFERROR(_xlfn.XLOOKUP($C35, INDIRECT("'在庫使用計画 ("&AW$1&")'!D:D"), INDIRECT("'在庫使用計画 ("&AW$1&")'!I:I") ),"")} | AX35: {=IFERROR(_xlfn.XLOOKUP($C35, INDIRECT("'在庫使用計画 ("&AX$1&")'!D:D"), INDIRECT("'在庫使用計画 ("&AX$1&")'!I:I") ),"")}
A36: 16”-C | B36: CLE-V56-AI9-470-5060-L6 Creator | C36: NDR9L-R56-C6 | D36: #REF! | F36: 5060 | H36: 348 | I36: #REF! | J36: #REF! | AC36: 100 | AD36: 100 | AE36: 100 | AF36: 100 | AG36: 100 | AH36: 100 | AI36: 180 | AJ36: 180 | AK36: 180 | AL36: 180 | AM36: 180 | AN36: 180 | AO36: 180 | AP36: 260 | AQ36: 330 | AR36: 150 | AS36: 150 | AT36: 150 | AU36: 150 | AV36: {=IFERROR(_xlfn.XLOOKUP($C36, INDIRECT("'在庫使用計画 ("&AV$1&")'!D:D"), INDIRECT("'在庫使用計画 ("&AV$1&")'!I:I") ),"")} | AW36: {=IFERROR(_xlfn.XLOOKUP($C36, INDIRECT("'在庫使用計画 ("&AW$1&")'!D:D"), INDIRECT("'在庫使用計画 ("&AW$1&")'!I:I") ),"")} | AX36: {=IFERROR(_xlfn.XLOOKUP($C36, INDIRECT("'在庫使用計画 ("&AX$1&")'!D:D"), INDIRECT("'在庫使用計画 ("&AX$1&")'!I:I") ),"")}
A37: 16”-C | B37: CLE-V54-HX370-UMA-L6 Creator | C37: DL9R-IG-C4A | D37: #REF! | F37: 5060 | H37: 26 | I37: #REF! | J37: #REF! | AC37: 100 | AD37: 100 | AE37: 100 | AF37: 100 | AG37: 100 | AH37: 100 | AI37: 180 | AJ37: 180 | AK37: 180 | AL37: 180 | AM37: 180 | AN37: 180 | AO37: 180 | AP37: 260 | AQ37: 498.9194 | AR37: 498.9194 | AS37: 498.9194 | AT37: 498.9194 | AU37: 498.9194 | AV37: {=IFERROR(_xlfn.XLOOKUP($C37, INDIRECT("'在庫使用計画 ("&AV$1&")'!D:D"), INDIRECT("'在庫使用計画 ("&AV$1&")'!I:I") ),"")} | AW37: {=IFERROR(_xlfn.XLOOKUP($C37, INDIRECT("'在庫使用計画 ("&AW$1&")'!D:D"), INDIRECT("'在庫使用計画 ("&AW$1&")'!I:I") ),"")} | AX37: {=IFERROR(_xlfn.XLOOKUP($C37, INDIRECT("'在庫使用計画 ("&AX$1&")'!D:D"), INDIRECT("'在庫使用計画 ("&AX$1&")'!I:I") ),"")}
A38: 16”-C | B38: CLE-V54-AI9-470-UMA-L6 Creator | C38: NDR9L-IG-C4 | D38: #REF! | F38: 5060 | H38: 420 | I38: #REF! | J38: #REF! | AC38: 100 | AD38: 100 | AE38: 100 | AF38: 100 | AG38: 100 | AH38: 100 | AI38: 180 | AJ38: 180 | AK38: 180 | AL38: 180 | AM38: 180 | AN38: 180 | AO38: 180 | AP38: 260 | AQ38: 396 | AR38: 116 | AS38: 116 | AT38: 116 | AU38: 116 | AV38: {=IFERROR(_xlfn.XLOOKUP($C38, INDIRECT("'在庫使用計画 ("&AV$1&")'!D:D"), INDIRECT("'在庫使用計画 ("&AV$1&")'!I:I") ),"")} | AW38: {=IFERROR(_xlfn.XLOOKUP($C38, INDIRECT("'在庫使用計画 ("&AW$1&")'!D:D"), INDIRECT("'在庫使用計画 ("&AW$1&")'!I:I") ),"")} | AX38: {=IFERROR(_xlfn.XLOOKUP($C38, INDIRECT("'在庫使用計画 ("&AX$1&")'!D:D"), INDIRECT("'在庫使用計画 ("&AX$1&")'!I:I") ),"")}
AV39: {=IFERROR(_xlfn.XLOOKUP($C39, INDIRECT("'在庫使用計画 ("&AV$1&")'!D:D"), INDIRECT("'在庫使用計画 ("&AV$1&")'!I:I") ),"")} | AW39: {=IFERROR(_xlfn.XLOOKUP($C39, INDIRECT("'在庫使用計画 ("&AW$1&")'!D:D"), INDIRECT("'在庫使用計画 ("&AW$1&")'!I:I") ),"")} | AX39: {=IFERROR(_xlfn.XLOOKUP($C39, INDIRECT("'在庫使用計画 ("&AX$1&")'!D:D"), INDIRECT("'在庫使用計画 ("&AX$1&")'!I:I") ),"")}
A40: 15"-C | B40: CLE-V35-14650HX-5060-L6 Creator | C40: RL7C-R56-C5N | D40: #REF! | E40: RPL-HX R i7-14650HX | H40: 536 | I40: #REF! | J40: #REF! | K40: 1205 | L40: 1155 | M40: 1155 | N40: 1155 | O40: 1118 | P40: 1118 | Q40: 1118 | R40: 1118 | S40: 1118 | T40: 1063 | U40: 1063 | V40: 1063 | W40: 1063 | X40: 1063 | Y40: 1063 | Z40: 1255 | AA40: 1255 | AB40: 1525 | AC40: 1525 | AD40: 1525 | AE40: 1251.3768 | AF40: 1251.3768 | AG40: 1001.5135 | AH40: 1001.5135 | AI40: 925.21626 | AJ40: 925.21626 | AK40: 871.14523 | AL40: 831.14523 | AM40: 831.14523 | AN40: 831.14523 | AO40: 831.14523 | AP40: 608.40347 | AQ40: 648.40347 | AR40: 648.40347 | AS40: 648.40347 | AT40: 698.40347 | AU40: 698.40347 | AV40: {=IFERROR(_xlfn.XLOOKUP($C40, INDIRECT("'在庫使用計画 ("&AV$1&")'!D:D"), INDIRECT("'在庫使用計画 ("&AV$1&")'!I:I") ),"")} | AW40: {=IFERROR(_xlfn.XLOOKUP($C40, INDIRECT("'在庫使用計画 ("&AW$1&")'!D:D"), INDIRECT("'在庫使用計画 ("&AW$1&")'!I:I") ),"")} | AX40: {=IFERROR(_xlfn.XLOOKUP($C40, INDIRECT("'在庫使用計画 ("&AX$1&")'!D:D"), INDIRECT("'在庫使用計画 ("&AX$1&")'!I:I") ),"")}
A41: 16”-C | B41: QNT-NLT-240H-5060-L6-GC | C41: NSC7L-R56-C6 | D41: #REF! | F41: 5060 | G41: DDR5 | H41: 1100 | I41: #REF! | J41: #REF! | R41: 0 | S41: 0 | T41: 0 | U41: 0 | V41: 0 | W41: 0 | X41: 0 | Y41: 0 | Z41: 0 | AA41: 0 | AB41: 0 | AC41: 0 | AD41: 0 | AE41: 0 | AF41: 0 | AG41: 0 | AH41: 0 | AI41: 0 | AJ41: 0 | AK41: 0 | AL41: 30 | AM41: 30 | AN41: 30 | AO41: 30 | AP41: 135 | AQ41: 130 | AR41: 50 | AS41: 50 | AT41: 0 | AU41: 0 | AV41: {=IFERROR(_xlfn.XLOOKUP($C41, INDIRECT("'在庫使用計画 ("&AV$1&")'!D:D"), INDIRECT("'在庫使用計画 ("&AV$1&")'!I:I") ),"")} | AW41: {=IFERROR(_xlfn.XLOOKUP($C41, INDIRECT("'在庫使用計画 ("&AW$1&")'!D:D"), INDIRECT("'在庫使用計画 ("&AW$1&")'!I:I") ),"")} | AX41: {=IFERROR(_xlfn.XLOOKUP($C41, INDIRECT("'在庫使用計画 ("&AX$1&")'!D:D"), INDIRECT("'在庫使用計画 ("&AX$1&")'!I:I") ),"")}
A42: 15"-C | B42: CLE-V35-14650HX-5050-L6 Creator | C42: RL7C-R55-C5N | D42: #REF! | E42: RPL-HX R i7-14650HX | H42: 42 | I42: #REF! | J42: #REF! | K42: 600.07209 | L42: 620.07209 | M42: 620.07209 | N42: 620.07209 | O42: 615.07209 | P42: 615.07209 | Q42: 615.07209 | R42: 676.07209 | S42: 676.07209 | T42: 705 | U42: 705 | V42: 705 | W42: 705 | X42: 705 | Y42: 705 | Z42: 715 | AA42: 715 | AB42: 800 | AC42: 800 | AD42: 800 | AE42: 512.55073 | AF42: 512.55073 | AG42: 555.95217 | AH42: 555.95217 | AI42: 514.39735 | AJ42: 514.39735 | AK42: 543.56041 | AL42: 508.56041 | AM42: 508.56041 | AN42: 508.56041 | AO42: 508.56041 | AP42: 383.8026 | AQ42: 418.8026 | AR42: 418.8026 | AS42: 418.8026 | AT42: 448.8026 | AU42: 448.8026 | AV42: {=IFERROR(_xlfn.XLOOKUP($C42, INDIRECT("'在庫使用計画 ("&AV$1&")'!D:D"), INDIRECT("'在庫使用計画 ("&AV$1&")'!I:I") ),"")} | AW42: {=IFERROR(_xlfn.XLOOKUP($C42, INDIRECT("'在庫使用計画 ("&AW$1&")'!D:D"), INDIRECT("'在庫使用計画 ("&AW$1&")'!I:I") ),"")} | AX42: {=IFERROR(_xlfn.XLOOKUP($C42, INDIRECT("'在庫使用計画 ("&AX$1&")'!D:D"), INDIRECT("'在庫使用計画 ("&AX$1&")'!I:I") ),"")}
A43: 16”-C | B43: QNT-NLT-240H-5050-L6-GC | C43: NSC7L-R55-C6 | D43: #REF! | F43: 5050 | G43: DDR5 | H43: 730 | I43: #REF! | J43: #REF! | R43: 0 | S43: 0 | T43: 0 | U43: 0 | V43: 0 | W43: 0 | X43: 0 | Y43: 0 | Z43: 0 | AA43: 0 | AB43: 0 | AC43: 0 | AD43: 0 | AE43: 0 | AF43: 0 | AG43: 0 | AH43: 0 | AI43: 0 | AJ43: 0 | AK43: 0 | AL43: 43 | AM43: 43 | AN43: 43 | AO43: 43 | AP43: 203 | AQ43: 100 | AR43: 30 | AS43: 30 | AT43: 0 | AU43: 0 | AV43: {=IFERROR(_xlfn.XLOOKUP($C43, INDIRECT("'在庫使用計画 ("&AV$1&")'!D:D"), INDIRECT("'在庫使用計画 ("&AV$1&")'!I:I") ),"")} | AW43: {=IFERROR(_xlfn.XLOOKUP($C43, INDIRECT("'在庫使用計画 ("&AW$1&")'!D:D"), INDIRECT("'在庫使用計画 ("&AW$1&")'!I:I") ),"")} | AX43: {=IFERROR(_xlfn.XLOOKUP($C43, INDIRECT("'在庫使用計画 ("&AX$1&")'!D:D"), INDIRECT("'在庫使用計画 ("&AX$1&")'!I:I") ),"")}
A44: 15"-C | B44: UNW-E-13620H-4050-L6 Creator | C44: RL7C-R45-C5N | D44: #REF! | E44: RPL i7-13620H | F44: 4050 | G44: DDR5 | H44: 555 | I44: #REF! | J44: #REF! | R44: 0 | S44: 0 | T44: 0 | U44: 0 | V44: 0 | W44: 0 | X44: 0 | Y44: 0 | Z44: 0 | AA44: 0 | AB44: 0 | AC44: 995 | AD44: 995 | AE44: 331.77369 | AF44: 331.77369 | AG44: 406.5634 | AH44: 406.5634 | AI44: 334.31373 | AJ44: 334.31373 | AK44: 377.96056 | AL44: 452.96056 | AM44: 452.96056 | AN44: 452.96056 | AO44: 452.96056 | AP44: 406.82384 | AQ44: 396.82384 | AR44: 503.73989 | AS44: 503.73989 | AT44: 503.73989 | AU44: 503.73989 | AV44: {=IFERROR(_xlfn.XLOOKUP($C44, INDIRECT("'在庫使用計画 ("&AV$1&")'!D:D"), INDIRECT("'在庫使用計画 ("&AV$1&")'!I:I") ),"")} | AW44: {=IFERROR(_xlfn.XLOOKUP($C44, INDIRECT("'在庫使用計画 ("&AW$1&")'!D:D"), INDIRECT("'在庫使用計画 ("&AW$1&")'!I:I") ),"")} | AX44: {=IFERROR(_xlfn.XLOOKUP($C44, INDIRECT("'在庫使用計画 ("&AX$1&")'!D:D"), INDIRECT("'在庫使用計画 ("&AX$1&")'!I:I") ),"")}
A45: 15"-C | B45: UNW-E-13620H-3050-L6 Creator | C45: RL7C-R35-C5N | D45: #REF! | E45: RPL i7-13620H | F45: 3050 | G45: DDR5 | H45: 11 | I45: #REF! | J45: #REF! | K45: 790.10813 | L45: 788.10813 | M45: 828.10813 | N45: 828.10813 | O45: 828.10813 | P45: 828.10813 | Q45: 828.10813 | R45: 864.10813 | S45: 864.10813 | T45: 870 | U45: 870 | V45: 870 | W45: 870 | X45: 870 | Y45: 870 | Z45: 870 | AA45: 870 | AB45: 995 | AC45: 840 | AD45: 840 | AE45: 639.60313 | AF45: 639.60313 | AG45: 752.62576 | AH45: 752.62576 | AI45: 624.38005 | AJ45: 624.38005 | AK45: 699.06852 | AL45: 699.06852 | AM45: 699.06852 | AN45: 699.06852 | AO45: 699.06852 | AP45: 501.38601 | AQ45: 501.38601 | AR45: 451.42654 | AS45: 451.42654 | AT45: 451.42654 | AU45: 451.42654 | AV45: {=IFERROR(_xlfn.XLOOKUP($C45, INDIRECT("'在庫使用計画 ("&AV$1&")'!D:D"), INDIRECT("'在庫使用計画 ("&AV$1&")'!I:I") ),"")} | AW45: {=IFERROR(_xlfn.XLOOKUP($C45, INDIRECT("'在庫使用計画 ("&AW$1&")'!D:D"), INDIRECT("'在庫使用計画 ("&AW$1&")'!I:I") ),"")} | AX45: {=IFERROR(_xlfn.XLOOKUP($C45, INDIRECT("'在庫使用計画 ("&AX$1&")'!D:D"), INDIRECT("'在庫使用計画 ("&AX$1&")'!I:I") ),"")}
A46: 15"-C | B46: #N/A | C46: NSC5L-IG-C4 | D46: #REF! | E46: RPL i7-13620H | F46: 3050 | G46: DDR5 | H46: #N/A | I46: #REF! | J46: #REF! | K46: 790.10813 | L46: 788.10813 | M46: 828.10813 | N46: 828.10813 | O46: 828.10813 | P46: 828.10813 | Q46: 828.10813 | R46: 864.10813 | S46: 864.10813 | T46: 870 | U46: 870 | V46: 870 | W46: 870 | X46: 870 | Y46: 870 | Z46: 870 | AA46: 870 | AB46: 995 | AC46: 840 | AD46: 840 | AE46: 639.60313 | AF46: 639.60313 | AG46: 752.62576 | AH46: 752.62576 | AI46: 624.38005 | AJ46: 624.38005 | AK46: 699.06852 | AL46: 699.06852 | AM46: 699.06852 | AN46: 699.06852 | AO46: 699.06852 | AP46: 501.38601 | AQ46: 0 | AR46: 0 | AS46: 0 | AT46: 0 | AU46: 0 | AV46: {=IFERROR(_xlfn.XLOOKUP($C46, INDIRECT("'在庫使用計画 ("&AV$1&")'!D:D"), INDIRECT("'在庫使用計画 ("&AV$1&")'!I:I") ),"")} | AW46: {=IFERROR(_xlfn.XLOOKUP($C46, INDIRECT("'在庫使用計画 ("&AW$1&")'!D:D"), INDIRECT("'在庫使用計画 ("&AW$1&")'!I:I") ),"")} | AX46: {=IFERROR(_xlfn.XLOOKUP($C46, INDIRECT("'在庫使用計画 ("&AX$1&")'!D:D"), INDIRECT("'在庫使用計画 ("&AX$1&")'!I:I") ),"")}
K47: 1485.1802 | L47: 1590.1802 | M47: 1170.1802 | N47: 1170.1802 | O47: 1170.1802 | P47: 1170.1802 | Q47: 1170.1802 | R47: 1235.1802 | S47: 1235.1802 | T47: 1160 | U47: 1160 | V47: 1160 | W47: 1160 | X47: 1160 | Y47: 1160 | Z47: 1160 | AA47: 1160 | AB47: 840 | AV47: {=IFERROR(_xlfn.XLOOKUP($C47, INDIRECT("'在庫使用計画 ("&AV$1&")'!D:D"), INDIRECT("'在庫使用計画 ("&AV$1&")'!I:I") ),"")} | AW47: {=IFERROR(_xlfn.XLOOKUP($C47, INDIRECT("'在庫使用計画 ("&AW$1&")'!D:D"), INDIRECT("'在庫使用計画 ("&AW$1&")'!I:I") ),"")} | AX47: {=IFERROR(_xlfn.XLOOKUP($C47, INDIRECT("'在庫使用計画 ("&AX$1&")'!D:D"), INDIRECT("'在庫使用計画 ("&AX$1&")'!I:I") ),"")}
A48: 14"-C | B48: CLE-MiniPC-AI9-HX470-黒-GC | C48: MDR9N-IG-CB | D48: #REF! | E48: MTL-UL7-155H | F48: UMA | G48: DDR5 | H48: #N/A | I48: #REF! | J48: #REF! | K48: 708.6865 | L48: 732.6865 | M48: 732.6865 | N48: 732.6865 | O48: 953 | P48: 953 | Q48: 953 | R48: 953 | S48: 953 | T48: 913 | U48: 913 | V48: 913 | W48: 913 | X48: 913 | Y48: 913 | Z48: 913 | AA48: 913 | AB48: 963 | AC48: 0 | AD48: 0 | AE48: 0 | AF48: 0 | AG48: 0 | AH48: 0 | AI48: 0 | AJ48: 0 | AK48: 0 | AL48: 0 | AM48: 0 | AN48: 0 | AO48: 0 | AP48: 0 | AQ48: 0 | AR48: 0 | AS48: 0 | AT48: 0 | AU48: 0 | AV48: {=IFERROR(_xlfn.XLOOKUP($C48, INDIRECT("'在庫使用計画 ("&AV$1&")'!D:D"), INDIRECT("'在庫使用計画 ("&AV$1&")'!I:I") ),"")} | AW48: {=IFERROR(_xlfn.XLOOKUP($C48, INDIRECT("'在庫使用計画 ("&AW$1&")'!D:D"), INDIRECT("'在庫使用計画 ("&AW$1&")'!I:I") ),"")} | AX48: {=IFERROR(_xlfn.XLOOKUP($C48, INDIRECT("'在庫使用計画 ("&AX$1&")'!D:D"), INDIRECT("'在庫使用計画 ("&AX$1&")'!I:I") ),"")}
A49: 15"-C | B49: CLE-MiniPC-AI9-HX470-白-GC | C49: MDR9N-IG-CW | D49: #REF! | E49: RPL-HX R i7-14650HX | H49: #N/A | I49: #REF! | J49: #REF! | K49: 600.07209 | L49: 620.07209 | M49: 620.07209 | N49: 620.07209 | O49: 615.07209 | P49: 615.07209 | Q49: 615.07209 | R49: 676.07209 | S49: 676.07209 | T49: 705 | U49: 705 | V49: 705 | W49: 705 | X49: 705 | Y49: 705 | Z49: 715 | AA49: 715 | AB49: 800 | AC49: 800 | AD49: 800 | AE49: 512.55073 | AF49: 512.55073 | AG49: 555.95217 | AH49: 555.95217 | AI49: 514.39735 | AJ49: 514.39735 | AK49: 543.56041 | AL49: 508.56041 | AM49: 508.56041 | AN49: 508.56041 | AO49: 508.56041 | AP49: 383.8026 | AQ49: 0 | AR49: 0 | AS49: 0 | AT49: 0 | AU49: 0 | AV49: {=IFERROR(_xlfn.XLOOKUP($C49, INDIRECT("'在庫使用計画 ("&AV$1&")'!D:D"), INDIRECT("'在庫使用計画 ("&AV$1&")'!I:I") ),"")} | AW49: {=IFERROR(_xlfn.XLOOKUP($C49, INDIRECT("'在庫使用計画 ("&AW$1&")'!D:D"), INDIRECT("'在庫使用計画 ("&AW$1&")'!I:I") ),"")} | AX49: {=IFERROR(_xlfn.XLOOKUP($C49, INDIRECT("'在庫使用計画 ("&AX$1&")'!D:D"), INDIRECT("'在庫使用計画 ("&AX$1&")'!I:I") ),"")}
A50: 16”-C | B50: CLE-MiniPC-AI7-450-黒-GC | C50: MSR7N-IG-CB | D50: #REF! | F50: 5050 | G50: DDR5 | H50: #N/A | I50: #REF! | J50: #REF! | R50: 0 | S50: 0 | T50: 0 | U50: 0 | V50: 0 | W50: 0 | X50: 0 | Y50: 0 | Z50: 0 | AA50: 0 | AB50: 0 | AC50: 0 | AD50: 0 | AE50: 0 | AF50: 0 | AG50: 0 | AH50: 0 | AI50: 0 | AJ50: 0 | AK50: 0 | AL50: 43 | AM50: 43 | AN50: 43 | AO50: 43 | AP50: 203 | AQ50: 0 | AR50: 0 | AS50: 0 | AT50: 0 | AU50: 0 | AV50: {=IFERROR(_xlfn.XLOOKUP($C50, INDIRECT("'在庫使用計画 ("&AV$1&")'!D:D"), INDIRECT("'在庫使用計画 ("&AV$1&")'!I:I") ),"")} | AW50: {=IFERROR(_xlfn.XLOOKUP($C50, INDIRECT("'在庫使用計画 ("&AW$1&")'!D:D"), INDIRECT("'在庫使用計画 ("&AW$1&")'!I:I") ),"")} | AX50: {=IFERROR(_xlfn.XLOOKUP($C50, INDIRECT("'在庫使用計画 ("&AX$1&")'!D:D"), INDIRECT("'在庫使用計画 ("&AX$1&")'!I:I") ),"")}
A51: 15"-C | B51: CLE-MiniPC-AI7-450-白-GC | C51: MSR7N-IG-CW | D51: #REF! | E51: RPL i7-13620H | F51: 4050 | G51: DDR5 | H51: #N/A | I51: #REF! | J51: #REF! | R51: 0 | S51: 0 | T51: 0 | U51: 0 | V51: 0 | W51: 0 | X51: 0 | Y51: 0 | Z51: 0 | AA51: 0 | AB51: 0 | AC51: 995 | AD51: 995 | AE51: 331.77369 | AF51: 331.77369 | AG51: 406.5634 | AH51: 406.5634 | AI51: 334.31373 | AJ51: 334.31373 | AK51: 377.96056 | AL51: 452.96056 | AM51: 452.96056 | AN51: 452.96056 | AO51: 452.96056 | AP51: 406.82384 | AQ51: 0 | AR51: 0 | AS51: 0 | AT51: 0 | AU51: 0 | AV51: {=IFERROR(_xlfn.XLOOKUP($C51, INDIRECT("'在庫使用計画 ("&AV$1&")'!D:D"), INDIRECT("'在庫使用計画 ("&AV$1&")'!I:I") ),"")} | AW51: {=IFERROR(_xlfn.XLOOKUP($C51, INDIRECT("'在庫使用計画 ("&AW$1&")'!D:D"), INDIRECT("'在庫使用計画 ("&AW$1&")'!I:I") ),"")} | AX51: {=IFERROR(_xlfn.XLOOKUP($C51, INDIRECT("'在庫使用計画 ("&AX$1&")'!D:D"), INDIRECT("'在庫使用計画 ("&AX$1&")'!I:I") ),"")}
A52: 15"-C | B52: CLE-MiniPC-R7-255-黒-GC | C52: MCR7N-IG-CB | D52: #REF! | E52: RPL i7-13620H | F52: 3050 | G52: DDR5 | H52: #N/A | I52: #REF! | J52: #REF! | K52: 790.10813 | L52: 788.10813 | M52: 828.10813 | N52: 828.10813 | O52: 828.10813 | P52: 828.10813 | Q52: 828.10813 | R52: 864.10813 | S52: 864.10813 | T52: 870 | U52: 870 | V52: 870 | W52: 870 | X52: 870 | Y52: 870 | Z52: 870 | AA52: 870 | AB52: 995 | AC52: 840 | AD52: 840 | AE52: 639.60313 | AF52: 639.60313 | AG52: 752.62576 | AH52: 752.62576 | AI52: 624.38005 | AJ52: 624.38005 | AK52: 699.06852 | AL52: 699.06852 | AM52: 699.06852 | AN52: 699.06852 | AO52: 699.06852 | AP52: 501.38601 | AQ52: 0 | AR52: 0 | AS52: 0 | AT52: 0 | AU52: 0 | AV52: {=IFERROR(_xlfn.XLOOKUP($C52, INDIRECT("'在庫使用計画 ("&AV$1&")'!D:D"), INDIRECT("'在庫使用計画 ("&AV$1&")'!I:I") ),"")} | AW52: {=IFERROR(_xlfn.XLOOKUP($C52, INDIRECT("'在庫使用計画 ("&AW$1&")'!D:D"), INDIRECT("'在庫使用計画 ("&AW$1&")'!I:I") ),"")} | AX52: {=IFERROR(_xlfn.XLOOKUP($C52, INDIRECT("'在庫使用計画 ("&AX$1&")'!D:D"), INDIRECT("'在庫使用計画 ("&AX$1&")'!I:I") ),"")}
A53: 15"-C | B53: CLE-MiniPC-R7-255-白-GC | C53: MCR7N-IG-CW | D53: #REF! | E53: RPL i7-13620H | F53: 3050 | G53: DDR5 | H53: #N/A | I53: #REF! | J53: #REF! | K53: 790.10813 | L53: 788.10813 | M53: 828.10813 | N53: 828.10813 | O53: 828.10813 | P53: 828.10813 | Q53: 828.10813 | R53: 864.10813 | S53: 864.10813 | T53: 870 | U53: 870 | V53: 870 | W53: 870 | X53: 870 | Y53: 870 | Z53: 870 | AA53: 870 | AB53: 995 | AC53: 840 | AD53: 840 | AE53: 639.60313 | AF53: 639.60313 | AG53: 752.62576 | AH53: 752.62576 | AI53: 624.38005 | AJ53: 624.38005 | AK53: 699.06852 | AL53: 699.06852 | AM53: 699.06852 | AN53: 699.06852 | AO53: 699.06852 | AP53: 501.38601 | AQ53: 0 | AR53: 0 | AS53: 0 | AT53: 0 | AU53: 0 | AV53: {=IFERROR(_xlfn.XLOOKUP($C53, INDIRECT("'在庫使用計画 ("&AV$1&")'!D:D"), INDIRECT("'在庫使用計画 ("&AV$1&")'!I:I") ),"")} | AW53: {=IFERROR(_xlfn.XLOOKUP($C53, INDIRECT("'在庫使用計画 ("&AW$1&")'!D:D"), INDIRECT("'在庫使用計画 ("&AW$1&")'!I:I") ),"")} | AX53: {=IFERROR(_xlfn.XLOOKUP($C53, INDIRECT("'在庫使用計画 ("&AX$1&")'!D:D"), INDIRECT("'在庫使用計画 ("&AX$1&")'!I:I") ),"")}
K54: 1485.1802 | L54: 1590.1802 | M54: 1170.1802 | N54: 1170.1802 | O54: 1170.1802 | P54: 1170.1802 | Q54: 1170.1802 | R54: 1235.1802 | S54: 1235.1802 | T54: 1160 | U54: 1160 | V54: 1160 | W54: 1160 | X54: 1160 | Y54: 1160 | Z54: 1160 | AA54: 1160 | AB54: 840 | AV54: {=IFERROR(_xlfn.XLOOKUP($C54, INDIRECT("'在庫使用計画 ("&AV$1&")'!D:D"), INDIRECT("'在庫使用計画 ("&AV$1&")'!I:I") ),"")} | AW54: {=IFERROR(_xlfn.XLOOKUP($C54, INDIRECT("'在庫使用計画 ("&AW$1&")'!D:D"), INDIRECT("'在庫使用計画 ("&AW$1&")'!I:I") ),"")} | AX54: {=IFERROR(_xlfn.XLOOKUP($C54, INDIRECT("'在庫使用計画 ("&AX$1&")'!D:D"), INDIRECT("'在庫使用計画 ("&AX$1&")'!I:I") ),"")}
AD55: 0 | AE55: 0 | AV55: {=IFERROR(_xlfn.XLOOKUP($C55, INDIRECT("'在庫使用計画 ("&AV$1&")'!D:D"), INDIRECT("'在庫使用計画 ("&AV$1&")'!I:I") ),"")} | AW55: {=IFERROR(_xlfn.XLOOKUP($C55, INDIRECT("'在庫使用計画 ("&AW$1&")'!D:D"), INDIRECT("'在庫使用計画 ("&AW$1&")'!I:I") ),"")} | AX55: {=IFERROR(_xlfn.XLOOKUP($C55, INDIRECT("'在庫使用計画 ("&AX$1&")'!D:D"), INDIRECT("'在庫使用計画 ("&AX$1&")'!I:I") ),"")}
AV56: {=IFERROR(_xlfn.XLOOKUP($C56, INDIRECT("'在庫使用計画 ("&AV$1&")'!D:D"), INDIRECT("'在庫使用計画 ("&AV$1&")'!I:I") ),"")} | AW56: {=IFERROR(_xlfn.XLOOKUP($C56, INDIRECT("'在庫使用計画 ("&AW$1&")'!D:D"), INDIRECT("'在庫使用計画 ("&AW$1&")'!I:I") ),"")} | AX56: {=IFERROR(_xlfn.XLOOKUP($C56, INDIRECT("'在庫使用計画 ("&AX$1&")'!D:D"), INDIRECT("'在庫使用計画 ("&AX$1&")'!I:I") ),"")}
B57: GALLERIA Creator 合計 | C57: Creator 計画合計 | K57: 5626.399 | L57: 5841.399 | M57: 5461.399 | N57: 5461.399 | O57: 5639.7125 | P57: 5639.7125 | Q57: 5639.7125 | R57: 5801.7125 | S57: 5801.7125 | T57: 5689 | U57: 5689 | V57: 5689 | W57: 5689 | X57: 5689 | Y57: 5689 | Z57: 5707.9742 | AA57: 5707.9742 | AB57: 5952.6359 | AC57: 6172.6359 | AD57: 6172.6359 | AE57: 3935.9893 | AF57: 3935.9893 | AG57: 3871.002 | AH57: 3871.002 | AI57: 3610.2728 | AJ57: 3610.2728 | AK57: 3826.9073 | AL57: 3936.9073 | AM57: 3936.9073 | AN57: 3936.9073 | AO57: 3936.9073 | AP57: 3698.0424 | AQ57: 3749.0424 | AR57: 3271.2479 | AS57: 3271.2479 | AT57: 3271.2479 | AU57: 3306.2479 | AV57: =_xlfn.AGGREGATE(9,0,AV30:AV56) -> 0 | AW57: =_xlfn.AGGREGATE(9,0,AW30:AW56) -> 0 | AX57: =_xlfn.AGGREGATE(9,0,AX30:AX56) -> 0
B58: GALLERIA Creator 予算 | AD58: 0 | AE58: 0 | AF58: 0 | AG58: 0 | AH58: 0 | AI58: 0 | AJ58: 0 | AK58: 0 | AL58: 0 | AM58: 0 | AN58: 0 | AO58: 0 | AP58: 0 | AQ58: 0 | AR58: 0 | AS58: 0 | AT58: 0 | AU58: 0 | AV58: {=IFERROR(_xlfn.XLOOKUP($C58, INDIRECT("'在庫使用計画 ("&AV$1&")'!C:C"), INDIRECT("'在庫使用計画 ("&AV$1&")'!H:H") ),"")} | AW58: {=IFERROR(_xlfn.XLOOKUP($C58, INDIRECT("'在庫使用計画 ("&AW$1&")'!C:C"), INDIRECT("'在庫使用計画 ("&AW$1&")'!H:H") ),"")} | AX58: {=IFERROR(_xlfn.XLOOKUP($C58, INDIRECT("'在庫使用計画 ("&AX$1&")'!C:C"), INDIRECT("'在庫使用計画 ("&AX$1&")'!H:H") ),"")}
B59: GALLERIA合計 | K59: 20170.346 | L59: 21231.448 | M59: 20035.56 | N59: 20035.56 | O59: 19971.873 | P59: 19971.873 | Q59: 19971.873 | R59: 20223.873 | S59: 20223.873 | T59: 22014.521 | U59: 22692.312 | V59: 22001.533 | W59: 22001.533 | X59: 22001.533 | Y59: 22001.533 | Z59: 19056.386 | AA59: 19056.386 | AB59: 21060.576 | AC59: 21280.576 | AD59: 21305.576 | AE59: 17383.426 | AF59: 17383.426 | AG59: 16846.274 | AH59: 16846.274 | AI59: 16383.875 | AJ59: 16383.875 | AK59: 16451.113 | AL59: 16592.113 | AM59: 16592.113 | AN59: 16432.113 | AO59: 16432.113 | AP59: 15449.886 | AQ59: 14951.807 | AR59: 14424.61 | AS59: 14424.61 | AT59: 14424.61 | AU59: 14491.61 | AV59: =_xlfn.AGGREGATE(9,0,AV2:AV58) -> 0 | AW59: =_xlfn.AGGREGATE(9,0,AW2:AW58) -> 0 | AX59: =_xlfn.AGGREGATE(9,0,AX2:AX58) -> 0
B60: GALLERIA全体予算 | AD60: 0 | AE60: 0 | AF60: 0 | AG60: 0 | AH60: 0 | AI60: 0 | AJ60: 0 | AK60: 0 | AL60: 0 | AM60: 0 | AN60: 0 | AO60: 0 | AP60: 0 | AQ60: 0 | AR60: 0 | AS60: 0 | AT60: 0 | AU60: 0 | AV60: {=IFERROR(_xlfn.XLOOKUP($C60, INDIRECT("'在庫使用計画 ("&AV$1&")'!C:C"), INDIRECT("'在庫使用計画 ("&AV$1&")'!H:H") ),"")} | AW60: {=IFERROR(_xlfn.XLOOKUP($C60, INDIRECT("'在庫使用計画 ("&AW$1&")'!C:C"), INDIRECT("'在庫使用計画 ("&AW$1&")'!H:H") ),"")} | AX60: {=IFERROR(_xlfn.XLOOKUP($C60, INDIRECT("'在庫使用計画 ("&AX$1&")'!C:C"), INDIRECT("'在庫使用計画 ("&AX$1&")'!H:H") ),"")}
B61: THIRDWAVE | E61: CPU | F61: GPU | AD61: 0 | AE61: 0 | AF61: 0 | AG61: 0 | AH61: 0 | AI61: 0 | AJ61: 0 | AK61: 0 | AL61: 0 | AM61: 0 | AN61: 0 | AO61: 0 | AP61: 0 | AQ61: 0 | AR61: 0 | AS61: 0 | AT61: 0 | AU61: 0 | AV61: {=IFERROR(_xlfn.XLOOKUP($C61, INDIRECT("'在庫使用計画 ("&AV$1&")'!C:C"), INDIRECT("'在庫使用計画 ("&AV$1&")'!H:H") ),"")} | AW61: {=IFERROR(_xlfn.XLOOKUP($C61, INDIRECT("'在庫使用計画 ("&AW$1&")'!C:C"), INDIRECT("'在庫使用計画 ("&AW$1&")'!H:H") ),"")} | AX61: {=IFERROR(_xlfn.XLOOKUP($C61, INDIRECT("'在庫使用計画 ("&AX$1&")'!C:C"), INDIRECT("'在庫使用計画 ("&AX$1&")'!H:H") ),"")}
A62: 16" GPU | B62: MSH-15F3-185H-5000-L6 Thirdwave | C62: M9652 | D62: {=IF($C62:$C125<>"", _xlfn.MAXIFS(#REF!,マスタ_EOLリスト[製品型番],$C62:$C125), "")} -> #REF! | H62: {=IF(C62:C125<>"", _xlfn.XLOOKUP($C62:$C125, '在庫使用計画 (ノート全体試算)'!C:C, '在庫使用計画 (ノート全体試算)'!G:G),"")} -> 177 | I62: {=IF(_xlfn.ANCHORARRAY(D62)<>"", _xlfn.XLOOKUP(_xlfn.ANCHORARRAY(D62),購買計画one_note_貼り付け[コード],購買計画one_note_貼り付け[納品日],""), "")} -> #REF! | J62: {=IF(_xlfn.ANCHORARRAY(D62)<>"", _xlfn.XLOOKUP(_xlfn.ANCHORARRAY(D62),購買計画one_note_貼り付け[コード],購買計画one_note_貼り付け[数量],""), "")} -> #REF! | K62: 74 | L62: 126 | M62: 63 | N62: 63 | O62: 63 | P62: 63 | Q62: 63 | R62: 63 | S62: 63 | T62: 88 | U62: 88 | V62: 88 | W62: 88 | X62: 88 | Y62: 88 | Z62: 88 | AA62: 88 | AB62: 125 | AC62: 125 | AD62: 125 | AE62: 125 | AF62: 125 | AG62: 125 | AH62: 125 | AI62: 110 | AJ62: 110 | AK62: 110 | AL62: 110 | AM62: 110 | AN62: 128 | AO62: 128 | AP62: 101 | AQ62: 101 | AR62: 101 | AS62: 101 | AT62: 101 | AU62: 101 | AV62: {=IFERROR(_xlfn.XLOOKUP($C62, INDIRECT("'在庫使用計画 ("&AV$1&")'!D:D"), INDIRECT("'在庫使用計画 ("&AV$1&")'!I:I") ),"")} | AW62: {=IFERROR(_xlfn.XLOOKUP($C62, INDIRECT("'在庫使用計画 ("&AW$1&")'!D:D"), INDIRECT("'在庫使用計画 ("&AW$1&")'!I:I") ),"")} | AX62: {=IFERROR(_xlfn.XLOOKUP($C62, INDIRECT("'在庫使用計画 ("&AX$1&")'!D:D"), INDIRECT("'在庫使用計画 ("&AX$1&")'!I:I") ),"")}
A63: 16" GPU | B63: MSH-15F4-185H-2000-L6 Thirdwave | C63: M9622 | D63: #REF! | E63: MTL-U9-185H | F63: 2000Ada | H63: 36 | I63: #REF! | J63: #REF! | K63: 22 | L63: 38 | M63: 19 | N63: 19 | O63: 19 | P63: 19 | Q63: 19 | R63: 19 | S63: 19 | T63: 33 | U63: 33 | V63: 33 | W63: 33 | X63: 33 | Y63: 33 | Z63: 33 | AA63: 33 | AB63: 50 | AC63: 50 | AD63: 50 | AE63: 50 | AF63: 50 | AG63: 50 | AH63: 50 | AI63: 47 | AJ63: 47 | AK63: 47 | AL63: 47 | AM63: 47 | AN63: 64 | AO63: 64 | AP63: 59 | AQ63: 59 | AR63: 59 | AS63: 59 | AT63: 59 | AU63: 59 | AV63: {=IFERROR(_xlfn.XLOOKUP($C63, INDIRECT("'在庫使用計画 ("&AV$1&")'!D:D"), INDIRECT("'在庫使用計画 ("&AV$1&")'!I:I") ),"")} | AW63: {=IFERROR(_xlfn.XLOOKUP($C63, INDIRECT("'在庫使用計画 ("&AW$1&")'!D:D"), INDIRECT("'在庫使用計画 ("&AW$1&")'!I:I") ),"")} | AX63: {=IFERROR(_xlfn.XLOOKUP($C63, INDIRECT("'在庫使用計画 ("&AX$1&")'!D:D"), INDIRECT("'在庫使用計画 ("&AX$1&")'!I:I") ),"")}
A64: 16" GPU | B64: UNW-U-14650HX-5060-L6 Thirdwave | C64: DX-16RP7A-6 | D64: #REF! | E64: RPL i7-14650HX | F64: 5060 | H64: 230 | I64: #REF! | J64: #REF! | K64: 80 | L64: 290 | M64: 290 | N64: 290 | O64: 290 | P64: 290 | Q64: 290 | R64: 290 | S64: 290 | T64: 870 | U64: 870 | V64: 870 | W64: 870 | X64: 870 | Y64: 870 | Z64: 870 | AA64: 870 | AB64: 1240 | AC64: 1240 | AD64: 1160 | AE64: 1160 | AF64: 1160 | AG64: 950 | AH64: 950 | AI64: 1270 | AJ64: 1270 | AK64: 1270 | AL64: 1210 | AM64: 1210 | AN64: 1210 | AO64: 1210 | AP64: 1410 | AQ64: 1460 | AR64: 1460 | AS64: 1460 | AT64: 1460 | AU64: 1460 | AV64: {=IFERROR(_xlfn.XLOOKUP($C64, INDIRECT("'在庫使用計画 ("&AV$1&")'!D:D"), INDIRECT("'在庫使用計画 ("&AV$1&")'!I:I") ),"")} | AW64: {=IFERROR(_xlfn.XLOOKUP($C64, INDIRECT("'在庫使用計画 ("&AW$1&")'!D:D"), INDIRECT("'在庫使用計画 ("&AW$1&")'!I:I") ),"")} | AX64: {=IFERROR(_xlfn.XLOOKUP($C64, INDIRECT("'在庫使用計画 ("&AX$1&")'!D:D"), INDIRECT("'在庫使用計画 ("&AX$1&")'!I:I") ),"")}
AV65: {=IFERROR(_xlfn.XLOOKUP($C65, INDIRECT("'在庫使用計画 ("&AV$1&")'!D:D"), INDIRECT("'在庫使用計画 ("&AV$1&")'!I:I") ),"")} | AW65: {=IFERROR(_xlfn.XLOOKUP($C65, INDIRECT("'在庫使用計画 ("&AW$1&")'!D:D"), INDIRECT("'在庫使用計画 ("&AW$1&")'!I:I") ),"")} | AX65: {=IFERROR(_xlfn.XLOOKUP($C65, INDIRECT("'在庫使用計画 ("&AX$1&")'!D:D"), INDIRECT("'在庫使用計画 ("&AX$1&")'!I:I") ),"")}
A66: 17" | B66: CLE-NL70-1334U-UMA-L6-TPM Thirdwave | C66: DX-17RP5A | D66: #REF! | E66: RPL-i5-1334U | F66: UMA | H66: 436 | I66: #REF! | J66: #REF! | K66: 100 | L66: 145 | M66: 55 | N66: 55 | O66: 55 | P66: 55 | Q66: 55 | R66: 55 | S66: 55 | T66: 100 | U66: 100 | V66: 100 | W66: 100 | X66: 100 | Y66: 100 | Z66: 100 | AA66: 100 | AB66: 140 | AC66: 140 | AD66: 140 | AE66: 140 | AF66: 140 | AG66: 140 | AH66: 140 | AI66: 155 | AJ66: 155 | AK66: 155 | AL66: 170 | AM66: 170 | AN66: 170 | AO66: 170 | AP66: 180 | AQ66: 190 | AR66: 190 | AS66: 190 | AT66: 190 | AU66: 190 | AV66: {=IFERROR(_xlfn.XLOOKUP($C66, INDIRECT("'在庫使用計画 ("&AV$1&")'!D:D"), INDIRECT("'在庫使用計画 ("&AV$1&")'!I:I") ),"")} | AW66: {=IFERROR(_xlfn.XLOOKUP($C66, INDIRECT("'在庫使用計画 ("&AW$1&")'!D:D"), INDIRECT("'在庫使用計画 ("&AW$1&")'!I:I") ),"")} | AX66: {=IFERROR(_xlfn.XLOOKUP($C66, INDIRECT("'在庫使用計画 ("&AX$1&")'!D:D"), INDIRECT("'在庫使用計画 ("&AX$1&")'!I:I") ),"")}
AV67: {=IFERROR(_xlfn.XLOOKUP($C67, INDIRECT("'在庫使用計画 ("&AV$1&")'!D:D"), INDIRECT("'在庫使用計画 ("&AV$1&")'!I:I") ),"")} | AW67: {=IFERROR(_xlfn.XLOOKUP($C67, INDIRECT("'在庫使用計画 ("&AW$1&")'!D:D"), INDIRECT("'在庫使用計画 ("&AW$1&")'!I:I") ),"")} | AX67: {=IFERROR(_xlfn.XLOOKUP($C67, INDIRECT("'在庫使用計画 ("&AX$1&")'!D:D"), INDIRECT("'在庫使用計画 ("&AX$1&")'!I:I") ),"")}
A68: 16” | B68: CLE-L26-258V-UMA-32G-L7 Thirdwave | C68: DX-L7LA | D68: #REF! | E68: LNL-U7-258V | F68: UMA-ARC | G68: CPU | H68: #N/A | I68: #REF! | J68: #REF! | K68: 213 | L68: 201 | M68: 201 | N68: 201 | O68: 201 | P68: 201 | Q68: 201 | R68: 201 | S68: 201 | T68: 139 | U68: 139 | V68: 139 | W68: 139 | X68: 139 | Y68: 139 | Z68: 139 | AA68: 139 | AB68: 98 | AC68: 98 | AD68: 98 | AE68: 98 | AF68: 98 | AG68: 98 | AH68: 98 | AI68: 50 | AJ68: 50 | AK68: 50 | AL68: 50 | AM68: 50 | AN68: 50 | AO68: 50 | AP68: 0 | AQ68: 0 | AR68: 0 | AS68: 0 | AT68: 0 | AU68: 0 | AV68: {=IFERROR(_xlfn.XLOOKUP($C68, INDIRECT("'在庫使用計画 ("&AV$1&")'!D:D"), INDIRECT("'在庫使用計画 ("&AV$1&")'!I:I") ),"")} | AW68: {=IFERROR(_xlfn.XLOOKUP($C68, INDIRECT("'在庫使用計画 ("&AW$1&")'!D:D"), INDIRECT("'在庫使用計画 ("&AW$1&")'!I:I") ),"")} | AX68: {=IFERROR(_xlfn.XLOOKUP($C68, INDIRECT("'在庫使用計画 ("&AX$1&")'!D:D"), INDIRECT("'在庫使用計画 ("&AX$1&")'!I:I") ),"")}
A69: 16” | B69: CLE-L26-228V-UMA-32G-L7 Thirdwave | C69: DX-L5LA | D69: #REF! | E69: LNL-U5-228V | F69: UMA-ARC | G69: CPU | H69: #N/A | I69: #REF! | J69: #REF! | K69: 113 | L69: 98 | M69: 98 | N69: 98 | O69: 98 | P69: 98 | Q69: 98 | R69: 98 | S69: 98 | T69: 68 | U69: 68 | V69: 68 | W69: 68 | X69: 68 | Y69: 68 | Z69: 68 | AA69: 68 | AB69: 49 | AC69: 49 | AD69: 49 | AE69: 49 | AF69: 49 | AG69: 49 | AH69: 49 | AI69: 25 | AJ69: 25 | AK69: 25 | AL69: 25 | AM69: 25 | AN69: 25 | AO69: 25 | AP69: 0 | AQ69: 0 | AR69: 0 | AS69: 0 | AT69: 0 | AU69: 0 | AV69: {=IFERROR(_xlfn.XLOOKUP($C69, INDIRECT("'在庫使用計画 ("&AV$1&")'!D:D"), INDIRECT("'在庫使用計画 ("&AV$1&")'!I:I") ),"")} | AW69: {=IFERROR(_xlfn.XLOOKUP($C69, INDIRECT("'在庫使用計画 ("&AW$1&")'!D:D"), INDIRECT("'在庫使用計画 ("&AW$1&")'!I:I") ),"")} | AX69: {=IFERROR(_xlfn.XLOOKUP($C69, INDIRECT("'在庫使用計画 ("&AX$1&")'!D:D"), INDIRECT("'在庫使用計画 ("&AX$1&")'!I:I") ),"")}
A70: 16” | B70: CLE-L260-155U-UMA-L6 Thirdwave | C70: DX-M7L | D70: #REF! | E70: MTL-7 | F70: UMA | G70: DDR5 | H70: #N/A | I70: #REF! | J70: #REF! | K70: 202 | L70: 102 | M70: 292 | N70: 292 | O70: 292 | P70: 292 | Q70: 292 | R70: 292 | S70: 292 | T70: 199 | U70: 199 | V70: 199 | W70: 199 | X70: 199 | Y70: 199 | Z70: 199 | AA70: 199 | AB70: 106 | AC70: 106 | AD70: 106 | AE70: 106 | AF70: 106 | AG70: 106 | AH70: 106 | AI70: 13 | AJ70: 13 | AK70: 13 | AL70: 13 | AM70: 13 | AN70: 13 | AO70: 13 | AP70: 0 | AQ70: 0 | AR70: 0 | AS70: 0 | AT70: 0 | AU70: 0 | AV70: {=IFERROR(_xlfn.XLOOKUP($C70, INDIRECT("'在庫使用計画 ("&AV$1&")'!D:D"), INDIRECT("'在庫使用計画 ("&AV$1&")'!I:I") ),"")} | AW70: {=IFERROR(_xlfn.XLOOKUP($C70, INDIRECT("'在庫使用計画 ("&AW$1&")'!D:D"), INDIRECT("'在庫使用計画 ("&AW$1&")'!I:I") ),"")} | AX70: {=IFERROR(_xlfn.XLOOKUP($C70, INDIRECT("'在庫使用計画 ("&AX$1&")'!D:D"), INDIRECT("'在庫使用計画 ("&AX$1&")'!I:I") ),"")}
A71: 16” | B71: CLE-L26-U7-355-UMA-32G-L7 Thirdwave | C71: DX-16PN7A | D71: #REF! | E71: PTL H404 U7 335 | F71: UMA | G71: DDR5 | H71: 168 | I71: #REF! | J71: #REF! | K71: 202 | L71: 102 | V71: 40 | W71: 40 | X71: 40 | Y71: 40 | Z71: 40 | AA71: 40 | AB71: 95 | AC71: 95 | AD71: 95 | AE71: 95 | AF71: 95 | AG71: 95 | AH71: 95 | AI71: 140 | AJ71: 140 | AK71: 140 | AL71: 140 | AM71: 140 | AN71: 140 | AO71: 140 | AP71: 175 | AQ71: 175 | AR71: 175 | AS71: 175 | AT71: 175 | AU71: 175 | AV71: {=IFERROR(_xlfn.XLOOKUP($C71, INDIRECT("'在庫使用計画 ("&AV$1&")'!D:D"), INDIRECT("'在庫使用計画 ("&AV$1&")'!I:I") ),"")} | AW71: {=IFERROR(_xlfn.XLOOKUP($C71, INDIRECT("'在庫使用計画 ("&AW$1&")'!D:D"), INDIRECT("'在庫使用計画 ("&AW$1&")'!I:I") ),"")} | AX71: {=IFERROR(_xlfn.XLOOKUP($C71, INDIRECT("'在庫使用計画 ("&AX$1&")'!D:D"), INDIRECT("'在庫使用計画 ("&AX$1&")'!I:I") ),"")}
AV72: {=IFERROR(_xlfn.XLOOKUP($C72, INDIRECT("'在庫使用計画 ("&AV$1&")'!D:D"), INDIRECT("'在庫使用計画 ("&AV$1&")'!I:I") ),"")} | AW72: {=IFERROR(_xlfn.XLOOKUP($C72, INDIRECT("'在庫使用計画 ("&AW$1&")'!D:D"), INDIRECT("'在庫使用計画 ("&AW$1&")'!I:I") ),"")} | AX72: {=IFERROR(_xlfn.XLOOKUP($C72, INDIRECT("'在庫使用計画 ("&AX$1&")'!D:D"), INDIRECT("'在庫使用計画 ("&AX$1&")'!I:I") ),"")}
A73: 15” | B73: QNT-LGHB-1355U-UMA-L6 | C73: DX-R7 | D73: #REF! | E73: RPL-i7-1355U | F73: UMA | G73: DDR4 | H73: 104 | I73: #REF! | J73: #REF! | K73: 555 | L73: 538 | M73: 538 | N73: 538 | O73: 802 | P73: 802 | Q73: 802 | R73: 802 | S73: 802 | T73: 856 | U73: 856 | V73: 856 | W73: 856 | X73: 856 | Y73: 856 | Z73: 856 | AA73: 856 | AB73: 746 | AC73: 746 | AD73: 746 | AE73: 746 | AF73: 746 | AG73: 746 | AH73: 746 | AI73: 556 | AJ73: 556 | AK73: 556 | AL73: 304 | AM73: 304 | AN73: 304 | AO73: 304 | AP73: 286 | AQ73: 286 | AR73: 286 | AS73: 286 | AT73: 286 | AU73: 286 | AV73: {=IFERROR(_xlfn.XLOOKUP($C73, INDIRECT("'在庫使用計画 ("&AV$1&")'!D:D"), INDIRECT("'在庫使用計画 ("&AV$1&")'!I:I") ),"")} | AW73: {=IFERROR(_xlfn.XLOOKUP($C73, INDIRECT("'在庫使用計画 ("&AW$1&")'!D:D"), INDIRECT("'在庫使用計画 ("&AW$1&")'!I:I") ),"")} | AX73: {=IFERROR(_xlfn.XLOOKUP($C73, INDIRECT("'在庫使用計画 ("&AX$1&")'!D:D"), INDIRECT("'在庫使用計画 ("&AX$1&")'!I:I") ),"")}
A74: 15” | B74: WZN-1051-1355U-UMA-L6 Thirdwave | C74: DX-R7S | D74: #REF! | E74: RPL-i7-1355U | F74: UMA | G74: DDR4 | H74: 69 | I74: #REF! | J74: #REF! | K74: 1176 | L74: 1351 | M74: 1750 | N74: 1750 | O74: 1375 | P74: 1375 | Q74: 1375 | R74: 1375 | S74: 1375 | T74: 1130 | U74: 1130 | V74: 1130 | W74: 1130 | X74: 1130 | Y74: 1130 | Z74: 1130 | AA74: 1130 | AB74: 735 | AC74: 735 | AD74: 735 | AE74: 735 | AF74: 735 | AG74: 735 | AH74: 735 | AI74: 405 | AJ74: 405 | AK74: 405 | AL74: 485 | AM74: 485 | AN74: 485 | AO74: 485 | AP74: 165 | AQ74: 165 | AR74: 165 | AS74: 165 | AT74: 165 | AU74: 165 | AV74: {=IFERROR(_xlfn.XLOOKUP($C74, INDIRECT("'在庫使用計画 ("&AV$1&")'!D:D"), INDIRECT("'在庫使用計画 ("&AV$1&")'!I:I") ),"")} | AW74: {=IFERROR(_xlfn.XLOOKUP($C74, INDIRECT("'在庫使用計画 ("&AW$1&")'!D:D"), INDIRECT("'在庫使用計画 ("&AW$1&")'!I:I") ),"")} | AX74: {=IFERROR(_xlfn.XLOOKUP($C74, INDIRECT("'在庫使用計画 ("&AX$1&")'!D:D"), INDIRECT("'在庫使用計画 ("&AX$1&")'!I:I") ),"")}
A75: 15” | B75: CLE-NL55-1355U‐UMA Thirdwave | C75: DX-15RP7A | D75: #REF! | E75: RPL-i7-1355U | F75: UMA | G75: DDR5 | H75: 702 | I75: #REF! | J75: #REF! | R75: 0 | S75: 0 | T75: 145 | U75: 145 | V75: 145 | W75: 145 | X75: 145 | Y75: 145 | Z75: 145 | AA75: 145 | AB75: 741 | AC75: 741 | AD75: 741 | AE75: 741 | AF75: 741 | AG75: 741 | AH75: 741 | AI75: 1062 | AJ75: 1062 | AK75: 1062 | AL75: 870 | AM75: 870 | AN75: 870 | AO75: 870 | AP75: 1069 | AQ75: 1149 | AR75: 870 | AS75: 870 | AT75: 870 | AU75: 870 | AV75: {=IFERROR(_xlfn.XLOOKUP($C75, INDIRECT("'在庫使用計画 ("&AV$1&")'!D:D"), INDIRECT("'在庫使用計画 ("&AV$1&")'!I:I") ),"")} | AW75: {=IFERROR(_xlfn.XLOOKUP($C75, INDIRECT("'在庫使用計画 ("&AW$1&")'!D:D"), INDIRECT("'在庫使用計画 ("&AW$1&")'!I:I") ),"")} | AX75: {=IFERROR(_xlfn.XLOOKUP($C75, INDIRECT("'在庫使用計画 ("&AX$1&")'!D:D"), INDIRECT("'在庫使用計画 ("&AX$1&")'!I:I") ),"")}
A76: 15” | B76: CLE-NL55-1355U‐UMA Thirdwave | C76: DX-15RP7B | D76: #REF! | E76: RPL-i7-1355U | F76: UMA | G76: DDR5 | H76: #N/A | I76: #REF! | J76: #REF! | R76: 0 | S76: 0 | T76: 145 | U76: 145 | V76: 145 | W76: 145 | X76: 145 | Y76: 145 | Z76: 145 | AA76: 145 | AB76: 741 | AC76: 741 | AD76: 741 | AE76: 741 | AF76: 741 | AG76: 741 | AH76: 741 | AI76: 1062 | AJ76: 1062 | AK76: 1062 | AL76: 870 | AM76: 870 | AN76: 870 | AO76: 870 | AP76: 1069 | AQ76: 0 | AR76: 0 | AS76: 0 | AT76: 0 | AU76: 0 | AV76: {=IFERROR(_xlfn.XLOOKUP($C76, INDIRECT("'在庫使用計画 ("&AV$1&")'!D:D"), INDIRECT("'在庫使用計画 ("&AV$1&")'!I:I") ),"")} | AW76: {=IFERROR(_xlfn.XLOOKUP($C76, INDIRECT("'在庫使用計画 ("&AW$1&")'!D:D"), INDIRECT("'在庫使用計画 ("&AW$1&")'!I:I") ),"")} | AX76: {=IFERROR(_xlfn.XLOOKUP($C76, INDIRECT("'在庫使用計画 ("&AX$1&")'!D:D"), INDIRECT("'在庫使用計画 ("&AX$1&")'!I:I") ),"")}
A77: 15” | B77: QNT-LGHB-1335U-UMA-L6 | C77: DX-R5 | D77: #REF! | E77: RPL-i5-1335U | F77: UMA | G77: DDR4 | H77: 302 | I77: #REF! | J77: #REF! | K77: 300 | L77: 460 | M77: 460 | N77: 460 | O77: 460 | P77: 460 | Q77: 460 | R77: 460 | S77: 460 | T77: 600 | U77: 600 | V77: 600 | W77: 600 | X77: 600 | Y77: 600 | Z77: 600 | AA77: 600 | AB77: 710 | AC77: 710 | AD77: 710 | AE77: 710 | AF77: 710 | AG77: 710 | AH77: 710 | AI77: 680 | AJ77: 680 | AK77: 680 | AL77: 370 | AM77: 370 | AN77: 370 | AO77: 370 | AP77: 270 | AQ77: 270 | AR77: 270 | AS77: 270 | AT77: 270 | AU77: 270 | AV77: {=IFERROR(_xlfn.XLOOKUP($C77, INDIRECT("'在庫使用計画 ("&AV$1&")'!D:D"), INDIRECT("'在庫使用計画 ("&AV$1&")'!I:I") ),"")} | AW77: {=IFERROR(_xlfn.XLOOKUP($C77, INDIRECT("'在庫使用計画 ("&AW$1&")'!D:D"), INDIRECT("'在庫使用計画 ("&AW$1&")'!I:I") ),"")} | AX77: {=IFERROR(_xlfn.XLOOKUP($C77, INDIRECT("'在庫使用計画 ("&AX$1&")'!D:D"), INDIRECT("'在庫使用計画 ("&AX$1&")'!I:I") ),"")}
A78: 15” | B78: WZN-1051-1335U-UMA-L6 Thirdwave | C78: DX-R5S | D78: #REF! | E78: RPL-i5-1335U | F78: UMA | G78: DDR4 | H78: 1 | I78: #REF! | J78: #REF! | K78: 180 | R78: 0 | S78: 0 | T78: 0 | U78: 0 | V78: 0 | W78: 0 | X78: 0 | Y78: 0 | Z78: 0 | AA78: 0 | AB78: 0 | AC78: 0 | AD78: 0 | AE78: 0 | AF78: 0 | AG78: 0 | AH78: 0 | AI78: 0 | AJ78: 0 | AK78: 0 | AL78: 0 | AM78: 0 | AN78: 0 | AO78: 0 | AP78: 0 | AQ78: 0 | AR78: 0 | AS78: 0 | AT78: 0 | AU78: 0 | AV78: {=IFERROR(_xlfn.XLOOKUP($C78, INDIRECT("'在庫使用計画 ("&AV$1&")'!D:D"), INDIRECT("'在庫使用計画 ("&AV$1&")'!I:I") ),"")} | AW78: {=IFERROR(_xlfn.XLOOKUP($C78, INDIRECT("'在庫使用計画 ("&AW$1&")'!D:D"), INDIRECT("'在庫使用計画 ("&AW$1&")'!I:I") ),"")} | AX78: {=IFERROR(_xlfn.XLOOKUP($C78, INDIRECT("'在庫使用計画 ("&AX$1&")'!D:D"), INDIRECT("'在庫使用計画 ("&AX$1&")'!I:I") ),"")}
A79: 15” | B79: WZN-1051-1334U-UMA-L6 Thirdwave | C79: DX-R5T | D79: #REF! | E79: RPL-i5-1334U | F79: UMA | G79: DDR4 | H79: 244 | I79: #REF! | J79: #REF! | K79: 2339 | L79: 2342 | M79: 2643 | N79: 2643 | O79: 2558 | P79: 2558 | Q79: 2358 | R79: 2808 | S79: 2808 | T79: 2808 | U79: 2808 | V79: 2808 | W79: 2808 | X79: 3064 | Y79: 3064 | Z79: 3064 | AA79: 3064 | AB79: 2568 | AC79: 2568 | AD79: 2568 | AE79: 2568 | AF79: 2568 | AG79: 2568 | AH79: 2568 | AI79: 1839 | AJ79: 1839 | AK79: 1839 | AL79: 1539 | AM79: 1539 | AN79: 1539 | AO79: 1539 | AP79: 844 | AQ79: 944 | AR79: 944 | AS79: 944 | AT79: 944 | AU79: 944 | AV79: {=IFERROR(_xlfn.XLOOKUP($C79, INDIRECT("'在庫使用計画 ("&AV$1&")'!D:D"), INDIRECT("'在庫使用計画 ("&AV$1&")'!I:I") ),"")} | AW79: {=IFERROR(_xlfn.XLOOKUP($C79, INDIRECT("'在庫使用計画 ("&AW$1&")'!D:D"), INDIRECT("'在庫使用計画 ("&AW$1&")'!I:I") ),"")} | AX79: {=IFERROR(_xlfn.XLOOKUP($C79, INDIRECT("'在庫使用計画 ("&AX$1&")'!D:D"), INDIRECT("'在庫使用計画 ("&AX$1&")'!I:I") ),"")}
A80: 15” | B80: CLE-NL55-1334U‐UMA Thirdwave | C80: DX-15RP5A | D80: #REF! | E80: RPL-i5-1334U | F80: UMA | G80: DDR5 | H80: 471 | I80: #REF! | J80: #REF! | R80: 0 | S80: 0 | T80: 420 | U80: 420 | V80: 420 | W80: 420 | X80: 420 | Y80: 420 | Z80: 420 | AA80: 420 | AB80: 1132 | AC80: 1132 | AD80: 1132 | AE80: 1132 | AF80: 1132 | AG80: 1132 | AH80: 1132 | AI80: 1844 | AJ80: 1844 | AK80: 1844 | AL80: 1524 | AM80: 1524 | AN80: 1524 | AO80: 1524 | AP80: 2103 | AQ80: 2003 | AR80: 1700 | AS80: 1700 | AT80: 1700 | AU80: 1700 | AV80: {=IFERROR(_xlfn.XLOOKUP($C80, INDIRECT("'在庫使用計画 ("&AV$1&")'!D:D"), INDIRECT("'在庫使用計画 ("&AV$1&")'!I:I") ),"")} | AW80: {=IFERROR(_xlfn.XLOOKUP($C80, INDIRECT("'在庫使用計画 ("&AW$1&")'!D:D"), INDIRECT("'在庫使用計画 ("&AW$1&")'!I:I") ),"")} | AX80: {=IFERROR(_xlfn.XLOOKUP($C80, INDIRECT("'在庫使用計画 ("&AX$1&")'!D:D"), INDIRECT("'在庫使用計画 ("&AX$1&")'!I:I") ),"")}
A81: 15” | B81: WZN-1051-1315U-UMA-L6 Thirdwave | C81: DX-15RP5B | D81: #REF! | E81: RPL-i3-1315U | F81: UMA | G81: DDR4 | H81: 833 | I81: #REF! | J81: #REF! | K81: 866 | L81: 1010 | M81: 1010 | N81: 1010 | O81: 1105 | P81: 1105 | Q81: 1105 | R81: 1105 | S81: 1105 | T81: 1050 | U81: 1050 | V81: 1050 | W81: 1050 | X81: 1080 | Y81: 1080 | Z81: 1080 | AA81: 1080 | AB81: 945 | AC81: 945 | AD81: 945 | AE81: 945 | AF81: 945 | AG81: 945 | AH81: 945 | AI81: 650 | AJ81: 650 | AK81: 650 | AL81: 830 | AM81: 830 | AN81: 830 | AO81: 830 | AP81: 680 | AQ81: 0 | AR81: 0 | AS81: 0 | AT81: 0 | AU81: 0 | AV81: {=IFERROR(_xlfn.XLOOKUP($C81, INDIRECT("'在庫使用計画 ("&AV$1&")'!D:D"), INDIRECT("'在庫使用計画 ("&AV$1&")'!I:I") ),"")} | AW81: {=IFERROR(_xlfn.XLOOKUP($C81, INDIRECT("'在庫使用計画 ("&AW$1&")'!D:D"), INDIRECT("'在庫使用計画 ("&AW$1&")'!I:I") ),"")} | AX81: {=IFERROR(_xlfn.XLOOKUP($C81, INDIRECT("'在庫使用計画 ("&AX$1&")'!D:D"), INDIRECT("'在庫使用計画 ("&AX$1&")'!I:I") ),"")}
A82: 15” | B82: WZN-1051-1315U-UMA-L6 Thirdwave | C82: DX-R3S | D82: #REF! | E82: RPL-i3-1315U | F82: UMA | G82: DDR4 | H82: 45 | I82: #REF! | J82: #REF! | K82: 866 | L82: 1010 | M82: 1010 | N82: 1010 | O82: 1105 | P82: 1105 | Q82: 1105 | R82: 1105 | S82: 1105 | T82: 1050 | U82: 1050 | V82: 1050 | W82: 1050 | X82: 1080 | Y82: 1080 | Z82: 1080 | AA82: 1080 | AB82: 945 | AC82: 945 | AD82: 945 | AE82: 945 | AF82: 945 | AG82: 945 | AH82: 945 | AI82: 650 | AJ82: 650 | AK82: 650 | AL82: 830 | AM82: 830 | AN82: 830 | AO82: 830 | AP82: 680 | AQ82: 750 | AR82: 340 | AS82: 340 | AT82: 340 | AU82: 340 | AV82: {=IFERROR(_xlfn.XLOOKUP($C82, INDIRECT("'在庫使用計画 ("&AV$1&")'!D:D"), INDIRECT("'在庫使用計画 ("&AV$1&")'!I:I") ),"")} | AW82: {=IFERROR(_xlfn.XLOOKUP($C82, INDIRECT("'在庫使用計画 ("&AW$1&")'!D:D"), INDIRECT("'在庫使用計画 ("&AW$1&")'!I:I") ),"")} | AX82: {=IFERROR(_xlfn.XLOOKUP($C82, INDIRECT("'在庫使用計画 ("&AX$1&")'!D:D"), INDIRECT("'在庫使用計画 ("&AX$1&")'!I:I") ),"")}
A83: 15” | B83: CLE-NL55-1315U‐UMA Thirdwave | C83: DX-15RP3A | D83: #REF! | E83: RPL-i3-1315U | F83: UMA | G83: DDR5 | H83: 442 | I83: #REF! | J83: #REF! | R83: 0 | S83: 0 | T83: 50 | U83: 50 | V83: 50 | W83: 50 | X83: 0 | Y83: 0 | Z83: 0 | AA83: 0 | AB83: 310 | AC83: 310 | AD83: 310 | AE83: 310 | AF83: 310 | AG83: 310 | AH83: 310 | AI83: 501 | AJ83: 501 | AK83: 501 | AL83: 110 | AM83: 110 | AN83: 110 | AO83: 110 | AP83: 130 | AQ83: 130 | AR83: 80 | AS83: 80 | AT83: 80 | AU83: 80 | AV83: {=IFERROR(_xlfn.XLOOKUP($C83, INDIRECT("'在庫使用計画 ("&AV$1&")'!D:D"), INDIRECT("'在庫使用計画 ("&AV$1&")'!I:I") ),"")} | AW83: {=IFERROR(_xlfn.XLOOKUP($C83, INDIRECT("'在庫使用計画 ("&AW$1&")'!D:D"), INDIRECT("'在庫使用計画 ("&AW$1&")'!I:I") ),"")} | AX83: {=IFERROR(_xlfn.XLOOKUP($C83, INDIRECT("'在庫使用計画 ("&AX$1&")'!D:D"), INDIRECT("'在庫使用計画 ("&AX$1&")'!I:I") ),"")}
AV84: {=IFERROR(_xlfn.XLOOKUP($C84, INDIRECT("'在庫使用計画 ("&AV$1&")'!D:D"), INDIRECT("'在庫使用計画 ("&AV$1&")'!I:I") ),"")} | AW84: {=IFERROR(_xlfn.XLOOKUP($C84, INDIRECT("'在庫使用計画 ("&AW$1&")'!D:D"), INDIRECT("'在庫使用計画 ("&AW$1&")'!I:I") ),"")} | AX84: {=IFERROR(_xlfn.XLOOKUP($C84, INDIRECT("'在庫使用計画 ("&AX$1&")'!D:D"), INDIRECT("'在庫使用計画 ("&AX$1&")'!I:I") ),"")}
A85: 14” | B85: CLE-L24-258V-UMA-32G-L7 Thirdwave | C85: F-14LN7LA | D85: #REF! | E85: LNL-U7-258V | F85: UMA-ARC | G85: CPU | H85: 62 | I85: #REF! | J85: #REF! | K85: 370 | L85: 317 | M85: 329 | N85: 329 | O85: 469 | P85: 469 | Q85: 469 | R85: 469 | S85: 469 | T85: 456 | U85: 456 | V85: 456 | W85: 456 | X85: 456 | Y85: 456 | Z85: 456 | AA85: 456 | AB85: 440 | AC85: 440 | AD85: 440 | AE85: 440 | AF85: 440 | AG85: 440 | AH85: 440 | AI85: 340 | AJ85: 340 | AK85: 340 | AL85: 340 | AM85: 340 | AN85: 580 | AO85: 580 | AP85: 510 | AQ85: 600 | AR85: 600 | AS85: 600 | AT85: 600 | AU85: 600 | AV85: {=IFERROR(_xlfn.XLOOKUP($C85, INDIRECT("'在庫使用計画 ("&AV$1&")'!D:D"), INDIRECT("'在庫使用計画 ("&AV$1&")'!I:I") ),"")} | AW85: {=IFERROR(_xlfn.XLOOKUP($C85, INDIRECT("'在庫使用計画 ("&AW$1&")'!D:D"), INDIRECT("'在庫使用計画 ("&AW$1&")'!I:I") ),"")} | AX85: {=IFERROR(_xlfn.XLOOKUP($C85, INDIRECT("'在庫使用計画 ("&AX$1&")'!D:D"), INDIRECT("'在庫使用計画 ("&AX$1&")'!I:I") ),"")}
A86: 14” | B86: CLE-L24-228V-UMA-32G-L7 Thirdwave | C86: F-14LN5LA-228V | D86: #REF! | E86: LNL-U5-228V | F86: UMA-ARC | G86: CPU | H86: 0 | I86: #REF! | J86: #REF! | K86: 139 | L86: 138 | M86: 138 | N86: 138 | O86: 138 | P86: 138 | Q86: 138 | R86: 138 | S86: 138 | T86: 113 | U86: 113 | V86: 113 | W86: 113 | X86: 113 | Y86: 113 | Z86: 113 | AA86: 113 | AB86: 83 | AC86: 83 | AD86: 83 | AE86: 83 | AF86: 83 | AG86: 83 | AH86: 83 | AI86: 47 | AJ86: 47 | AK86: 47 | AL86: 37 | AM86: 37 | AN86: 37 | AO86: 37 | AP86: 0 | AQ86: 0 | AR86: 0 | AS86: 0 | AT86: 0 | AU86: 0 | AV86: {=IFERROR(_xlfn.XLOOKUP($C86, INDIRECT("'在庫使用計画 ("&AV$1&")'!D:D"), INDIRECT("'在庫使用計画 ("&AV$1&")'!I:I") ),"")} | AW86: {=IFERROR(_xlfn.XLOOKUP($C86, INDIRECT("'在庫使用計画 ("&AW$1&")'!D:D"), INDIRECT("'在庫使用計画 ("&AW$1&")'!I:I") ),"")} | AX86: {=IFERROR(_xlfn.XLOOKUP($C86, INDIRECT("'在庫使用計画 ("&AX$1&")'!D:D"), INDIRECT("'在庫使用計画 ("&AX$1&")'!I:I") ),"")}
A87: 14” | B87: CLE-L24-226V-UMA-16G-L7 Thirdwave | C87: F-14LN5LA | D87: #REF! | E87: LNL-U5-226V | F87: UMA-ARC | G87: CPU | H87: 625 | I87: #REF! | J87: #REF! | K87: 578 | L87: 572 | M87: 467 | N87: 467 | O87: 527 | P87: 527 | Q87: 527 | R87: 527 | S87: 527 | T87: 557 | U87: 557 | V87: 557 | W87: 557 | X87: 431 | Y87: 431 | Z87: 431 | AA87: 431 | AB87: 536 | AC87: 536 | AD87: 536 | AE87: 536 | AF87: 536 | AG87: 536 | AH87: 536 | AI87: 463 | AJ87: 463 | AK87: 463 | AL87: 463 | AM87: 463 | AN87: 693 | AO87: 693 | AP87: 760 | AQ87: 698 | AR87: 698 | AS87: 698 | AT87: 698 | AU87: 698 | AV87: {=IFERROR(_xlfn.XLOOKUP($C87, INDIRECT("'在庫使用計画 ("&AV$1&")'!D:D"), INDIRECT("'在庫使用計画 ("&AV$1&")'!I:I") ),"")} | AW87: {=IFERROR(_xlfn.XLOOKUP($C87, INDIRECT("'在庫使用計画 ("&AW$1&")'!D:D"), INDIRECT("'在庫使用計画 ("&AW$1&")'!I:I") ),"")} | AX87: {=IFERROR(_xlfn.XLOOKUP($C87, INDIRECT("'在庫使用計画 ("&AX$1&")'!D:D"), INDIRECT("'在庫使用計画 ("&AX$1&")'!I:I") ),"")}
A88: 14” | B88: CLE-L24-U7-355-UMA-32G-L7 Thirdwave | C88: F-14PN7A | D88: #REF! | E88: PTL H404 U7 335 | F88: UMA | H88: 1001 | I88: #REF! | J88: #REF! | V88: 25 | W88: 35 | X88: 35 | Y88: 35 | Z88: 35 | AA88: 35 | AB88: 95 | AC88: 95 | AD88: 95 | AE88: 95 | AF88: 95 | AG88: 95 | AH88: 95 | AI88: 145 | AJ88: 145 | AK88: 145 | AL88: 145 | AM88: 145 | AN88: 145 | AO88: 145 | AP88: 225 | AQ88: 275 | AR88: 275 | AS88: 275 | AT88: 275 | AU88: 275 | AV88: {=IFERROR(_xlfn.XLOOKUP($C88, INDIRECT("'在庫使用計画 ("&AV$1&")'!D:D"), INDIRECT("'在庫使用計画 ("&AV$1&")'!I:I") ),"")} | AW88: {=IFERROR(_xlfn.XLOOKUP($C88, INDIRECT("'在庫使用計画 ("&AW$1&")'!D:D"), INDIRECT("'在庫使用計画 ("&AW$1&")'!I:I") ),"")} | AX88: {=IFERROR(_xlfn.XLOOKUP($C88, INDIRECT("'在庫使用計画 ("&AX$1&")'!D:D"), INDIRECT("'在庫使用計画 ("&AX$1&")'!I:I") ),"")}
A89: 14” | B89: CLE-L24-U5-325-UMA-16G-L7 Thirdwave | C89: F-14PN5A | D89: #REF! | E89: PTL H404 U5 325 | F89: UMA | H89: 1247 | I89: #REF! | J89: #REF! | K89: 370 | L89: 317 | V89: 35 | W89: 45 | X89: 45 | Y89: 45 | Z89: 45 | AA89: 45 | AB89: 115 | AC89: 115 | AD89: 115 | AE89: 115 | AF89: 115 | AG89: 115 | AH89: 115 | AI89: 175 | AJ89: 175 | AK89: 175 | AL89: 175 | AM89: 175 | AN89: 175 | AO89: 175 | AP89: 265 | AQ89: 270 | AR89: 270 | AS89: 270 | AT89: 270 | AU89: 270 | AV89: {=IFERROR(_xlfn.XLOOKUP($C89, INDIRECT("'在庫使用計画 ("&AV$1&")'!D:D"), INDIRECT("'在庫使用計画 ("&AV$1&")'!I:I") ),"")} | AW89: {=IFERROR(_xlfn.XLOOKUP($C89, INDIRECT("'在庫使用計画 ("&AW$1&")'!D:D"), INDIRECT("'在庫使用計画 ("&AW$1&")'!I:I") ),"")} | AX89: {=IFERROR(_xlfn.XLOOKUP($C89, INDIRECT("'在庫使用計画 ("&AX$1&")'!D:D"), INDIRECT("'在庫使用計画 ("&AX$1&")'!I:I") ),"")}
A90: 14” | B90: CLE-L24-258V-UMA-32G-L7 TW | C90: F-14LN7LS | D90: #REF! | E90: LNL-U7-258V | F90: UMA-ARC | H90: #N/A | I90: #REF! | J90: #REF! | K90: 139 | L90: 138 | AF90: 0 | AG90: 0 | AH90: 0 | AI90: 240 | AJ90: 240 | AK90: 240 | AL90: 240 | AM90: 240 | AN90: 0 | AO90: 0 | AP90: 0 | AQ90: 0 | AR90: 0 | AS90: 0 | AT90: 0 | AU90: 0 | AV90: {=IFERROR(_xlfn.XLOOKUP($C90, INDIRECT("'在庫使用計画 ("&AV$1&")'!D:D"), INDIRECT("'在庫使用計画 ("&AV$1&")'!I:I") ),"")} | AW90: {=IFERROR(_xlfn.XLOOKUP($C90, INDIRECT("'在庫使用計画 ("&AW$1&")'!D:D"), INDIRECT("'在庫使用計画 ("&AW$1&")'!I:I") ),"")} | AX90: {=IFERROR(_xlfn.XLOOKUP($C90, INDIRECT("'在庫使用計画 ("&AX$1&")'!D:D"), INDIRECT("'在庫使用計画 ("&AX$1&")'!I:I") ),"")}
A91: 14” | B91: CLE-L24-226V-UMA-16G-L7 TW | C91: F-14LN5LS | D91: #REF! | E91: LNL-U5-228V | F91: UMA-ARC | H91: #N/A | I91: #REF! | J91: #REF! | K91: 578 | L91: 572 | AF91: 0 | AG91: 0 | AH91: 0 | AI91: 280 | AJ91: 280 | AK91: 280 | AL91: 280 | AM91: 280 | AN91: 0 | AO91: 0 | AP91: 0 | AQ91: 0 | AR91: 0 | AS91: 0 | AT91: 0 | AU91: 0 | AV91: {=IFERROR(_xlfn.XLOOKUP($C91, INDIRECT("'在庫使用計画 ("&AV$1&")'!D:D"), INDIRECT("'在庫使用計画 ("&AV$1&")'!I:I") ),"")} | AW91: {=IFERROR(_xlfn.XLOOKUP($C91, INDIRECT("'在庫使用計画 ("&AW$1&")'!D:D"), INDIRECT("'在庫使用計画 ("&AW$1&")'!I:I") ),"")} | AX91: {=IFERROR(_xlfn.XLOOKUP($C91, INDIRECT("'在庫使用計画 ("&AX$1&")'!D:D"), INDIRECT("'在庫使用計画 ("&AX$1&")'!I:I") ),"")}
AV92: {=IFERROR(_xlfn.XLOOKUP($C92, INDIRECT("'在庫使用計画 ("&AV$1&")'!D:D"), INDIRECT("'在庫使用計画 ("&AV$1&")'!I:I") ),"")} | AW92: {=IFERROR(_xlfn.XLOOKUP($C92, INDIRECT("'在庫使用計画 ("&AW$1&")'!D:D"), INDIRECT("'在庫使用計画 ("&AW$1&")'!I:I") ),"")} | AX92: {=IFERROR(_xlfn.XLOOKUP($C92, INDIRECT("'在庫使用計画 ("&AX$1&")'!D:D"), INDIRECT("'在庫使用計画 ("&AX$1&")'!I:I") ),"")}
A93: 14” | B93: CLE-L240-125U-UMA-L6 Thirdwave | C93: F-14MTL | D93: #REF! | E93: MTL-5-125U | F93: UMA | G93: DDR5 | H93: 0 | I93: #REF! | J93: #REF! | R93: 0 | S93: 0 | T93: 0 | U93: 0 | V93: 0 | W93: 0 | X93: 0 | Y93: 0 | Z93: 25 | AA93: 25 | AB93: 10 | AC93: 10 | AD93: 10 | AE93: 10 | AF93: 10 | AG93: 10 | AH93: 10 | AI93: 0 | AJ93: 0 | AK93: 0 | AL93: 0 | AM93: 0 | AN93: 0 | AO93: 0 | AP93: 0 | AQ93: 0 | AR93: 0 | AS93: 0 | AT93: 0 | AU93: 0 | AV93: {=IFERROR(_xlfn.XLOOKUP($C93, INDIRECT("'在庫使用計画 ("&AV$1&")'!D:D"), INDIRECT("'在庫使用計画 ("&AV$1&")'!I:I") ),"")} | AW93: {=IFERROR(_xlfn.XLOOKUP($C93, INDIRECT("'在庫使用計画 ("&AW$1&")'!D:D"), INDIRECT("'在庫使用計画 ("&AW$1&")'!I:I") ),"")} | AX93: {=IFERROR(_xlfn.XLOOKUP($C93, INDIRECT("'在庫使用計画 ("&AX$1&")'!D:D"), INDIRECT("'在庫使用計画 ("&AX$1&")'!I:I") ),"")}
A94: 14” | B94: CLE-NL45-150U-UMA-L6-TPM Thirdwave | C94: F-14RP7F-B | D94: #REF! | E94: RPL-R-i7-150U | F94: UMA | H94: 63 | I94: #REF! | J94: #REF! | K94: 74 | L94: 217 | M94: 217 | N94: 217 | O94: 139 | P94: 139 | Q94: 139 | R94: 139 | S94: 139 | T94: 285 | U94: 285 | V94: 285 | W94: 285 | X94: 285 | Y94: 285 | Z94: 285 | AA94: 285 | AB94: 285 | AC94: 285 | AD94: 285 | AE94: 285 | AF94: 285 | AG94: 285 | AH94: 285 | AI94: 232 | AJ94: 232 | AK94: 232 | AL94: 354 | AM94: 354 | AN94: 354 | AO94: 354 | AP94: 268 | AQ94: 268 | AR94: 268 | AS94: 268 | AT94: 268 | AU94: 268 | AV94: {=IFERROR(_xlfn.XLOOKUP($C94, INDIRECT("'在庫使用計画 ("&AV$1&")'!D:D"), INDIRECT("'在庫使用計画 ("&AV$1&")'!I:I") ),"")} | AW94: {=IFERROR(_xlfn.XLOOKUP($C94, INDIRECT("'在庫使用計画 ("&AW$1&")'!D:D"), INDIRECT("'在庫使用計画 ("&AW$1&")'!I:I") ),"")} | AX94: {=IFERROR(_xlfn.XLOOKUP($C94, INDIRECT("'在庫使用計画 ("&AX$1&")'!D:D"), INDIRECT("'在庫使用計画 ("&AX$1&")'!I:I") ),"")}
A95: 14” | B95: CLE-NL45-120U-UMA-L6-TPM Thirdwave | C95: F-14RP5F-B | D95: #REF! | E95: RPL-R-i5-120U | F95: UMA | H95: 362 | I95: #REF! | J95: #REF! | K95: 252 | L95: 504 | M95: 504 | N95: 504 | O95: 870 | P95: 870 | Q95: 870 | R95: 1136 | S95: 1136 | T95: 686 | U95: 686 | V95: 686 | W95: 686 | X95: 686 | Y95: 686 | Z95: 686 | AA95: 686 | AB95: 686 | AC95: 686 | AD95: 686 | AE95: 686 | AF95: 686 | AG95: 686 | AH95: 686 | AI95: 138 | AJ95: 138 | AK95: 138 | AL95: 668 | AM95: 668 | AN95: 668 | AO95: 668 | AP95: 430 | AQ95: 545 | AR95: 545 | AS95: 545 | AT95: 545 | AU95: 545 | AV95: {=IFERROR(_xlfn.XLOOKUP($C95, INDIRECT("'在庫使用計画 ("&AV$1&")'!D:D"), INDIRECT("'在庫使用計画 ("&AV$1&")'!I:I") ),"")} | AW95: {=IFERROR(_xlfn.XLOOKUP($C95, INDIRECT("'在庫使用計画 ("&AW$1&")'!D:D"), INDIRECT("'在庫使用計画 ("&AW$1&")'!I:I") ),"")} | AX95: {=IFERROR(_xlfn.XLOOKUP($C95, INDIRECT("'在庫使用計画 ("&AX$1&")'!D:D"), INDIRECT("'在庫使用計画 ("&AX$1&")'!I:I") ),"")}
A96: 14” | B96: CLE-NL45-150U-UMA-L6-TPM DDR5 Thirdwave | C96: F-14RP7H-B | D96: #REF! | E96: RPL-R-i7-150U | G96: DDR5 | H96: 648 | I96: #REF! | J96: #REF! | U96: 0 | V96: 0 | W96: 0 | X96: 0 | Y96: 0 | Z96: 0 | AA96: 0 | AB96: 273 | AC96: 273 | AD96: 273 | AE96: 273 | AF96: 273 | AG96: 313 | AH96: 313 | AI96: 486 | AJ96: 486 | AK96: 486 | AL96: 352 | AM96: 352 | AN96: 352 | AO96: 352 | AP96: 513 | AQ96: 513 | AR96: 445 | AS96: 445 | AT96: 445 | AU96: 445 | AV96: {=IFERROR(_xlfn.XLOOKUP($C96, INDIRECT("'在庫使用計画 ("&AV$1&")'!D:D"), INDIRECT("'在庫使用計画 ("&AV$1&")'!I:I") ),"")} | AW96: {=IFERROR(_xlfn.XLOOKUP($C96, INDIRECT("'在庫使用計画 ("&AW$1&")'!D:D"), INDIRECT("'在庫使用計画 ("&AW$1&")'!I:I") ),"")} | AX96: {=IFERROR(_xlfn.XLOOKUP($C96, INDIRECT("'在庫使用計画 ("&AX$1&")'!D:D"), INDIRECT("'在庫使用計画 ("&AX$1&")'!I:I") ),"")}
A97: 14” | B97: CLE-NL45-120U-UMA-L6-TPM DDR5 Thirdwave | C97: F-14RP5H-B | D97: #REF! | E97: RPL-R-i5-120U | G97: DDR5 | H97: 1460 | I97: #REF! | J97: #REF! | U97: 1038 | V97: 1038 | W97: 1038 | X97: 1038 | Y97: 1038 | Z97: 1038 | AA97: 1038 | AB97: 2086 | AC97: 2086 | AD97: 2086 | AE97: 2086 | AF97: 2086 | AG97: 2086 | AH97: 2086 | AI97: 2544 | AJ97: 2544 | AK97: 2544 | AL97: 820 | AM97: 820 | AN97: 820 | AO97: 820 | AP97: 1070 | AQ97: 1070 | AR97: 1070 | AS97: 1070 | AT97: 1070 | AU97: 1070 | AV97: {=IFERROR(_xlfn.XLOOKUP($C97, INDIRECT("'在庫使用計画 ("&AV$1&")'!D:D"), INDIRECT("'在庫使用計画 ("&AV$1&")'!I:I") ),"")} | AW97: {=IFERROR(_xlfn.XLOOKUP($C97, INDIRECT("'在庫使用計画 ("&AW$1&")'!D:D"), INDIRECT("'在庫使用計画 ("&AW$1&")'!I:I") ),"")} | AX97: {=IFERROR(_xlfn.XLOOKUP($C97, INDIRECT("'在庫使用計画 ("&AX$1&")'!D:D"), INDIRECT("'在庫使用計画 ("&AX$1&")'!I:I") ),"")}
A98: 14” | B98: CLE-NL45-1355U-UMA-L6-TPM Thirdwave | C98: F-14RP7S | D98: #REF! | E98: RPL-i7-1355U | F98: UMA | G98: DDR4 | H98: 1 | I98: #REF! | J98: #REF! | K98: 730 | L98: 627 | M98: 627 | N98: 627 | O98: 627 | P98: 627 | Q98: 627 | R98: 627 | S98: 627 | T98: 497 | U98: 497 | V98: 497 | W98: 497 | X98: 497 | Y98: 497 | Z98: 497 | AA98: 497 | AB98: 377 | AC98: 377 | AD98: 377 | AE98: 377 | AF98: 377 | AG98: 377 | AH98: 377 | AI98: 268 | AJ98: 268 | AK98: 268 | AL98: 348 | AM98: 348 | AN98: 348 | AO98: 348 | AP98: 301 | AQ98: 301 | AR98: 200 | AS98: 200 | AT98: 200 | AU98: 200 | AV98: {=IFERROR(_xlfn.XLOOKUP($C98, INDIRECT("'在庫使用計画 ("&AV$1&")'!D:D"), INDIRECT("'在庫使用計画 ("&AV$1&")'!I:I") ),"")} | AW98: {=IFERROR(_xlfn.XLOOKUP($C98, INDIRECT("'在庫使用計画 ("&AW$1&")'!D:D"), INDIRECT("'在庫使用計画 ("&AW$1&")'!I:I") ),"")} | AX98: {=IFERROR(_xlfn.XLOOKUP($C98, INDIRECT("'在庫使用計画 ("&AX$1&")'!D:D"), INDIRECT("'在庫使用計画 ("&AX$1&")'!I:I") ),"")}
A99: 14” | B99: CLE-NL45-1355U-UMA-L6-TPM DDR5 Thirdwave | C99: F-14RP7V | D99: #REF! | E99: RPL-R i7-1355U | G99: DDR5 | H99: 152 | I99: #REF! | J99: #REF! | U99: 0 | V99: 0 | W99: 0 | X99: 0 | Y99: 0 | Z99: 0 | AA99: 0 | AB99: 134 | AC99: 134 | AD99: 134 | AE99: 134 | AF99: 134 | AG99: 134 | AH99: 134 | AI99: 251 | AJ99: 251 | AK99: 251 | AL99: 30 | AM99: 30 | AN99: 0 | AO99: 0 | AP99: 0 | AQ99: 0 | AR99: 0 | AS99: 0 | AT99: 0 | AU99: 0 | AV99: {=IFERROR(_xlfn.XLOOKUP($C99, INDIRECT("'在庫使用計画 ("&AV$1&")'!D:D"), INDIRECT("'在庫使用計画 ("&AV$1&")'!I:I") ),"")} | AW99: {=IFERROR(_xlfn.XLOOKUP($C99, INDIRECT("'在庫使用計画 ("&AW$1&")'!D:D"), INDIRECT("'在庫使用計画 ("&AW$1&")'!I:I") ),"")} | AX99: {=IFERROR(_xlfn.XLOOKUP($C99, INDIRECT("'在庫使用計画 ("&AX$1&")'!D:D"), INDIRECT("'在庫使用計画 ("&AX$1&")'!I:I") ),"")}
AV100: {=IFERROR(_xlfn.XLOOKUP($C100, INDIRECT("'在庫使用計画 ("&AV$1&")'!D:D"), INDIRECT("'在庫使用計画 ("&AV$1&")'!I:I") ),"")} | AW100: {=IFERROR(_xlfn.XLOOKUP($C100, INDIRECT("'在庫使用計画 ("&AW$1&")'!D:D"), INDIRECT("'在庫使用計画 ("&AW$1&")'!I:I") ),"")} | AX100: {=IFERROR(_xlfn.XLOOKUP($C100, INDIRECT("'在庫使用計画 ("&AX$1&")'!D:D"), INDIRECT("'在庫使用計画 ("&AX$1&")'!I:I") ),"")}
A101: 14” | B101: CLE-NL45-1334U-UMA-L6 Thirdwave | C101: F-14RP5S | D101: #REF! | E101: RPL-i5-1334U | F101: UMA | G101: DDR4 | H101: 15 | I101: #REF! | J101: #REF! | K101: 1776 | L101: 1503 | M101: 1503 | N101: 1503 | O101: 1923 | P101: 1923 | Q101: 1923 | R101: 1480 | S101: 1480 | T101: 890 | U101: 890 | V101: 890 | W101: 890 | X101: 890 | Y101: 890 | Z101: 890 | AA101: 890 | AB101: 435 | AC101: 435 | AD101: 435 | AE101: 435 | AF101: 435 | AG101: 435 | AH101: 435 | AI101: 50 | AJ101: 50 | AK101: 50 | AL101: 50 | AM101: 50 | AN101: 50 | AO101: 50 | AP101: 10 | AQ101: 50 | AR101: 50 | AS101: 50 | AT101: 50 | AU101: 50 | AV101: {=IFERROR(_xlfn.XLOOKUP($C101, INDIRECT("'在庫使用計画 ("&AV$1&")'!D:D"), INDIRECT("'在庫使用計画 ("&AV$1&")'!I:I") ),"")} | AW101: {=IFERROR(_xlfn.XLOOKUP($C101, INDIRECT("'在庫使用計画 ("&AW$1&")'!D:D"), INDIRECT("'在庫使用計画 ("&AW$1&")'!I:I") ),"")} | AX101: {=IFERROR(_xlfn.XLOOKUP($C101, INDIRECT("'在庫使用計画 ("&AX$1&")'!D:D"), INDIRECT("'在庫使用計画 ("&AX$1&")'!I:I") ),"")}
...

Sheet 改善予定
A2: 1 | B2: 新モデル追加時、修正するシートが多い
C3: 在庫使用計画 (全体実績+予測）
C4: 在庫使用計画 (計画 予測)
C5: 在庫使用計画 (ノート全体試算)
C6: 在庫使用計画 (一般)
C7: 在庫使用計画 (法人)
B8: 方法 | C8: A | D8: 同じ行に同じモデルが記入される状態とする。
D9: 参照を用いないため軽量かつ単純作業を続ければ上記リストの在庫使用計画 (計画 予測)以外は適用可能。
D10: それなりに時間を要する上、複数人が編集可能なリストのため、構成が壊れる可能性が高い。
C11: B | D11: マスタとなるリストを先に作成し、そこだけを修正すれば全体に適用する仕組みを作る。
D12: 作業者の学習コストに加え、在庫使用計画 (計画 予測)にどう反映させるかに懸念あり。
C13: →暫定Aとし、マスタは過不足確認用として用いる
A16: 2 | B16: 季節係数の算出と運用について
C17: 新季節係数の適用タイミング：期始め(8月) or 随時
D18: 大きな差異はないと思われるが、次回の8月以降の予測をする際は前年までの季節係数を用いるか、季節係数を用いた予測から季節係数を算出することになる（これ意味あるか？）
C20: 直近の年になるほど重み付けをする必要はあるか？
D21: また、外れ値を弾く仕組みは中央値を用いるだけで十分か
C23: そもそもよりよい季節係数の算出方法があるのでは
A25: 3 | B25: 次期ファイル名称
C26: ノート在庫使用計画_44期_2026-27
A28: 4 | B28: 軽量化
C29: 条件付き書式の多用により定期的に飛び地になった条件付き書式の整理が必要になってしまっている。
C30: 揮発性関数の使用回数を減らす
C31: 何年分の計画を保持するか？
A33: 5

Sheet 参考資料(係数 通販+店舗　台数実績)
A1: 43期使用 | B1: 月間の係数（期全体を100%とした場合の各月の貢献率） | S1: 自動計算 | AK1: 計算値 | AL1: 12ヶ月周期があると仮定 | AO1: {=AK6:AO6} -> 実績 | AP1: 指数平滑法予測 | AQ1: 40期以降抜粋予測 | AR1: 41期以降抜粋予測 | AS1: 季節係数予測 | AV1: 43
E2: 8月 | F2: 9月 | G2: 10月 | H2: 11月 | I2: 12月 | J2: 1月 | K2: 2月 | L2: 3月 | M2: 4月 | N2: 5月 | O2: 6月 | P2: 7月 | T2: 8月 | U2: 9月 | V2: 10月 | W2: 11月 | X2: 12月 | Y2: 1月 | Z2: 2月 | AA2: 3月 | AB2: 4月 | AC2: 5月 | AD2: 6月 | AE2: 7月 | AJ2: Seasonality: | AK2: =_xlfn.FORECAST.ETS.SEASONALITY($AK$7:$AK$112,$AJ$7:$AJ$112,1,1) -> 0 | AL2: 12 | AN2: 41-42期合計 | AO2: =SUM(AK$87:AK$110) -> 54232 | AP2: =SUM(AL$87:AL$110) -> 67901.461 | AQ2: =SUM(AM$87:AM$110) -> 67126.996 | AR2: =SUM(AN$87:AN$110) -> 64545.874 | AS2: =SUM(AO$87:AO$110) -> 66929.098 | AW2: 8月 | AX2: 9月 | AY2: 10月 | AZ2: 11月 | BA2: 12月 | BB2: 1月 | BC2: 2月 | BD2: 3月 | BE2: 4月 | BF2: 5月 | BG2: 6月 | BH2: 7月
A3: 通販+店舗 | B3: GG | C3: 台数 | E3: 0.075406343 | F3: 0.066042416 | G3: 0.059262702 | H3: 0.063689562 | I3: 0.10866966 | J3: 0.087282782 | K3: 0.074697777 | L3: 0.10939599 | M3: 0.094391577 | N3: 0.083906676 | O3: 0.087418592 | P3: 0.089835917 | S3: GG | T3: {=T28:AE28} -> 0.083546435 | U3: 0.067358863 | V3: 0.058564135 | W3: 0.066556831 | X3: 0.10464919 | Y3: 0.087506691 | Z3: 0.0787732 | AA3: 0.1133387 | AB3: 0.08724341 | AC3: 0.069647981 | AD3: 0.080590325 | AE3: 0.10222423 | AF3: =SUM(T3:AE3) -> 1 | AJ3: STAT: | AK3: =_xlfn.FORECAST.ETS.STAT($AK$7:$AK$112,$AJ$7:$AJ$112,1,AK2,1,1) -> 0.5 | AL3: =_xlfn.FORECAST.ETS.STAT($AK$7:$AK$112,$AJ$7:$AJ$112,1,AL2,1,1) -> 0.75 | AV3: GG | AW3: {=AW28:BH28} -> 0 | AX3: 0 | AY3: 0 | AZ3: 0 | BA3: 0 | BB3: 0 | BC3: 0 | BD3: 0 | BE3: 0 | BF3: 0 | BG3: 0 | BH3: 0
A4: 通販+店舗 | B4: GC | C4: 台数 | E4: 0.055646705 | F4: 0.071993925 | G4: 0.080768448 | H4: 0.073831238 | I4: 0.11682497 | J4: 0.10320135 | K4: 0.079908853 | L4: 0.099358244 | M4: 0.09416313 | N4: 0.082950041 | O4: 0.071136137 | P4: 0.070216963 | S4: GC | T4: {=T61:AE61} -> 0.072498752 | U4: 0.078354011 | V4: 0.079124973 | W4: 0.079865035 | X4: 0.12552459 | Y4: 0.10616903 | Z4: 0.07019467 | AA4: 0.10504426 | AB4: 0.078510122 | AC4: 0.0663959 | AD4: 0.069775629 | AE4: 0.068543031 | AF4: =SUM(T4:AE4) -> 1 | AV4: GC | AW4: {=AW56:BH56} -> 0 | AX4: 0 | AY4: 0 | AZ4: 0 | BA4: 0 | BB4: 0 | BC4: 0 | BD4: 0 | BE4: 0 | BF4: 0 | BG4: 0 | BH4: 0
A5: 通販+店舗 | B5: TW | C5: 台数 | E5: 0.06662979 | F5: 0.080932899 | G5: 0.076969131 | H5: 0.079158728 | I5: 0.11770487 | J5: 0.10754906 | K5: 0.08992384 | L5: 0.12080482 | M5: 0.082398749 | N5: 0.052841661 | O5: 0.060776229 | P5: 0.064310232 | S5: TW | T5: {=T94:AE94} -> 0.063819922 | U5: 0.068940116 | V5: 0.074241085 | W5: 0.076835796 | X5: 0.11325044 | Y5: 0.097731568 | Z5: 0.09214255 | AA5: 0.1361705 | AB5: 0.083613057 | AC5: 0.060638723 | AD5: 0.063228589 | AE5: 0.069387648 | AF5: =SUM(T5:AE5) -> 1 | AV5: TW | AW5: {=AW93:BH93} -> 0 | AX5: 0 | AY5: 0 | AZ5: 0 | BA5: 0 | BB5: 0 | BC5: 0 | BD5: 0 | BE5: 0 | BF5: 0 | BG5: 0 | BH5: 0
AI6: 期 | AJ6: 年月 | AK6: 実績 | AL6: 指数平滑法予測 | AM6: 40期以降抜粋予測 | AN6: 41期以降抜粋予測 | AO6: 季節係数予測
AI7: 34 | AJ7: 42736 | AK7: 829 | AL7: =_xlfn.FORECAST.ETS($AJ7,$AK$7:$AK$110,$AJ$7:$AJ$110,12,1,1) -> 1077.0421
A8: 通販+店舗 | B8: GG | C8: 前月比 | E8: 0.98470799 | F8: 0.91612249 | G8: 0.88987781 | H8: 1.1013468 | I8: 1.6831152 | J8: 0.86955444 | K8: 0.84778056 | L8: 1.5116833 | M8: 0.82707022 | N8: 0.90011478 | O8: 1.0885157 | P8: 1.1327499 | S8: GG | T8: {=T3:T5/AE3:AE5} -> 0.81728601 | U8: {=U3:AE5/T3:AD5} -> 0.80624461 | V8: 0.86943473 | W8: 1.1364777 | X8: 1.5723284 | Y8: 0.83619079 | Z8: 0.90019631 | AA8: 1.4387978 | AB8: 0.76975831 | AC8: 0.79831796 | AD8: 1.1571093 | AE8: 1.268443 | AF8: =SUM(T8:AE8) -> 12.370585 | AJ8: 42767 | AK8: 765 | AL8: =_xlfn.FORECAST.ETS(AJ8,$AK$7:$AK$110,$AJ$7:$AJ$110,12,1,1) -> 890.0526 | AV8: GG | AW8: {=AW3:AW5/BH3:BH5} -> #DIV/0! | AX8: {=AX3:BH5/AW3:BG5} -> #DIV/0! | AY8: #DIV/0! | AZ8: #DIV/0! | BA8: #DIV/0! | BB8: #DIV/0! | BC8: #DIV/0! | BD8: #DIV/0! | BE8: #DIV/0! | BF8: #DIV/0! | BG8: #DIV/0! | BH8: #DIV/0!
A9: 通販+店舗 | B9: GC | C9: 前月比 | E9: 0.9362476 | F9: 1.0222488 | G9: 1.0266749 | H9: 1.2210711 | I9: 1.75817 | J9: 0.9852383 | K9: 0.66607012 | L9: 0.975279 | M9: 0.58149914 | N9: 0.93176797 | O9: 1.4277213 | P9: 1.7559427 | S9: GC | T9: 1.0577115 | U9: 1.0807636 | V9: 1.0098395 | W9: 1.0093531 | X9: 1.5717089 | Y9: 0.84580268 | Z9: 0.66115956 | AA9: 1.4964706 | AB9: 0.74740041 | AC9: 0.84569859 | AD9: 1.0509027 | AE9: 0.98233483 | AF9: =SUM(T9:AE9) -> 12.359146 | AJ9: 42826 | AK9: 866 | AL9: =_xlfn.FORECAST.ETS(AJ9,$AK$7:$AK$110,$AJ$7:$AJ$110,12,1,1) -> 1538.5921 | AV9: GC | AW9: #DIV/0! | AX9: #DIV/0! | AY9: #DIV/0! | AZ9: #DIV/0! | BA9: #DIV/0! | BB9: #DIV/0! | BC9: #DIV/0! | BD9: #DIV/0! | BE9: #DIV/0! | BF9: #DIV/0! | BG9: #DIV/0! | BH9: #DIV/0!
A10: 通販+店舗 | B10: TW | C10: 前月比 | E10: 0.94961599 | F10: 1.2214241 | G10: 1.0115978 | H10: 1.0696908 | I10: 1.4588276 | J10: 0.94281153 | K10: 0.87458803 | L10: 1.4009721 | M10: 0.69994855 | N10: 0.64044473 | O10: 1.2281161 | P10: 1.0584312 | S10: TW | T10: 0.91975911 | U10: 1.0802288 | V10: 1.0768924 | W10: 1.0349498 | X10: 1.4739282 | Y10: 0.86296851 | Z10: 0.94281257 | AA10: 1.4778243 | AB10: 0.61403209 | AC10: 0.7252303 | AD10: 1.0427098 | AE10: 1.0974094 | AF10: =SUM(T10:AE10) -> 12.348745 | AJ10: 42795 | AK10: 883 | AL10: =_xlfn.FORECAST.ETS(AJ10,$AK$7:$AK$110,$AJ$7:$AJ$110,12,1,1) -> 1279.4139 | AV10: TW | AW10: #DIV/0! | AX10: #DIV/0! | AY10: #DIV/0! | AZ10: #DIV/0! | BA10: #DIV/0! | BB10: #DIV/0! | BC10: #DIV/0! | BD10: #DIV/0! | BE10: #DIV/0! | BF10: #DIV/0! | BG10: #DIV/0! | BH10: #DIV/0!
AJ11: 42856 | AK11: 724 | AL11: =_xlfn.FORECAST.ETS(AJ11,$AK$7:$AK$110,$AJ$7:$AJ$110,12,1,1) -> 1159.299
AJ12: 42887 | AK12: 642 | AL12: =_xlfn.FORECAST.ETS(AJ12,$AK$7:$AK$110,$AJ$7:$AJ$110,12,1,1) -> 1073.8621
A13: 台数実績 | C13: 期 | D13: 年 | E13: 8月 | F13: 9月 | G13: 10月 | H13: 11月 | I13: 12月 | J13: 1月 | K13: 2月 | L13: 3月 | M13: 4月 | N13: 5月 | O13: 6月 | P13: 7月 | Q13: 年合計 | T13: 8月 | U13: 9月 | V13: 10月 | W13: 11月 | X13: 12月 | Y13: 1月 | Z13: 2月 | AA13: 3月 | AB13: 4月 | AC13: 5月 | AD13: 6月 | AE13: 7月 | AJ13: 42917 | AK13: 912 | AL13: =_xlfn.FORECAST.ETS(AJ13,$AK$7:$AK$110,$AJ$7:$AJ$110,12,1,1) -> 1110.0468
A14: 通販+店舗 | B14: GG | C14: 34 | D14: 16-17 | E14: {=_xlfn.LET( _xlpm._期,$C14, _xlpm._見出し,E$13, _xlpm._月,IF(ISNUMBER(_xlpm._見出し),IF(_xlpm._見出し<=12,_xlpm._見出し,MONTH(_xlpm._見出し)),--SUBSTITUTE(_xlpm._見出し,"月","")), _xlpm._年,_xlpm._期+1982+(_xlpm._月<8), _xlpm._年月,DATE(_xlpm._年,_xlpm._月,1), _xlpm._列, MATCH( TEXT(_xlpm._年月,"yy-mm"), INDEX( IF( ISNUMBER('在庫使用計画 (全体実績+予測）0701'!$A$1:$BD$1), TEXT('在庫使用計画 (全体実績+予測）0701'!$A$1:$BD$1,"yy-mm"), '在庫使用計画 (全体実績+予測）0701'!$A$1:$BD$1 ), 1,0 ), 0 ), IF( _xlpm._期<43, "", IFERROR( INDEX( '在庫使用計画 (全体実績+予測）0701'!$A$1:$BD$198, MATCH("GALLERIA Gaming 合計",'在庫使用計画 (全体実績+予測）0701'!$B$1:$B$198,0), _xlpm._列 ), "" ) ) )} | J14: 829 | K14: 765 | L14: 883 | M14: 866 | N14: 724 | O14: 642 | P14: 912 | AI14: 35 | AJ14: 42948 | AK14: 787 | AL14: =_xlfn.FORECAST.ETS(AJ14,$AK$7:$AK$110,$AJ$7:$AJ$110,12,1,1) -> 1114.4349
B15: Gaming | C15: 35 | D15: 17-18 | E15: 787 | F15: 630 | G15: 564 | H15: 568 | I15: 844 | J15: 546 | K15: 387 | L15: 540 | M15: 355 | N15: 450 | O15: 498 | P15: 605 | Q15: =SUM(E15:P15) -> 6774 | R15: 35期 | S15: 17-18 | T15: =E15/$Q15 -> 0.11617951 | U15: =F15/$Q15 -> 0.093002657 | V15: =G15/$Q15 -> 0.083259522 | W15: =H15/$Q15 -> 0.083850015 | X15: =I15/$Q15 -> 0.12459404 | Y15: =J15/$Q15 -> 0.080602303 | Z15: =K15/$Q15 -> 0.057130204 | AA15: =L15/$Q15 -> 0.079716563 | ... AE15: =P15/$Q15 -> 0.089312076 | AJ15: 42979 | AK15: 630 | AL15: =_xlfn.FORECAST.ETS(AJ15,$AK$7:$AK$110,$AJ$7:$AJ$110,12,1,1) -> 1057.7275
